Workbook

Sheet comparison
A1: Grant ID | B1: Title | C1: Abstract | D1: scope | E1: scope_LLM | F1: confidence_LLM | G1: reasoning_LLM | H1: correct_scope | I1: pillar | J1: pillar_LLM | K1: correct_pillar | L1: plant_based_LLM | M1: fermentation_LLM | N1: cultivated_LLM | O1: cross_cutting_LLM | P1: status | Q1: error
A2: grant.14917108 | B2: Scientific Exchange to assess QUality and Risks of FOODs obtained by novel processing and PackagingTechnologies | C2: The goal of SEQUR FOOD is to build an international scientific network including researchers from EU and South America that will work on the development of novel food processing technologies, (i.e. UV treatment, cold plasma processing, nanoemulsification, freeze concentration and drying) and/or active bioactive packaging (i.e. bacterial cellulose, antibacterial paper, etc.) to obtain safe products for the EU market with higher shelf-life and high nutritional and functional properties. This includes optimization of the novel food processing technologies, nutritional and risk assessment of these technologies and obtained products as novel foods within EFSA’s framework, and documenting their health claims, if relevant. To achieve this objective, a consortium of 5 universities from EU (Greece, Poland, Romania, and Spain) with expertise in all the aspects of EU risk assessment, 1 plant-based products processing company based in Poland together with 1 university and 1 research institute from South America (Colombia) with extended expertise in novel food processing techniques will work on a variety of case studies spread across several novel food processing technologies and products relevant for Colombia: fruit (passionfruit, uchuva (Physalis peruviana L.), blueberries); cold brewed coffee; oat milk (including oat grains and nuts needed for its production); and high oleic palm oil as compared to olive oil. These case studies will be a proof of concept for the holistic assessment of each technology-foodstuff pair and will constitute the basis for further research, but also for food processors, the principal stakeholders of the project. The activities proposed in SEQUR FOOD are innovative in many aspects. The most important innovation is the holistic approach of new food product development in terms of the complete physico-chemical, microbiological, nutritional and functional properties, but also sensory evaluation and multicultural consumer acceptance. | D2: out | E2: out | F2: 2 | G2: Although the project includes oat milk as a case study, the research focuses on novel food processing and packaging technologies for food safety and shelf-life across a broad range of products (fruits, coffee, palm oil), with no stated focus on alternative protein development or substitution of animal-derived products. | H2: =TRUE() -> TRUE | I2: NA | J2: NA | K2: =TRUE() -> TRUE | L2: =FALSE() -> FALSE | M2: =FALSE() -> FALSE | N2: =FALSE() -> FALSE | O2: =FALSE() -> FALSE | P2: ok
A3: grant.15145414 | B3: VegVit | C3: "VegVit" is een interdisciplinair project dat gericht is op de ontwikkeling van een assortiment veganistische zuivel- en vleesalternatieven met een verbeterd nutritioneel profiel (vitamine B12, maar ook proteïnekwaliteit/breder aminozuurprofiel). Het eerste concrete doel van het project is dat voedselveilige starterculturen geïdentificeerd en geselecteerd kunnen worden die onder geschikte omstandigheden hoge niveaus van vitamine B12 vormen. Het tweede concrete doel is dat vitamine B12-verrijkte ingrediënten geproduceerd kunnen worden door eerst grondstoffen zoals geëxtrudeerde plantaardige eiwitten of eiwitsuspensies te fermenteren. Deze verrijkte ingrediënten kunnen vervolgens in een tweede stap worden omgezet in hoogwaardige analogen met verhoogde B12-gehaltes en een beter proteïnekwaliteit. Het derde concrete doel is dat vitamine B12 in-situ gevormd wordt via een co-fermentatieproces, door tijdens het productieproces van salami- yoghurt- of smeerkaasanalogen geschikte starterculturen toe te voegen. Afhankelijk van de aard en samenstelling van de matrix (geselecteerde ingrediënten, homogene of heterogene matrix structuur, pH, wateractiviteit) kan de ene aanpak voordeliger zijn dan de andere. Hierbij ligt de focus op het creëren van producten die zowel in kwaliteit als voedingswaarde voldoen aan de verwachtingen van de consument. | D3: in | E3: in | F3: 7 | G3: This project explicitly develops vegan dairy and meat analogues (salami, yoghurt, cheese analogues) using fermentation of plant-based proteins to improve nutritional profile (vitamin B12 and protein quality), directly advancing alternative protein product development. | H3: =TRUE() -> TRUE | I3: PB | J3: CC | K3: =FALSE() -> FALSE | L3: =TRUE() -> TRUE | M3: =TRUE() -> TRUE | N3: =FALSE() -> FALSE | O3: =FALSE() -> FALSE | P3: ok | R3: Acceptable as CC, but PB preferred.
A4: grant.14631940 | B4: Growing well Study (GWS): the role of portion size, plant-based foods and commercially manufactured foods and drinks | C4: What are the study aims? To understand more about eating habits of children aged 1-5 years old, and how this affects their growth and dental health. We also want to find age-appropriate food/drink portion sizes. Why is this research important? Healthy diets in early years are important for growth and development. However, it is difficult to give parents clear guidance on what and how much children should eat due to lack of up-to-date information. Commercially manufactured foods/drinks for young children are often high in free sugars, salt, and fat. Plant-based diets (PBDs) may also be low in important nutrients. What will we do? Part 1: Collect data on foods/nutrients/dietary patterns of children to determine optimum growth and dental health At baseline, parents of children aged 1-5 years from Leeds, Doncaster and East London will complete questionnaires about their child s food intake. They will be asked to record what their child has eaten for three one-day periods across 6 months using an online system called myfood24 . This has a large commercial product database with child-appropriate portion sizes. Parents will also attend one in-person session with their child. Children s length/height, weight, and head circumference will be measured at local children s centres/nurseries or in homes. We will ask these same people to complete surveys again one year later, with another measurement session to look at growth. We will also assess dental health to identify healthy and decayed teeth. Part 2: Analyse the results of surveys and measurements We want to understand how growth and dental health are influenced by nutrient intakes (e.g. sugar or fat), diet pattern (vegetarian/vegan/dairy free), and portion sizes for key food groups. We will identify how much of different foods children should be eating for their age. We can also find out whether commercial foods designed for children are needed. How will parents be involved? Our parent advisors have provided input to this summary and helped in study design including planning how best to collect information and engage with participants. We will create a Parent Advisory Group in Leeds/Doncaster/East London. Representatives will form part of the Project Steering Committee. What do we expect to achieve and what happens next? We will identify the optimum nutrient composition of diets to support healthier children; and how sub-optimal intakes in vulnerable groups may be redressed. Guidelines will be developed to help parents and policy-makers promote age-appropriate portion sizes of foods. We will also know whether contemporary vegetarian/vegan/non-dairy dietary patterns can support optimum growth. New guidance will be provided on caring for children s teeth. Our findings will be shared in written reports, through a social media/media campaign to promote guidelines; plus visual storytelling feedback for participants and key influencer groups.Research question We will answer questions posed by the recent Scientific Advisory Committee on Nutrition (SACN) report: What are age-appropriate food and drink portion sizes in relation to growth and dental health? What are the short-term effects (12 months) on growth and dental health of commercial foods for children; vegetarian/vegan/dairy-free dietary patterns? What is the impact on growth and dental health of macro- and micro-nutrient intakes; fruit juices/free sugars; formula milks for 12m+; sweeteners? Background In the UK, little contemporary data exists on diet in young children but worrying trends in preschool overweight and dental health are reported. Current young child diets do not meet dietary recommendations and evidence-driven age-appropriate portion size recommendations are missing. Further research into the impact of plant-based diets, the use of commercial foods, and toddler milks is also recommended by SACN. Aims and Objectives To provide new evidence on diet in children aged 1-5y, linked to optimum growth and dental health. Quantifying age-appropriate portion sizes for different foods and drinks. Collect data on child dietary intake, portion sizes. Collect data on parent and child attributes, including child anthropometrics and dental health. Evaluate food and nutrient intake in relation to i) growth over 12 months, ii) child and parent characteristics, including ethnic diversity, deprivation and iii) dental health. Make recommendations for nutrition and age-appropriate portions. Methods We will recruit 2100 parents of young children (1-5years) through the Born and Bred in (BaBi) Network birth cohorts in Leeds, Doncaster, and East London. Recruitment will include at least 400 in each year bracket, 20% non-white, 20% from deprived locations, and 300 (15%) vegetarian/vegan/non-dairy diet. Plans are in place to ensure recruitment targets are met. Protocols, consent forms, and questionnaires will be co-designed with our Parent Advisory Group. Baseline data will be collected using i) online survey, ii) face-to-face growth measures of height, weight, length, head circumference iii) 3 x 24h measures of diet spanning 6 months. Follow-up data collected after 12 months will repeat baseline measures and include a dental assessment. Cross-sectional and longitudinal analysis will explore how growth and dental health are influenced by nutrient intakes, diet pattern, and food portion sizes. Age/gender appropriate portion sizes for key food groups will be characterised with linear mixed-effects modelling for specific foods/food groups in relation to the child s position on the growth chart centiles. Timelines Month 3 Study start (ethics, questionnaires etc.) completed. Month 5 Pilot test. Months 6-12 baseline data collection. Month 18 all baseline diet information collected. Months 19- 24 follow-up data collected. Month 36 analysis and write up complete. Anticipated Impact and Dissemination Knowledge of associations between food and nutrient intakes and growth/dental health and knowledge of suboptimal intakes in vegan/vegetarian/dairy-free or vulnerable groups will enable evidence-based guidelines on age-appropriate portion sizes and optimal diet composition. Guideline promotion to key stakeholders and visual feedback to participants will support intake of age-appropriate portions and healthier diets. Ultimately resulting in healthier children, with better dental health. Guidelines will also highlight social inequalities, indicating specific actions to redress imbalances. | D4: out | E4: out | F4: 2 | G4: This study examines dietary habits and growth outcomes in young children, including vegetarian/vegan/dairy-free diets, but focuses on general nutritional epidemiology rather than the development, characterisation, or societal aspects of alternative protein products specifically. | H4: =TRUE() -> TRUE | I4: NA | J4: NA | K4: =TRUE() -> TRUE | L4: =FALSE() -> FALSE | M4: =FALSE() -> FALSE | N4: =FALSE() -> FALSE | O4: =FALSE() -> FALSE | P4: ok
A5: grant.15060106 | B5: "Een Exclusieve Duurzaamheidstransitie van de Mode? Hoe Culturele Duurzaamheidsentrepreneurs in Culturele Industrieën Klimaatpolarisatie Riskeren" | C5: Dit project neemt de ecologisch destructieve case van mode om te bestuderen hoe belangrijke klimaatvoorvechters in culturele industrieën, zoals groene influencers, mogelijk bijdragen aan polarisatie door burgers met andere achtergronden en opvattingen over duurzaamheid uit te sluiten en te moraliseren. Aangezien de cultuursociologie aantoont dat culturele industrieën gedomineerd worden door witte hogere middenklassen, en klimaatsociologie waarschuwt dat hun klimaatbenadering moraliserend is, verwacht dit project dat duurzaamheid in culturele velden gericht is op de 'havermelkelite', met mogelijke polarisatie en klimaattegenslag tot gevolg. Door deze perspectieven uit de cultuursociologie, klimaatsociologie en politicologie te verbinden, toont dit project (1) wie, in termen van sociaal, cultureel en economisch kapitaal, het duurzaamheidsframe in de mode bepalen, (2) in welke mate en hoe ze burgers met minder kapitaal en andere duurzaamheidsbenaderingen moraliseren en uitsluiten (3) hoe dit leidt tot affectieve polarisatie tot ver buiten de mode. Door kwalitatieve en kwantitatieve methoden te combineren, bestudeert dit project deze vragen in 3 Europese landen (België, Zweden en Italië) met nadruk op sociale media, de plek voor de discursieve constructie van duurzaamheid in de mode en daarbuiten. Dit project toont zo hoe de ongelijkheden van culturele productie uitsluiting en polarisatie rond de klimaatcrisis veroorzaakt en legt de culturele wortels van klimaatpolarisatie bloot. | D5: out | E5: out | F5: 1 | G5: This grant concerns the sociology of sustainability in the fashion industry, studying climate polarisation and cultural inequality — it has no connection to alternative proteins or food science. | H5: =TRUE() -> TRUE | I5: NA | J5: NA | K5: =TRUE() -> TRUE | L5: =FALSE() -> FALSE | M5: =FALSE() -> FALSE | N5: =FALSE() -> FALSE | O5: =FALSE() -> FALSE | P5: ok
A6: grant.15150934 | B6: From Potato Waste to Mycoprotein – A Sustainable Food Innovation | C6: This project aims to upcycle food-grade potato side streams from Orkla, into protein-rich food ingredients via solid-state fermentation with the filamentous fungus Fusarium venenatum (used in Quorn). The resulting mycoprotein is a biomass high in protein and fiber that can serve as a sustainable meat alternative. Our approach tackles two challenges simultaneously: reducing food waste by valorizing agro-industrial by-products, and creating new climate-friendly protein sources. A prior proof-of-concept demonstrated that Fusarium can effectively grow on potato and significantly increase their protein content. Building on this foundation, the plan is to develop the fermentation process further, enabling the next step of implementing the process in pre-pilot scale utilising Biotech Heights, with Orkla, providing side streams in-kind and help align the research with relevant conditions. The project will deliver optimized fermentation protocols, comparisons of different reactor designs, nutritional and sensory evaluation of the resulting protein, and prototype food products incorporating it. The expected outcomes will show a circular “food-from-food-waste” model in which potato residues are converted into a valuable protein ingredient. This aligns with the objectives of the national research program on Food and Climate by developing resource-efficient, circular production systems that reduce environmental impact while enhancing sustainable food supply and industry competitiveness. | D6: in | E6: in | F6: 7 | G6: This grant directly concerns biomass fermentation using Fusarium venenatum (the organism used in Quorn mycoprotein) on potato side streams to produce a protein-rich meat alternative ingredient, which is clearly within the fermentation alternative protein category. | H6: =TRUE() -> TRUE | I6: F | J6: F | K6: =TRUE() -> TRUE | L6: =FALSE() -> FALSE | M6: =TRUE() -> TRUE | N6: =FALSE() -> FALSE | O6: =FALSE() -> FALSE | P6: ok
A7: grant.14933116 | B7: Flexible and Efficient Capture and Bioconversion of CO2 to Materials and Ingredients | C7: The UNICO2RN project aims to demonstrate novel routes to convert biogenic CO2 into ingredients and materials, involving metal organic framework-based capture and purification technology and biotechnological processes based on Hydrogen Oxidizing Bacteria. The modularity and flexibility of the developed processes will be shown through 2 demonstration cases in real industrial settings at TRL 7 for sustainable and efficient production of microbial proteins and PHA, from 2 types of biogenic CO2 sources of different concentration and purity. These new routes bring clear advantages in terms of efficiency, safety, environmental footprint and greenhouse gas emission reductions with respect to benchmarks. Their development to TRL7 will enable their industrialization and thus lead to major positive economic, environmental and social/societal impacts. | D7: in | E7: in | F7: 6 | G7: The project involves Hydrogen Oxidizing Bacteria to produce microbial proteins (single-cell protein via biomass fermentation), which is an alternative protein production method within the fermentation category. | H7: =TRUE() -> TRUE | I7: F | J7: F | K7: =TRUE() -> TRUE | L7: =FALSE() -> FALSE | M7: =TRUE() -> TRUE | N7: =FALSE() -> FALSE | O7: =FALSE() -> FALSE | P7: ok
A8: grant.15162658 | B8: FUNGAL SINGLE CELL PROTEIN FROM MACROALGAL WASTE FERMENTATION: IMPROVING SUSTAINABILITY AND REDUCING THE CARBON FOOTPRINT OF FISH AQUAFEEDS | C8: ALFUNFEED BUSCA TRANSFORMAR LA PRODUCCION DE ALIMENTOS ACUICOLAS MEDIANTE PROCESOS BIOTECNOLOGICOS INNOVADORES. SU OBJETIVO PRINCIPAL ES SUSTITUIR LAS FUENTES DE PROTEINA VEGETAL (PP) EN ALIMENTOS ACUICOLAS PARA ESPECIES DE PECES CARNIVOROS POR PROTEINA UNICELULAR (SCP) DERIVADA DE LA FERMENTACION FUNGICA DE SUSTRATOS A BASE DE MACROALGAS. ALFUNFEED SE BASA EN UN ENFOQUE MULTIDISCIPLINARIO QUE APROVECHA LA EXPERIENCIA DE DIVERSOS CAMPOS. LA FASE INICIAL, LIDERADA POR ODS, SE CENTRA EN EL DESARROLLO DE SCP A PARTIR DE TRES CEPAS DE HONGOS FILAMENTOSOS (NEUROSPORA CRASSA, RHIZOPUS ORYZAE Y FUSARIUM VENENATUM), CONSIDERANDO CUATRO VARIABLES DE PRODUCCION (TEMPERATURA, PH, OXIGENACION Y COMPOSICION DEL MEDIO), LO QUE DA COMO RESULTADO TRES SCP QUE SUSTITUYEN EL 15 % DE PP EN LAS DIETAS DE LUBINA (DICENTRARCHUS LABRAX), COMO MODELO DE ESPECIES DE PECES CARNIVOROS. CON LAS CONDICIONES OPTIMAS DEFINIDAS, SE FORMULARAN TRES DIETAS CON SCP DE CADA CEPA PARA ALIMENTAR A JUVENILES DE LUBINA EN UN ESTUDIO PILOTO QUE INCLUYE PRUEBAS DE ALIMENTACION Y EVALUACION DEL ESTADO INMUNITARIO (CIIMAR), REGULACION DE LA INGESTA DE ALIMENTO, PERFIL NUTRICIONAL Y FUNCION DIGESTIVA (UVIGO), MICROBIOTA INTESTINAL (UTH) Y BIENESTAR DE LOS PECES (UNIVPM). EL SCP MAS PROMETEDOR DEL ESTUDIO PILOTO SE SOMETERA A UN ESTUDIO DE VALIDACION SEGUN LAS RECOMENDACIONES DE LA EFSA CON DIFERENTES NIVELES DE SUSTITUCION DE PP (15-25%) PARA DETERMINAR LA SUSTITUCION OPTIMA SIN COMPROMETER LA ROBUSTEZ DE LOS PECES. TAMBIEN SE EVALUARA EL ANALISIS DE COSTES Y EL IMPACTO AMBIENTAL DEL SCP Y LA PRODUCCION DE ALIMENTOS ACUICOLAS INTEGRALES. LOS SOCIOS DEL CONSORCIO, PROCEDENTES DE PAISES EUROPEOS CLAVE EN ACUICULTURA (GRECIA, ESPAÑA, ITALIA Y PORTUGAL), QUE REPRESENTAN LAS CUENCAS MEDITERRANEA Y ATLANTICA, BUSCAN GENERAR INFORMACION Y DATOS VALIOSOS QUE BENEFICIEN LAS PRACTICAS ACUICOLAS A NIVEL MUNDIAL. ESTE ESFUERZO COLABORATIVO ENCARNA EL MODELO DE LA CUADRUPLE HELICE, INVOLUCRANDO AL MUNDO ACADEMICO, LA INDUSTRIA, EL GOBIERNO Y LA SOCIEDAD CIVIL PARA IMPULSAR EL SECTOR ACUICOLA HACIA LA SOSTENIBILIDAD Y LA RESILIENCIA. EL PROYECTO ENFATIZA LOS PRINCIPIOS DE SOSTENIBILIDAD Y ECONOMIA CIRCULAR AL VALORIZAR LOS DESCARTES DE MACROALGAS COMO UN RECURSO VALIOSO PARA LA PRODUCCION DE SCP. ALFUNFEED CONTRIBUYE AL DESARROLLO DE UNA ECONOMIA OCEANICA MAS EQUITATIVA Y RESPETUOSA CON EL MEDIO AMBIENTE, ALINEANDOSE CON LOS DESAFIOS ESPECIFICOS DESCRITOS EN EL DECENIO DE LAS NACIONES UNIDAS DE LAS CIENCIAS OCEANICAS, COMO EL DESARROLLO SOSTENIBLE DE LA ECONOMIA OCEANICA Y LA SEGURIDAD ALIMENTARIA MUNDIAL, ABORDANDO ASI PROBLEMAS GLOBALES CRITICOS. ALFUNFEED TAMBIEN PRIORIZA LAS ACTIVIDADES DE SENSIBILIZACION Y PARTICIPACION PARA PROMOVER LA CULTURA OCEANICA Y LAS PRACTICAS ACUICOLAS RESPONSABLES. A TRAVES DE INICIATIVAS DE DIFUSION, EL PROYECTO BUSCA LLEGAR A PUBLICOS DIVERSOS Y FOMENTAR UNA COMPRENSION MAS PROFUNDA DE LA IMPORTANCIA DE LA PRESERVACION DE LOS RECURSOS MARINOS. LA IMPLEMENTACION EXITOSA DE ALFUNFEED PODRIA CONDUCIR A LA ADOPCION GENERALIZADA DE FORMULAS DE ALIMENTOS ACUICOLAS SOSTENIBLES A ESCALA INDUSTRIAL. SE HAN IMPLEMENTADO ESTRATEGIAS INTEGRALES DE DIFUSION Y GESTION DE LA PROPIEDAD INTELECTUAL PARA GARANTIZAR LA EXPLOTACION RESPONSABLE DE LOS RESULTADOS DEL PROYECTO, MAXIMIZANDO SU IMPACTO Y FACILITANDO LA TRANSICION HACIA UN SECTOR ACUICOLA MAS SOSTENIBLE. | D8: out | E8: out | F8: 1 | G8: This grant focuses on producing fungal single-cell protein from macroalgal waste for use in aquafeeds (fish feed) for carnivorous fish species, which is explicitly a non-human food/aquafeed application and therefore out of scope. | H8: =TRUE() -> TRUE | I8: NA | J8: NA | K8: =TRUE() -> TRUE | L8: =FALSE() -> FALSE | M8: =FALSE() -> FALSE | N8: =FALSE() -> FALSE | O8: =FALSE() -> FALSE | P8: ok
A9: grant.15166434 | B9: Sustainable production of microbial proteins and their application in value-added cereal goods manufacturing | C9: As demand for animal origin food products increases faster than a global production can offer, novel strategies for carbon-neutral food manufacturing are an important part for diversifying food products and ensuring food self-sufficiency. Nowadays, more than one-fifth of global greenhouse gas emissions come from agriculture. Therefore, the development of alternative proteins and their adoption by consumers is critical to reduce negative climate change. Although plant-based alternatives make up 99% of this market, and most other proteins types (insects or microbes) are still in research and development pushing their greater commercialization at the end of this decade. The market with microbial proteins will be driven mainly by the expected increase in the world population, associated with countries' effort to secure food self-sufficiency and current trends in food consumption, which won’t be reachable by conventional agriculture/economy. Among the advantages of microbial proteins is their simple production, which includes a very short production time compared to the duration of growing crops, or raising animals, and also lower land and water requirements. Moreover, already available and producible mycoproteins (used as whole-cell products; without necessity of protein concentration or isolation) contain 40 % protein, have a high fibre content, limited saccharides content and don’t contain cholesterol, which makes them nutritionally more interesting compared to „classic“ proteins. The presented project focuses on potential production of microbial proteins using filamentous fungi and yeast by utilization of waste byproducts from industry. The main waste side-stream would be corn mash (form ethanol production) and glycerol (from biodiesel production). Returning of such waste into production has significant environmental effect. Furthermore, the produced biomass will be employed into process of bakery good production. Thus the effect of usage of these alternative would b | D9: in | E9: in | F9: 7 | G9: The grant focuses on biomass fermentation using filamentous fungi and yeast to produce microbial proteins (mycoprotein) as alternative protein ingredients for food applications, which is clearly within scope. | H9: =TRUE() -> TRUE | I9: F | J9: F | K9: =TRUE() -> TRUE | L9: =FALSE() -> FALSE | M9: =TRUE() -> TRUE | N9: =FALSE() -> FALSE | O9: =FALSE() -> FALSE | P9: ok
A10: grant.14933075 | B10: Upcycling mushroom waste to replace animal derived chemicals | C10: Animal-derived materials are surprisingly widespread in everyday products. For example, in the cosmetics, pharmaceutical and agrochemicals industries, squalene (from shark liver oil), chitin/chitosan (from crustaceans) and animal-derived proteins and fats are widely exploited despite growing ethical and sustainability concerns. Fungal biomass is rich in chitin, while recent advances in fermentation technologies offer opportunities to convert fungal glucans into microbial proteins, oils and even triterpenes such as squalene. However, scalability is a major challenge, due to the limited availability of clean fungal biomass and competition with food/feed value chains. Moreover, oil production using existing fungal fermentation routes is limited to low-value triglycerides, and efficient product extraction remains a bottleneck. Feedstock diversification is needed, alongside innovation towards higher-value products and more efficient processes. The production of edible mushrooms produces ~189M tpa of mycelium rich wastes, contaminated with lignocellulosic growth substrate. This contamination makes these wastes unsuitable for food/feeds, and incompatible with existing valorisation approaches. MYCOCIRCLE will focus on this challenging feedstock, developing new technologies including an enzymatic fractionation process, two parallel fermentation routes, and novel enzymatic chitin conversion reactions. The resulting product streams, including fungal chitosan/chito-oligosaccharides, a high-value squalene-rich microbial oil, and microbial proteins, will be validated as replacements to animal derived materials in cosmetic and agrochemical applications. The MYCOCIRCLE consortium represents the entire value chain, from feedstock producers (SYLVAN, KORONA) to industrial biotechnology companies (GST), and end users (GI, THGL). This value chain will be supported by world experts in biomass valorisation, enzymatic processing, and SSbD development: TUM, SINTEF, NMBU, SLU and IDENER. | D10: out | E10: out | F10: 2 | G10: The grant focuses on upcycling mushroom waste to produce chitin/chitosan, squalene-rich oils, and microbial proteins for cosmetic and agrochemical applications — not for human food or as substitutes for animal-derived food products. | H10: =TRUE() -> TRUE | I10: NA | J10: NA | K10: =TRUE() -> TRUE | L10: =FALSE() -> FALSE | M10: =FALSE() -> FALSE | N10: =FALSE() -> FALSE | O10: =FALSE() -> FALSE | P10: ok
A11: grant.14486646 | B11: Rim-kinases in fungal secondary metabolism and pathogenicity | C11: Molds play a variety of ecological roles on our planet, especially in natural nutrient cycles and as pathogens of plants and animals. Of particular interest is their ability to produce a wide variety of small, bioactive molecules. One example of a very useful molecule is the antibiotic penicillin, which has saved millions of lives to date. But there are also dangerous molecules, such as toxins produced by molds, that can contaminate our food and thereby threaten consumer health. So the final goal must be to precisely understand the molecular and cellular programs in those fungi and thus develop natural solutions against fungal infections. Our previous research has shown that epigenetic processes regulate toxin production, but also a specific kinase - a regulatory protein that can chemically modify other proteins in its environment - plays a decisive role. In a previously unknown way, it is able to transmit a starvation signal in the cell, which ultimately leads to a complete change in the cellular metabolism and thereby activates the genetic machinery for toxin formation. In this project, we are now addressing the question of exactly how the starvation signal is processed by the fungal cell so that mycotoxins are formed. For this, we are using as experimental systems a conventional mold that is present ubiquitously in nature and buildings (Aspergillus) and a fungus that is considered one of the most important pathogens in crop plants worldwide (Fusarium). The entire genetic response of both fungi at the RNA level and at the protein level will be analyzed molecularly, biochemically and bioinformatically during different stages of their life cycles. In addition, those proteins whose function is regulated by the kinase should be identified. In this way, the signaling pathway from nutrient deficiency from the cell surface to the genetic activation of toxin production in two different molds should be elucidated as completely as possible. Ultimately, the results of this research could close a gap in the fundamental understanding of cellular processes during toxin production in mold fungi. This knowledge can then be used to develop new control strategies to ward off plant diseases and prevent biological contamination of food. | D11: out | E11: out | F11: 1 | G11: This grant concerns fungal pathogenicity and mycotoxin production mechanisms in Aspergillus and Fusarium, with no connection to alternative protein development or production. | H11: =TRUE() -> TRUE | I11: NA | J11: NA | K11: =TRUE() -> TRUE | L11: =FALSE() -> FALSE | M11: =FALSE() -> FALSE | N11: =FALSE() -> FALSE | O11: =FALSE() -> FALSE | P11: ok
A12: grant.14878552 | B12: Designing a professional-secretory synthetic endoplasmic reticulum in yeasts and plant cells | C12: The endoplasmic reticulum (ER) is the key organelle for folding and processing of secretory proteins. Inefficient folding and secretion are a major challenge in production of recombinant proteins needed as biopharmaceuticals or for securing future food requirements. In most non-mammalian cells, the ER is spatially limiting these processes. SynthER aims to go beyond mere physical ER expansion by tailoring functionality through orthogonal and combinatorial expression of synthetic ER shaping proteins in yeast and plant cells. Inspired by professional secretory mammalian cells, SynthER envisages to biomimic their stacked ER sheet and luminal architecture in yeast and plants. The new morphologies will be monitored by a wide range of microscopic methods and quantitative image analyses, and their impact on the quality and quantity of secreted recombinant proteins will be determined.Furthermore, synthetic ER exit vesicles (SERV) will be designed to deliver their protein cargo directly to the plasma membrane, bypassing the often adverse functions of the Golgi and vacuole. SERVs shall be programmable synthetic circuits, that can be expressed on demand.Taken together, SynthER will develop novel cell factory concepts that represent a significant advance to the state of the art. Synthetic endomembrane engineering addresses a timely research topic through a pioneering synthetic biology approach with significant potential for advancing both the scientific understanding of secretory pathway plasticity and impacting technological applications, thus benefiting medicine and biotechnology.Our ground-breaking interdisciplinary combination of cross-kingdom molecular and cell biology in microbes and whole plants together with advanced microscopy and engineering unlocks new scientific opportunities and expands the toolkit of synthetic cellular design. | D12: out | E12: out | F12: 2 | G12: This grant focuses on engineering the endoplasmic reticulum in yeast and plant cells to improve recombinant protein secretion for biopharmaceutical and general biotechnology applications, with no specific mention of alternative protein products or ingredients intended to substitute animal-derived foods. | H12: =TRUE() -> TRUE | I12: CC | J12: NA | K12: =FALSE() -> FALSE | L12: =FALSE() -> FALSE | M12: =FALSE() -> FALSE | N12: =FALSE() -> FALSE | O12: =FALSE() -> FALSE | P12: ok
A13: grant.15078549 | B13: SEAlgaePower － Sustainable development of microalgae-based ingredients using waste streams from aquaculture and seafood processing industry as feedstock | C13: The overall objective of the SEAlgaePower project is to develop innovative microalgae-based technologies to clean wastewater from the aquaculture and seafood processing industry while simultaneously producing biomass for novel ingredients in a sustainable way. The specific aims are to: (i) select suitable microalgae species from the North and the Mediterranean Sea in a lab-scale cultivation system based on the ability to grow in different wastewater types; (ii) develop protocols for pilot-scale algae cultivation and wastewater cleaning; (iii) develop biorefinery protocols for protein, lipid and carbohydrate recovery from the microalgal biomass; (iv) develop microalgae-based product prototypes and ingredients; (v) assess environmental and socio-economic aspects associated with the project solutions for wastewater cleaning, microalgae cultivation and biomass valorisation, and (v) maximise the project impact, visibility, and legacy. In this project, UGOT will employ a two-stage cultivation in lab-scale for screening of microalgae growth in wastewater from salmon aquaculture and process waters from the seafood industry. Chalmers will analyse the biochemical composition of the various water types and will also contribute to biorefining of microalgal biomass by extracting protein for development of alternative food protein ingredients. RISE will use polysaccharide-enriched fractions from the biorefinery to develop fibre prototypes for use in wound care and regenerative medicine. | D13: in | E13: in | F13: 5 | G13: The project explicitly aims to extract protein from microalgal biomass for development of alternative food protein ingredients, which falls under fermentation/biomass fermentation scope, though the project also includes out-of-scope elements such as wastewater treatment, aquafeed, and medical applications (wound care, regenerative medicine). | H13: =TRUE() -> TRUE | I13: F | J13: F | K13: =TRUE() -> TRUE | L13: =FALSE() -> FALSE | M13: =TRUE() -> TRUE | N13: =FALSE() -> FALSE | O13: =FALSE() -> FALSE | P13: ok
A14: grant.15201530 | B14: 24BBR: Integrated bioinformatics resources for fungal and oomycetes pathogens of plants | C14: The spread of fungal and oomycete species presents significant challenges for current and future efforts in global food security, and threatens important non-food plant species in the UK ecosystem. Monoculture farming, changing climate and international trade are driving phytopathogen expansion into new geographical regions and new hosts. Discovery and translational research is increasingly reliant on genomic and other large-scale technologies, for example to identify genes implicated in invasion, pathogenesis, and plant responses/immunity. Genomes, population diversity data, and genomic-scale gene/protein expression datasets are now available in archival repositories for many phytopathogens, but, these static repositories do not support robust updating, querying and data-mining, making them difficult to exploit even by groups with extensive bioinformatics expertise. Our teams are responsible for the development and dissemination of two major international genome database resources: Ensembl and VEuPathDB (the Eukaryotic Pathogen, Vector and Host Knowledgebase) – both recognized as Global Core Biodata and Core Elixir Data resources, reflecting their international importance. Ensembl subsites relevant to plant health include Ensembl Fungi, Ensembl Protists (including oomycetes) and Ensembl Plants. Key features include a powerful, customisable genome browser supporting community tracks, phylogenetic gene trees displaying ortholog and paralog relationships across taxa, and visualisation of synteny, driven by whole genome alignments. Ensembl also provides production-grade genome annotation and transcriptome analysis, used in-house and integrated into the VEuPathDB pipeline to maximise efficiency and consistency, and minimise duplication of effort. VEuPathDB includes subsites focussed on infectious disease pathogens, including human and animal diseases prioritised by past/current funders, but also including plant pathogens with extensive functional data. The FungiDB component supports hundreds of species, including scores of important plant pathogens (Blumeria, Botrytis, Colletotrichum, Fusarium, Magnaporthe, Melampsora, Phytophthora, Puccinia, Ustilago, Zymoseptoria, etc) as well as taxa important in the food production and biotech sectors. In addition to gene/genome browsers, this knowledgebase provides powerful web-based tools and APIs for data integration and exploration, enabling users to ask their own questions in silico, seeking (for example) plant pathogen effectors based on protein motifs, gene/protein expression timing, signatures of selection and epigenetic marks, gene set enrichment, and leveraging orthology for cross-species functional inference based on phenotypic information. The HostDB component supports simultaneous interrogation of combined host-pathogen datasets. These proven, cost-effective resources have coordinated efforts for years, but have not previously benefited from dedicated funding to focus on phytopathogens. We propose to: Load or update 80+ genomes from archival repositories, using Ensembl annotation pipelines to build new or improve gene annotations, and the Apollo interface to capture expert knowledge from the community. Generate orthology mappings across taxa, protein domain annotations for all genomes, and further develop/deploy fungal-specific annotation tools focused on virulence factors, biosynthetic gene clusters and, protein structure-driven discovery of new or updated functions. Process/load 200+ functional genomic datasets and 30-40 plant response to infection datasets, enabling user-driven queries to identify genes of interest (e.g. for specific plant diseases), including support for analysis and visualisation of host-pathogen interactions (e.g. co-expression networks). Building on a history of successful collaboration and community engagement, outreach efforts will obtain community input on dataset prioritisation, and promote/explain effective use of informatics tools to advance research. FAIR data access is a priority; all datasets, tools and code will be fully open source and freely available through multiple routes (web browser, API, downloads) in support of plant health research. | D14: out | E14: out | F14: 1 | G14: This grant concerns bioinformatics database resources for fungal and oomycete plant pathogens to support plant health and food security research, with no connection to alternative protein development, production, or any related societal/environmental analysis. | H14: =TRUE() -> TRUE | I14: NA | J14: NA | K14: =TRUE() -> TRUE | L14: =FALSE() -> FALSE | M14: =FALSE() -> FALSE | N14: =FALSE() -> FALSE | O14: =FALSE() -> FALSE | P14: ok
A15: grant.15195928 | B15: 3D Bioprinting of cultivated meat: Biopolymer matrices supporting formation of muscle fibers in vitro | C15: Due to disruptive effects of conventional mass meat production – on climate, animals and human health, I work towards sustainable food for the next generation while maintaining taste, protein content and texture of real meat. Combining natural food ingredients, cells and tunable recombinant proteins, we may be able to grow whole beef cuts under controlled, animal-free conditions; innovative bioprinting techniques allow scale-up and nutrient supply in larger tissues. By adjusting the protein composition, I define the formation of edible muscle fibers. Improving the quality of cellular agriculture accelerates development of products with a real-world impact. | D15: in | E15: in | F15: 7 | G15: This grant explicitly focuses on cultivated meat, including scaffolding/biopolymer matrices, bioprinting techniques, and in vitro muscle fiber formation for growing beef cuts under animal-free conditions. | H15: =TRUE() -> TRUE | I15: CM | J15: CM | K15: =TRUE() -> TRUE | L15: =FALSE() -> FALSE | M15: =FALSE() -> FALSE | N15: =TRUE() -> TRUE | O15: =FALSE() -> FALSE | P15: ok
A16: grant.15051286 | B16: SEAlgaePower: Sustainable development of microalgae-based products using waste streams from aquaculture and seafood processing industry | C16: The fast-growing land-based aquaculture and seafood processing industry generate large amounts of nutrient-rich wastewater, posing a high cost for discharge and environmental impact. At the same time, there is an increasing demand for new resources intended for carbon-neutral production of food, material and energy. The ability of microalgae to perform photosynthesis and efficiently convert dissolved nutrients into valuable biomass could contribute to solving this dual problem. The overall objective of SEAlgaePower is to develop microalgae-based technologies to clean wastewater from the aquaculture and seafood processing industry while simultaneously producing biomass for novel ingredients in a sustainable way. The specific aims are to: (i) select suitable microalgae species/strains from the North and the Mediterranean Sea in a lab-scale cultivation system based on the ability to grow in different wastewater types; ((ii) develop pilot-scale algae cultivation protocols and wastewater cleaning; (iii) develop biorefinery protocols for protein, lipid and carbohydrate recovery from the microalgal biomass; (iv) develop microalgae-based prototypes and ingredients; (v) assess environmental and socio-economic aspects associated with the project solutions on wastewater cleaning, microalgae cultivation and biomass valorisation, and (v) maximise the project impact, visibility, and legacy. The SEAlgaePower consortium, coordinated by the University of Gothenburg, consists of thirteen partners from seven countries: Chalmers University of Technology, NORCE Norwegian Research Centre, University of Aveiro, University of Palermo, Sustainable Innovation Technology Services, RISE Research Institutes of Sweden, Nordicflexhouse, Danish Technological Institute, Universidade de Sao Paulo, Norwegian Institute of Bioeconomy Research, Klädesholmen Seafood, and RAGN-SELLS HAVBRUK. | D16: in | E16: in | F16: 5 | G16: The project develops microalgae biomass as a source of protein, lipid, and carbohydrate ingredients for novel food products, which falls under biomass fermentation/microalgae as an alternative protein source, though the application to alternative proteins specifically is implied rather than explicitly stated and the project also covers non-food applications (materials, energy, wastewater treatment). | H16: =TRUE() -> TRUE | I16: PB | J16: F | K16: =FALSE() -> FALSE | L16: =FALSE() -> FALSE | M16: =TRUE() -> TRUE | N16: =FALSE() -> FALSE | O16: =FALSE() -> FALSE | P16: ok
A17: grant.14881068 | B17: Expanding the CRISPR Toolbox for Engineering Synthetic Oscillators in Bacteria | C17: Synthetic biology offers innovative solutions to pressing global challenges such as climate change, food security, environmental degradation, and public health crises. Synthetic gene regulatory networks play a key role in harnessing the power of engineered biological systems. However, the inherent constraints of commonly used transcription factors, such the burden they place on the host metabolism, insufficient orthogonality, modularity and programmability, limit progress in engineering complex synthetic circuits for precise and programmable control of gene expression. CRISPR (clustered regularly interspaced short palindromic repeats)-based synthetic circuits, where interactions between different network nodes are implemented with CRISPR interference (CRISPRi) and CRISPR activation (CRISPRa), circumvent some of those shortcomings and make circuit design more modular and scalable. Despite the enormous potential, research on how to engineer such circuits in bacteria is still at its beginning. I propose to further improve the toolbox of bacterial CRISPR-based dynamic synthetic circuits and to apply it to build CRISPR-based synthetic oscillators in Escherichia coli. Oscillatory circuits exhibit periodic fluctuations in gene expression and are pervasive in living organisms, with examples in cell cycles, circadian rhythms, metabolic activities, and pattern formation during multicellular development. Diverse applications of synthetic oscillators have already been proposed, ranging from fundamental research, bioproduction, biological computing and therapeutic applications to biological timers.We will establish a collection of synthetic CRISPRi-based oscillators with different Cas proteins and circuit topologies. The collection will span oscillators differing in their properties, such as amplitude, frequency, and accuracy. We will also go beyond the-state-of-the-art in integrating CRISPRi and CRISPRa in the same circuit. Finally, we will assess and if necessary, improve the evolutionary stability of the built CRISPR-based oscillators. To reach our objectives, we will apply a combination of experimental approaches (including optogenetics, microfluidics, and evolutionary experiments) and computational modelling.Our work will be at the forefront of synthetic biology by developing novel CRISPRi/a systems, applying them to synthetic oscillators and enabling the combination of multiple circuits within a single cell. Ensuring the stability of our circuits will enhance their future applications in fields as diverse as biotechnology, medicine, biological sensors, engineered living materials and biocomputing. The results of this project are also highly relevant to developmental biology, where temporal oscillations play a critical role in pattern formation during embryonic development. In summary, this project holds potential to unlock new possibilities in both fundamental biology and applied science. | D17: out | E17: out | F17: 1 | G17: This grant concerns CRISPR-based synthetic gene regulatory circuits and oscillators in bacteria for general synthetic biology applications, with no connection to alternative protein production or any alternative protein product. | H17: =TRUE() -> TRUE | I17: NA | J17: NA | K17: =TRUE() -> TRUE | L17: =FALSE() -> FALSE | M17: =FALSE() -> FALSE | N17: =FALSE() -> FALSE | O17: =FALSE() -> FALSE | P17: ok
A18: grant.14950468 | B18: Mechanisms of enoyl reductase recruitment and iterative module suppression in trans-acyltransferase polyketide synthases | C18: Bacteria are remarkable chemists capable of assembling complex molecules that enter cells and bind biomolecular targets with high affinity and selectivity. Consequently, bacterial natural products have wide-ranging applications in medicine (as antibiotics, anticancer agents, and immunomodulators) and agriculture (as insecticides, fungicides, and herbicides). How the "blind watchmaker" of evolution creates structurally diverse molecular architectures is a key question in contemporary biosynthesis research. In this proposal, we seek to illuminate how enoylreductase (ER) enzymes contribute to structural diversification of an important class of bacterial natural products called polyketides by understanding how trans-acting ERs are recruited to and suppress iteration in specific modules of trans-acyltransferase (trans-AT) polyketide synthases (PKSs). The specific objectives of our proposal are: Establish the structural basis for productive interaction between trans-acting ERs and specific acyl carrier protein domains in trans-AT PKSs. Elucidate the substrate tolerance and catalytic mechanism of trans-acting ERs involved in the assembly of the antibiotic gladiolin and the anticancer agent gladiostatin. Investigate the generality and molecular mechanism for suppression of trans-AT PKS module iteration by trans-acting ERs. The knowledge gained from this interdisciplinary research will enable the development of bioengineering approaches to alter the degree of unsaturation and chain length of polyketide natural products, which often require structural modification to optimise them for therapeutic or agricultural application. Structural modification of polyketides using synthetic chemistry is challenging due to their complexity. Moreover, such methods rely on non-renewable petrochemical feedstocks, are energy intensive, create environmentally damaging byproducts, and are expensive. In contrast, structural modification of polyketides via bioengineering enables optimised derivatives to be produced via fermentation, which is cheaper, more energy efficient, has lower environmental impact, and utilises sustainable plant-derived feedstocks. This research is directly relevant to the Engineering Biology theme of BBSRC's Transformative Technologies priority of the Advancing the Frontiers of Bioscience Discovery high level objective. It also aligns with the Sustainable Agricultural Systems focus area of the Bioscience for Sustainable Agriculture and Food priority, the Production of More Sustainable Products focus area of the Bioscience for Advanced Manufacturing and Clean Growth priority, and the Combatting Antimicrobial Resistance research priority of the Bioscience for an Integrated Understanding of Health priority of BBSRC's Tackling Strategic Challenges high level objective. | D18: out | E18: out | F18: 1 | G18: This grant concerns fundamental biochemistry of polyketide synthases for antibiotic and anticancer agent development, with no connection to alternative proteins or animal product substitution. | H18: =TRUE() -> TRUE | I18: NA | J18: NA | K18: =TRUE() -> TRUE | L18: =FALSE() -> FALSE | M18: =FALSE() -> FALSE | N18: =FALSE() -> FALSE | O18: =FALSE() -> FALSE | P18: ok
A19: grant.14959694 | B19: Samenwerking tussen methanotrofen en sulfide oxiderende bacteriën om uit biogas hoogwaardig eiwitrijk aquacultuur voeder te produceren. | C19: Duurzame voedselvoorziening voor de groeiende wereldbevolking is een belangrijke uitdaging in de 21e eeuw. Aquacultuur kan hierin een centrale rol spelen, maar gebruikt momenteel vismeel en andere dierlijke eiwitten als voeder om een eiwitrijk product te genereren met alle essentiële aminozuren voor de mens. Er is dus nood aan de ontwikkeling van nieuwe, duurzame voedingsbronnen uit herwonnen, hernieuwbare grondstoffen. Hier zullen we biogas gebruiken, geproduceerd uit afval van recirculerende aquacultuursystemen, om hoogwaardige microbiële eiwitten te produceren. We zullen een nieuw consortium creëren van methaan-oxiderende (MOB) en sulfide-oxiderende (SOB) bacteriën die rijk zijn aan alle essentiële aminozuren. Eerst zullen we MOB combineren met SOB door (1) het individueel en samen opgroeien van pure MOB- en SOB-culturen en (2) het (samen) aanrijken van de SOB en MOB. Vervolgens zullen de meest optimale MOB-SOB-partnerschappen, op basis van het essentieel aminozuurgehalte, worden gebruikt om nieuwe macrostructuren of “biovlokken” te creëren. Vervolgens zullen we deze MOB-SOB microbiële biomassa gebruiken als voeder voor Artemia. Ten slotte zullen we de MOB-SOB-biomassa direct (als biovlokken) en indirect (als Artemia gekweekt op MOB-SOB-biomassa) gebruiken als voeder om garnalen te kweken tot een voedselbron, rijk aan alle essentiële aminozuren. De hier gegenereerde kennis zal het mogelijk maken om naar circulariteit in de aquacultuur te evolueren. | D19: out | E19: out | F19: 2 | G19: This grant concerns the production of microbial protein (from methanotrophs and sulfide-oxidizing bacteria) as aquafeed for shrimp and Artemia aquaculture, not as a substitute for animal-derived foods for human consumption, placing it outside the scope of alternative proteins for human food. | H19: =TRUE() -> TRUE | I19: NA | J19: NA | K19: =TRUE() -> TRUE | L19: =FALSE() -> FALSE | M19: =FALSE() -> FALSE | N19: =FALSE() -> FALSE | O19: =FALSE() -> FALSE | P19: ok
A20: grant.14955094 | B20: Demonstrating a cost competitive, sustainable, scalable intensified micro-algae bioprocess for the production of food-grade medium value, carbon negative Ingredients exceeding Market Standards | C20: Micro-Algae offer a solution to many of the European bioeconomy needs. Nevertheless, significant challenges still exist to their acceptance on the market, including organoleptic and functionality challenges. CleanAlgae2Value seeks to unlock such potential via a cascading approach to white-microalgae-derived medium-price ingredients, including protein isolates, oils, natural pigments and starch. The project will build and operate a replicable “upgrading-module” to drastically enhance relevant biorefineries performance via a cost-competitive, sustainable, and scalable microalgae fractionation and valorisation process for producing food-grade, medium-value, carbon-negative ingredients that exceed market standards. More specifically, the project will prove the effectiveness and efficiency of a “Micro-Algae Biorefinery Upgrade Module” (MABUM), able to unlock productions of protein isolates, protein concentrates, starch-rich fraction and oils (respectively 2, 1.3, 3.98 and 1.8 tons) to be validated into 15 prototypes, 13 for food and 2 for bio-packaging markets. The project will do so while increasing operative margins, by decreasing “value-normalised” CAPEX and OPEX, also thanks to modelling optimisation, contributing to market penetration. Importantly, CleanAlgae2Value would also benefit from synergies with a recently granted EIC Accelerator project, which focuses on upstream algae production from CO2 via SOL two-step fermentation, using solely CO2 as carbon source. The project brings together 16 organizations from 9 European countries, collaborating with end-users to produce added value ingredients. Holistic evaluations, including both empirical (surveys, workshops) and horizontal considerations (LCA, TEA, SSbD), will allow for the assessment of market acceptance and environmental, economic and societal sustainability, as well as further support and boost the project DCE activities and pathways towards EFSA positive opinion for those ingredients that still require it. | D20: in | E20: in | F20: 6 | G20: The grant focuses on microalgae biorefinery processes to produce protein isolates and concentrates as food-grade ingredients, which falls under fermentation/biomass fermentation (microalgae as a protein source), with explicit food applications and LCA/TEA assessments relevant to alternative proteins. | H20: =TRUE() -> TRUE | I20: PB | J20: F | K20: =FALSE() -> FALSE | L20: =FALSE() -> FALSE | M20: =TRUE() -> TRUE | N20: =FALSE() -> FALSE | O20: =FALSE() -> FALSE | P20: ok
A21: grant.15196386 | B21: OPTIPRO: Optimizing protein production in Bacillus | C21: Bacillus species are widely used for the industrial-scale production of enzymes used in e.g. washing powders, food and agricultural applications and in the pharmaceutical and biotechnological industry. However, the range of enzymes that are secreted at high-levels by these bacteria is currently limited. The University of Amsterdam, VU University, and 4 biotech firms are collaborating to address this problem by combining deep sequencing-based transposon mutagenesis with novel high-throughput single cell selection techniques to improve the production of a diverse set of commercially relevant enzymes. This project will provide valuable knowledge to optimize enzyme secretion in Bacillus species, and other microbial production platforms. | D21: out | E21: out | F21: 1 | G21: This grant focuses on optimizing enzyme secretion in Bacillus species for industrial applications (washing powders, pharmaceuticals, agriculture), with no stated application in alternative protein production or substitution of animal-derived foods. | H21: =TRUE() -> TRUE | I21: NA | J21: NA | K21: =TRUE() -> TRUE | L21: =FALSE() -> FALSE | M21: =FALSE() -> FALSE | N21: =FALSE() -> FALSE | O21: =FALSE() -> FALSE | P21: ok
A22: grant.14751838 | B22: Secondary treatment of RAS water and nutrient revalorization by site-specific microbial biofilm | C22: Rising demand for nutritious fish and seafood, coupled with declining wild catches, has made aquaculture the fastest growing sector in food production. Two of the largest current bottlenecks for sustainable increased production of farmed fish are 1) identifying alternative and sustainable sources of protein and fatty acids for fish feed, and 2) finding new solutions for sustainable treatment of side streams in recirculating aquaculture systems (RAS). To steer away from current unsustainable practices innovative and sustainable ideas focusing on re-valorisation and bio-circularity needs to be implemented. In this project we propose the integration of a microalgal reactor as a modular process unit that can be included in RAS facilities, to upcycle side streams from the fish farming and generate a valuable biomass that can be valorized in the agri-food sector. In the module we will growth a naturally selected, benthic biofilm community arising from a mixture of organisms already present in the nitrogen (N)-rich RAS water of the facility. This benthic community, native to the RAS water, can effectively capture nutrients in the water phase. With an interdisciplinary team of chemist, biologist, engeeniers and modellers we plan to build and run pilots at two industrial RAS sites and evaluate the production yield and the composition of recovered microalgal biomass for different end-uses. We will explore where this system can be integrated in the process scheme of a RAS facility and evaluate the footprint and costs connected to running it. Once harvested the biomass will be evaluated for suitability as a feed ingredient (for chicken or salmon) or directly as food for snails. Biggest challenges this project will help solve are related to the high costs of productivity, feasibility of integration of the system in a RAS facility, evaluation the environmental footprint and reproducibility/consistency of recovered biomass between different farms. | D22: out | E22: out | F22: 2 | G22: This grant focuses on microalgal biofilm for treating aquaculture wastewater and producing biomass for animal feed (chicken, salmon) or snail food, not for human alternative protein products. | H22: =TRUE() -> TRUE | I22: NA | J22: NA | K22: =TRUE() -> TRUE | L22: =FALSE() -> FALSE | M22: =FALSE() -> FALSE | N22: =FALSE() -> FALSE | O22: =FALSE() -> FALSE | P22: ok
A23: grant.14932889 | B23: Tailored immune receptor engineering for resistance against rice blast disease | C23: Fungal pathogens are a major constraint to crop production worldwide. As part of their virulence strategy, pathogens secrete effector proteins to manipulate host machinery and promote colonization. Effectors can be recognized by host immune receptors that launch a robust immune response that restricts pathogen spread. Pathogens quickly overcome immune receptor-mediated resistance by modifying or losing effectors to evade detection. In the Tailored Immunity project, our aim is to massively expand the effector recognition specificity of immune receptors to provide durable disease resistance against the fungus Magnaportha oryzae, the causal agent of blast disease, and one of the most destructive diseases of rice. In order to do this, we will use a host-target guided engineering approach to replace the heavy-metal associated (HMA) effector binding domain of nucleotide-binding and leucine-rich repeat domain (NLR) immune receptors from rice with the HMA domain of host proteins that are targeted by multiple M. oryzae effectors. We hypothesize that introducing the HMA domain of the newly identified effector hubs to NLRs will allow the simultaneous recognition of numerous effectors. As the pathogen would need to undergo complex mutation pathways to escape this detection, and since changing multiple effectors is presumably associated with high fitness costs, we expect that this new strategy will generate resistance that the pathogen has difficulties to overcome and that is therefore highly durable. By these means, this ambitious project promises to provide a proof-of-concept for a new knowledge-guided and powerful approach for the creation of durable immune receptors that will be highly valuable for the improvement of a large range of crop species. In addition to boosting host immunity, the Tailored Immunity project will provide invaluable information about how immune receptors can be engineered for tailored disease resistance in crops. | D23: out | H23: =FALSE() -> FALSE | I23: NA | J23: CC | K23: =FALSE() -> FALSE | P23: parse_error | Q23: no structured output
A24: grant.15172132 | B24: The uniqueness of the genetic diversity of Slovak beans: Innovative approaches to increase resistance to phytopathogenic fungi and viruses | C24: Common bean (Phaseolus vulgaris L.) is one of the key protein crops, playing a crucial role in agriculture and food security. The project focuses on utilizing a unique collection of Slovak bean cultivars, landraces, and breeding material of Phaseolus vulgaris L., maintained in the Slovak Gene Bank. These cultivars represent not only an essential part of natural and cultural heritage but also a valuable genetic resource that can be used to improve agronomic traits of beans, such as resistance or increased tolerance to phytopathogenic fungi and viruses. The biological experiments will be preceded by a detailed assessment of the current distribution and molecular diversity of selected bean pathogens in Slovakia (fColletotrichum lindemuthianum, potyviruses). Representative isolates of these pathogens will be used to study pathogen-plant interactions. The project combines innovative approaches, incorporating modern biotechnological techniques such as RT-qPCR and high-throughput sequencing, along with inoculation experiments conducted under controlled and field conditions. The aim of the research is to obtain missing original and practical data contributing to the improvement of bean resistance to selected phytopathogenic fungi and viruses. These findings can support more sustainable agriculture and the breeding of new bean cultivars with enhanced agronomic traits. | D24: out | E24: out | F24: 1 | G24: This grant focuses on agronomic research on bean disease resistance (fungal and viral pathogens) with no stated application to protein extraction, processing, or alternative protein product development. | H24: =TRUE() -> TRUE | I24: NA | J24: NA | K24: =TRUE() -> TRUE | L24: =FALSE() -> FALSE | M24: =FALSE() -> FALSE | N24: =FALSE() -> FALSE | O24: =FALSE() -> FALSE | P24: ok
A25: grant.14611344 | B25: Mucin glycans as key mediators of gut health | C25: The human gut is populated by helpful bacteria that assist food digestion. To support these bacteria, the intestine produces a mucus slime layer consisting of proteins and sugar molecules. Gut bacteria break down mucus and they eat the freed proteins and sugars. Excessive mucus breakdown destroys the mucus layer leading to inflammation and Crohn’s disease. Many aspects of how bacteria degrade human mucus are unknown. Therefore, novel molecular probes and methods for measuring bacterial mucus breakdown will be developed. Moreover, molecules that stop excessive mucus degradation will be created to reduce inflammation in the gut. | D25: out | E25: out | F25: 1 | G25: This grant concerns gut health, mucin glycans, and bacterial mucus degradation related to inflammation and Crohn's disease, with no connection to alternative proteins or substitutes for animal-derived foods. | H25: =TRUE() -> TRUE | I25: NA | J25: NA | K25: =TRUE() -> TRUE | L25: =FALSE() -> FALSE | M25: =FALSE() -> FALSE | N25: =FALSE() -> FALSE | O25: =FALSE() -> FALSE | P25: ok
A26: grant.15197259 | B26: Interplay of sHsp sequestrases and protein disaggregases in extreme bacterial stress resistance | C26: Bacteria as single-celled organisms are particularly exposed to environmental stress conditions challenging protein homeostasis. This demands for a sophisticated protein quality control (PQC) network protecting cells from protein unfolding and aggregation. Small heat shock proteins (sHsps) are central components of PQC systems. The bacterial sHsp member IbpA binds misfolded proteins to sequester them in IbpA/substrate complexes. Dissociation and reactivation of IbpA-bound substrates requires the activity of a disaggregation activity executed by the canonical Hsp70/ClpB disaggregase. Bacteria can acquire additional sHsps and protein disaggregases raising the question whether the expansions of their sHsp and disaggregase repertories are functionally linked. The presence of novel sHsps might also allow for optimized adaptation to environmental growth conditions and provide enhanced stress resistance. Here, we will use the major pathogen Pseudomonas aeruginosa as model system to dissect whether and how the expansion of sHsp and disaggregase repertoires is linked to the acquisition of extreme stress resistance protecting bacteria against temperature-based sterilization protocols used in food industry and clinics. P. aeruginosa harbors Hsp20 and ClpG as novel sHsp and disaggregase members. Both genes are coorganized on the mobile tLST island, which provides extreme stress resistance. Our initial data indicate specific Hsp20 features, separating it from the canonical IbpA sHsp. These features include a temperature-based activity control and a specific cooperation with the ClpG disaggregase. By combining our complementary expertises in chaperone biochemistry and P. aeruginosa genetics and physiology we plan to: (1) Determine the substrate pools of IbpA and Hsp20 under diverse stress conditions and dissect the mechanistic basis of the differing sHsp substrate specificities. (2) Determine the consequences of extreme temperatures on sHsp activities and stabilities and their individual contributions to bacterial survival at extreme temperatures. (3) Determine the mode of the selective interplay of sHsps and protein disaggregases and the relevance of sHsp/disaggregase cooperations in bacterial resistance against severe stress. | D26: out | E26: out | F26: 1 | G26: This grant concerns bacterial protein quality control mechanisms and stress resistance in Pseudomonas aeruginosa, with no connection to alternative proteins or food protein substitutes. | H26: =TRUE() -> TRUE | I26: NA | J26: NA | K26: =TRUE() -> TRUE | L26: =FALSE() -> FALSE | M26: =FALSE() -> FALSE | N26: =FALSE() -> FALSE | O26: =FALSE() -> FALSE | P26: ok
A27: grant.15162542 | B27: MICROALGAL BIOMASS VALORIZATION FOR SUSTAINABLE PRODUCTION OF FUNCTIONAL FOOD AND FEED INGREDIENTS | C27: EL PROYECTO BIOVAL RESPONDE AL CRECIENTE DESAFIO DE GARANTIZAR ALIMENTOS SOSTENIBLES Y SALUDABLES MEDIANTE EL DESARROLLO DE UNA BIORREFINERIA AVANZADA DE MICROALGAS, CONCEBIDA BAJO UN MODELO DE CERO RESIDUOS Y ECONOMICAMENTE VIABLE. SE TRABAJARA CON TRES ESPECIES MARINAS DE ALTO POTENCIAL BIOTECNOLOGICO (PHAEODACTYLUM TRICORNUTUM, TETRASELMIS CHUII Y SKELETONEMA MARINOI), ORIENTANDO LA PRODUCCION HACIA 2-MONOACILGLICERIDOS (2-MAGS) DE ELEVADO VALOR AÑADIDO, ESPECIALMENTE ENRIQUECIDOS EN ACIDOS GRASOS OMEGA-3 (EPA Y DHA), CON APLICACIONES FUNCIONALES EN LA INDUSTRIA ALIMENTARIA PARA LA PREVENCION DEL SINDROME METABOLICO. LA SINTESIS QUIMICA CONVENCIONAL DE MAGS PRESENTA LIMITACIONES CRITICAS (ALTAS TEMPERATURAS, CATALIZADORES Y SUBPRODUCTOS TOXICOS COMO ESTERES DE GLICIDILO). BIOVAL PROPONE UNA ESTRATEGIA DISRUPTIVA Y SOSTENIBLE BASADA EN LA EXTRACCION VERDE DE 2-MAGS NATIVOS Y, PRINCIPALMENTE, EN SU SINTESIS ENZIMATICA CONTROLADA, GARANTIZANDO PRODUCTOS MAS PUROS Y SEGUROS, CON MAYOR EFICIENCIA DE PROCESO. LA INNOVACION ABARCA TODA LA CADENA DE VALOR: CULTIVO: IMPLEMENTACION DE ESTRATEGIAS MIXOTROFICAS EMPLEANDO SUBPRODUCTOS AGRICOLAS HIDROLIZADOS COMO FUENTE DE CARBONO ORGANICO, OPTIMIZANDO PRODUCTIVIDAD DE BIOMASA Y LIPIDOS. DIGITALIZACION: USO DE INTELIGENCIA ARTIFICIAL MEDIANTE REDES NEURONALES ARTIFICIALES PARA MODELAR Y OPTIMIZAR CONDICIONES DE CULTIVO EN TIEMPO REAL. MEJORA DE CEPAS: APLICACION DE TECNOLOGIAS OMICAS (GENOMICA, TRANSCRIPTOMICA Y METABOLOMICA) PARA IDENTIFICAR Y MODULAR RUTAS METABOLICAS CLAVE EN LA BIOSINTESIS DE 2-MAGS. VALIDACION FUNCIONAL: ENSAYOS IN VITRO E IN VIVO PARA EVALUAR LA BIOACTIVIDAD DE LOS 2-MAGS (CAPACIDAD ANTIINFLAMATORIA Y MEJORA DE LA SENSIBILIDAD A LA INSULINA). EL PROCESO SE DISEÑARA PARA ALCANZAR TRL 6, VALIDANDO LA TECNOLOGIA EN UN ENTORNO INDUSTRIALMENTE RELEVANTE. LAS FRACCIONES RESIDUALES (PROTEINAS, CARBOHIDRATOS) SE CO-VALORIZARAN EN PIENSOS FUNCIONALES PARA ACUICULTURA, CERRANDO EL CICLO PRODUCTIVO Y MAXIMIZANDO EL APROVECHAMIENTO INTEGRAL DE LA BIOMASA. BIOVAL CONTRIBUIRA A LOS OBJETIVOS DEL SUSTAINABLE BLUE ECONOMY PARTNERSHIP, IMPULSANDO LA BIOECONOMIA AZUL CIRCULAR, LA REDUCCION DE LA HUELLA DE CARBONO Y LA GENERACION DE INGREDIENTES FUNCIONALES SEGUROS Y SOSTENIBLES, CON IMPACTO DIRECTO EN LA SALUD PUBLICA, LA COMPETITIVIDAD INDUSTRIAL Y LA RESILIENCIA DEL SECTOR ACUICOLA EUROPEO. | D27: out | E27: out | F27: 2 | G27: This project focuses on microalgal biomass valorization for production of omega-3 fatty acid-rich 2-monoacylglycerols (2-MAGs) as functional food ingredients for metabolic syndrome prevention, with residual fractions (proteins, carbohydrates) directed to aquafeed — the primary focus is lipid/omega-3 production rather than protein as an alternative protein source, and the protein fraction is explicitly destined for aquafeed (out of scope), not human alternative protein applications. | H27: =TRUE() -> TRUE | I27: F | J27: NA | K27: =FALSE() -> FALSE | L27: =FALSE() -> FALSE | M27: =FALSE() -> FALSE | N27: =FALSE() -> FALSE | O27: =FALSE() -> FALSE | P27: ok
A28: grant.14973726 | B28: Solar-driven synthesis of proteins and lipids via photoelectrochemistry of living organisms | C28: Biohybrid systems offer unique energy-efficient routes to harness solar energy for the fixation of CO2 and nitrogen into valuable, complex molecules. This project will integrate living photosynthetic bacteria and food-producing autotrophic bacteria into stand-alone photoelectrochemical devices tailored for the direct production of proteins and lipids from sunlight, air and water. Cyanobacteria will supply electrons via light-driven water oxidation, organic dyes will provide these electrons with sufficient energy to generate substrates that would directly feed either a culture or a consortia of food producing microorganisms in the same device. The result will be the demonstration of the first direct conversion of CO2 and N2 from air to protein- or lipid-rich food materials using solar energy, with the aim to produce a prototype that can reach 1% solar-conversion efficiency or surpass present food production processes via agriculture. Our bioengineering efforts will focus on three key innovations: (i) overcoming complex electron transfer pathway barriers at the cell-electrode interface, aided by the coupling of electrode engineering with advanced modelling of the interface; (ii) expanding the range of Solar-to-X products to two essential food groups (proteins and lipids), enabled by the formation of novel microbial consortia on redox polymer films that mitigate their conflicting microenvironment needs; and iii) device engineering that synergizes the different outputs and needs of the bio-anode and cathode whilst also facilitating easy food-product collection. The delivery of our envisioned Solar-to-Food devices will open the door to re-imagining sustainable food production for off-grid locations, kitchens in future households and spaceships. Current food industries, such as our partner Solar Foods, would be an immediate benefactor. Our envisioned solar-to-lipids production process could be a stepping stone to fuels production lines of the future. | D28: in | E28: in | F28: 7 | G28: This grant focuses on using autotrophic bacteria (including cyanobacteria and food-producing microorganisms like those used by Solar Foods) to produce protein- and lipid-rich food materials via photoelectrochemical systems, which is directly relevant to biomass fermentation/single-cell protein production as an alternative protein source. | H28: =TRUE() -> TRUE | I28: F | J28: F | K28: =TRUE() -> TRUE | L28: =FALSE() -> FALSE | M28: =TRUE() -> TRUE | N28: =FALSE() -> FALSE | O28: =FALSE() -> FALSE | P28: ok
A29: grant.14881472 | B29: Fermented Foods and Bone Health: Investigating the Gut-Bone Axis in Premenopausal Vegan Women | C29: With the increasing popularity of plant-based diets, recent epidemiological studies suggest that individuals following vegan diets may be at higher risk of lower bone mineral density (BMD) and fractures, particularly among women. This highlights bone health as a critical concern within vegan and plant-based diets, underscoring the need for effective strategies to mitigate these risks. Evidence suggests that the gut microbiota plays a key role in regulating bone metabolism through the "gut-bone axis." Fermented foods, such as yogurts and fermented vegetables, have been shown to positively influence gut microbiota, supporting bone health by supplying essential nutrients like calcium, phosphorus, and protein, enhancing nutrient absorption, and reducing bone resorption. However, dairy products are typically absent in vegan diets or replaced by plant-based alternatives with different nutrient compositions. While some studies are exploring the effects of these alternatives on the gut microbiome, their potential benefits for bone health in humans remain unclear. Notably, there is a lack of randomized controlled trials (RCTs) investigating the effects of fermented plant-based products on gut microbiota and bone metabolism, revealing a significant gap in the literature. This project aims to test the hypothesis that consuming plant-based fermented foods can improve bone turnover markers (BTMs) in vegan premenopausal women over a 12-week period. To address this, we will conduct a two-center, cross-over RCT in Switzerland and the Czech Republic, and will complement this with the microbial characterisation of plant-based fermented foods, in-vitro mineral bioavailability and bioaccessibility assays, as well as ex-vivo fermentations. In the RCT, we will recruit 40 premenopausal women aged 30-45 years, with primary outcomes focusing on collagen type 1 cross-linked C-terminal telopeptide (CTX) and procollagen type I amino-terminal propeptide (P1NP). Secondary outcomes will include assessments of gut microbiota composition using whole genome sequencing, inflammatory markers (CRP, AGP, IL-6), markers of gut integrity (iFABP, calprotectin), and metabolomic and proteomic profiles of both the host and microbiome. The broader impact of vegan diets and fermentation processes on nutrient bioavailability and gut microbiota leads to the following secondary hypotheses: a long-term adherence to a vegan diet may increase bone resorption risk independent of calcium intake; plant-based fermented foods have distinct microbial loads and produce metabolites beneficial for bone health; these foods improve the bioaccessibility and bioavailability of key micronutrients for bone health compared to non-fermented counterparts; and the spectrum of microbially produced metabolites relevant to bone health differs between fermented and non-fermented foods. Additionally, the project will leverage existing data on vegans to conduct a comprehensive analysis of BMD and BTMs, metabolomic profiles, and dietary patterns in vegan and omnivore populations across multiple European countries. This comprehensive approach, integrating observational data analysis, laboratory experiments, and clinical trials, aims to provide novel insights into the chemical and microbial profiles of next-generation plant-based fermented foods, along with mechanistic studies on their mineral bioaccessibility, bioavailability, metabolite production, and their impact on the vegan gut microbiota. By evaluating their effects on BTMs in a randomized controlled trial, the findings could guide future dietary recommendations, potentially leading to the inclusion of fermented foods in existing dietary guidelines. | D29: out | E29: out | F29: 2 | G29: This grant focuses on the health effects of fermented plant-based foods on bone metabolism and gut microbiota in vegan women, which is a medical/nutritional health outcome study rather than research advancing alternative protein development, characterisation, or substitution of animal products. | H29: =TRUE() -> TRUE | I29: NA | J29: NA | K29: =TRUE() -> TRUE | L29: =FALSE() -> FALSE | M29: =FALSE() -> FALSE | N29: =FALSE() -> FALSE | O29: =FALSE() -> FALSE | P29: ok
A30: grant.14704971 | B30: Development of approaches to complex processing of microalgae biomass for the production of cosmetic and food products | C30: The proposed study is devoted to the development of fundamental improved approaches to the complex processing of microalgae biomass by hydrolysis and hydrolysis-reduction to obtain a set of products that are promising for use in the cosmetic and food industries, such as protein-carbohydrate extracts with antioxidant activity and higher polyols used as sugar substitutes and in pharmaceuticals. The relevance of the research is justified by the following factors. 1. The deficit, absence of a significant amount of domestic production, and the high cost and low availability under sanctions of imported bio-raw materials for the production of cosmetic and cosmeceutical products based on microalgae biomass. 2. The significant demand for sorbitol, which is widely used in the food, cosmetics industry and in medicine, in Russia with complete import dependence. 3. Approaches using microalgae to obtain valuable products are highly relevant from an environmental point of view. It has been shown that microalgae can be cultivated using water containing organic pollutants. Thus, microalgae cultivation can be used in water purification processes with the simultaneous production of high-margin products. 4. Development of methods for synthesizing microalgae with their subsequent processing meets modern requirements for increasing the carbon neutrality of production, since microalgae actively consume carbon dioxide during their growth. The project will last for two years, and upon its completion, the following fundamental results will be obtained. 1. New promising microalgae strains have been identified, the biomass of which has a high potential for use in the cosmetics industry (antioxidant activity of aqueous hydrolysates) and the food industry (high carbohydrate content). 2. Effective approaches to hydrothermal and acid hydrolysis of microalgae biomass to obtain carbohydrates and aqueous hydrolysates, including the isolation and purification of carbohydrates, have been developed. 3. The study has been conducted of the prospects for using aqueous hydrolysates as cosmetics for external use (skin care) taking into account data on antioxidant activity. 4. Methods have been developed for preparing carbohydrate raw materials from microalgae by removing impurities that prevent deep processing into valuable substances. 5. The approach has been developed for the catalytic hydrolysis-reduction of carbohydrates from microalgae biomass to obtain higher polyols (sorbitol) used in the food industry (sweetener). The project will be carried out at the intersection of catalysis and biotechnology. An interdisciplinary approach to the work will allow obtaining results that are highly innovative. The novelty of the project can also be noted in the following: 1. In the creation of a complex technology for obtaining a group of products suitable for use in cosmetology and the food industry. 2. In the use of original highly effective solid catalysts for the formation of polyhydric alcohols. 3. In the development of an effective method for purifying microalgae biomass carbohydrates from impurities, which allows removing restrictions on the processing of such raw materials into valuable products. 4. For the first time, a method for obtaining polyhydric alcohols, such as sorbitol, from microalgae carbohydrates (glucose and starch) will be developed. 5. In a single-stage one-pot approach to the hydrolysis-reduction of the carbohydrate component of microalgae biomass. 6. For the first time, the possibility of using some collection and our own strains of microalgae of the genus Chlorella, Parachlorella, Desmodesmus, Bracteacoccus and others to create cosmetics and food products will be studied. 7. For the first time, the antioxidant activity of aqueous extracts from the biomass of the microalgae strains used in this work will be studied. | D30: out | E30: out | F30: 2 | G30: While microalgae biomass is processed for food applications, the primary focus is on cosmetics, sugar substitutes (sorbitol/polyols), and antioxidant extracts — not on protein as a food ingredient or alternative protein product substituting animal-derived foods. | H30: =TRUE() -> TRUE | I30: F | J30: NA | K30: =FALSE() -> FALSE | L30: =FALSE() -> FALSE | M30: =FALSE() -> FALSE | N30: =FALSE() -> FALSE | O30: =FALSE() -> FALSE | P30: ok
A31: grant.14952019 | B31: Tracking Ancestral DIX-DOmain cell polarity processes in plant Root nodulE symbioses – ADDORE | C31: Certain plants have the remarkable ability of establishing beneficial root symbioses with soil bacteria to acquire nitrogen, an essential nutrient for their growth. The bacteria provide nitrogen to their host within new specialized root organs, called nodules, formed through integrated multicellular re-differentiation of plant cells. Bacterial entry is a crucial step in this process, and often occurs through the creation of new transcellular apoplastic compartments called infection threads (IT), which guide the symbiotic bacteria towards the developing nodule. These processes must be tightly coordinated, and partner’s exciting new findings suggest that cross-kingdom cell polarisation processes may regulate them. Indeed, through expression and functional studies, they discovered that genes encoding novel DIX-domain plant polarity proteins are linked to nodule formation in various nitrogen-fixing symbioses. DIX-domains are key for plasma membrane association, enabling these proteins to orchestrate PM signal relay via protein-protein interactions. These findings raise the exciting question of whether plants use ancestral DIX-mediated polarization process for nodule ontogeny and bacterial accommodation. Using complementary model legumes (Medicago, Lotus and Mimosa) and non-legume (Parasponia) this project will combine original multi-species functional genomics, phylogenetic foot printing, live microscopy and protein biochemistry strategies to study their roles in the unexplored context of root nodule symbioses. The project should provide innovative results on their ancestral cellular roles, evolutionary recruitment and molecular interactors, and thus shed light on how they organize the infection machinery and nodule formation across different species. | D31: out | E31: out | F31: 1 | G31: This grant concerns plant cell biology and root nodule symbiosis with nitrogen-fixing bacteria, with no connection to alternative proteins, food science, or protein production for human consumption. | H31: =TRUE() -> TRUE | I31: NA | J31: NA | K31: =TRUE() -> TRUE | L31: =FALSE() -> FALSE | M31: =FALSE() -> FALSE | N31: =FALSE() -> FALSE | O31: =FALSE() -> FALSE | P31: ok
A32: grant.15201827 | B32: Dissecting the Antibacterial Role of Campylobacter's Type VI Secretion System and Effectors Across Diverse Host Environments | C32: Campylobacter is the leading cause of foodborne diseases annually in the UK, costing the country's economy a significant amount of money each year. Specifically, the Food Standards Agency estimates that Campylobacter infections alone incur a hefty £900 million expense, out of a total of £1.5 billion for all foodborne infections. Particularly, Campylobacter jejuni species is responsible for over 80% of these cases. This bacterium is becoming increasingly resistant to commonly used antibiotics. Remarkably, it naturally resides in birds, where trillions of these bacteria coexist in their guts without causing harm. However, just 100 of these bacteria can lead to severe illness in humans. Consuming or handling poultry is the main way humans contract the infection, which can result in symptoms like bloody diarrhoea, fever, and abdominal pain. In areas with limited resources, Campylobacter infections are particularly prevalent among young children, leading to health issues such as stunted growth, lifelong physical and cognitive impairments, and in severe cases, death. Despite its prevalence and importance, our understanding of how C. jejuni causes disease is limited when compared to other gut pathogens such as Salmonella. Recently, we have identified many strains of C. jejuni that have a Type VI Secretion System (T6SS). The T6SS acts as a weapon firing bullets (toxins known as effector proteins) that neutralise bacterial competitors, thereby conferring them a competitive edge within a host environment. The functions of C. jejuni T6SS effectors, particularly in chicken and human host environments and their impact on the resulting infection outcome remains unclear. Our research suggests that T6SS and its effectors equip C. jejuni with antibacterial properties to thrive in specific host environments. By analysing the genomes of C. jejuni, we have identified a new range of these effectors and we hypothesise that these are important mediators of C. jejuni pathogenesis and niche establishment. To test this, we propose a multidisciplinary research programme. Our aims and objectives include (1) characterisation of how the T6SS and its effectors of C. jejuni contribute to antibacterial competitive fitness; (2) to determine how different human and chicken in vitro host gut models impact the functionality of the T6SS; and (3) characterise how C. jejuni T6SS and its effectors impact the chicken gut microbial population structure in an in vivo colonisation model. These insights hold transformative potential, informing the development of new antimicrobials based on T6SS toxin mechanisms and novel vaccine targets derived from characterised effectors. The increasing prevalence of Campylobacter infections, coupled with the growing challenge of antimicrobial resistance, presents a significant strain on public health resources, demanding urgent action. To address this pressing issue, our cutting-edge, interdisciplinary project aims to unravel the complex molecular and cellular mechanisms underlying C. jejuni T6SS and effector functions in different hosts, directly aligning with a key BBSRC objective, understanding the rules of life. The knowledge accrued by our research will improve our understanding of this important human pathogen and how it causes disease, with the goal of developing evidence-based interventions to prevent and treat infections and thus improve health. Our impact aligns closely with key pillars of the BBSRC; sustainable agriculture and food, integrated understanding of health and tackling infections. | D32: out | E32: out | F32: 1 | G32: This grant concerns the pathogenesis and antimicrobial resistance of Campylobacter jejuni, a foodborne pathogen, with no relevance to alternative protein research or production. | H32: =TRUE() -> TRUE | I32: NA | J32: NA | K32: =TRUE() -> TRUE | L32: =FALSE() -> FALSE | M32: =FALSE() -> FALSE | N32: =FALSE() -> FALSE | O32: =FALSE() -> FALSE | P32: ok
A33: grant.14949587 | B33: Dissecting the Antibacterial Role of Campylobacter's Type VI Secretion System and Effectors Across Diverse Host Environments | C33: Campylobacter is the leading cause of foodborne diseases annually in the UK, costing the country's economy a significant amount of money each year. Specifically, the Food Standards Agency estimates that Campylobacter infections alone incur a hefty £900 million expense, out of a total of £1.5 billion for all foodborne infections. Particularly, Campylobacter jejuni species is responsible for over 80% of these cases. This bacterium is becoming increasingly resistant to commonly used antibiotics. Remarkably, it naturally resides in birds, where trillions of these bacteria coexist in their guts without causing harm. However, just 100 of these bacteria can lead to severe illness in humans. Consuming or handling poultry is the main way humans contract the infection, which can result in symptoms like bloody diarrhoea, fever, and abdominal pain. In areas with limited resources, Campylobacter infections are particularly prevalent among young children, leading to health issues such as stunted growth, lifelong physical and cognitive impairments, and in severe cases, death. Despite its prevalence and importance, our understanding of how C. jejuni causes disease is limited when compared to other gut pathogens such as Salmonella. Recently, we have identified many strains of C. jejuni that have a Type VI Secretion System (T6SS). The T6SS acts as a weapon firing bullets (toxins known as effector proteins) that neutralise bacterial competitors, thereby conferring them a competitive edge within a host environment. The functions of C. jejuni T6SS effectors, particularly in chicken and human host environments and their impact on the resulting infection outcome remains unclear. Our research suggests that T6SS and its effectors equip C. jejuni with antibacterial properties to thrive in specific host environments. By analysing the genomes of C. jejuni, we have identified a new range of these effectors and we hypothesise that these are important mediators of C. jejuni pathogenesis and niche establishment. To test this, we propose a multidisciplinary research programme. Our aims and objectives include (1) characterisation of how the T6SS and its effectors of C. jejuni contribute to antibacterial competitive fitness; (2) to determine how different human and chicken in vitro host gut models impact the functionality of the T6SS; and (3) characterise how C. jejuni T6SS and its effectors impact the chicken gut microbial population structure in an in vivo colonisation model. These insights hold transformative potential, informing the development of new antimicrobials based on T6SS toxin mechanisms and novel vaccine targets derived from characterised effectors. The increasing prevalence of Campylobacter infections, coupled with the growing challenge of antimicrobial resistance, presents a significant strain on public health resources, demanding urgent action. To address this pressing issue, our cutting-edge, interdisciplinary project aims to unravel the complex molecular and cellular mechanisms underlying C. jejuni T6SS and effector functions in different hosts, directly aligning with a key BBSRC objective, understanding the rules of life. The knowledge accrued by our research will improve our understanding of this important human pathogen and how it causes disease, with the goal of developing evidence-based interventions to prevent and treat infections and thus improve health. Our impact aligns closely with key pillars of the BBSRC; sustainable agriculture and food, integrated understanding of health and tackling infections. | D33: out | E33: out | F33: 1 | G33: This grant concerns the pathogenesis of Campylobacter jejuni and its Type VI Secretion System in host environments, which is a microbiology/infectious disease study with no relevance to alternative proteins. | H33: =TRUE() -> TRUE | I33: NA | J33: NA | K33: =TRUE() -> TRUE | L33: =FALSE() -> FALSE | M33: =FALSE() -> FALSE | N33: =FALSE() -> FALSE | O33: =FALSE() -> FALSE | P33: ok
A34: grant.14705292 | B34: Study of the resistance of various strains of soybean nodule bacteria of the genus Bradyrhizobium in liquid biological preparations (inoculants) to physical, chemical and biological stress factors characteristic of agriculture in the Russian Federation | C34: Protein is an essential component in human nutrition and in feed for farm animals. One of the main sources of protein in the domestic food and feed industry is soybean grain. The high yield of soybeans and the increased protein content in soybean grains is due to the fact that soybeans are able to form a highly active nitrogen-fixing legume-rhizobia symbiosis with nodule bacteria. To increase the efficiency of symbiotic nitrogen fixation, soybean seeds are artificially treated with preparations (inoculants) of highly active nodule bacteria before sowing. Under controlled conditions, rhizobia preparations can increase soybean yield by 25-40%, and the protein content in grain by 2-5%. However, when using inoculants in industrial conditions, the effectiveness of this technique is significantly reduced, which can be explained by the low adaptability of rhizobia to the conditions in which exposed to bacteria in industrial crop production. In addition to the high symbiotic compatibility of the partners and favorable soil and climatic conditions for the formation of symbiosis, the effectiveness of inoculation is determined by such parameters as: the titer of rhizobia at the time of use of the drug (i.e., using the inoculant to prepare the working solution), the composition and concentration of chemical plant protection products in the working solution, stability rhizobia to chemical stress and the time of contact of bacteria with pesticides in the working solution, the resistance of rhizobia to drying out on treated seeds, the effectiveness of a protector that protects bacteria from osmotic stress and the time that elapsed from the moment of processing the seeds until they are embedded in the soil. This study is devoted to studying the factors that determine the resistance of promising strains of soybean microsymbionts of the genus Bradyrhizobium to physical, chemical and biological stress factors to which rhizobia are exposed during the industrial cultivation of soybeans. The scientific novelty of the study lies in the fact that: 1. For the first time, the resistance of promising soybean rhizobia strains B. japonicum pcs. will be determined. 634b, 640b, RZ300 to osmotic stress (drying) on inoculated soybean seeds of varieties widely used in agricultural practice. In addition, the conditions affecting the osmotic stability of soybean rhizobia were studied for the first time, such as the technology for obtaining a bacterial preparation (composition of the nutrient medium and cultivation parameters), the density of the bacterial culture applied to the seeds, the qualitative and quantitative composition of the bacterial protector, the holding time and temperature conditions for storing inoculated balls and seeds; 2. For the first time, the resistance of soybean rhizobia strains B. japonicum pcs. will be determined. 634b, 640b, RZ300 to chemical stress (contact with pesticides) with a number of chemical disinfectants for legumes widely used in agricultural practice. In addition, for the first time, factors influencing the resistance of rhizobia to chemical stress, such as the concentration of pesticide disinfectant in the working solution, temperature and exposure time of the working solution, will be studied. 3. For the first time, the compatibility of soybean rhizobia strains B. japonicum pcs. will be determined. 634b, 640b, RZ300 with a number of strains of the most common biological microorganisms in agricultural practice, in particular bacteria of the genera Bacillus and Pseudomonas. 4. For the first time, the productivity of soybean plants grown under growing conditions from seeds inoculated with preparations of soybean rhizobia B. japonicum pcs. will be assessed. 634b, 640b, RZ300 together with their treatment with chemical fungicides and simultaneous treatment with various bacterial protector compositions. 5. For the first time, the influence of the technology for obtaining preparations of nodule bacteria (composition of nutrient media, cultivation modes, modes of centrifugation and resuspension of bacterial sediment) on the resistance of rhizobia to stress (drying on seeds, contact with chemical and biopesticides), and the productivity of inoculated soybean plants will be studied. | D34: out | E34: out | F34: 1 | G34: This grant concerns agronomic research on Bradyrhizobium inoculants to improve soybean yield and protein content for food and feed, but does not address alternative protein development, processing, or any substitution of animal-derived products. | H34: =TRUE() -> TRUE | I34: NA | J34: NA | K34: =TRUE() -> TRUE | L34: =FALSE() -> FALSE | M34: =FALSE() -> FALSE | N34: =FALSE() -> FALSE | O34: =FALSE() -> FALSE | P34: ok
A35: grant.15147311 | B35: One Health Rationale to Investigate the emerGence of AMR related to chicken Meat and Egg consumption (OHRIGAME) | C35: With growing demand for protein from animal origin, the poultry industry is experiencing an unprecedented intensification in Southeast Asia. Industrialisation of livestock farming is accompanied by an overuse/misuse of antimicrobial drugs (AMD) which is believed to be a significant driver of antimicrobial resistance (AMR). AMR is a major threat for human and is reported to be responsible for close to a million deaths, yearly. The team assembled in this project has worked together within the UKRI GCRF One Health Poultry Hub, to generate robust evidence of excess AMD use in poultry production systems within Vietnam, using a holistic One Health approach that integrates studies from biological and social science disciplines. This foundation has generated knowledge on the overall structure and vulnerability of poultry production systems in Vietnam, with insights into the lives of farmers and other actors, including differences in the roles, responsibilities and behaviours of men and women working across the network. It also highlighted an alarming prevalence of food-borne pathogens in chickens, showed that chicken gut bacteria and microbial communities have high levels of AMR genes resulting in resistance to many AMDs, and that AMD residues over the maximum residue limit (MRL) are present in ~ 9% of meat on sale to the public. This project will continue the interdisciplinary approach to generate new knowledge on the dynamics of AMR acquisition during the production cycle, to understand the drivers of high AMD use in Vietnam chicken production, and to investigate potential impacts of unintentional exposure to AMD and resistant bacteria by ingestion of contaminated water (chickens) of food (chickens and humans). The objectives of the OHRIGAME project (One Health Rationale to Investigate the emerGence of AMR related to chicken Meat and Egg consumption) are to: Through longitudinal sampling, evaluate AMR in chicken gut bacterial populations during their breeding until sale Use forensic investigative analyses to identify underlying reasons for the high level of veterinary drugs in meat, by analysis eggs, chicken feed and drinking water, and relate this to AMR profiles within the same chickens. The Vietnamese government’s ban of prophylactic antimicrobial use, coming into place in 2025, will constitute a natural intervention. Use questionnaire based research to understand farmers’ motivations for under-reporting use of AMD. We will also sample chicken meat imported from Vietnam and hospital-grade food in the UK to evaluate the risk of that AMD residues and AMR genes could pose to clinical populations of patients at risk of gut bacteria dysregulation. From the start in Vietnam we will work with local and national stakeholders from government, particularly the Department of Animal Health within the Ministry of Agriculture and Rural Development, with whom we have a well-established relationship, and with the One Health Partnership secretariat, agencies, NGOs and the poultry sector. With expansion of analysis capacity, we will propose a framework to increase Vietnam capability to screen AMD residue and AMR in chicken meat production to protect the national consumers, a key priority of the Vietnam’s Decision No. 4 14 /QD-TTg (Strengthening capacity to manage and control animal diseases and diseases transmitted between animals and humans).Our international One Health approach includes AMR diplomacy actions which will benefit people locally in Vietnam and is completely aligned with the UK National Action Plan on AMR. | D35: out | E35: out | F35: 1 | G35: This grant concerns antimicrobial resistance in conventional poultry production and chicken/egg consumption, with no relevance to alternative proteins. | H35: =TRUE() -> TRUE | I35: NA | J35: NA | K35: =TRUE() -> TRUE | L35: =FALSE() -> FALSE | M35: =FALSE() -> FALSE | N35: =FALSE() -> FALSE | O35: =FALSE() -> FALSE | P35: ok
A36: grant.14971973 | B36: One Health Rationale to Investigate the emerGence of AMR related to chicken Meat and Egg consumption (OHRIGAME) | C36: With growing demand for protein from animal origin, the poultry industry is experiencing an unprecedented intensification in Southeast Asia. Industrialisation of livestock farming is accompanied by an overuse/misuse of antimicrobial drugs (AMD) which is believed to be a significant driver of antimicrobial resistance (AMR). AMR is a major threat for human and is reported to be responsible for close to a million deaths, yearly. The team assembled in this project has worked together within the UKRI GCRF One Health Poultry Hub, to generate robust evidence of excess AMD use in poultry production systems within Vietnam, using a holistic One Health approach that integrates studies from biological and social science disciplines. This foundation has generated knowledge on the overall structure and vulnerability of poultry production systems in Vietnam, with insights into the lives of farmers and other actors, including differences in the roles, responsibilities and behaviours of men and women working across the network. It also highlighted an alarming prevalence of food-borne pathogens in chickens, showed that chicken gut bacteria and microbial communities have high levels of AMR genes resulting in resistance to many AMDs, and that AMD residues over the maximum residue limit (MRL) are present in ~ 9% of meat on sale to the public. This project will continue the interdisciplinary approach to generate new knowledge on the dynamics of AMR acquisition during the production cycle, to understand the drivers of high AMD use in Vietnam chicken production, and to investigate potential impacts of unintentional exposure to AMD and resistant bacteria by ingestion of contaminated water (chickens) of food (chickens and humans). The objectives of the OHRIGAME project (One Health Rationale to Investigate the emerGence of AMR related to chicken Meat and Egg consumption) are to: Through longitudinal sampling, evaluate AMR in chicken gut bacterial populations during their breeding until sale Use forensic investigative analyses to identify underlying reasons for the high level of veterinary drugs in meat, by analysis eggs, chicken feed and drinking water, and relate this to AMR profiles within the same chickens. The Vietnamese government’s ban of prophylactic antimicrobial use, coming into place in 2025, will constitute a natural intervention. Use questionnaire based research to understand farmers’ motivations for under-reporting use of AMD. We will also sample chicken meat imported from Vietnam and hospital-grade food in the UK to evaluate the risk of that AMD residues and AMR genes could pose to clinical populations of patients at risk of gut bacteria dysregulation. From the start in Vietnam we will work with local and national stakeholders from government, particularly the Department of Animal Health within the Ministry of Agriculture and Rural Development, with whom we have a well-established relationship, and with the One Health Partnership secretariat, agencies, NGOs and the poultry sector. With expansion of analysis capacity, we will propose a framework to increase Vietnam capability to screen AMD residue and AMR in chicken meat production to protect the national consumers, a key priority of the Vietnam’s Decision No. 4 14 /QD-TTg (Strengthening capacity to manage and control animal diseases and diseases transmitted between animals and humans).Our international One Health approach includes AMR diplomacy actions which will benefit people locally in Vietnam and is completely aligned with the UK National Action Plan on AMR. | D36: out | E36: out | F36: 1 | G36: This grant concerns antimicrobial resistance in conventional poultry production and chicken/egg consumption, with no relevance to alternative proteins. | H36: =TRUE() -> TRUE | I36: NA | J36: NA | K36: =TRUE() -> TRUE | L36: =FALSE() -> FALSE | M36: =FALSE() -> FALSE | N36: =FALSE() -> FALSE | O36: =FALSE() -> FALSE | P36: ok
A37: grant.15073719 | B37: Zilt & Zuur | C37: The Zilt & Zuur project explores how fermentation can make toothed wrack (seaweed) more palatable and digestible. Seaweed is a sustainable protein source but is rarely consumed due to its flavour (fishy, salty) and texture. Fermentation can enhance its appeal for the hospitality and food industries. In collaboration with Michelin-starred restaurant De Kromme Watergang and Zeeuwse Zeewierhandel, HZ University of Applied Sciences is developing a fermentation protocol to create new culinary applications. This research contributes to a more sustainable food system and offers economic opportunities for Zeeland by opening new markets for fermented seaweed. | D37: in | E37: in | F37: 6 | G37: The project uses fermentation to process seaweed (macroalgae) as a sustainable protein source for food applications, which falls under plant-based alternative proteins; traditional fermentation applied to plant/algal material is classified as plant-based. | H37: =TRUE() -> TRUE | I37: PB | J37: PB | K37: =TRUE() -> TRUE | L37: =TRUE() -> TRUE | M37: =FALSE() -> FALSE | N37: =FALSE() -> FALSE | O37: =FALSE() -> FALSE | P37: ok
A38: grant.14705189 | B38: Glycogen as a source of trehalose in methanotrophs | C38: Bacteria that use methane as a source of carbon and energy (methanotrophs) are unique natural factories that supply polycarbon compounds from a single-carbon (C1) substrate. Aerobic methanotrophs are active players in the global carbon cycle, significantly reducing atmospheric methane level. Since methane is a non-food compound and the main component of natural gas, methanotrophs have attracted the attention of biotechnologists with the opportunity to obtain high added value products through the bioconversion of CH4. The development of postgenomic technologies has significantly expanded the understanding of the potential of methanotrophs as producers of a variety of valuable metabolites. Methanotrophic cultures have been tested for their ability to produce complete feed protein, the biodegradable polymer poly-β-hydroxybutyrate, components for nanotechnology, lipids and carotenoids, and carbohydrate feedstocks for microbial fermentation. One of the most promising strains for biotechnology is the halotolerant methanotroph Methylotuvimicrobium alcaliphilum 20Z, which has a high growth rate and stability in a wide range of conditions - in the presence of 0.5 - 6% NaCl and in the pH range 7.5-10.5. When growing under standard conditions, M. alcaliphilum 20Z accumulated more than 10% of glycogen in cells, while when growth was limited by a nitrogen source, the polysaccharide content reaches 35% of the cell mass (Khmelenina et al., 1999, Booth et al., 2020). This project is aimed at genetic modification of the methanotroph in order to redirect the carbon flow from glycogen accumulation to trehalose synthesis; enrichment of biomass with this disaccharide is intended to improve the feeding properties of the biomass. The main component of the project is the production of a number of marker-free mutations in M. alcaliphilum. Analysis of the culture response to the deletion of genes presumably involved in transformation of trehalose, which is an intermediate of glycogen carbon mobilization/degradation, will provide possibility to establish the function of the encoded enzymes, as well as to select candidates for subsequent combination of deletions to construct producer strain. The introduction of the treT gene, encoding trehalose synthase from the related methanotroph Methylomicrobium album BG8, will enhance trehalose synthesis due to the utilization of free glucose, as well as redistribute the carbon flow from sucrose synthesis to trehalose formation. At the final stage, it is planned to test the trehalose content in the biomass, as well as determine the growth characteristics of the recombinant strain under bioreactor conditions. In addition, the planned strand-specific 3'-terminal sequencing of mRNA is of fundamental importance, which will make it possible to identify at the gene level the mechanism of regulation of glycogen synthesis/decomposition by free glucose in the M. alcaliphilum strain with a knockout of the gene encoding glucokinase, the distinctive property of which is lack of glycogen in cells. | D38: out | E38: out | F38: 2 | G38: This research concerns methanotroph biotechnology for trehalose production and feed protein, not alternative proteins for human food substitution of animal-derived products. | H38: =TRUE() -> TRUE | I38: NA | J38: NA | K38: =TRUE() -> TRUE | L38: =FALSE() -> FALSE | M38: =FALSE() -> FALSE | N38: =FALSE() -> FALSE | O38: =FALSE() -> FALSE | P38: ok
A39: grant.14972633 | B39: AlgFlavor, Enhancing algal biomass consumer acceptance for food markets | C39: As society shifts away from animal-based diets driven by environmental, health and animal welfare concerns, both seaweed and microalgae (collectively referred to as algae) emerge as a promising sustainable food source. With their rich nutritional content, including protein, minerals, vitamins, fiber and omega-3 fatty acids, these low trophic marine species offer a viable solution to meet consumer demands for healthy and eco-friendly diets. Despite the potential of algae, the widespread adoption in European markets faces hurdles due to limited consumer acceptance stemming from the impact of algal biomass on taste, aroma and visual appeal in food products. AlgFlavor will tackle these concerns as it is crucial for building consumer trust and promoting the widespread use of algae in food. | D39: in | E39: in | F39: 6 | G39: The grant focuses on improving consumer acceptance of seaweed and microalgae as food ingredients, explicitly highlighting their protein content and role as sustainable food sources substituting animal-based diets, which falls within the plant-based alternative protein category. | H39: =TRUE() -> TRUE | I39: PB | J39: PB | K39: =TRUE() -> TRUE | L39: =TRUE() -> TRUE | M39: =FALSE() -> FALSE | N39: =FALSE() -> FALSE | O39: =FALSE() -> FALSE | P39: ok
A40: grant.14970420 | B40: BiochAIn - BiochAIn ist ein Softwareprojekt für die Optimierung einer gesamten biotechnologischen Verfahrenskette(Chain) mittels AI | C40: Biotechnologische Produktionsverfahren finden breite Anwendung in der pharmazeutischen Industrie, zur Herstellung von Feinchemikalien, in der Umwelttechnologie und in der Lebensmittelindustrie und generieren eine hohe Wertschöpfung. Aufgrund der hohen Komplexität dieser Verfahren, bedingt durch das vielschichtige Zusammenspiel von Biologie und Verfahrenstechnik, besteht in zahlreichen Fällen ein nur sehr eingeschränktes Prozessverständnis. Dies wiederum führt zu wenig effizienten und daher teuren Prozessen, limitiert die Möglichkeiten zur Prozessoptimierung und ist auch ein wesentlicher Grund dafür, dass bis dato die enormen Fortschritte im Bereich der Digitalisierung, Methoden der künstlichen Intelligenz und Modellierung/Simulation nicht im erforderlichen Ausmaß zur Auslegung und Führung von Bioprozessen zur Anwendung kommen. Im Rahmen des Projektes soll daher eine generische Software-Toolbox entwickelt werden um genannte Fortschritte im Bereich der Digitalisierung den Experten der Domäne Bioprozess-technik zugänglich machen und eine Implementierung der Digitalisierung gemäß Industrie 4.0 im Bio-Manufacturing ermöglichen. Mit dem BiochAIn Projekt hat sich die Novasign zum Ziel gesetzt, weltweit die erste digitale Prozessmodellierungstoolbox für die Optimierung aller biotechnologisch relevanten Verfahrensschritte zu entwickeln. Mit dieser Software-Suite soll es erstmals möglich werden, dass Biotechnologen und Bioprozessingenieur:innen über eine nutzerzentrierte grafische Bedienoberfläche alle Einzelschritte der Prozesskette, sowohl individuell als auch in ihrer Gesamtheit, mit Hilfe von Modellen und Simulation selbstständig und unabhängig von hochspezialisierten Softwareentwicklern und Data Scientists optimieren können. Die Software wird auch ermöglichen, dass Prozessingenieur:innen abteilungsübergreifend Herstellungsprozesse für Produkte (zum Beispiel einen Antikörper für die Krebstherapie) in einem integrativen Ansatz optimieren können um lebensrettende Medizin den Patient:innen früher und günstiger zur Verfügung stellen zu können. Die Softwareentwicklung wird in 4 Blöcke aufgeteilt und soll über einen Zeitraum von 4 Jahren (durch schnelleren Fortschritt verkürzt auf 3 Jahre) erfolgen. Im ersten Schritt wurde eine geeignete Softwarearchitektur festgelegt, welche einerseits alle technischen Herausforderungen bewältigen kann und andererseits für Benutzer:innen, einfach bedienbar ist. In einem Datenvorverarbeitungs-/Visualisierungsblock werden Onlinedaten (Prozesssystem) und Offlinedaten (Messungen) mit Methoden der statistischen Datenaufbereitung und Analyse vorprozessiert, verknüpft und so für Visualisierung und Modellierung vorbereitet. Der Modellierblock wird so aufgesetzt, dass die unterschiedlichsten State-of-the-art Machine Learning (ML) Methoden implementiert werden und so die jeweils bestgeeignete Methode für zur Modellierung unterschiedlicher Bioprozessschritte eingesetzt werden kann. Im finalen Schritt, dem digitalen Zwilling, kann jeder einzelne der Modellblöcke individuell oder mittels drag-and-drop mit anderen Einheiten verknüpft zu einer Prozesskette nach einer bestimmten Zielgröße (z.B. höchstmögliche Produktausbeute oder kürzere Prozessdauer) optimiert werden und für die online Monitoring angewendet werden. Um Nutzer:innen bestmöglich unterstützen zu können, wird die Software über eine selbstlernende Funktion (Artificial Intelligence) verfügen, welche es möglich macht, jeden einzelnen Verfahrensschritt als auch die gesamte Prozesskette schnell, zielgerichtet und automatisiert entlang eines Workflows zu optimieren. Die Software soll neben der biopharmazeutischen Industrie auch für die industrielle Biotechnologie (Herstellung von Enzymen und biobasierten Polymeren aus Abfallströmen) als auch im Bereich der Lebensmittelindustrie für die Erzeugung von Proteinersatzstoffen (Cultured Meat, Precision Fermentation) Verwendung finden. Der Name BiochAIn leitet sich daher aus Bio (für Bioprozess), chain (für Prozesskette) und AI (für die Künstliche Intelligenz der Selbstlernfunktion) ab. | D40: in | E40: in | F40: 5 | G40: The grant develops a general bioprocess optimization software toolbox that explicitly names cultivated meat and precision fermentation as intended application areas for alternative protein production, making it in scope despite its broader pharmaceutical and industrial biotechnology focus. | H40: =TRUE() -> TRUE | I40: CC | J40: CC | K40: =TRUE() -> TRUE | L40: =FALSE() -> FALSE | M40: =TRUE() -> TRUE | N40: =TRUE() -> TRUE | O40: =FALSE() -> FALSE | P40: ok
A41: grant.14940383 | B41: Role of sensory perception in cell non-autonomous proteostasis signaling | C41: The accumulation of damaged and aggregated proteins is associated with cellular toxicity and loss of physiological integrity. Degradation of damaged proteins is mediated by the 26S proteasome upon attachment of ubiquitin proteins (ubiquitination). Despite progress in the characterization of proteolytic degradation pathways at the cellular level, cell non-autonomous mechanisms that coordinate the organism-wide activity of the ubiquitin-proteasome system (UPS) in response to environmental changes remain largely unexplored. The nematode Caenorhabditis elegans has a sophisticated chemosensory system involved in the regulation of development, mating, noxious avoidance, and food intake. Chemosensory preferences can be modified by sensory adaptation, allowing the integration of experience into behavior and physiology. We have identified changes in ubiquitin-dependent degradation rates and proteostasis upon feeding worms with different bacterial food sources. Our recent data indicate that these dietary changes in proteostasis are coordinated by a single pair of chemosensory neurons. The microRNA miR-71 functions as a regulatory node to induce cell non-autonomous coordination between olfactory neurons and intestinal cells. The central goal of the proposed research is to understand how olfactory perception and neuronal stimulation are translated into organismal adaptation of proteostasis networks. The proposed project will address brain-gut communication and systematically analyze neuronal response mechanisms induced by olfactory stimulation and proteotoxic stress conditions (Aim 1), regulation of cell non-autonomous signaling between olfactory neurons and intestinal cells (Aim 2), and tissue-specific adaptation of proteostasis pathways (Aim 3). To this end, single-cell transcriptomic/proteomic analyses, chemicalgenetic/optogenetic control of neuronal signaling, CRISPR/Cas9 gene editing, and large-scale genetic screenings will be performed. | D41: out | E41: out | F41: 1 | G41: This grant concerns fundamental cell biology research on protein degradation and proteostasis signaling in C. elegans, with no connection to alternative proteins or food applications. | H41: =TRUE() -> TRUE | I41: NA | J41: NA | K41: =TRUE() -> TRUE | L41: =FALSE() -> FALSE | M41: =FALSE() -> FALSE | N41: =FALSE() -> FALSE | O41: =FALSE() -> FALSE | P41: ok
A42: grant.15150298 | B42: Microbial Feed from Swedish Biogas – Business Models, Verification and Implementation in Aquaculture | C42: The project aims to operationalise the use of methanotrophic biomass, derived from Swedish biogas, as a functional and sustainable feed ingredient in aquaculture. Methanotrophic bacteria convert methane into protein-rich biomass with favourable digestibility and documented benefits for intestinal health in salmonids. While production technologies are established internationally, current systems rely on fossil methane. This project targets renewable biogas as substrate, addressing both climate and resource efficiency.SLU is responsible for modelling the production system under varying methane content, including energy and nutrient flows, yield and cost structures. The University of Gothenburg conducts full-scale feeding trials with rainbow trout to verify growth, feed efficiency, and health outcomes. Sustainable Foods develops business models, investment logic, and communication tools tailored to feed buyers and biogas producers.The project addresses key barriers to implementation, including lack of performance validation, cost benchmarks, and decision-support for procurement. It bridges applied research, system modelling, and market preparation to enable commercial deployment. The results are expected to be scalable within the Nordic region and transferable to international contexts with established biogas infrastructure. | D42: out | E42: out | F42: 1 | G42: This grant concerns methanotrophic biomass as an aquafeed ingredient for salmonids, which is explicitly an animal feed/aquafeed application and not intended for human food consumption. | H42: =TRUE() -> TRUE | I42: NA | J42: NA | K42: =TRUE() -> TRUE | L42: =FALSE() -> FALSE | M42: =FALSE() -> FALSE | N42: =FALSE() -> FALSE | O42: =FALSE() -> FALSE | P42: ok
A43: grant.15148188 | B43: Commercialisation of a therapeutic bacterial vesicle engineering and manufacturing platform | C43: Bacteria naturally release portions of their cell membrane. These outer membrane vesicles (OMVs) are essentially tiny molecular packages containing proteins, fats and other molecules. Bacteria use OMVs to communicate with other cells and to transfer molecules. OMVs are also attractive for use as vaccines or as vehicles for delivering drugs and other therapeutic agents because of their ability to interact with host cells and their natural immunogenic properties. OMV vaccines for use in humans include GSK’s Bexsero®, a Neisseria meningitidis vaccine, that has received MHRA, EMA and US FDA approval and has achieved sales of £218m in Q1 of 2023 alone. Future OMV-based animal vaccines are also likely to have economic and food security importance, or as an exemplar, could help to protect the broiler industry from losing significant numbers of chickens each year due to avian pathogenic E. coli (APEC) related diseases. Further to this, APEC isolates have genetic similarities in terms of virulence markers, with human uropathogenic E. coli (UPEC), and as such may have zoonotic potentials. Worryingly, some APEC strains have also been reported to be resistant to all classes of antibiotics. It may therefore, become increasingly desirable for OMV-based cross protective vaccines to be developed to protect against UPEC and/or APEC in poultry and humans. However, whilst OMV vaccines and therapeutics are promising, our engagements with industry have highlighted important challenges. For example, OMV vaccine manufacturing is typically non-standardised and requires the culture of weakened or highly infectious bacteria to generate the relevant vaccine antigens. Furthermore, the custom engineering of each new bacterial strain to ensure commercially viable OMV yields can slow down OMV vaccine development. Additionally, widely used OMV isolation methods during the manufacturing process might not produce OMVs at suitable yields, purity or bioactivities required for specific applications. Further advancements in OMV engineering approaches are also desirable to enable the manufacture of OMVs with novel therapeutic modalities to treat additional animal or human diseases. To help accelerate next generation OMV therapeutics we have developed an Outer Membrane vEsicle enGineering and mAnufacturing (OMEGA) platform technology to create better and scalable methods for manufacturing new kinds of vaccine or therapeutic OMVs. Our approach differentiates itself from competing technologies through the way in which we have specially engineered our OMEGA bacterial strains to help make it easier to biomanufacture many kinds of therapeutic OMVs in a modular or "Lego-like" fashion. Importantly, our approach also incorporates methods that help simplify our OMV manufacturing process making it easier to produce and isolate OMVs at larger scales. BBSRC FoF support will be used to further scale our OMV manufacturing platform technology, strengthen OMEGA IP, and to carry out focused comparative studies that derisk and show the competitiveness of our approach. Importantly, we will also develop a panel of OMV R&D products and candidate OMV-based APEC vaccines that alongside our continued engagement with the EV industry and other stakeholders will help us to shape and expedite a responsible translational pathway for OMEGA-OMV vaccine and therapeutic manufacturing for the future benefit of animal and human health. | D43: out | E43: out | F43: 1 | G43: This grant concerns bacterial outer membrane vesicle (OMV) engineering for vaccine and therapeutic applications, with no relevance to alternative proteins or plant-based, fermentation-derived, or cultivated substitutes for animal-derived foods. | H43: =TRUE() -> TRUE | I43: NA | J43: NA | K43: =TRUE() -> TRUE | L43: =FALSE() -> FALSE | M43: =FALSE() -> FALSE | N43: =FALSE() -> FALSE | O43: =FALSE() -> FALSE | P43: ok
A44: grant.15201374 | B44: Novel Mechanism-of-Action (NMoA) genes: a pathway to durable Soybean Rust resistance | C44: Implementing the latest knowledge of plant science is critical for achieving resilient crops in the face of increasing food system challenges, such as growing populations, changing climates, and for decreasing inputs of land, water, and chemicals leading to better sustainability. Among the most significant threats to our food supply are losses due to crop diseases, weeds, and pests. Crop diseases and related threats are a widespread and underrecognised cause of food loss that is worsening. One of the most damaging crop diseases for which durable resistance is a high priority is Soybean Rust (SBR). Caused by an airborne fungus, Phakopsora pachyrhizi, SBR is a global, fast-moving disease that can destroy up to 90% of a soybean harvest within just 3 weeks of infection. Conventional methods for combating SBR, such as crop protection chemicals and conventional breeding, have provided some defense but come with significant drawbacks. Chemical treatments are expensive and raise concerns about their potential impacts on human health and the environment. Moreover, the target pathogen (P. pachyrhizi) is quickly adapting and building tolerance to these chemical controls. Conventional breeding efforts are also limited. Though soybean has several resistance genes that have been used in breeding efforts, P. pachyrhizi races have defeated them. With both chemical and conventional breeding interventions losing efficacy against SBR, new sources of resistance are in high demand by growers and seed companies globally. This proposal seeks to advance a recently discovered novel mechanism-of-action (NMoA) that has the potential to contribute to long-lasting, durable protection against SBR for both commercial agriculture and smallholder farmers. The NMoA originates from a locus identified in the wild legume Glycine spp., which exhibits strong resistance to P. pachyrhizi. When transferred into soybean (G. max), it confers robust resistance to SBR in the crop. The main aim of this research is to fully characterize and implement this newly discovered immune response by assessing the breadth and diversity of related sequences across plant species, identifying the interactions between regulatory, signalling, and pathogen effector proteins, elucidating its site of action and impacts on plant defense responses, and lastly determining whether the homologue in soybean can be edited to become functional. NMoAs are highly valuable on their own and in combination with other more common defense responses to create long-lasting, effective resistance. Disease resistance genes from crop relatives have proved to be an effective path to expanding resistance gene diversity. Discovering and characterising a diversity of disease resistance mechanisms-of-action is critical to safeguarding our crop agriculture in the face of global pressures. Data from this study will enable Bayer, a program partner and collaborator, to advance new soybean varieties with durable resistance against this critical disease for commercial agriculture in South America, and for 2Blades to similarly advance new soybean varieties with durable resistance for smallholder deployment in Africa. | D44: out | H44: =FALSE() -> FALSE | I44: NA | J44: CC | K44: =FALSE() -> FALSE | P44: parse_error | Q44: no structured output
A45: grant.15084865 | B45: Maturing food footprint tools, solutions, and uptake to accelerate a rapid EU food transition | C45: There is a recognized and urgent need for better food footprint data to accurately inform the sustainable food system transition as the current knowledge infrastructure is inadequate both in terms of scientific robustness and real-world suitability for regulatory and business decision support. The objective of GREENGROCER is to make foundation-strengthening investments in critical knowledge infrastructure in order to advance food footprint data from lab to application. The project packages investments across over a dozen leading mainstream tools including Trase, HESTIA, CoolFarm, FABIO, and EXIOBASE, which collectively form the foundation of most food footprint data currently in use. Work in GREENGROCER: 1) improves the scientific depth by revisiting long standing weak areas including on subnational supply chain specificity, reliability information, and novel and neglected products and impacts such as spices, seaweed, insect protein, cellular agriculture, cold chain energy use, and seafloor disturbance; 2) makes foundation-strengthening investments that take all models towards full compliance with the EU’s Product Environmental Footprint standards and improve FAIRness and interoperability; and 3) promotes exploitation through multi-stakeholder dialogue between food system researchers, industry, and regulators aimed at prioritising pain points and supporting effective regulation. Finally, to collate data without yet another centralised repository, the project leverages Europe’s competitive advantage in marrying AI with scientific expertise to pioneer a fact-based AI expert which can interact with and gather the rapidly growing volume of food system science. Aimed at the Horizon Europe work program destination of reducing the environmental impact of the food system, GREENGROCER outputs are oriented around 13 specific relevant EU policy frameworks including FSFS, EUDR, ESRS, CSRD, CSDDD, and the CAP. | D45: in | E45: out | F45: 2 | G45: GREENGROCER focuses on improving food footprint data tools and environmental impact assessment infrastructure for the EU food system broadly, and while it briefly mentions cellular agriculture and seaweed among many other topics, alternative proteins are not a primary focus and the grant is fundamentally about food system LCA/footprint methodology rather than alternative protein research or assessment. | H45: =FALSE() -> FALSE | I45: CC | J45: NA | K45: =FALSE() -> FALSE | L45: =FALSE() -> FALSE | M45: =FALSE() -> FALSE | N45: =FALSE() -> FALSE | O45: =FALSE() -> FALSE | P45: ok
A46: grant.15164543 | B46: Antybakteryjne cząsteczki oparte na białkach bakteriofagowych oraz fragmentach stałych przeciwciał o potencjale terapeutycznym w zwalczaniu infekcji bakteryjnych | C46: Zgodnie z informacjami zawartymi w raportach Światowej Organizacji Zdrowia, problem antybiotykooporności, w tym nadużywania antybiotyków, jest jednym z głównych problemów współczesnych systemów opieki zdrowotnej. Antybiotykooporność stanowi poważne wyzwanie dla naukowców i zmusza do ciągłego poszukiwania nowych środków przeciwdrobnoustrojowych. Jednym z obiecujących obszarów badań jest terapia fagowa, która osiąga pozytywne rezultaty na całym świecie. Jest to terapia wykorzystująca wirusy atakujące komórki bakterii, a tym samym powodujące ich eliminacj ę. Podejście to pozostaje terapią eksperymentalną i nie zo stało jeszcze wprowadzone do powszechnego systemu opieki zdrowotnej . Oprócz stosowania całych cząsteczek fagów, można również wykorzystać ich składniki o określonych właściwościach. Interesującą grupą cząsteczek z klinicznego punktu widzenia, ale pozostającą niedostatecznie zbadaną, są białka wiążące receptory (RBP). T a grupa białek wykazuj e unikalne właściwości, ponieważ pozwalają wirusowi infekować bakterie z wysoką specyficznością w stosunku do określonych szczepów bakterii. Innym obiecującym podejściem są terapeutyczne przeciwciała monoklonalne (mAbs), które stanowią strategię leczenia różnych chorób. Obecnie mAbs są szeroko stosowane w leczeniu chorób onkologicznych i immunologicznych. Jednak rozwój mAbs do leczenia chorób zakaźnych pozostaje wyzwaniem. Niewiele przeciwbakteryjnych mAbs ukończyło badania kliniczne, a do tej pory tylko trzy mAbs zostały zatwierdzone przez Amerykańską Agencję Żywności i Leków tzw. FDA do leczenia infekcji, z których wszystkie neutralizują toksyny wytwarzane przez bakterie. Nasze badania mają na celu połączenie mechanizmu działania mAb z właściwościami RBP bakteriofagów, które są wysoce specyficznymi białkami rozpoznającymi bakterie. W tym projekcie proponujemy opracowanie cząsteczki składającej się z białka bakteriofaga i fragmentu przeciwciała. Taka konstrukcja łączy ich funkcje biologiczne: (1) składnik bakteriofagowy umożliwi rozpoznawanie i wiązanie komórek bakteryjnych, a (2) fragment przeciwciała ułatwi interakcję z receptorami na komórkach immunologicznych, takich ja k makrofagi. Makrofagi to komórki układu odpornościowego, które pochłaniają bakterie i trawią je, eliminując w ten sposób patogeny. Proces ten nazywany jest fagocytozą. W tym projekcie proponujemy modułową platformę cząsteczek składających się z białek fagowych i części przeciwciał z wykorzystaniem systemu SpyCatcher, który umożliwia nieodwracalne łączenie dwóch białek. Platforma będzie składać się z „bloków” cząsteczek. Interesujące nas białka będą produkowane przy użyciu inżynierii genetycznej. Wytworzone „bloki”, po zmieszaniu, będą nieodwracalnie reagować i tworzyć funkcjonalne czasteczki. Opisany modułowy charakter platformy umożliwi łączenie cząsteczek w różnych kombinacjach, aby wybrać najbardziej efektywną kombinację w testach funkcjonalnych z wykorzystaniem linii komórkowych. Podsumowując, głównym celem tego projektu jest stworzenie platformy białek naśladujących przeciwciała, skutecznie łącząc różne mechanizmy biologiczne w celu wzmocnienia naturalnej odpowiedzi immunologicznej przeciwko infekcjom zagrażającym życiu. Platforma ta jest szczególnie ukierunkowana na zwalczanie bakterii wielolekoopornych, takich jak Pseudomonas aeruginosa i Escherichia coli, które są klasyfikowane jako patogeny o wysokim priorytecie. Jeśli uda się uzyskać funkcjonalną cząsteczkę, która będzie skuteczna w badaniach na liniach komórkowych, z pewnością przyczyni się to do rozwoju kolejnych rozwiązań opartych na bakteriofagach, co z kolei zapewni w przyszłości remedium na trudne przypadki infekcji szczepami wielolekoopornymi. Aby osiągnąć cele projektu, wykorzystane zostaną różne zaawansowane metody, takie jak cytometria przepływowa czy mikroskopia holotomograficzna do badania zjawiska fagocytozy oraz skuteczności zabijania fagocytowanych patogenów. Wszystkie wybrane metody pozwolą nam ocenić potencjał prezentowanego przez nas rozwiązania. | D46: out | E46: out | F46: 1 | G46: This grant concerns bacteriophage-based antibacterial molecules and antibody fragments for therapeutic use against bacterial infections, which is a pharmaceutical/medical application with no relevance to alternative proteins for human food. | H46: =TRUE() -> TRUE | I46: NA | J46: NA | K46: =TRUE() -> TRUE | L46: =FALSE() -> FALSE | M46: =FALSE() -> FALSE | N46: =FALSE() -> FALSE | O46: =FALSE() -> FALSE | P46: ok
A47: grant.15149477 | B47: Unravelling the mechanism of meiotic crossover patterning in diploid and polyploid plants | C47: Eukaryotic sex cells (e.g., sperm and eggs in humans) are produced by a specialised cell division called meiosis, where chromosomes exchange large DNA segments. These DNA exchanges, or crossovers, are essential for generating genetic diversity, and are a driving force for evolution and selective breeding. Crucially, crossover frequency and position along chromosomes are tightly controlled, introducing a bottleneck for plant and animal breeders due to low crossover numbers and their skewed distribution. However, despite a century of research, the cellular mechanisms that determine where, how quickly and how many, crossovers form has remained mostly mysterious. Chromosome size, ploidy and the dynamics of chromosome pairing during early meiosis are all known to have profound effects on crossover patterning, yet how these features interact to influence crossover site designation is unknown. We recently proposed a ‘coarsening’ model for crossover patterning that creates a unique framework to mechanistically dissect the influence of these key features on the crossover landscape. Our coarsening model captures the dynamics of a conserved protein involved in promoting crossovers called HEI10, including its ability to associate into increasingly large, distantly-spaced foci on the chromosomes as meiosis progresses. The dynamics of HEI10 orthologs are very similar in organisms as diverse as plants, fungi and animals, making our model of wide applicability. However, HEI10 is unlikely to be acting alone during the coarsening process, making it critical to also investigate the roles played by the many other recombination proteins. In this proposal, we will address these key issues by performing live-imaging and super-resolution cytogenetics of HEI10 and other recombination proteins in diploid and polyploid plant species, closely coupled with computational modelling. Our goal is to comprehensively understand the processes that determine meiotic crossover site selection. Generating mechanistic insight into this highly conserved aspect of eukaryotic genetics could drive future innovation in plant and animal breeding. Our specific objectives are: 1) Unravel how chromosome pairing, as well as the coarsening dynamics of HEI10 and other recombination proteins, control crossover patterning in Arabidopsis thaliana, a plant with a compact genome commonly used in research. We will use predictive modelling, live-imaging and genetic dissection to understand how these factors interact in time and space to shape the plant recombination landscape. 2) Dissect crossover positioning in polyploids, which are common among major crop species. The presence of multiple homologous chromosomes in polyploids poses a unique challenge for homologue pairing and crossover site selection, causing dramatic reductions in fertility in newly formed polyploid species due to misplaced crossovers. Using modelling and experiments, we will therefore investigate how crossover patterning dynamics are altered to drive the evolutionary stabilisation of meiosis in newly-formed and established polyploids of the Arabidopsis genus. 3) Dissect crossover positioning in a giant polyploid genome, wheat, that is ~120 times bigger than the Arabidopsis genome. Using modelling and experiments, and our insights from Objectives 1 and 2, we will examine whether we can predict how coarsening and pairing contribute to the low numbers and skewed distribution of crossovers along wheat chromosomes. These objectives will enable our team to comprehensively investigate universal mechanisms that drive crossover positions in eukaryotes, including crop species such as wheat, that are economically critical. Our project goals closely align with the BBSRC’s ‘Understanding the rules of life’ and ‘Sustainable agriculture and food’ strategic objectives. | D47: out | E47: out | F47: 1 | G47: This grant concerns fundamental plant genetics and meiotic crossover mechanisms in Arabidopsis and wheat, with no connection to alternative protein development, production, or applications. | H47: =TRUE() -> TRUE | I47: NA | J47: NA | K47: =TRUE() -> TRUE | L47: =FALSE() -> FALSE | M47: =FALSE() -> FALSE | N47: =FALSE() -> FALSE | O47: =FALSE() -> FALSE | P47: ok
A48: grant.15147565 | B48: BacCORAC: Bacterial modulation of plant responses via CORonafacic Acid Conjugates | C48: Potato, the world’s third main food crop, is produced in over 100 countries and is a critical crop in terms of food security in the face of increasing populations and hunger rates. Potato food security is challenged by multiple pests and pathogens compounded with climate change and the need for sustainable agri-chemical solutions to improve crop resilience. To find potential solutions, research into the actions of natural biological products is fundamental. Plant development and health is partly controlled by a complex regulatory network and cross-talk of phytohormones including auxins, gibberellins, ethylene, salicylic acid and jasmonates. This cross-talk can be influenced by bacteria, both beneficial and pathogenic, colonising the plant through hormone mimicry, sequestration or degradation. Secondary metabolites produced from microbes offer a natural resource for future agri-chemical products and many biosynthetic gene clusters (BGCs) remain to be fully understood across different bacterial species. Distantly related plant or soil-associated bacterial species encode the BGC for coronafacic acid (CFA), which has phytotoxic properties when joined to amino acids or their derivatives, such as coronamic acid (CMA). The first discovered and most characterised such phytotoxin is coronatine (COR; CFA+CMA). COR acts as a potent jasmonate mimic modulating downstream plant responses, such as plant immunity and root growth. The potato pathogen Pectobacterium atrosepticum produce CFA, but cannot produce CMA, resulting in amino acids valine/isoleucine being joined to CFA instead (hereby called CFA-conjugates). COR’s strong effects on the jasmonate signalling pathways have been well characterised in the model plant Arabidopsis, but less is known about the responses to CFA-conjugate mimics, and little is known about such responses in major crops such as potato. The project will focus on the phytopathogen P. atrosepticum (Pba) which causes blackleg and tuber soft rot of potato, with no chemical methods of control. To date, only Pectobacterium strains that are restricted to cause disease symptoms on potato can produce CFA-conjugates. Our preliminary results show that Pba produce mainly CFA-valine and Pba CFA knock-out mutants are reduced in plant root colonisation, root growth inhibition and disease progression. The aim of the project is to understand the regulation of CFA production in Pba and the biological role of CFA conjugates in potato-Pba interactions. Our approach will be across three work-packages to: Elucidate the regulation of CFA expression in Pba. Identify plant proteins that bind to CFA-valine/isoleucine conjugates. Identify potato genes that are affected by the presence of CFA- conjugates. COR has been studied for multiple agri-chem applications, including as a weedkiller (herbicide) or promoting plant resistance to drought-stress or insect-feeding. Jasmonates and COR have been shown to promote potato tuber initiation and expansion. Understanding the function of CFA-valine/isoleucine in Pba-potato interactions could inform on potential points of intervention to control potato infection or disease progression. Fundamental insights into CFA-conjugates modulating potato responses can lead to innovative ways to improve potato plant growth and tolerance to stresses. This interdisciplinary project fits well within the BBSRC strategic plan for sustainable agriculture and food linking to the spotlight area of ’developing novel crop protection strategies’. Although this project focusses on the Pba-potato pathosystem, the outcomes from the project will inform on other important plant pathogens which produce CFA-AA, such as Brenneria spp (causes Acute Oak Decline) or Pseudomonas spp (infects broad range of plants). | D48: out | H48: =FALSE() -> FALSE | I48: NA | J48: CC | K48: =FALSE() -> FALSE | P48: parse_error | Q48: no structured output
A49: grant.15148367 | B49: iTKP fusions: Structure, function and engineering of an emerging plant disease resistance system | C49: Context and Challenge: Yield from key crops that feed the world is threatened by abiotic and biotic stresses. Pre-harvest plant disease can decimate crop production by small-holder farmers and is estimated to reduce yields by 20-30% in modern agriculture despite the intensive interventions used (e.g. pesticides). However, current chemical control of pathogens is not sustainable due to the direct impact of their use on the environment and the environmental and economic cost of production. There’s a pressing need to reduce chemical control of plant diseases within the background of the climate emergency and emergence of pathogens in new areas. The overarching aim of this proposal is to develop new genetic solutions for managing blast disease, caused by the fungus Magnaporthe oryzae, in cereal crops. With collaborators, we have discovered novel components of the plant immune system that could deliver new solutions to managing plant diseases, but first we need to understand how they work, and then how they can be engineered. In time, our discoveries should be applicable to managing other plant diseases. Like animals, plants have an immune system that helps defend against disease. This immune system includes receptors, proteins that detect pathogens and pests, and activate immune responses. Frequently, immune receptors from inside plant cells (intracellular receptors) detect “effector” proteins, pathogen-derived molecules delivered to promote disease. Pathogens are often adapted to particular plant hosts, and plant/pathogen co-evolution has led to a diverse set of immune receptors encoded in different plant genomes. Most research in the last ~30 years has focussed on one type of intracellular immune receptor (called NLRs). Recently though, a new type of receptor (the tandem kinase proteins or TKPs) is being repeatedly found using modern approaches to disease resistance discovery. Aims and Objectives: There is an urgent need for broadening the genetic basis of plant disease resistance and understanding how we can help plants fight back against disease. This project will address this challenge by integrating extensive preliminary data and expertise in the Banfield Lab, along with collaborators, to address the following specific objectives: Demonstrate that binding determines immune activation by validating crystal structures of effector/receptor domain complexes using in vitro and in vivo assays. Establish the diversity of interactions available to drive immune engineering by profiling an interaction matrix of iTKP-HMA (receptor) domains and effectors from M. oryzae and other pathogens. Explore the molecular mechanism of iTKP signalling, specifically in the context of integrated HMA domains. Develop and test iTKPs as chassis for engineering immune responses to pathogen effectors. Potential applications and benefits: Plant immune receptors are deployed in breeding programs to genetically encode resistance, protecting crop harvests from disease. But due to pathogen co-evolution with plants, new disease management resources are continually required. Here, by understanding how a new family of receptors works and can be engineered we will boost plant immunity, providing new avenues towards more sustainable agriculture. The research fits BBSRC's priorities for “sustainable agriculture and food” as detailed in the Strategic Delivery Plan 2022-2025, addressing a crucial global challenge. It also fits the current responsive mode spotlight area of “Plant Health - Development of novel crop protection strategies”. | D49: out | H49: =FALSE() -> FALSE | I49: NA | J49: CC | K49: =FALSE() -> FALSE | P49: parse_error | Q49: no structured output
A50: grant.14954839 | B50: Nourishing Europe's Future through Regenerative Livestock Feed | C50: NUTRIFEEDS is dedicated to developing regenerative animal feed solutions by transforming underutilised local plants and agri-food by-products into high-protein feed through cutting-edge, cross-disciplinary methods. Aligning with the EU's Farm2Fork strategy, the project aims to reduce the reliance on imported feeds, enhance agricultural circularity, and minimize waste. The initiative involves detailed analysis of raw materials, including net energy, followed by their enhancement through Black Soldier Fly larvae and targeted fermentation to improve nutrient content and reduce anti-nutritional factors. Experimental validation will contribute to enhanced diet formulation. The project explores the impacts on welfare, health, immune responses, microbiome, and behaviour of both monogastric animals and ruminants. Through collaborations with farms, experimental feeds from insect upcycling and fermentation will be refined. NUTRIFEEDS also seeks to build on existing silvopasture systems and engages farmers in co-creating local policies. It also integrates AI for insightful data analysis and development of software aiding farmers with efficient monitoring and feeding systems, allowing hence for the creation of feed formulations that enhance both animal health and welfare while sustaining productivity. Thus, the project emphasizes animal welfare, aims to reduce the environmental impact of feed production, and involves stakeholders in the development and dissemination of its solutions. Methods of preserving energy, such as drying powered by solar energy, will help to create extra revenue streams from the sale of feed. A proposed European Centre for Regenerative Animal Nutrition will facilitate dissemination and promote uptake of these innovations and will implement online courses based on NUTRIFEEDS findings. NUTRIFEEDS will factor in environmental, social and economic sustainability and will create guidelines to reinforce Europe's position as a leader in global innovation. | D50: out | E50: out | F50: 1 | G50: This grant focuses on developing animal feed solutions using insects, fermentation, and plant by-products for livestock nutrition, which is explicitly an animal feed application and not an alternative protein product for human consumption. | H50: =TRUE() -> TRUE | I50: NA | J50: NA | K50: =TRUE() -> TRUE | L50: =FALSE() -> FALSE | M50: =FALSE() -> FALSE | N50: =FALSE() -> FALSE | O50: =FALSE() -> FALSE | P50: ok
A51: grant.15163028 | B51: Wykorzystanie niekonwencjonalnych, nietermicznych metod obróbki wstępnej oraz ich kombinacji do kształtowania właściwości fizycznych, chemicznych oraz jakości mikrobiologicznej suszonego mącznika młynarka (Tenebrio molitor L.) | C51: Zainteresowanie owadami w kontekście ich spożycia wynika z ich interesującego składu chemicznego, tj. wysokiej zawartości białka, zawartości tłuszczu bogatego w jedno- i wielonienasycone kwasy tłuszczowe, chityny, a także obecności składników mineralnych oraz witamin. Dodatkowo, hodowla owadów niesie ze sobą zdecydowanie mniejszy negatywny wpływ na środowisko niż tradycyjna hodowla zwierząt. Jednak oprócz wymienionych korzyści, występują niestety pewne zagrożenia. Wśród najważniejszych wymienić należy zagrożenia mikrobiologiczne, tj. obecność bakterii, drożdży, pleśni oraz alergenów. Jednak wiedza na temat wartości odżywczej wielu gatunków owadów jest wciąż ograniczona. Brakuje również badań, w których sprawdzano wpływ i wyjaśniano mechanizm stosowania różnych metod obróbki na jakość mikrobiologiczną oraz skład chemiczny owadów. Dlatego też poszukuje się nowych rozwiązań pozwalających na szersze wykorzystanie owadów w technologii żywności. Z tego względu prowadzenie badań w tym zakresie wydaje się być w pełni uzasadnione. Uzasadnieniem podjętej tematyki badawczej jest rosnąca liczba ludzi na świecie, która według szacunków FAO (Organizacja Narodów Zjednoczonych do spraw Wyżywienia i Rolnictwa) w 2050 r. zbliży się do 10 miliardów, a więc wzrośnie o 34%. Wraz z globalnym wzrostem populacji na świecie rośnie zapotrzebowanie na żywność, szczególnie na produkty charakteryzujące się wysoką zawartością pełnowartościowego białka. Rosnące zapotrzebowanie na żywność powoduje intensyfikację produkcji rolnej oraz hodowli zwierząt, co niekorzystnie wpływa na środowisko naturalne. Obiecującym rozwiązaniem tego problemu wydaje się być hodowla owadów jadalnych jako źródło nowej żywności. Celem projektu jest określenie podstawowego składu chemicznego oraz liczby drobnoustrojów w owadach jadalnych na przykładzie larw mącznika młynarka Tenebrio molitor , a także wyjaśnienie mechanizmu oddziaływania nietermicznych metod obróbki wstępnej oraz określenie ich wpływu, jak i procesu suszenia, na jakość mikrobiologiczną oraz właściwości fizyczne i chemiczne owadów jadalnych i składników z nich pochodzących (np. tłuszczu) . Dodatkowo, badania mają na celu poznanie zmian we właściwościach tkanki owadziej, w wyniku zastosowania metod obróbki wstępnej oraz procesu suszenia. W ramach projektu zbadany zostanie wpływ blanszowania (BL) jako próbki odniesienia, a także innowacyjnych, nietermicznych metod obróbki, tj. pulsacyjnego pola elektrycznego (PEF), ultradźwięków (US) , wysokiego ciśnienia hydrostatycznego (HHP) , jak i metod łączonych na właściwości obrabianego materiału, przebieg procesu suszenia konwekcyjnego oraz właściwości otrzymanych suszy i tłuszczu . Rezultaty projektu pozwolą na wyjaśnienie mechanizmu oddziaływania nowych nietermicznych metod ob róbki wstępnej na strukturę owadów jadalnych na przykładzie larw mącznika młynarka Tenebrio molitor oraz porównanie ich skuteczności, w szczególności na jakość mikrobiologiczną oraz wybrane jej cechy jakościowe m.in. zawartość białka i tłuszczu wraz z ich charakterystyką. Zdobyta podczas realizacji projektu wiedza pozwoli na lepsze zrozumienie zjawisk zachodzących w trakcie obróbki wstępnej, a także przewidywanie skutków tych zjawisk. Przeprowadzone badania mogą dostarczyć rzetelnej, naukowo udokumentowanych informacji na temat wartości odżywczej owadów jako alternatywnego źródła żywności. Takie dane mogą pomóc decydentom w podejmowaniu bardziej świadomych decyzji dotyczących zrównoważonej produkcji żywności i promocji nowych źródeł białka. Wnioski z tego projektu mogą więc wesprzeć rozwój polityki żywieniowej, społecznej i ekologicznej, przyczyniając się do tworzenia bardziej zrównoważonych i zrównoważonych systemów żywnościowych. Uzyskane wyniki badań będą mogły posłużyć jako punkt wyjścia do dalszych badań nad jakością mikrobiologiczną owadów jadalnych, a także modyfikacją właściwości fizycznych ich tkanki. Wyniki badań przyczynią się także do poszerzenia wiedzy na temat wartości odżywczej owadów jadalnych oraz zachęcą potencjalnych konsumentów do włączenia ich w swoją codzienną dietę. Co ważne, uzyskane wyniki mogą być w przyszłości wykorzystane w sektorze produkcji żywności. Owady przygotowane w sposób zaproponowany w projekcie mogą stanowić interesujący składnik do potencjalnego wykorzystania w celu wzbogacenia powszechnie znanych produktów spożywczych jako źródło białka lub innych składników, bioaktywnych lub mineralnych. | D51: out | E51: out | F51: 1 | G51: This grant focuses entirely on insect-based proteins (Tenebrio molitor larvae), which are explicitly excluded from the alternative proteins scope. | H51: =TRUE() -> TRUE | I51: NA | J51: NA | K51: =TRUE() -> TRUE | L51: =FALSE() -> FALSE | M51: =FALSE() -> FALSE | N51: =FALSE() -> FALSE | O51: =FALSE() -> FALSE | P51: ok
A52: grant.14954840 | B52: New business for farmers and cooperatives in rural areas by local upcycling solutions using underutilized agricultural feedstocks | C52: PRIMARY aims to develop and pilot local solutions for the production of food, feed, bio-based materials, bioenergy, and fertilizers by valorizing agricultural biomass feedstocks, including grass, greenhouse and cotton by-products, and olive tree pruning that are currently underutilized and exist in substantial amounts in Europe. The project focuses on North-East Europe (Finland) and South-East Europe (Greece), providing business models and demonstrations in rural areas where pilot and demo plants are rare. PRIMARY works with primary producers and local actors, and pilots six process concepts: 1) separation of protein and fibre rich fractions from grass to produce food/feed and biobased materials, respectively; 2) submerged and 3) solid-state fermentation processes to upcycle the feedstocks to protein rich food and feed ingredients; 4) fibre forming technology to enable production of packaging and construction materials; 5) pelletizing process to solid biofuel for gasification to bioenergy from olive-tree pruning and cotton byproducts; 6) pyrolysis of cotton and olive byproducts to biochar for fertilizer and material applications. The solutions piloted in the project are selected based on cascading use of the feedstocks to find the highest possible value, considering the regional conditions. Sustainability of the new value chains is broadly assessed. To maximise project outcomes and impact, other partners and regions are engaged through an open innovation call to promote the ecosystem for valorizing agricultural biomass, and to show replicability of the project solutions. PRIMARY outcomes, including new processes, products and service concepts, will be communicated via various channels, including a stakeholder platform, to ensure wide exploitation of the solutions. A multi-actor approach is used in the development of processes and replicable business models, and for delivering guidance to farmers and SMEs, and advice to policymakers at national and EU level. | D52: in | E52: out | F52: 2 | G52: While the project involves protein separation from grass and fermentation to produce protein-rich ingredients, the primary focus is on agricultural biomass valorization for food, feed, bioenergy, and materials broadly, with no specific application to alternative protein products substituting animal-derived foods. | H52: =FALSE() -> FALSE | I52: F | J52: NA | K52: =FALSE() -> FALSE | L52: =FALSE() -> FALSE | M52: =FALSE() -> FALSE | N52: =FALSE() -> FALSE | O52: =FALSE() -> FALSE | P52: ok
A53: grant.15202198 | B53: Uncovering the antimicrobial and antibiotic potentiating mechanism of acesulfame-K and maximising its topical therapeutic potential. | C53: Infectious diseases were once the leading cause of death amongst men and women in almost all age demographics in the UK. However, the discovery of antibiotics revolutionised our ability to treat bacterial infections and, as a result, saved millions of lives. Bacteria inhabit almost every corner of our planet due to their incredible ability to adapt to different environmental niches. This capacity to evolve and survive even in the most inhospitable environments means that, following the introduction of a new antibiotic to our healthcare systems, resistant bacterial strains rapidly appear. This cycle has kept repeating until the emergence, in some instances, of infections that cannot be effectively treated with any currently available antibiotics. This is creating a dangerous situation where a "post-antibiotic" era is now becoming a reality, threatening all aspects of healthcare from cancer treatment to dental work. At the forefront of pathogens that can evolve multidrug resistance is Acinetobacter baumannii. This pathogen can infect individuals who are already sick or have a supressed immune system, leading to a variety of life-threatening clinical complications and, potentially, death. This creates a problem particularly in hospitals where most A. baumannii outbreaks occur. Prior to the 2000s, A. baumannii infections were relatively infrequent and, typically, very treatable. However, there has been a rapid increase in the number of these infections, such that this bacterium now accounts for 20% of all infections seen in Intensive Care Units (ICUs) worldwide. These infections are incredibly difficult to treat, with up to 75% of A. baumannii isolated from these patients being resistant to more than 3 types of antibiotic. Previously, we have shown that the artificial sweetener acesulfame K (ace-K), a compound is consumed by millions of people around the world every day in "sugar free" or "calorie free" food and drinks, has a remarkable ability to tackle this pathogen. We demonstrated that not only can ace-K inhibit this pathogens growth. It can also inhibit a range of virulent processes that it uses to establish infection, including the ability to move from the initial site of infection and the capacity of this bacteria to form communities called biofilms which help it overcome antibiotic therapy. Remarkably, we also demonstrated that this compound will make A. baumannii vulnerable to antibiotics that it has previously evolved resistance to. We now want to explore what exactly ace-K is doing to the cell to stop it growing and to increase its sensitivity to antibiotics. We will use a range of cutting-edge fluorescent microscopy, proteomics and molecular biology techniques to uncover exactly how ace-k effects the bacterial cell and resensitises it to antibiotics. We will develop, characterise and assess novel ace-K loaded wound dressings to tackle acute and long-term, difficult to treat infections and test them in a porcine ex vivo wound model. We will also test these loaded wound dressings in a mouse wound model to determine their capacity to treat infection. As ace-k is approved for consumption by every international regulatory body including the Food and Drug Administration, it means it has been extensively tested for safety. Therefore, there is significant potential that the use of ace-K as a therapeutic to tackle infection could be fast tracked to clinical trials and into hospitals. This would overcome one of the main barriers delaying the introduction of new antimicrobials drugs which is that all the safety testing and trials required before final approval can take over 15 years on average to complete. Technical Summary A central facet to the pathogenic success of Acinetobacter baumannii is in part attributable to its ability to overcome antibiotic therapy. Recent work from the McCarthy Lab has identified a compound, acesulfame K (ace-K), with previously unrecognised antimicrobial and antibiotic potentiating activity. This proposal takes a highly interdisciplinary and disruptive approach to characterising the mechanism of action of this compound and determining its therapeutic potential. This includes the use of cutting-edge technologies such as thermal proteomic profiling and mouse models of chronic wound infection. For aim 1 this proposal will use a combination of live cell microscopy, and state-of-the-art molecular genetics tools that have been developed by the McCarthy lab to define the consequences of ace-K exposure on peptidoglycan in the cell envelope, and the role the DnaK/GrpE/GroSL system in influencing cell envelope disturbances. We will also use cutting-edge Proteome Integral Solubility Alteration assays integrated with Expression Proteomics (PISA-Express) to identify direct protein-ace-K interactions and impacts on the total proteome. We will also repeat this assay to understand the fate of meropenem within the cell in the presence and absence of ace-K. For aim 2 we will develop and characterise novel ace-K, and ace-K + antibiotic loaded aerogel and hydrogel wound therapies to target acute and chronic wound infections. We will then assess the developed formulations using an ex vivo porcine skin model of wound infection. Finally, in aim 3, we will rigorously assess the efficacy of the developed wound therapies in a world leading mouse acute and chronic wound model to demonstrate the therapeutic potential of ace-K. | D53: out | E53: out | F53: 1 | G53: This grant concerns antimicrobial properties of acesulfame-K against bacterial pathogens and wound infection therapy, with no connection to alternative proteins or plant-based, fermentation-derived, or cultivated food products. | H53: =TRUE() -> TRUE | I53: NA | J53: NA | K53: =TRUE() -> TRUE | L53: =FALSE() -> FALSE | M53: =FALSE() -> FALSE | N53: =FALSE() -> FALSE | O53: =FALSE() -> FALSE | P53: ok
A54: grant.15156012 | B54: Exploring the Morphogenesis of Omniphobic Nano-Ornamentations on the Springtail Cuticle | C54: Wetting resistance (omniphobicity) is a highly desired material property in all-day life, industry, medicine or marine and aviation applications. Omniphobicity enables machines and tools to remain dry, clean and functional for longer periods, extends shelf times of food and reduces transmission of germs on surfaces. For many years, researchers have proposed various top-down approaches to create omniphobic surfaces, but none have been scalable or economically viable for large-area coatings. Springtails (Collembola), close relatives of insects, have adopted to life on landwith a respiration through their body surface. This requires a priori a strongly repellant cuticle, which is achieved by nano-scale surface architecture. The responsible structures possess mushroom-like overhanging cross-sections, a structure shape which is known for its ability to endow omniphobicity. This structure is embedded in a grid-like ornamentation which furthermore promotes mechanical resistance. Previous research has shown that the entire omniphobic nano-ornamentation is associated with the topmost proteinaceous epicuticle, rather than the chitin layers below. However, the underlying biological morphogenesis of these structures is not yet clarified despite its potential in informing a scalable bottom-up process. The proposed project aims to identify the structural proteins involved in the formation of this structure and elucidate the spatio-temporal morphogenic processes. To achieve this, we will employ advanced imaging techniques, transcriptomic and proteomic analyses, and diverse spectroscopic methods. In parallel, we will use high-throughput screening, supported by a design of experiment approach and multivariate statistical analysis, to effectively reverse-engineer the structure formation using recombinant proteins in vitro. Our main hypothesis predicts that morphogenesis is based on Turing's reaction-diffusion theory, involving the interplay between a fast-diffusing lipid phase and a slow-diffusing protein phase during cuticular renewal within the moulting cycle. Modeling and simulation will accompany the in vitro experiments, allowing for feedback between experiment and simulation to confirm or disprove model assumptions and adjustments, such as diffusion parameters or phase ratios. This project not only aims to elucidate the unknown morphogenetic processes in the epicuticle of arthropods in general but also represents the first step towards translating this knowledge into synthetic self-assembling omniphobic interfaces. | D54: out | E54: out | F54: 1 | G54: This grant concerns the biological morphogenesis of omniphobic nano-structures on springtail cuticles for materials science applications, with no connection to alternative proteins or food protein substitutes. | H54: =TRUE() -> TRUE | I54: NA | J54: NA | K54: =TRUE() -> TRUE | L54: =FALSE() -> FALSE | M54: =FALSE() -> FALSE | N54: =FALSE() -> FALSE | O54: =FALSE() -> FALSE | P54: ok
A55: grant.15059255 | B55: Impacto dos líquidos iónicos no metabolismo secundário das plantas | C55: As plantas produzem uma enorme diversidade de compostos orgânicos de baixo peso molecular. Mais de 200 000 metabolitos secundários das plantas (MSP) foram isolados e identificados. Os MSPs possuem estruturas químicas variadas e uma ampla gama de atividades biológicas, com uma função na interação planta – ambiente, e com aplicações na indústria, agricultura, biomedicina e ecologia. A biossíntese de MSPs está muitas vezes sujeita a uma regulação apertada, o que se traduz numa disponibilidade limitada destes metabolitos. Assim, têm sido exploradas diversas abordagens estratégicas de bioengenharia, entre outras, para potenciar a síntese de MSPs por forma a responder às necessidades da indústria e da agricultura, entre outras (15, 16). Os líquidos iónicos (LIs) são sais orgânicos líquidos a uma temperatura inferior a 100°C. São altamente versáteis devido à enorme variedade de combinações possíveis de aniões e catiões, e têm propriedades químicas diversas (17). Em culturas de fungos, observou-se que a suplementação com concentrações sub-inibitórias destes sais orgânicos complexos altera o perfil metabólico e as vias de resposta ao stress dos fungos (9). Neste projeto, temos como objetivo utilizar o sistema de protoplastos de Arabidopsis como uma plataforma de triagem para o estudo e optimização do impacto dos líquidos iónicos no metabolismo secundário das plantas. Este sistema transitório e versátil de células vegetais será utilizado para caracterizar e optimizar as interações entre líquidos iónicos à base de colina e a planta modelo Arabidopsis thaliana . O conhecimento adquirido sobre as interações entre fungos filamentosos e líquidos iónicos à base de colina, será traduzido para outro organismo eucariótico. Em particular, estamos interessados na ativação e na diversificação da produção de metabolitos secundários com atividade biológica desencadeada pelos líquidos iónicos em culturas de fungos (9, 24, 25), e vamos usar o sistema de protoplastos de Arabidopsis para testar se o mesmo se verifica em plantas, como uma prova de conceito. Será dada uma ênfase especial ao estudo dos mecanismos moleculares subjacentes à produção de metabolitos secundários em plantas em resposta à suplementação com líquidos iónicos. Para tal, iremos utilizar abordagens de bioquímica e de biologia molecular para analisar a resposta de várias vias metabólicas e de sinalização de stresse alvo nas plantas, ao nível dos transcriptos e da proteína. Além disso, iremos executar análises imparciais ao transcriptoma e metaboloma para desvendar a assinatura dos líquidos iónicos à base de colina nas vias metabólicas das plantas. O conhecimento inovador obtido com estas abordagens no sistema de protoplastos de Arabidopsis, poderá depois ser traduzido para a produção de compostos orgânicos de baixo peso molecular, por exemplo de alto valor nutricional e de elevada procura pela indústria alimentar, utilizando os modelos de plantas mais adequados e/ou fábricas de células vegetais, em resposta aos líquidos iónicos. | D55: out | E55: out | F55: 2 | G55: This grant studies the impact of ionic liquids on secondary metabolism in Arabidopsis plants, with no stated application in alternative protein products; the mention of potential food industry applications is vague and concerns low-molecular-weight compounds, not protein substitutes for animal-derived foods. | H55: =TRUE() -> TRUE | I55: NA | J55: NA | K55: =TRUE() -> TRUE | L55: =FALSE() -> FALSE | M55: =FALSE() -> FALSE | N55: =FALSE() -> FALSE | O55: =FALSE() -> FALSE | P55: ok
A56: grant.14716787 | B56: Food Responsive Sensor for Colorimetric Observation | C56: Enhancing food safety and reducing waste are global challenges, especially with the rise in food consumption and distribution. Food spoilage is a key component of these challenges. One of the critical indicators of food spoilage is the presence of toxic compounds formed by microbial activity in protein-rich foods such as fish, meat, and cheese. The FRESCO project develops an innovative colorimetric sensor for detecting toxic by-products. This sensor utilizes advanced porous materials that change color when exposed to harmful levels of toxic by-products, enabling real-time monitoring in food packaging. The sensor material, combined with a polymeric-based matrix, will be integrated into flexible packaging materials, allowing continuous observation of food freshness. By tracking color changes, it will be possible to monitor food quality. FRESCO aligns with the United Nations Sustainable Development Goals (SDGs), particularly SDG 2 (Zero Hunger) by promoting food safety and reducing waste, SDG 3 (Good Health and Well-being) by minimizing the risk of foodborne illnesses, and SDG 12 (Responsible Consumption and Production) by enabling more sustainable food management practices. This project utilizes advanced porous composites and builds upon the findings of previous ERC-funded work to deliver a practical, scalable, and cost-effective solution. With its potential to improve food quality control in real-time and reduce food spoilage, FRESCO is set to advance the food packaging industry and contribute to healthier and more sustainable consumption. | D56: out | E56: out | F56: 1 | G56: This grant concerns colorimetric sensors for detecting food spoilage in conventional protein-rich foods (fish, meat, cheese), with no focus on alternative proteins or their development, production, or assessment. | H56: =TRUE() -> TRUE | I56: NA | J56: NA | K56: =TRUE() -> TRUE | L56: =FALSE() -> FALSE | M56: =FALSE() -> FALSE | N56: =FALSE() -> FALSE | O56: =FALSE() -> FALSE | P56: ok
A57: grant.15145615 | B57: AlgFlavor - Verbeteren van de consumentenacceptatie van algen voor de voedselmarkt | C57: AlgFlavor gaat over het gebruik van zeewier en microalgen (samen alg genoemd) als duurzamevoedselbron. Deze zijn rijk aan voedingsstoffen zoals eiwitten, mineralen en omega-3 vetzuren, enkunnen helpen aan de groeiende vraag naar gezonde, duurzame voeding. Er zijn uitdagingen omvoedsel op basis van algen beter te maken, voornamelijk vanwege hun smaak en geur.Om deze uitdagingen aan te pakken, werkt AlgFlavor aan het verbeteren van deconsumentenacceptatie van voedingsmiddelen met algen. Verschillende soorten algen hebbenverschillende smaken, variërend van bitter tot hartig. Sommige algen hebben zelfs een smaak dielijkt op zeevruchten, waardoor ze geschikt zijn voor plantaardige alternatieven voor zeevruchten.De smaak van algen kan worden beïnvloed door hoe ze worden geteeld en verwerkt. AlgFlavor zaldeze omstandigheden optimaliseren om een consistente smaak te garanderen en om algen teverwerken in verschillende voedingsproducten (oa brood, sauzen).Algen hebben veelbelovende smaak- en voedingseigenschappen, maar moeten consistenter,betaalbaarder en beter worden voor consumptie. AlgFlavor zal dit doen door sensorische evaluatiesen chemische analyses uit te voeren en diverse voedselprototypes te ontwikkelen.Het ultieme doel is om een markt te creëren voor voedingsmiddelen op basis van algen, gericht opplantaardige alternatieven voor zeevruchten, door de consumentenacceptatie te verbeteren en debehoeften van zowel producenten als consumenten te begrijpen. | D57: in | E57: in | F57: 6 | G57: The grant focuses on improving consumer acceptance of seaweed and microalgae as food ingredients, explicitly targeting plant-based seafood alternatives, which falls within the plant-based alternative protein category. | H57: =TRUE() -> TRUE | I57: PB | J57: PB | K57: =TRUE() -> TRUE | L57: =TRUE() -> TRUE | M57: =FALSE() -> FALSE | N57: =FALSE() -> FALSE | O57: =FALSE() -> FALSE | P57: ok
A58: grant.14878648 | B58: Metal-induced resistance in pepper against Botrytis cinerea | C58: Plants often face challenges like poor soil quality, lack of nutrients, and diseases caused by pests and pathogens. These issues can reduce crop yields and threaten food security. A study found that diseases and pests cause over 20% of the annual loss in the world`s major crops like wheat, rice, and maize. This highlights the need for effective ways to protect plants. The European Commission aims to reduce the use of chemical pesticides and promote eco-friendly farming practices. Organic farming and integrated pest management are two methods that use natural ways to control diseases, such as biological agents, resistant plant varieties, and balanced fertilization. Our research focuses on how micronutrients, specifically copper (Cu) and zinc (Zn), can boost the plant immune system. Unlike high concentrations of these metals used in conventional plant protection, which can be harmful, we use low, non-toxic levels. This approach can reduce the need for chemical pesticides, which are energy-intensive to produce and apply. Recent studies suggest that micronutrients like Zn and Cu play a crucial role in plant defense mechanisms. For example, adding extra Zn to pepper plants helped them resist a common fungal disease, Botrytis cinerea, by increasing Zn-binding proteins at the infection site. The project aims to understand how these micronutrients enhance plant immunity. We will study the effects of surplus but non-toxic levels of Zn and Cu on pepper plants and their response to infection. We will investigate the proteins and compounds involved in the defense process and how they work together to protect the plants. An interesting question will be whether we can connect the molecular defense mechanisms with the role of Zn- and Cu-containing proteins and metabolites and how the defense responses differ between Zn and Cu treatments. For this we will use advanced techniques in plant physiology, biochemistry, and molecular biology to study the effects of micronutrients on plant defense. This includes measuring physiological parameters, imaging, analyzing proteins and metabolites, and studying gene expression. We hope to uncover the mechanisms of micronutrient-induced plant resistance. This knowledge could lead to new, sustainable ways to protect crops and improve food security. The project will also provide valuable training for PhD students and establish strong scientific cooperation between research institutions in Austria and the Czech Republic. | D58: out | E58: out | F58: 1 | G58: This grant concerns plant disease resistance mechanisms in pepper crops using micronutrients, with no connection to alternative protein development, production, or any alternative protein product. | H58: =TRUE() -> TRUE | I58: NA | J58: NA | K58: =TRUE() -> TRUE | L58: =FALSE() -> FALSE | M58: =FALSE() -> FALSE | N58: =FALSE() -> FALSE | O58: =FALSE() -> FALSE | P58: ok
A59: grant.14487762 | B59: Improving plant immunity by synthetic exploitation of the ubiquitin system | C59: Plants are continuously attacked by pathogens and pests, resulting globally in large agricultural losses and food insecurity at high economic cost. To counter infection, plants have developed sophisticated immune responses in which the post-translational modifier, ubiquitin, plays indispensable roles. Ubiquitination is a versatile protein modification that regulates the amplitude and intensity of immune responses, thereby establishing durable resistance. Substrate ubiquitination is performed by E3 ligases that act as matchmakers by recruiting specific substrates. Despite the essential roles of E3 ligases in plant immunity, it remains unclear how they achieve such extraordinary substrate selectivity and how they evolved to adapt to changing threats in their environment, including new pathogens. Conversely, pathogens have evolved effector proteins that hijack ubiquitin signalling to prevent immune activation, but the underpinning molecular mechanisms remain obscure. The SynUbL project will establish interactions between the major cereal crop, barley, and fungal pathogen, Puccinia hordei, as an economically relevant host-pathogen system for addressing these questions and to bioengineer durable resistance. By functionally tracking immune-induced E3 ligases along the evolutionary tree, we will reveal how these enzymes evolved structural features for specific substrate recognition. Simultaneously, we will expose P. hordei’s hijacking tactics, thereby uncovering the significance of ubiquitin in shaping the evolutionary arms race between host and pathogen. Collective insights are then utilised to synthetically engineer novel E3 ligases to allow on-demand activation of host immune pathways and on-demand destruction of immune-suppressing pathogen effectors. Hence, this project not only provides fundamental discoveries in ubiquitin signalling, it exploits these innovations by generating sustainable strategies for durable crop resistance in the agrifood sector. | D59: out | H59: =FALSE() -> FALSE | I59: NA | J59: CC | K59: =FALSE() -> FALSE | P59: parse_error | Q59: no structured output
A60: grant.14626747 | B60: Proteínas para o futuro: Explorar a segurança dos insetos comestíveis para satisfazer as necessidades alimentares globais | C60: A procura por soluções alimentares sustentáveis está a crescer exponencialmente em todo o mundo devido à necessidade inadiável de satisfazer de forma sustentável uma maior procura por alimentos baratos e ricos em proteínas. A FAO prevê que, até 2050, teremos de aumentar 60% a produção de alimentos para alimentar mais de 9 mil milhões de pessoas. O futuro reserva-nos assim uma mudança para hábitos alimentares sustentáveis, que permitam alimentar mais pessoas do que o possível com as matérias-primas atuais. Nutricionalmente, os insetos emergem como uma alternativa à carne de elevado teor proteico. Muitos insetos edíveis apresentam perfis nutricionais semelhantes aos de outros produtos vegetais e animais comummente consumidos, paralelamente ao potencial de serem fonte de nutrientes mais sustentável e ecológica. No entanto, a segurança alimentar dos insetos ainda não consensual e a legislação europeia não é conclusiva no que diz respeito à utilização de insetos como alimento. Os estudos sobre a segurança alimentar dos insetos são escassos e a avaliação dos riscos microbiológicos necessita de mais investigação. Embora na última década tenham sido publicados muitos estudos sobre este assunto, a maioria não é baseada em dados experimentais. O ponto de partida deste projeto será analisar o conhecimento e a perceção dos consumidores portugueses sobre a segurança alimentar dos insetos edíveis, através da aplicação de um questionário. Com este projeto, pretendemos caraterizar microbiologicamente as larvas de Tenebrio molitor por técnicas clássicas dependentes e independentes de cultura para avaliar a diversidade microbiana, bem como para obter informações sobre a presença e prevalência de genes de resistência a antibióticos. Dado a possível contaminação cruzada do produto final pronto a consumir, é também nosso objetivo avaliar a segurança pós-produção. Serão realizados testes de desafio em dois cenários diferentes, avaliando, em primeiro lugar, o crescimento de agentes patogénicos se houver contaminação no substrato de criação e, em segundo lugar, a persistência de agentes patogénicos em produtos pós-processamento com contaminação cruzada. O impacto da nutrição na microbiota intestinal humana tem sido um assunto amplamente discutido, especialmente quando se trata de novos produtos. Para aprofundar o conhecimento sobre o impacto dos produtos à base de insetos no microbioma intestinal humano, utilizaremos o protocolo INFOGEST para dois produtos diferentes (larvas inteiras torradas e larvas em pó) seguido de fermentação fecal para avaliar possíveis alterações nas comunidades microbianas devido ao consumo de insetos comestíveis. Será também importante avaliar o potencial citotóxico dos produtos de digestão de T. molitor numa linha celular modelo da barreira epitelial intestinal. O mercado de insetos edíveis está em crescimento e o conhecimento sobre a sua segurança terá um impacto económico e industrial. Este projeto representa um importante passo em frente para a ciência a nível global e contribuirá para o aumento do conhecimento científico no sector agroalimentar: i) com conhecimento sobre a perceção dos consumidores portugueses sobre insectos edíveis; ii) com conhecimento sobre o perfil microbiológico, diversidade microbiana e presença de genes de resistência a antibióticos de T. molitor; iii) avaliando a segurança das técnicas de pós-colheita em relação ao crescimento de agentes patogénicos e iv) com conhecimento sobre o impacto dos produtos de T. molitor na microbiota intestinal humana. O desafio é colossal e exigirá uma forte interdisciplinaridade e colaboração entre todos os membros da equipa e associados, a fim de fornecer conhecimentos científicos para o sector agroalimentar, essenciais para garantir a segurança alimentar. InsectSafe surge como um projeto com um objetivo pertinente focado em colmatar lacunas de conhecimento relativas à segurança microbiológica de insetos comestíveis, juntamente com a avaliação do seu impacto na saúde intestinal humana. A equipa acredita verdadeiramente que o âmbito deste projeto é muito desejável e revela-se uma importante adição ao conhecimento científico baseado em dados experimentais, na esperança de um mundo mais sustentável que satisfaça as necessidades alimentares de todos, garantindo a segurança alimentar e erradicando a insegurança alimentar para as gerações futuras. Os diferentes pontos fortes dos diferentes membros proporcionarão uma forte abordagem multidisciplinar vital para assegurar o sucesso deste projeto. O projeto InsectSafe reúne uma equipa multidisciplinar de investigadores seniores e juniores, com mérito e experiência reconhecidos em diversas áreas, incluindo microbiologia, genética, bioinformática, biotecnologia e sociologia. A equipa inclui uma investigadora no início do seu doutoramento, que já colaborou com a equipa durante o seu mestrado. Com a adição do membro a contratar (BI-b1) e a equipa de consultores, estamos confiantes no sucesso deste projeto. | D60: out | E60: out | F60: 1 | G60: This grant focuses entirely on edible insects (Tenebrio molitor), which are explicitly excluded from the alternative proteins scope. | H60: =TRUE() -> TRUE | I60: NA | J60: NA | K60: =TRUE() -> TRUE | L60: =FALSE() -> FALSE | M60: =FALSE() -> FALSE | N60: =FALSE() -> FALSE | O60: =FALSE() -> FALSE | P60: ok
A61: grant.14705592 | B61: Activation of antibacterial bacteriolytic milk proteins by low molecular weight additives | C61: Milk (both human and other mammals) contains lysozyme, which can destroy the cells of various bacteria, i.e. is “non-specific antimicrobial factors of milk”. Lysozyme, as the main bacteriolytic enzyme of the body, has been studied for a very long time, but in recent years, completely new information has appeared both about different isoforms of lysozyme (for example, four types of lysozymes were found in cow's milk) and that this protein also has antiviral, anticancer and immunoregulatory effects. It has also recently been discovered that the activity of lysozyme can be significantly enhanced (up to 8-10 times) against a number of bacteria in the presence of mixtures of charged amino acids and glycine. The activity of lysozyme is also affected by the presence of certain surfactants, analogues of which may be included in food products. Another very important milk protein that can potentially exhibit direct bacteriolytic activity against various bacteria is lactoferrin. In this work, it is planned to isolate lysozyme and lactoferrin from milk samples of black-and-white Holstein cows, followed by a study of the characteristics of the bacteriolytic action of these proteins and the influence of low molecular weight substances on their antibacterial activity in comparison with the corresponding activity of raw cow milk. Approaches will be developed for a simple and rapid method for assessing the amount of these proteins in milk for rapid monitoring of milk quality using simple and safe reagents and simple equipment. The main biochemical and antioxidant parameters of milk samples from these animals will be determined, as well as the correlations between all the above parameters. Lysozyme and lactoferrin will be tested for bacteriolytic activity on three different model microorganisms: Escherichia coli, Micrococcus luteus and Priestia megaterium. Histidine, lysine, arginine, glycine, glutamate, surfactants (surfactants) Tween-21 and Pluronic-P123, and a natural analogue of surfactants - typhoid lipopolysaccharide ( endotoxin). Fundamental knowledge about the bacteriolytic properties of lysozyme and lactoferrin in cow milk, which will be obtained in the work, is extremely important for a deeper understanding of the role of these proteins in the immune defense of animals. The fundamental knowledge obtained in the work is important for assessing the quality of milk, the possibilities of its processing and creation, in the future, of functional dairy products with a set of specified properties. | D61: out | E61: out | F61: 1 | G61: This research focuses on antibacterial properties of lysozyme and lactoferrin in conventional cow's milk, with no connection to alternative protein development or substitution of animal-derived foods. | H61: =TRUE() -> TRUE | I61: NA | J61: NA | K61: =TRUE() -> TRUE | L61: =FALSE() -> FALSE | M61: =FALSE() -> FALSE | N61: =FALSE() -> FALSE | O61: =FALSE() -> FALSE | P61: ok
A62: grant.15060235 | B62: Exploratie van de plasticiteit en functionaliteit van de darmmicrobiomen van insecten voor de valorizatie van residuele biomassa | C62: Lignocellulose-rijke organische reststromen uit landbouw en bosbouw kunnen een belangrijke grondstof zijn voor de biogebaseerde circulaire economie. Xylofage insecten en hun microbiomen in de spijsvertering kunnen een manier zijn om residuele biomassa te valoriseren voor de productie van derde generatie eiwitten en hoogwaardige chemicaliën. Larven van de zwarte soldatenvlieg, bekend om zijn potentieel in insectenkweek, kunnen een breed scala aan organisch restafval gebruiken als voeding. Daarentegen kan het gespecialiseerde microbioom van houtlevende insecten de moeilijk te verteren lignine in houtvezels omzetten. In dit project streven we ernaar om de principes te onderzoeken die ten grondslag liggen aan de samenstelling en werking van microbiële gemeenschappen tijdens de vertering van weinig voedzame lignocellulose biomassa door insecten. Dit wordt bereikt door het gebruik van geïntegreerde omics, gecombineerd met eiwit-labeling technieken, om de belangrijkste bacteriën die betrokken zijn bij de omzetting van lignocellulose, naar de oppervlakte te brengen vanuit het darmmicrobioom van verschillende houtlevende keverlarven en de larven van de zwarte soldaatvlieg. Verder zal het belang van de nutritionele waarde van lignocellulosebiomassa voor de vertering ervan verduidelijkt worden. Tijdsvariabele geïntegreerde omics in BSF-larven die verschillende substraten voorgeschoteld krijgen, zal worden gebruikt om de plasticiteit en functionele redundantie van het darmmicrobioom te verduidelijken. Verder zullen microbiële stammen met belangrijke functionaliteiten worden gevolgd binnen de heterogene darmomgeving met microscopie om belangrijke aspecten van de rekruteringsecologie binnen de omgeving van het darmmicrobioom van insecten beter te begrijpen. Samen zullen de gegenereerde inzichten de basis vormen om microbiomen te ontwerpen met hogere lignocellulolytische capaciteiten door geschikte microben van gespecialiseerde houtlevende kevers te leveren voor rekrutering en de voedingswaarde van de reststroom te verbeteren. Er kan zo een direct effect zijn op het incorporeren van lignocellulose biomassa in de circulaire bio-economie. | D62: out | E62: out | F62: 1 | G62: This grant concerns insect gut microbiomes (black soldier fly larvae and wood-boring beetles) for valorisation of lignocellulose biomass, which is explicitly excluded as insect-based protein research and does not concern alternative proteins for human food. | H62: =TRUE() -> TRUE | I62: NA | J62: NA | K62: =TRUE() -> TRUE | L62: =FALSE() -> FALSE | M62: =FALSE() -> FALSE | N62: =FALSE() -> FALSE | O62: =FALSE() -> FALSE | P62: ok
A63: grant.15201791 | B63: Molecular imaging of in situ cellular machinery by cryo focused ion beam milling | C63: Context The molecular machines of living cells are essential for life. Correct function of these machines supports accurate development, physiological function and healthy ageing. Conversely, disruption of pathogen machinery can be used to tackle global health and food security threats, including antibiotic resistance and agricultural diseases. The ISMB is internationally recognised as a centre of excellence for the study of molecular machines, but most of our current work is undertaken on machinery that has been extracted from its cellular location and purified away from other cellular components. While such work provides crucial detailed information about how these macromolecular complexes operate, it misses out on the cell or tissue context in which they work. Imaging these machines in their functional environment is critical and provides unique insight into the context in which they act. However, cells and tissues are many times larger and more complex than the machines themselves. As a result, precise and specific sample preparation is needed to preserve the context of the machinery of interest, to help locate the machinery within the complex cellular environment and to enable the machinery to be imaged using high resolution electron microscopy. The requested cryo focused ion beam (cryo-FIB) microscope will allow thinning of such complex samples, providing a window into cells and tissues to reveal molecular machine organisation and functional context. The research the equipment will enable Specific projects that will benefit from this new equipment include: 1) Structural and mechanistic analysis of transcription-translation coupling; 2) Studies of the molecular machinery that controls the trafficking of cargo and metabolites through cells; 3) Studies of the malaria parasite that will uncover the mechanisms by which the parasite adapts to its different hosts, allowing parasite transmission; 4) Studies of the molecular mechanisms of bacterial conjugative transfer, the main means by which antibiotic resistance genes spread among bacteria; 5) Studies to elucidate the structural mechanisms underlying co-translational folding and cellular proteostasis; 6) Studies of regulatory proteins whose disruption by naturally occurring mutations cause age-related protein polymerisation that perturbs liver and lung cell function; 7) Studies of the contribution of the actin cytoskeleton to membrane remodelling during muscle development; 8) Studies of amyloid fibre assembly and disassembly that will reveal how the cell's quality control machinery handles protein misfolding associated with diseases of ageing. Aims and objectives Our overall objectives are 1) for the EM Facility team to establish efficient and robust workflows using the new cryo-FIB microscope; 2) to train both established and non-expert users to apply cryo-FIB workflows to current and new projects in BBSRC-relevant areas; 3) for users to share best-practice with the user community via CCPEM and other training networks. The new cryo-FIB microscope, together with our current equipment will provide researchers with a full workflow which spans biological scales, from tissues to atoms. This will be game-changing for EM Facility users and will be one of only a few such research facilities in the UK. Potential applications and benefits The research that will be conducted using the cryo-FIB microscope aligns with the UKRI-BBSRC Delivery plan by aiming at understanding the rules of life and providing an integrated understanding of health. This research will also exploit new ways of working, including the increasing implementation of machine learning methods to enhance the in situ molecular structure determination pipeline. | D63: out | E63: out | F63: 1 | G63: This grant concerns cryo-FIB microscopy infrastructure for studying molecular machines in cells and tissues, with no connection to alternative protein research. | H63: =TRUE() -> TRUE | I63: NA | J63: NA | K63: =TRUE() -> TRUE | L63: =FALSE() -> FALSE | M63: =FALSE() -> FALSE | N63: =FALSE() -> FALSE | O63: =FALSE() -> FALSE | P63: ok
A64: grant.14480598 | B64: Evolution of cross-kingdom small RNA crosstalk in fungal plant pathogens | C64: Crop pathogens are serious threats to food security globally. Plant genomes carry resistance genes encoding sensors for pathogen surveillance and defense. In turn, pathogens surmount plant resistance by manipulating defense response pathways and shielding molecules from detection. The past decade revealed that such interactions are not only governed by proteinaceous components (e.g. NLR) on the host side and effector proteins on the pathogen side. Small RNA (sRNA) can engage in bidirectional cross-talk between attacked plants and their pathogens. sRNA are short non-coding RNAs mostly generated by endoribonucleases (typically Dicer) from single-stranded RNAs encoding a hairpin structure. Mature sRNAs are inducing gene silencing by being loaded into Argonaute proteins to target gene transcripts guided by complementary sequences. Pathogen-produced sRNA typically target host immunity functions. In turn, plants are also producing sRNA to manipulate pathogen gene expression through host-induced gene silencing. Despite their importance for controlling pathogenicity and the broad conservation among host-pathogen systems, how sRNA species evolve in pathogens to successfully target host functions remains largely unknown. Here, we will focus on the best understood fungal plant pathogen model Botrytis cinerea for sRNA interference to determine evolutionary origins, mechanisms of sequence evolution and future trajectory of sRNA loci. The project will achieve four connected aims to build a comprehensive understanding of sRNA emergence and evolution. First, we will generate a high-quality and representative pangenome of the species focused on rigorous annotation of transposable elements (TEs) as the most likely embeddings of sRNA loci in the species. Second, we will carry out comparative sRNA sequencing experiments analyzing sRNA production in culture and on two hosts for each of the members of the pangenome. To determine within-species variation at sRNA loci, we will analyze presence/absence variation as well as functional variation in sRNA production and contingency on the environment (culture vs. hosts). This step also includes the reconstruction of evolutionary origins based on orthologous positions in sister species genomes. Third, we will use the extant diversity at sRNA loci and predictions of targeted plant RNA to train deep learning models. The model will be capable of both identifying the most robust, yet unknown sRNA loci in the pathogen as well as mechanisms of sequence evolution given. Fourth, we will build a user-friendly pipeline so that pangenome-focused sRNA analyses can be reproduced by members of the COST Action and beyond independent of the study organism. In conjunction, the innovative project will be one of the first to tackle the emergence of sRNA loci in plant pathogens and define trajectories of sequence evolution, which will ultimately help define more robust pathogen control based on externally applied sRNA. The project's ambition is well embedded within the scope of the COST Action exRNA-PATH, which wants to generate fundamental and applied insights into RNA biology and cross-kingdom communication. | D64: out | E64: out | F64: 1 | G64: This grant concerns the evolutionary biology of small RNA crosstalk between fungal plant pathogens and their hosts for crop disease resistance, with no connection to alternative protein development, production, or any related food application. | H64: =TRUE() -> TRUE | I64: NA | J64: NA | K64: =TRUE() -> TRUE | L64: =FALSE() -> FALSE | M64: =FALSE() -> FALSE | N64: =FALSE() -> FALSE | O64: =FALSE() -> FALSE | P64: ok
