Workbook

Sheet Dimensions combined
A1: Source | B1: Rank | C1: Grant ID | D1: duplicate check on grant ID | E1: return ID to check | F1: duplicate check with new airtabe entries | G1: return ID to check | H1: Grant Number(s) | I1: Title | J1: Title translated | K1: Abstract | L1: Abstract translated | M1: AI Scope check? | N1: Technology Pillar | O1: Research Category | P1: Keywords | Q1: Funding amount | R1: Currency | S1: Funding amount in USD | T1: Start date | U1: Start Year | V1: End Date | W1: End Year | X1: Researchers | Y1: Research Organization - original | Z1: Research Organization - standardized | AA1: GRID ID | AB1: City of standardized research organization | AC1: State of standardized research organization | AD1: Country of standardized research organization | AE1: Funder | AF1: Funder Group | AG1: Funder Country | AH1: Program | AI1: NIH activity code | AJ1: Resulting publications | AK1: Source Linkout | AL1: Dimensions URL | AM1: Fields of Research (ANZSRC 2020) | AN1: RCDC Categories | AO1: HRCS HC Categories | AP1: HRCS RAC Categories | AQ1: Health Research Areas | AR1: Broad Research Areas | AS1: Cancer Types | AT1: CSO Categories | AU1: Units of Assessment | AV1: Sustainable Development Goals
A2: 2025 Dimensions CM | B2: 1500 | C2: grant.15195353 | D2: =ISNUMBER(MATCH(C2, 'Airtable copy'!N:N, 0)) -> FALSE | E2: =VLOOKUP(C2,'Airtable copy'!N:N,1,FALSE) -> #REF! | F2: =ISNUMBER(MATCH(C2, 'Grants tracker download'!O:O, 0)) -> FALSE | G2: =VLOOKUP(C2,'Grants tracker download'!O:O,1,FALSE) -> #REF! | H2: 22740 | I2: Epigenetic Reprogramming for Cellular Agriculture (EPICA) | J2: Epigenetic Reprogramming for Cellular Agriculture (EPICA) | K2: Cellular agriculture has the potential to revolutionise protein production by offering sustainable and ethical alternatives to traditional animal farming. However, many challenges currently limit its commercial viability, including a critical lack of flexible, regulatory- and consumer-friendly technologies to engineer cell lines for large-scale production. EPICA (Epigenetic Reprogramming for Cellular Agriculture) will pioneer the use of epigenetic editing to enhance a variety of critical cell characteristics without genetic modification. We will build a toolkit for engineering of multiple cell types from different species, and demonstrate its use in industrial-scale cultivated meat and seafood bioprocesses, helping bring these technologies to market. | L2: Cellular agriculture has the potential to revolutionise protein production by offering sustainable and ethical alternatives to traditional animal farming. However, many challenges currently limit its commercial viability, including a critical lack of flexible, regulatory- and consumer-friendly technologies to engineer cell lines for large-scale production. EPICA (Epigenetic Reprogramming for Cellular Agriculture) will pioneer the use of epigenetic editing to enhance a variety of critical cell characteristics without genetic modification. We will build a toolkit for engineering of multiple cell types from different species, and demonstrate its use in industrial-scale cultivated meat and seafood bioprocesses, helping bring these technologies to market. | M2: Yes | N2: Cultivated | O2: Cell line development | Q2: 904867 | R2: EUR | S2: 960340 | T2: 2025-01-01 | U2: 2025 | X2: Joshua Flack, Marcel Ottens, Marianne Rots | Y2: Technische Universiteit Delft; Universitair Medisch Centrum Groningen | Z2: Delft University of Technology; University Medical Center Groningen | AA2: grid.5292.c; grid.4494.d | AB2: Delft; Groningen | AC2: Zuid-Holland; Groningen | AD2: Netherlands; Netherlands | AE2: Dutch Research Council | AF2: cOAlition S | AG2: Netherlands | AH2: Open technologieprogramma OTP 2025 2025-3 (Funding Scheme) | AI2: Not available | AL2: https://app.dimensions.ai/details/grant/grant.15195353 | AM2: 31 Biological Sciences; 3105 Genetics | AN2: Genetics | AO2: Generic health relevance | AU2: A01 Clinical Medicine | AV2: 2 Zero Hunger
A3: 2025 Dimensions CM | B3: 1395 | C3: grant.15195928 | D3: =ISNUMBER(MATCH(C3, 'Airtable copy'!N:N, 0)) -> FALSE | E3: =VLOOKUP(C3,'Airtable copy'!N:N,1,FALSE) -> #REF! | F3: =ISNUMBER(MATCH(C3, 'Grants tracker download'!O:O, 0)) -> FALSE | G3: =VLOOKUP(C3,'Grants tracker download'!O:O,1,FALSE) -> #REF! | H3: 10.61686/VFIVD43947; 21927 | I3: 3D Bioprinting of cultivated meat: Biopolymer matrices supporting formation of muscle fibers in vitro | J3: 3D Bioprinting of cultivated meat: Biopolymer matrices supporting formation of muscle fibers in vitro | K3: Due to disruptive effects of conventional mass meat production – on climate, animals and human health, I work towards sustainable food for the next generation while maintaining taste, protein content and texture of real meat. Combining natural food ingredients, cells and tunable recombinant proteins, we may be able to grow whole beef cuts under controlled, animal-free conditions; innovative bioprinting techniques allow scale-up and nutrient supply in larger tissues. By adjusting the protein composition, I define the formation of edible muscle fibers. Improving the quality of cellular agriculture accelerates development of products with a real-world impact. | L3: Due to disruptive effects of conventional mass meat production – on climate, animals and human health, I work towards sustainable food for the next generation while maintaining taste, protein content and texture of real meat. Combining natural food ingredients, cells and tunable recombinant proteins, we may be able to grow whole beef cuts under controlled, animal-free conditions; innovative bioprinting techniques allow scale-up and nutrient supply in larger tissues. By adjusting the protein composition, I define the formation of edible muscle fibers. Improving the quality of cellular agriculture accelerates development of products with a real-world impact. | M3: Yes | N3: Cultivated | O3: Scaffolding & Texturisation | Q3: 320000 | R3: EUR | S3: 339617 | T3: 2025-10-01 | U3: 2025 | X3: David Kilian | Y3: Maastricht University | Z3: Maastricht University | AA3: grid.5012.6 | AB3: Maastricht | AC3: Limburg | AD3: Netherlands | AE3: Dutch Research Council | AF3: cOAlition S | AG3: Netherlands | AH3: NWO-Talentprogramma Veni TTW 2024 (Funding Scheme) | AI3: Not available | AK3: https://doi.org/10.61686/VFIVD43947 | AL3: https://app.dimensions.ai/details/grant/grant.15195928 | AM3: 30 Agricultural, Veterinary and Food Sciences; 3003 Animal Production; 31 Biological Sciences | AN3: Biotechnology; Nutrition | AQ3: Biomedical | AR3: Basic Science | AU3: A06 Agriculture, Veterinary and Food Science | AV3: 2 Zero Hunger
A4: 2025 Dimensions CM | B4: 1328 | C4: grant.15156031 | D4: =ISNUMBER(MATCH(C4, 'Airtable copy'!N:N, 0)) -> FALSE | E4: =VLOOKUP(C4,'Airtable copy'!N:N,1,FALSE) -> #REF! | F4: =ISNUMBER(MATCH(C4, 'Grants tracker download'!O:O, 0)) -> FALSE | G4: =VLOOKUP(C4,'Grants tracker download'!O:O,1,FALSE) -> #REF! | H4: 565625683 | I4: Engineered bionanoparticles as carriers for growth factors and peptides that promote cell attachment, proliferation and differentiation to improve the production of low-cost cultured meat (NanoMeat) | J4: Engineered bionanoparticles as carriers for growth factors and peptides that promote cell attachment, proliferation and differentiation to improve the production of low-cost cultured meat (NanoMeat) | K4: Cultured or artificial meat is a form of cellular agriculture involving the production of meat from animal cells cultivated in vitro. This rapidly developing technology could provide meat to the world’s growing population while also addressing the drawbacks of traditional livestock agriculture, such as infectious diseases, antibiotic misuse, poor animal welfare, and greenhouse gas emissions. To become competitive, cultured meat must be economically comparable and ethically superior to natural meat, but this is challenging because fetal bovine serum (FBS) is needed in the culture medium to provide growth factors for cell proliferation and differentiation. FBS is expensive and can only be sourced by killing calves. A more cost-effective and ethical solution is the use of scaffolds for recombinant growth factors, offering the advantages of controlled release, greater efficacy and lower costs. Growth factors can be immobilized on plant virus-like nanoparticles (VNPs/VLPs), which are versatile and biocompatible scaffolds that act as protein-based carriers. VNPs/VLPs can be incorporated as hydrogel composites to enhance stem cell adhesion and promote cell differentiation in a 3D environment. Plant VNPs/VLPs are well tolerated by mammals and are neither toxic nor infectious to mammalian cells in vitro, making them ideal for the production of cultured meat. The proposed project will address the following research questions: (1) Can stem cells be cultivated with engineered VNPs/VLPs displaying cell adhesion peptides and growth factors in a hydrogel matrix? (2) Do these scaffolds promote stem cell attachment, proliferation, differentiation and maturation? (3) Can these scaffolds replace FBS, thus providing a safe, inexpensive and ethical alternative for cultured meat production? | L4: Cultured or artificial meat is a form of cellular agriculture involving the production of meat from animal cells cultivated in vitro. This rapidly developing technology could provide meat to the world’s growing population while also addressing the drawbacks of traditional livestock agriculture, such as infectious diseases, antibiotic misuse, poor animal welfare, and greenhouse gas emissions. To become competitive, cultured meat must be economically comparable and ethically superior to natural meat, but this is challenging because fetal bovine serum (FBS) is needed in the culture medium to provide growth factors for cell proliferation and differentiation. FBS is expensive and can only be sourced by killing calves. A more cost-effective and ethical solution is the use of scaffolds for recombinant growth factors, offering the advantages of controlled release, greater efficacy and lower costs. Growth factors can be immobilized on plant virus-like nanoparticles (VNPs/VLPs), which are versatile and biocompatible scaffolds that act as protein-based carriers. VNPs/VLPs can be incorporated as hydrogel composites to enhance stem cell adhesion and promote cell differentiation in a 3D environment. Plant VNPs/VLPs are well tolerated by mammals and are neither toxic nor infectious to mammalian cells in vitro, making them ideal for the production of cultured meat. The proposed project will address the following research questions: (1) Can stem cells be cultivated with engineered VNPs/VLPs displaying cell adhesion peptides and growth factors in a hydrogel matrix? (2) Do these scaffolds promote stem cell attachment, proliferation, differentiation and maturation? (3) Can these scaffolds replace FBS, thus providing a safe, inexpensive and ethical alternative for cultured meat production? | M4: Yes | N4: Cultivated | O4: Cell culture media | Q4: 0 | S4: 0 | T4: 2025-01-01 | U4: 2025 | X4: Che Julius Ngwa, Juliane Schuphan | Y4: Fraunhofer-Institut für Molekularbiologie und Angewandte Oekologie; Rheinisch-Westfälische Technische Hochschule Aachen | Z4: Fraunhofer Institute for Molecular Biology and Applied Ecology; RWTH Aachen University | AA4: grid.418010.c; grid.1957.a | AB4: Schmallenberg; Aachen | AC4: Nordrhein-Westfalen | AD4: Germany; Germany | AE4: Deutsche Forschungsgemeinschaft | AG4: Germany | AH4: Research Grants (DFG Programme) | AI4: Not available | AK4: https://gepris.dfg.de/gepris/projekt/565625683?language=en | AL4: https://app.dimensions.ai/details/grant/grant.15156031 | AM4: 30 Agricultural, Veterinary and Food Sciences; 3003 Animal Production; 31 Biological Sciences; 40 Engineering; 4003 Biomedical Engineering | AN4: Bioengineering; Biotechnology; Nanotechnology; Regenerative Medicine; Stem Cell Research; Stem Cell Research - Nonembryonic - Human; Stem Cell Research - Nonembryonic - Non-Human | AP4: 5.2 Cellular and gene therapies | AQ4: Biomedical | AR4: Basic Science | AU4: A05 Biological Sciences | AV4: 3 Good Health and Well Being
A5: 2025 Dimensions CM | B5: 1301 | C5: grant.14972651 | D5: =ISNUMBER(MATCH(C5, 'Airtable copy'!N:N, 0)) -> FALSE | E5: =VLOOKUP(C5,'Airtable copy'!N:N,1,FALSE) -> #REF! | F5: =ISNUMBER(MATCH(C5, 'Grants tracker download'!O:O, 0)) -> FALSE | G5: =VLOOKUP(C5,'Grants tracker download'!O:O,1,FALSE) -> #REF! | H5: 359609 | I5: Cell-cultured octopus production through sustainable marine biomass valorization | J5: Cell-cultured octopus production through sustainable marine biomass valorization | K5: SEANERGIES aims to develop the scientific and technological foundation for producing cultivated octopus—meat grown from cells without killing animals. As global demand for protein rises, traditional fishing and aquaculture face major challenges, including overfishing, pollution, and animal welfare concerns. Octopuses are especially vulnerable, yet they are also highly valued for their nutrition and cultural significance. The project uses an interdisciplinary approach combining marine biology, bioengineering, and social sciences. It will explore the octopus’s natural ability to regenerate muscle tissue to create the first stable octopus muscle cell line for use in cellular agriculture. To make this process sustainable and animal-free, SEANERGIES will develop innovative culture media based on microalgae and natural scaffolds from seaweed (Saccharina latissima, NORWEGIAN Partner's Role), providing the structure needed for muscle growth. Key R&D challenges include isolating and growing octopus cells long-term, replacing animal-derived nutrients in cell culture, and ensuring that marine-based materials can support cell attachment and development. The project will also assess the environmental and social impacts of cultivated seafood in Portugal, Italy, and Brazil. SEANERGIES contributes to global food security and ocean health by offering a sustainable alternative to traditional seafood, aligned with EU Green Deal goals and the UN Sustainable Development Goals. | L5: SEANERGIES aims to develop the scientific and technological foundation for producing cultivated octopus—meat grown from cells without killing animals. As global demand for protein rises, traditional fishing and aquaculture face major challenges, including overfishing, pollution, and animal welfare concerns. Octopuses are especially vulnerable, yet they are also highly valued for their nutrition and cultural significance. The project uses an interdisciplinary approach combining marine biology, bioengineering, and social sciences. It will explore the octopus’s natural ability to regenerate muscle tissue to create the first stable octopus muscle cell line for use in cellular agriculture. To make this process sustainable and animal-free, SEANERGIES will develop innovative culture media based on microalgae and natural scaffolds from seaweed (Saccharina latissima, NORWEGIAN Partner's Role), providing the structure needed for muscle growth. Key R&D challenges include isolating and growing octopus cells long-term, replacing animal-derived nutrients in cell culture, and ensuring that marine-based materials can support cell attachment and development. The project will also assess the environmental and social impacts of cultivated seafood in Portugal, Italy, and Brazil. SEANERGIES contributes to global food security and ocean health by offering a sustainable alternative to traditional seafood, aligned with EU Green Deal goals and the UN Sustainable Development Goals. | M5: Yes | N5: Cultivated | O5: Cell line development / Media | Q5: 2891999 | R5: NOK | S5: 262375 | T5: 2025-01-01 | U5: 2025 | V5: 2028-12-31 | W5: 2028 | X5: Alexander Jüterbock | Y5: NORD UNIVERSITET | Z5: Nord University | AA5: grid.465487.c | AB5: Bodø | AD5: Norway | AE5: The Research Council of Norway | AF5: cOAlition S | AG5: Norway | AH5: SEA-BASED-SEA-BASED (Funding scheme) | AI5: Not available | AK5: https://prosjektbanken.forskningsradet.no/en/project/FORISS/359609 | AL5: https://app.dimensions.ai/details/grant/grant.14972651 | AM5: 31 Biological Sciences; 41 Environmental Sciences; 4104 Environmental Management; 48 Law and Legal Studies; 4803 International and Comparative Law | AO5: Generic health relevance | AU5: B07 Earth Systems and Environmental Sciences | AV5: 14 Life Below Water; 2 Zero Hunger
A6: 2025 Dimensions CM | B6: 493 | C6: grant.14970420 | D6: =ISNUMBER(MATCH(C6, 'Airtable copy'!N:N, 0)) -> FALSE | E6: =VLOOKUP(C6,'Airtable copy'!N:N,1,FALSE) -> #REF! | F6: =ISNUMBER(MATCH(C6, 'Grants tracker download'!O:O, 0)) -> FALSE | G6: =VLOOKUP(C6,'Grants tracker download'!O:O,1,FALSE) -> #REF! | I6: BiochAIn - BiochAIn ist ein Softwareprojekt für die Optimierung einer gesamten biotechnologischen Verfahrenskette(Chain) mittels AI | J6: BiochAIn - BiochAIn is a software project for optimizing an entire biotechnological process chain using AI | K6: Biotechnologische Produktionsverfahren finden breite Anwendung in der pharmazeutischen Industrie, zur Herstellung von Feinchemikalien, in der Umwelttechnologie und in der Lebensmittelindustrie und generieren eine hohe Wertschöpfung. Aufgrund der hohen Komplexität dieser Verfahren, bedingt durch das vielschichtige Zusammenspiel von Biologie und Verfahrenstechnik, besteht in zahlreichen Fällen ein nur sehr eingeschränktes Prozessverständnis. Dies wiederum führt zu wenig effizienten und daher teuren Prozessen, limitiert die Möglichkeiten zur Prozessoptimierung und ist auch ein wesentlicher Grund dafür, dass bis dato die enormen Fortschritte im Bereich der Digitalisierung, Methoden der künstlichen Intelligenz und Modellierung/Simulation nicht im erforderlichen Ausmaß zur Auslegung und Führung von Bioprozessen zur Anwendung kommen. Im Rahmen des Projektes soll daher eine generische Software-Toolbox entwickelt werden um genannte Fortschritte im Bereich der Digitalisierung den Experten der Domäne Bioprozess-technik zugänglich machen und eine Implementierung der Digitalisierung gemäß Industrie 4.0 im Bio-Manufacturing ermöglichen. Mit dem BiochAIn Projekt hat sich die Novasign zum Ziel gesetzt, weltweit die erste digitale Prozessmodellierungstoolbox für die Optimierung aller biotechnologisch relevanten Verfahrensschritte zu entwickeln. Mit dieser Software-Suite soll es erstmals möglich werden, dass Biotechnologen und Bioprozessingenieur:innen über eine nutzerzentrierte grafische Bedienoberfläche alle Einzelschritte der Prozesskette, sowohl individuell als auch in ihrer Gesamtheit, mit Hilfe von Modellen und Simulation selbstständig und unabhängig von hochspezialisierten Softwareentwicklern und Data Scientists optimieren können. Die Software wird auch ermöglichen, dass Prozessingenieur:innen abteilungsübergreifend Herstellungsprozesse für Produkte (zum Beispiel einen Antikörper für die Krebstherapie) in einem integrativen Ansatz optimieren können um lebensrettende Medizin den Patient:innen früher und günstiger zur Verfügung stellen zu können. Die Softwareentwicklung wird in 4 Blöcke aufgeteilt und soll über einen Zeitraum von 4 Jahren (durch schnelleren Fortschritt verkürzt auf 3 Jahre) erfolgen. Im ersten Schritt wurde eine geeignete Softwarearchitektur festgelegt, welche einerseits alle technischen Herausforderungen bewältigen kann und andererseits für Benutzer:innen, einfach bedienbar ist. In einem Datenvorverarbeitungs-/Visualisierungsblock werden Onlinedaten (Prozesssystem) und Offlinedaten (Messungen) mit Methoden der statistischen Datenaufbereitung und Analyse vorprozessiert, verknüpft und so für Visualisierung und Modellierung vorbereitet. Der Modellierblock wird so aufgesetzt, dass die unterschiedlichsten State-of-the-art Machine Learning (ML) Methoden implementiert werden und so die jeweils bestgeeignete Methode für zur Modellierung unterschiedlicher Bioprozessschritte eingesetzt werden kann. Im finalen Schritt, dem digitalen Zwilling, kann jeder einzelne der Modellblöcke individuell oder mittels drag-and-drop mit anderen Einheiten verknüpft zu einer Prozesskette nach einer bestimmten Zielgröße (z.B. höchstmögliche Produktausbeute oder kürzere Prozessdauer) optimiert werden und für die online Monitoring angewendet werden. Um Nutzer:innen bestmöglich unterstützen zu können, wird die Software über eine selbstlernende Funktion (Artificial Intelligence) verfügen, welche es möglich macht, jeden einzelnen Verfahrensschritt als auch die gesamte Prozesskette schnell, zielgerichtet und automatisiert entlang eines Workflows zu optimieren. Die Software soll neben der biopharmazeutischen Industrie auch für die industrielle Biotechnologie (Herstellung von Enzymen und biobasierten Polymeren aus Abfallströmen) als auch im Bereich der Lebensmittelindustrie für die Erzeugung von Proteinersatzstoffen (Cultured Meat, Precision Fermentation) Verwendung finden. Der Name BiochAIn leitet sich daher aus Bio (für Bioprozess), chain (für Prozesskette) und AI (für die Künstliche Intelligenz der Selbstlernfunktion) ab. | L6: Biotechnological production processes are widely used in the pharmaceutical industry, for the production of fine chemicals, in environmental technology, and in the food industry, and generate high added value. Due to the high complexity of these processes, caused by the complex interplay of biology and process engineering, in many cases there is only a very limited understanding of the processes. This, in turn, leads to inefficient and therefore expensive processes, limits the possibilities for process optimization, and is also a key reason why the enormous advances in digitalization, artificial intelligence methods, and modeling/simulation have not yet been applied to the required extent for the design and management of bioprocesses. The project therefore aims to develop a generic software toolbox to make these advances in digitalization accessible to experts in the bioprocess engineering domain and enable the implementation of digitalization in accordance with Industry 4.0 in biomanufacturing. With the BiochAIn project, Novasign aims to develop the world's first digital process modeling toolbox for optimizing all biotechnologically relevant process steps. This software suite will enable biotechnologists and bioprocess engineers to independently optimize all individual steps of the process chain, both individually and as a whole, using models and simulations via a user-centered graphical user interface, independently of highly specialized software developers and data scientists. The software will also enable process engineers to optimize manufacturing processes for products (e.g., an antibody for cancer therapy) across departments using an integrative approach to make life-saving medicine available to patients sooner and more cost-effectively. Software development will be divided into four blocks and will be completed over a period of four years (shortened to three years due to faster progress). The first step involved defining a suitable software architecture that, on the one hand, can address all technical challenges and, on the other, is easy to use for users. In a data preprocessing/visualization block, online data (process system) and offline data (measurements) are preprocessed using statistical data processing and analysis methods, linked, and prepared for visualization and modeling. The modeling block is set up to implement a wide variety of state-of-the-art machine learning (ML) methods, allowing the most suitable method to be used for modeling different bioprocess steps. In the final step, the digital twin, each of the model blocks can be optimized individually or linked to other units via drag-and-drop to form a process chain according to a specific target (e.g., highest possible product yield or shorter process time) and applied for online monitoring. To provide the best possible support to users, the software will feature a self-learning function (artificial intelligence), which makes it possible to quickly, specifically, and automatically optimize each individual process step as well as the entire process chain along a workflow. In addition to the biopharmaceutical industry, the software is also intended to be used for industrial biotechnology (production of enzymes and bio-based polymers from waste streams) as well as in the food industry for the production of protein substitutes (cultured meat, precision fermentation). The name BiochAIn is therefore derived from Bio (for bioprocess), chain (for process chain), and AI (for the artificial intelligence of the self-learning function). | M6: Yes | N6: Cross-cutting | O6: Bioprocess design | Q6: 0 | S6: 0 | T6: 2025-01-04 | U6: 2025 | V6: 2026-03-31 | W6: 2026 | Y6: Novasign GmbH | AE6: Austrian Research Promotion Agency | AG6: Austria | AH6: IWI 24/26 (program); Basic Program Call for Proposals 2025 (program) | AI6: Not available | AK6: https://projekte.ffg.at/projekt/5139169 | AL6: https://app.dimensions.ai/details/grant/grant.14970420 | AM6: 46 Information and Computing Sciences; 4612 Software Engineering | AN6: Bioengineering; Biotechnology; Data Science; Machine Learning and Artificial Intelligence; Networking and Information Technology R&D (NITRD) | AO6: Generic health relevance | AU6: B12 Engineering | AV6: 9 Industry, Innovation and Infrastructure
A7: 2025 Dimensions CM | B7: 410 | C7: grant.15084865 | D7: =ISNUMBER(MATCH(C7, 'Airtable copy'!N:N, 0)) -> FALSE | E7: =VLOOKUP(C7,'Airtable copy'!N:N,1,FALSE) -> #REF! | F7: =ISNUMBER(MATCH(C7, 'Grants tracker download'!O:O, 0)) -> FALSE | G7: =VLOOKUP(C7,'Grants tracker download'!O:O,1,FALSE) -> #REF! | H7: 101182025; 277738; GREENGROCER; 10.3030/101182025 | I7: Maturing food footprint tools, solutions, and uptake to accelerate a rapid EU food transition | J7: Maturing food footprint tools, solutions, and uptake to accelerate a rapid EU food transition | K7: There is a recognized and urgent need for better food footprint data to accurately inform the sustainable food system transition as the current knowledge infrastructure is inadequate both in terms of scientific robustness and real-world suitability for regulatory and business decision support. The objective of GREENGROCER is to make foundation-strengthening investments in critical knowledge infrastructure in order to advance food footprint data from lab to application. The project packages investments across over a dozen leading mainstream tools including Trase, HESTIA, CoolFarm, FABIO, and EXIOBASE, which collectively form the foundation of most food footprint data currently in use. Work in GREENGROCER: 1) improves the scientific depth by revisiting long standing weak areas including on subnational supply chain specificity, reliability information, and novel and neglected products and impacts such as spices, seaweed, insect protein, cellular agriculture, cold chain energy use, and seafloor disturbance; 2) makes foundation-strengthening investments that take all models towards full compliance with the EU’s Product Environmental Footprint standards and improve FAIRness and interoperability; and 3) promotes exploitation through multi-stakeholder dialogue between food system researchers, industry, and regulators aimed at prioritising pain points and supporting effective regulation. Finally, to collate data without yet another centralised repository, the project leverages Europe’s competitive advantage in marrying AI with scientific expertise to pioneer a fact-based AI expert which can interact with and gather the rapidly growing volume of food system science. Aimed at the Horizon Europe work program destination of reducing the environmental impact of the food system, GREENGROCER outputs are oriented around 13 specific relevant EU policy frameworks including FSFS, EUDR, ESRS, CSRD, CSDDD, and the CAP. | L7: There is a recognized and urgent need for better food footprint data to accurately inform the sustainable food system transition as the current knowledge infrastructure is inadequate both in terms of scientific robustness and real-world suitability for regulatory and business decision support. The objective of GREENGROCER is to make foundation-strengthening investments in critical knowledge infrastructure in order to advance food footprint data from lab to application. The project packages investments across over a dozen leading mainstream tools including Trase, HESTIA, CoolFarm, FABIO, and EXIOBASE, which collectively form the foundation of most food footprint data currently in use. Work in GREENGROCER: 1) improves the scientific depth by revisiting long standing weak areas including on subnational supply chain specificity, reliability information, and novel and neglected products and impacts such as spices, seaweed, insect protein, cellular agriculture, cold chain energy use, and seafloor disturbance; 2) makes foundation-strengthening investments that take all models towards full compliance with the EU’s Product Environmental Footprint standards and improve FAIRness and interoperability; and 3) promotes exploitation through multi-stakeholder dialogue between food system researchers, industry, and regulators aimed at prioritising pain points and supporting effective regulation. Finally, to collate data without yet another centralised repository, the project leverages Europe’s competitive advantage in marrying AI with scientific expertise to pioneer a fact-based AI expert which can interact with and gather the rapidly growing volume of food system science. Aimed at the Horizon Europe work program destination of reducing the environmental impact of the food system, GREENGROCER outputs are oriented around 13 specific relevant EU policy frameworks including FSFS, EUDR, ESRS, CSRD, CSDDD, and the CAP. | M7: Yes | N7: Cross-cutting | O7: Impact assessments | Q7: 6999521 | R7: EUR | S7: 7428611 | T7: 2025-09-01 | U7: 2025 | V7: 2029-08-31 | W7: 2029 | Y7: UNIVERSITEIT LEIDEN; HOEGSKOLAN KRISTIANSTAD; TETRA PAK PACKAGING SOLUTIONS AB; NILU KLIMAT OCH MILJOINSTITUTET AB; INESC TEC - INSTITUTO DE ENGENHARIADE SISTEMAS E COMPUTADORES, TECNOLOGIA E CIENCIA; ARBORETICA BV; STIFTELSEN NILU; STIFTELSEN THE STOCKHOLM ENVIRONMENT INSTITUTE; SANTA MARIA AB; ECOLE NORMALE SUPERIEURE; UNIVERSITY OF YORK; BERGISCHE UNIVERSITAET WUPPERTAL; EIDGENOESSISCHE TECHNISCHE HOCHSCHULE ZUERICH; COOL FARM ALLIANCE COMMUNITY INTEREST COMPANY; CLIMATE AND COMPANY PUBLIC AFFAIRS UG; GLOBESCAN INCORPORATED; LATVIJAS UNIVERSITATE; THE CHANCELLOR, MASTERS AND SCHOLARS OF THE UNIVERSITY OF OXFORD; Départ de Sentier; CENTRE NATIONAL DE LA RECHERCHE SCIENTIFIQUE CNRS; ZURCHER HOCHSCHULE FUR ANGEWANDTE WISSENSCHAFTEN; CHALMERS TEKNISKA HOGSKOLA AB | Z7: Leiden University; Kristianstad University; Tetra Pak Packaging Solutions AB; INESC TEC - Institute for Systems and Computer Engineering, Technology and Science; Stockholm Environment Institute; Santa Maria AB; École Normale Supérieure - PSL; University of York; University of Wuppertal; ETH Zurich; Cool Farm Alliance; University of Latvia; University of Oxford; French National Centre for Scientific Research; Zurich University of Applied Sciences; Chalmers University of Technology | AA7: grid.5132.5; grid.16982.34; grid.570819.2; grid.20384.3d; grid.35843.39; grid.534081.b; grid.5607.4; grid.5685.e; grid.7787.f; grid.5801.c; grid.500093.f; grid.9845.0; grid.4991.5; grid.4444.0; grid.19739.35; grid.5371.0 | AB7: Leiden; Kristianstad; Lund; Porto; Stockholm; Paris; York; Wuppertal; Zurich; London; Riga; Oxford; Paris; Winterthur; Gothenburg | AC7: Île-de-France; York; Nordrhein-Westfalen; Oxfordshire | AD7: Netherlands; Sweden; Sweden; Portugal; Sweden; Sweden; France; United Kingdom; Germany; Switzerland; United Kingdom; Latvia; United Kingdom; France; Switzerland; Sweden | AE7: European Commission | AF7: EC & ERC - European Union; cOAlition S | AG7: Belgium | AH7: HORIZON.2.6 - Food, Bioeconomy Natural Resources, Agriculture and Environment (Programme); HORIZON-RIA - HORIZON Research and Innovation Actions (Funding scheme); HORIZON-CL6-2024-ZEROPOLLUTION-01 (Call for proposal) | AI7: Not available | AK7: https://cordis.europa.eu/project/id/101182025 | AL7: https://app.dimensions.ai/details/grant/grant.15084865 | AM7: 30 Agricultural, Veterinary and Food Sciences; 3006 Food Sciences; 46 Information and Computing Sciences | AU7: C18 Law | AV7: 12 Responsible Consumption and Production
A8: 2025 Dimensions CM | B8: 369 | C8: grant.15201033 | D8: =ISNUMBER(MATCH(C8, 'Airtable copy'!N:N, 0)) -> FALSE | E8: =VLOOKUP(C8,'Airtable copy'!N:N,1,FALSE) -> #REF! | F8: =ISNUMBER(MATCH(C8, 'Grants tracker download'!O:O, 0)) -> FALSE | G8: =VLOOKUP(C8,'Grants tracker download'!O:O,1,FALSE) -> #REF! | H8: UKRI633 | I8: Advanced Microchannel Structured SiC Hollow Fibre Membranes for Value-Added Oil Recovery in Precision Fermentation (PF) | J8: Advanced Microchannel Structured SiC Hollow Fibre Membranes for Value-Added Oil Recovery in Precision Fermentation (PF) | K8: Cellular Agriculture Manufacturing involves the production of agricultural products via cell culture. This innovative method significantly diminishes the environmental impact compared to traditional farming by reducing land use, greenhouse gas emissions, and water usage. It also provides enhanced resilience to climate change and enables more distributed manufacturing processes. This approach further generates added value for UK farmers, aligning with the primary goals of the £12 million EPSRC-funded CARMAR Hub. In addition to being assessed on sustainability, societal, and economic metrics, CARMAR's goal of transitioning "from lab to shopping basket" necessitates the development of "novel, underpinning manufacturing technologies". These technologies are designed to achieve necessary process intensities at scale in a cost-effective and sustainable manner. Considering that separation and purification processes account for approximately 15% of the world's energy demand, the innovation of bioseparation processes through the advancement of sophisticated separation technologies will be a key determinant of CARMAR's success. Given the high energy efficiency of membrane separation, which is up to ten times more energy-efficient than conventional separation methods, expertise in polymeric membranes has been secured within the CARMAR consortium. This project aims to further mitigate potential risks associated with chemical compatibility, fouling, and water permeation of polymeric membranes when interacting with a wide range of biomaterials and systems within the CARMAR value chain. To this end, the project is focused on advancing more resilient and high-throughput ceramic membrane technology, thereby elevating the versatility of CARMAR processes by overcoming the limitations of polymeric membranes. To achieve this, we plan to transfer the highly permeable, low fouling, and chemically robust SiC material into an advanced microchannel structured hollow fibre membrane. This membrane, with its high surface area to volume ratio and low permeation resistance, along with its scalable fabrication uniquely available through this project, aims to counteract the high fabrication cost challenge associated with such membranes. Beyond demonstrating its efficacy in bioseparation applications within CARMAR through collaborations, we will extend the benefits of this advanced material to broader research centres/hubs/institutes, such as the biological membrane and bioenergy research and development at Aston University. By providing a new powerful tool for efficient purifications at lower energy consumption, we aim to bring together membrane researchers from biological, polymeric, and ceramic membrane communities, thereby further advancing globally leading membrane innovations for both successful CARMAR and a more resilient UK society. | L8: Cellular Agriculture Manufacturing involves the production of agricultural products via cell culture. This innovative method significantly diminishes the environmental impact compared to traditional farming by reducing land use, greenhouse gas emissions, and water usage. It also provides enhanced resilience to climate change and enables more distributed manufacturing processes. This approach further generates added value for UK farmers, aligning with the primary goals of the £12 million EPSRC-funded CARMAR Hub. In addition to being assessed on sustainability, societal, and economic metrics, CARMAR's goal of transitioning "from lab to shopping basket" necessitates the development of "novel, underpinning manufacturing technologies". These technologies are designed to achieve necessary process intensities at scale in a cost-effective and sustainable manner. Considering that separation and purification processes account for approximately 15% of the world's energy demand, the innovation of bioseparation processes through the advancement of sophisticated separation technologies will be a key determinant of CARMAR's success. Given the high energy efficiency of membrane separation, which is up to ten times more energy-efficient than conventional separation methods, expertise in polymeric membranes has been secured within the CARMAR consortium. This project aims to further mitigate potential risks associated with chemical compatibility, fouling, and water permeation of polymeric membranes when interacting with a wide range of biomaterials and systems within the CARMAR value chain. To this end, the project is focused on advancing more resilient and high-throughput ceramic membrane technology, thereby elevating the versatility of CARMAR processes by overcoming the limitations of polymeric membranes. To achieve this, we plan to transfer the highly permeable, low fouling, and chemically robust SiC material into an advanced microchannel structured hollow fibre membrane. This membrane, with its high surface area to volume ratio and low permeation resistance, along with its scalable fabrication uniquely available through this project, aims to counteract the high fabrication cost challenge associated with such membranes. Beyond demonstrating its efficacy in bioseparation applications within CARMAR through collaborations, we will extend the benefits of this advanced material to broader research centres/hubs/institutes, such as the biological membrane and bioenergy research and development at Aston University. By providing a new powerful tool for efficient purifications at lower energy consumption, we aim to bring together membrane researchers from biological, polymeric, and ceramic membrane communities, thereby further advancing globally leading membrane innovations for both successful CARMAR and a more resilient UK society. | M8: Yes | N8: Fermentation | O8: Bioprocess design | Q8: 258814 | R8: GBP | S8: 327300 | T8: 2025-06-02 | U8: 2025 | V8: 2027-06-02 | W8: 2027 | X8: Zhentao Wu, Ming Xie | Y8: Aston University | Z8: Aston University | AA8: grid.7273.1 | AB8: Birmingham | AD8: United Kingdom | AE8: Engineering and Physical Sciences Research Council | AF8: cOAlition S; UKRI - UK Research and Innovation | AG8: United Kingdom | AH8: Research and Innovation (Project Category) | AI8: Not available | AK8: https://gtr.ukri.org/projects?ref=UKRI633 | AL8: https://app.dimensions.ai/details/grant/grant.15201033 | AM8: 40 Engineering; 4004 Chemical Engineering | AU8: B12 Engineering | AV8: 13 Climate Action; 7 Affordable and Clean Energy
A9: 2025 Dimensions CM | B9: 357 | C9: grant.15054223 | D9: =ISNUMBER(MATCH(C9, 'Airtable copy'!N:N, 0)) -> FALSE | E9: =VLOOKUP(C9,'Airtable copy'!N:N,1,FALSE) -> #REF! | F9: =ISNUMBER(MATCH(C9, 'Grants tracker download'!O:O, 0)) -> FALSE | G9: =VLOOKUP(C9,'Grants tracker download'!O:O,1,FALSE) -> #REF! | H9: 10144450 | I9: Scaling sustainable cocoa butter production using cellular agriculture | J9: Scaling sustainable cocoa butter production using cellular agriculture | K9: For the third year running, cocoa demand has outstripped supply, with a 2023/24 deficit of 462,000 tons predicted by the International Cocoa Organization. Consequently, in April 2024, cocoa prices reached an historic high of USD12,261/ton, compared to around USD3,000/ton in April 2023\. Cocoa yields, which are expected to fall by 11.7% in 2023/24, are already significantly affected by both the climate crisis and prevailing climate patterns (El Nino), which have led to more extreme weather conditions in key cocoa-producing regions. Seasonally wetter conditions have driven devastating fungal disease outbreaks (black pod disease causes 20-30% yield losses globally and up to 100% locally). Seasonally warmer and drier conditions have also driven mealybug outbreaks, exacerbating the spread of endemic viral diseases (cocoa swollen shoot virus disease can cause local yield losses of 15-50%). By 2050, it is estimated that 89.5% of cocoa-producing areas will be less suitable for production. Alongside climate and disease challenges, the rising price of agricultural inputs (including fertiliser and pesticides) has forced farmers to reduce application rates, further reducing yield and profits. With smallholder farmers having limited investment opportunities, cocoa trees are also ageing and less productive. Coupling these production challenges with low farm-gate prices and small farm sizes, the majority of farmers in the two main cocoa-producing countries (Côte d'Ivoire and Ghana) are unable to earn a living income. Consequently, younger generations are increasingly seeking more rewarding employment opportunities. Cocoa continues to be a major driver of deforestation, biodiversity loss, and serious labour issues including child labour and forced labour. With cocoa demand continuing to rise, alternatives to traditional cocoa that can future-proof supplies and offer improved social and environmental impacts are receiving increasing attention. First-generation cocoa alternatives substitute cocoa for natural alternatives (e.g., carob), but they cannot recreate the authentic organoleptic properties of cocoa. Second-generation cocoa alternatives use precision fermentation to recreate key components of cocoa, but because they do not generate the full range of natural compounds in cocoa, they cannot recreate the full organoleptic properties of cocoa. Precision fermentation techniques also rely on energy-intensive genetically modified microbial production processes, which are challenging to scale. Recently, plant cell culture processes have been developed that uniquely offer the opportunity to recreate nature-identical cocoa, without requiring the development or use of genetically modified microbes, and with an energy-efficient and theoretically scalable production process. Here, Extracellular (UK) and Celleste Bio (Israel) will scale plant cell cultured cocoa production. | L9: For the third year running, cocoa demand has outstripped supply, with a 2023/24 deficit of 462,000 tons predicted by the International Cocoa Organization. Consequently, in April 2024, cocoa prices reached an historic high of USD12,261/ton, compared to around USD3,000/ton in April 2023\. Cocoa yields, which are expected to fall by 11.7% in 2023/24, are already significantly affected by both the climate crisis and prevailing climate patterns (El Nino), which have led to more extreme weather conditions in key cocoa-producing regions. Seasonally wetter conditions have driven devastating fungal disease outbreaks (black pod disease causes 20-30% yield losses globally and up to 100% locally). Seasonally warmer and drier conditions have also driven mealybug outbreaks, exacerbating the spread of endemic viral diseases (cocoa swollen shoot virus disease can cause local yield losses of 15-50%). By 2050, it is estimated that 89.5% of cocoa-producing areas will be less suitable for production. Alongside climate and disease challenges, the rising price of agricultural inputs (including fertiliser and pesticides) has forced farmers to reduce application rates, further reducing yield and profits. With smallholder farmers having limited investment opportunities, cocoa trees are also ageing and less productive. Coupling these production challenges with low farm-gate prices and small farm sizes, the majority of farmers in the two main cocoa-producing countries (Côte d'Ivoire and Ghana) are unable to earn a living income. Consequently, younger generations are increasingly seeking more rewarding employment opportunities. Cocoa continues to be a major driver of deforestation, biodiversity loss, and serious labour issues including child labour and forced labour. With cocoa demand continuing to rise, alternatives to traditional cocoa that can future-proof supplies and offer improved social and environmental impacts are receiving increasing attention. First-generation cocoa alternatives substitute cocoa for natural alternatives (e.g., carob), but they cannot recreate the authentic organoleptic properties of cocoa. Second-generation cocoa alternatives use precision fermentation to recreate key components of cocoa, but because they do not generate the full range of natural compounds in cocoa, they cannot recreate the full organoleptic properties of cocoa. Precision fermentation techniques also rely on energy-intensive genetically modified microbial production processes, which are challenging to scale. Recently, plant cell culture processes have been developed that uniquely offer the opportunity to recreate nature-identical cocoa, without requiring the development or use of genetically modified microbes, and with an energy-efficient and theoretically scalable production process. Here, Extracellular (UK) and Celleste Bio (Israel) will scale plant cell cultured cocoa production. | M9: Yes | N9: N/A | O9: N/A | Q9: 249927 | R9: GBP | S9: 316058 | T9: 2025-04-30 | U9: 2025 | V9: 2027-04-29 | W9: 2027 | X9: Jamie Thompson | Y9: EXTRACELLULAR LTD | AE9: Innovate UK | AF9: cOAlition S; UKRI - UK Research and Innovation | AG9: United Kingdom | AH9: Collaborative R&D (Project Category) | AI9: Not available | AK9: https://gtr.ukri.org/projects?ref=10144450 | AL9: https://app.dimensions.ai/details/grant/grant.15054223 | AM9: 30 Agricultural, Veterinary and Food Sciences; 3002 Agriculture, Land and Farm Management | AN9: Complementary and Integrative Health | AU9: A06 Agriculture, Veterinary and Food Science | AV9: 13 Climate Action; 15 Life on Land; 2 Zero Hunger
A10: 2025 Dimensions F | B10: 3162 | C10: grant.14933116 | D10: =ISNUMBER(MATCH(C10, 'Airtable copy'!N:N, 0)) -> FALSE | E10: =VLOOKUP(C10,'Airtable copy'!N:N,1,FALSE) -> #REF! | F10: =ISNUMBER(MATCH(C10, 'Grants tracker download'!O:O, 0)) -> FALSE | G10: =VLOOKUP(C10,'Grants tracker download'!O:O,1,FALSE) -> #REF! | H10: 101214268; 272166; UNICO2RN; 10.3030/101214268 | I10: Flexible and Efficient Capture and Bioconversion of CO2 to Materials and Ingredients | J10: Flexible and Efficient Capture and Bioconversion of CO2 to Materials and Ingredients | K10: The UNICO2RN project aims to demonstrate novel routes to convert biogenic CO2 into ingredients and materials, involving metal organic framework-based capture and purification technology and biotechnological processes based on Hydrogen Oxidizing Bacteria. The modularity and flexibility of the developed processes will be shown through 2 demonstration cases in real industrial settings at TRL 7 for sustainable and efficient production of microbial proteins and PHA, from 2 types of biogenic CO2 sources of different concentration and purity. These new routes bring clear advantages in terms of efficiency, safety, environmental footprint and greenhouse gas emission reductions with respect to benchmarks. Their development to TRL7 will enable their industrialization and thus lead to major positive economic, environmental and social/societal impacts. | L10: The UNICO2RN project aims to demonstrate novel routes to convert biogenic CO2 into ingredients and materials, involving metal organic framework-based capture and purification technology and biotechnological processes based on Hydrogen Oxidizing Bacteria. The modularity and flexibility of the developed processes will be shown through 2 demonstration cases in real industrial settings at TRL 7 for sustainable and efficient production of microbial proteins and PHA, from 2 types of biogenic CO2 sources of different concentration and purity. These new routes bring clear advantages in terms of efficiency, safety, environmental footprint and greenhouse gas emission reductions with respect to benchmarks. Their development to TRL7 will enable their industrialization and thus lead to major positive economic, environmental and social/societal impacts. | M10: Yes | N10: Fermentation | O10: Bioprocess design | Q10: 7499958 | R10: EUR | S10: 7959724 | T10: 2025-06-01 | U10: 2025 | V10: 2029-05-31 | W10: 2029 | Y10: VLAAMSE INSTELLING VOOR TECHNOLOGISCH ONDERZOEK N.V.; NIZO FOOD RESEARCH BV; CO2BIOCLEAN GMBH; VEOLIA NV-SA; LESAFFRE INTERNATIONAL; SABIO SRL; NOVA-INSTITUT FUR POLITISCHE UND OKOLOGISCHE INNOVATION GMBH; IDENER RESEARCH & DEVELOPMENT AIE; MOF TECHNOLOGIES LIMITED; AERBIO A/S; AERBIO BV | Z10: Flemish Institute for Technological Research; Nederlands Instituut Voor Zuivel Oonderzoek; Lesaffre International SARL; Nova Institut | AA10: grid.6717.7; grid.419921.6; grid.700749.d; grid.425930.9 | AB10: Mol; Ede; Hürth | AD10: Belgium; Netherlands; France; Germany | AE10: European Commission | AF10: EC & ERC - European Union; cOAlition S | AG10: Belgium | AH10: HORIZON.2.6 - Food, Bioeconomy Natural Resources, Agriculture and Environment (Programme); HORIZON-JU-IA - HORIZON JU Innovation Actions (Funding scheme); HORIZON-JU-CBE-2024 (Call for proposal) | AI10: Not available | AK10: https://cordis.europa.eu/project/id/101214268 | AL10: https://app.dimensions.ai/details/grant/grant.14933116 | AM10: 40 Engineering; 4004 Chemical Engineering | AU10: B12 Engineering | AV10: 13 Climate Action
A11: 2025 Dimensions F | B11: 2438 | C11: grant.15166434 | D11: =ISNUMBER(MATCH(C11, 'Airtable copy'!N:N, 0)) -> FALSE | E11: =VLOOKUP(C11,'Airtable copy'!N:N,1,FALSE) -> #REF! | F11: =ISNUMBER(MATCH(C11, 'Grants tracker download'!O:O, 0)) -> FALSE | G11: =VLOOKUP(C11,'Grants tracker download'!O:O,1,FALSE) -> #REF! | H11: APVV-24-0069; 47a3727f-b41e-40a8-b1a3-4d27984ab6ba | I11: Sustainable production of microbial proteins and their application in value-added cereal goods manufacturing | J11: Sustainable production of microbial proteins and their application in value-added cereal goods manufacturing | K11: As demand for animal origin food products increases faster than a global production can offer, novel strategies for carbon-neutral food manufacturing are an important part for diversifying food products and ensuring food self-sufficiency. Nowadays, more than one-fifth of global greenhouse gas emissions come from agriculture. Therefore, the development of alternative proteins and their adoption by consumers is critical to reduce negative climate change. Although plant-based alternatives make up 99% of this market, and most other proteins types (insects or microbes) are still in research and development pushing their greater commercialization at the end of this decade. The market with microbial proteins will be driven mainly by the expected increase in the world population, associated with countries' effort to secure food self-sufficiency and current trends in food consumption, which won’t be reachable by conventional agriculture/economy. Among the advantages of microbial proteins is their simple production, which includes a very short production time compared to the duration of growing crops, or raising animals, and also lower land and water requirements. Moreover, already available and producible mycoproteins (used as whole-cell products; without necessity of protein concentration or isolation) contain 40 % protein, have a high fibre content, limited saccharides content and don’t contain cholesterol, which makes them nutritionally more interesting compared to „classic“ proteins. The presented project focuses on potential production of microbial proteins using filamentous fungi and yeast by utilization of waste byproducts from industry. The main waste side-stream would be corn mash (form ethanol production) and glycerol (from biodiesel production). Returning of such waste into production has significant environmental effect. Furthermore, the produced biomass will be employed into process of bakery good production. Thus the effect of usage of these alternative would b | L11: As demand for animal origin food products increases faster than a global production can offer, novel strategies for carbon-neutral food manufacturing are an important part for diversifying food products and ensuring food self-sufficiency. Nowadays, more than one-fifth of global greenhouse gas emissions come from agriculture. Therefore, the development of alternative proteins and their adoption by consumers is critical to reduce negative climate change. Although plant-based alternatives make up 99% of this market, and most other proteins types (insects or microbes) are still in research and development pushing their greater commercialization at the end of this decade. The market with microbial proteins will be driven mainly by the expected increase in the world population, associated with countries' effort to secure food self-sufficiency and current trends in food consumption, which won’t be reachable by conventional agriculture/economy. Among the advantages of microbial proteins is their simple production, which includes a very short production time compared to the duration of growing crops, or raising animals, and also lower land and water requirements. Moreover, already available and producible mycoproteins (used as whole-cell products; without necessity of protein concentration or isolation) contain 40 % protein, have a high fibre content, limited saccharides content and don’t contain cholesterol, which makes them nutritionally more interesting compared to „classic“ proteins. The presented project focuses on potential production of microbial proteins using filamentous fungi and yeast by utilization of waste byproducts from industry. The main waste side-stream would be corn mash (form ethanol production) and glycerol (from biodiesel production). Returning of such waste into production has significant environmental effect. Furthermore, the produced biomass will be employed into process of bakery good production. Thus the effect of usage of these alternative would b | M11: Yes | N11: Fermentation | O11: End product formulation | P11: microbial biomass; circular economy; industrial waste processing; bakery products | Q11: 300000 | R11: EUR | S11: 318365 | T11: 2025-01-09 | U11: 2025 | V11: 2029-08-31 | W11: 2029 | X11: Tatiana Klempová, Milan Čertík, Zlatica Kohajdová, Michaela Lauková, Peter Gajdoš, Lucia Minarovičová | Y11: Research and Development center s.r.o.; Slovak University of Technology in Bratislava, Faculty of Chemical and Food Technology | Z11: Slovak University of Technology in Bratislava | AA11: grid.440789.6 | AB11: Bratislava | AD11: Slovakia | AE11: Slovak Research and Development Agency | AG11: Slovakia | AH11: SR&DA (APVV) Public Call (Program type, financial source) | AI11: Not available | AK11: https://www.skcris.sk/sk/register-projektov/detail/47a3727f-b41e-40a8-b1a3-4d27984ab6ba | AL11: https://app.dimensions.ai/details/grant/grant.15166434 | AM11: 30 Agricultural, Veterinary and Food Sciences; 31 Biological Sciences; 44 Human Society; 4410 Sociology | AU11: A06 Agriculture, Veterinary and Food Science | AV11: 13 Climate Action; 2 Zero Hunger
A12: 2025 Dimensions F | B12: 2354 | C12: grant.14933075 | D12: =ISNUMBER(MATCH(C12, 'Airtable copy'!N:N, 0)) -> FALSE | E12: =VLOOKUP(C12,'Airtable copy'!N:N,1,FALSE) -> #REF! | F12: =ISNUMBER(MATCH(C12, 'Grants tracker download'!O:O, 0)) -> FALSE | G12: =VLOOKUP(C12,'Grants tracker download'!O:O,1,FALSE) -> #REF! | H12: 101212855; 271884; MYCOCIRCLE; 10.3030/101212855 | I12: Upcycling mushroom waste to replace animal derived chemicals | J12: Upcycling mushroom waste to replace animal derived chemicals | K12: Animal-derived materials are surprisingly widespread in everyday products. For example, in the cosmetics, pharmaceutical and agrochemicals industries, squalene (from shark liver oil), chitin/chitosan (from crustaceans) and animal-derived proteins and fats are widely exploited despite growing ethical and sustainability concerns. Fungal biomass is rich in chitin, while recent advances in fermentation technologies offer opportunities to convert fungal glucans into microbial proteins, oils and even triterpenes such as squalene. However, scalability is a major challenge, due to the limited availability of clean fungal biomass and competition with food/feed value chains. Moreover, oil production using existing fungal fermentation routes is limited to low-value triglycerides, and efficient product extraction remains a bottleneck. Feedstock diversification is needed, alongside innovation towards higher-value products and more efficient processes. The production of edible mushrooms produces ~189M tpa of mycelium rich wastes, contaminated with lignocellulosic growth substrate. This contamination makes these wastes unsuitable for food/feeds, and incompatible with existing valorisation approaches. MYCOCIRCLE will focus on this challenging feedstock, developing new technologies including an enzymatic fractionation process, two parallel fermentation routes, and novel enzymatic chitin conversion reactions. The resulting product streams, including fungal chitosan/chito-oligosaccharides, a high-value squalene-rich microbial oil, and microbial proteins, will be validated as replacements to animal derived materials in cosmetic and agrochemical applications. The MYCOCIRCLE consortium represents the entire value chain, from feedstock producers (SYLVAN, KORONA) to industrial biotechnology companies (GST), and end users (GI, THGL). This value chain will be supported by world experts in biomass valorisation, enzymatic processing, and SSbD development: TUM, SINTEF, NMBU, SLU and IDENER. | L12: Animal-derived materials are surprisingly widespread in everyday products. For example, in the cosmetics, pharmaceutical and agrochemicals industries, squalene (from shark liver oil), chitin/chitosan (from crustaceans) and animal-derived proteins and fats are widely exploited despite growing ethical and sustainability concerns. Fungal biomass is rich in chitin, while recent advances in fermentation technologies offer opportunities to convert fungal glucans into microbial proteins, oils and even triterpenes such as squalene. However, scalability is a major challenge, due to the limited availability of clean fungal biomass and competition with food/feed value chains. Moreover, oil production using existing fungal fermentation routes is limited to low-value triglycerides, and efficient product extraction remains a bottleneck. Feedstock diversification is needed, alongside innovation towards higher-value products and more efficient processes. The production of edible mushrooms produces ~189M tpa of mycelium rich wastes, contaminated with lignocellulosic growth substrate. This contamination makes these wastes unsuitable for food/feeds, and incompatible with existing valorisation approaches. MYCOCIRCLE will focus on this challenging feedstock, developing new technologies including an enzymatic fractionation process, two parallel fermentation routes, and novel enzymatic chitin conversion reactions. The resulting product streams, including fungal chitosan/chito-oligosaccharides, a high-value squalene-rich microbial oil, and microbial proteins, will be validated as replacements to animal derived materials in cosmetic and agrochemical applications. The MYCOCIRCLE consortium represents the entire value chain, from feedstock producers (SYLVAN, KORONA) to industrial biotechnology companies (GST), and end users (GI, THGL). This value chain will be supported by world experts in biomass valorisation, enzymatic processing, and SSbD development: TUM, SINTEF, NMBU, SLU and IDENER. | M12: Yes | N12: Fermentation | O12: Ingredient optimisation | Q12: 3486568 | R12: EUR | S12: 3700302 | T12: 2025-09-01 | U12: 2025 | V12: 2028-08-31 | W12: 2028 | Y12: SOMYCEL SA; TECHNISCHE UNIVERSITAET MUENCHEN; SINTEF AS; IDENER RESEARCH & DEVELOPMENT AIE; NORGES MILJO-OG BIOVITENSKAPELIGE UNIVERSITET; SVERIGES LANTBRUKSUNIVERSITET; GREEN IMPULSE; GLOBAL SUSTAINABLE TRANSFORMATION GST GmbH; Acheson & Acheson Limited T/A THG Labs | Z12: Technical University of Munich; SINTEF AS; Norwegian University of Life Sciences; Swedish University of Agricultural Sciences | AA12: grid.6936.a; grid.4319.f; grid.19477.3c; grid.6341.0 | AB12: Munich; Trondheim; Ås; Uppsala | AD12: Germany; Norway; Norway; Sweden | AE12: European Commission | AF12: EC & ERC - European Union; cOAlition S | AG12: Belgium | AH12: HORIZON.2.6 - Food, Bioeconomy Natural Resources, Agriculture and Environment (Programme); HORIZON-JU-RIA - HORIZON JU Research and Innovation Actions (Funding scheme); HORIZON-JU-CBE-2024 (Call for proposal) | AI12: Not available | AK12: https://cordis.europa.eu/project/id/101212855 | AL12: https://app.dimensions.ai/details/grant/grant.14933075 | AM12: 31 Biological Sciences; 3106 Industrial Biotechnology | AU12: B12 Engineering | AV12: 12 Responsible Consumption and Production
A13: 2025 Dimensions F | B13: 1862 | C13: grant.14878552 | D13: =ISNUMBER(MATCH(C13, 'Airtable copy'!N:N, 0)) -> FALSE | E13: =VLOOKUP(C13,'Airtable copy'!N:N,1,FALSE) -> #REF! | F13: =ISNUMBER(MATCH(C13, 'Grants tracker download'!O:O, 0)) -> FALSE | G13: =VLOOKUP(C13,'Grants tracker download'!O:O,1,FALSE) -> #REF! | H13: LS24-058 | I13: Designing a professional-secretory synthetic endoplasmic reticulum in yeasts and plant cells | J13: Designing a professional-secretory synthetic endoplasmic reticulum in yeasts and plant cells | K13: The endoplasmic reticulum (ER) is the key organelle for folding and processing of secretory proteins. Inefficient folding and secretion are a major challenge in production of recombinant proteins needed as biopharmaceuticals or for securing future food requirements. In most non-mammalian cells, the ER is spatially limiting these processes. SynthER aims to go beyond mere physical ER expansion by tailoring functionality through orthogonal and combinatorial expression of synthetic ER shaping proteins in yeast and plant cells. Inspired by professional secretory mammalian cells, SynthER envisages to biomimic their stacked ER sheet and luminal architecture in yeast and plants. The new morphologies will be monitored by a wide range of microscopic methods and quantitative image analyses, and their impact on the quality and quantity of secreted recombinant proteins will be determined.Furthermore, synthetic ER exit vesicles (SERV) will be designed to deliver their protein cargo directly to the plasma membrane, bypassing the often adverse functions of the Golgi and vacuole. SERVs shall be programmable synthetic circuits, that can be expressed on demand.Taken together, SynthER will develop novel cell factory concepts that represent a significant advance to the state of the art. Synthetic endomembrane engineering addresses a timely research topic through a pioneering synthetic biology approach with significant potential for advancing both the scientific understanding of secretory pathway plasticity and impacting technological applications, thus benefiting medicine and biotechnology.Our ground-breaking interdisciplinary combination of cross-kingdom molecular and cell biology in microbes and whole plants together with advanced microscopy and engineering unlocks new scientific opportunities and expands the toolkit of synthetic cellular design. | L13: The endoplasmic reticulum (ER) is the key organelle for folding and processing of secretory proteins. Inefficient folding and secretion are a major challenge in production of recombinant proteins needed as biopharmaceuticals or for securing future food requirements. In most non-mammalian cells, the ER is spatially limiting these processes. SynthER aims to go beyond mere physical ER expansion by tailoring functionality through orthogonal and combinatorial expression of synthetic ER shaping proteins in yeast and plant cells. Inspired by professional secretory mammalian cells, SynthER envisages to biomimic their stacked ER sheet and luminal architecture in yeast and plants. The new morphologies will be monitored by a wide range of microscopic methods and quantitative image analyses, and their impact on the quality and quantity of secreted recombinant proteins will be determined.Furthermore, synthetic ER exit vesicles (SERV) will be designed to deliver their protein cargo directly to the plasma membrane, bypassing the often adverse functions of the Golgi and vacuole. SERVs shall be programmable synthetic circuits, that can be expressed on demand.Taken together, SynthER will develop novel cell factory concepts that represent a significant advance to the state of the art. Synthetic endomembrane engineering addresses a timely research topic through a pioneering synthetic biology approach with significant potential for advancing both the scientific understanding of secretory pathway plasticity and impacting technological applications, thus benefiting medicine and biotechnology.Our ground-breaking interdisciplinary combination of cross-kingdom molecular and cell biology in microbes and whole plants together with advanced microscopy and engineering unlocks new scientific opportunities and expands the toolkit of synthetic cellular design. | M13: Yes | N13: Cross-cutting | O13: Cell line development / Strain development | Q13: 897906 | R13: EUR | S13: 952937 | T13: 2025-07-01 | U13: 2025 | V13: 2029-06-30 | W13: 2029 | X13: Brigitte Gasser, Eva Stöger | Y13: BOKU - University of Natural Resources and Life Sciences | Z13: University of Natural Resources and Life Sciences | AA13: grid.5173.0 | AB13: Vienna | AD13: Austria | AE13: Vienna Science and Technology Fund | AG13: Austria | AH13: Life Sciences (Programs) | AI13: Not available | AK13: https://www.wwtf.at/funding/programmes/ls/LS24-058 | AL13: https://app.dimensions.ai/details/grant/grant.14878552 | AM13: 31 Biological Sciences; 3101 Biochemistry and Cell Biology | AN13: Biotechnology | AO13: Generic health relevance | AR13: Basic Science | AU13: A05 Biological Sciences
A14: 2025 Dimensions F | B14: 1722 | C14: grant.15078549 | D14: =ISNUMBER(MATCH(C14, 'Airtable copy'!N:N, 0)) -> FALSE | E14: =VLOOKUP(C14,'Airtable copy'!N:N,1,FALSE) -> #REF! | F14: =ISNUMBER(MATCH(C14, 'Grants tracker download'!O:O, 0)) -> FALSE | G14: =VLOOKUP(C14,'Grants tracker download'!O:O,1,FALSE) -> #REF! | H14: 2024-02716_Formas | I14: SEAlgaePower － Sustainable development of microalgae-based ingredients using waste streams from aquaculture and seafood processing industry as feedstock | J14: SEAlgaePower － Sustainable development of microalgae-based ingredients using waste streams from aquaculture and seafood processing industry as feedstock | K14: The overall objective of the SEAlgaePower project is to develop innovative microalgae-based technologies to clean wastewater from the aquaculture and seafood processing industry while simultaneously producing biomass for novel ingredients in a sustainable way. The specific aims are to: (i) select suitable microalgae species from the North and the Mediterranean Sea in a lab-scale cultivation system based on the ability to grow in different wastewater types; (ii) develop protocols for pilot-scale algae cultivation and wastewater cleaning; (iii) develop biorefinery protocols for protein, lipid and carbohydrate recovery from the microalgal biomass; (iv) develop microalgae-based product prototypes and ingredients; (v) assess environmental and socio-economic aspects associated with the project solutions for wastewater cleaning, microalgae cultivation and biomass valorisation, and (v) maximise the project impact, visibility, and legacy. In this project, UGOT will employ a two-stage cultivation in lab-scale for screening of microalgae growth in wastewater from salmon aquaculture and process waters from the seafood industry. Chalmers will analyse the biochemical composition of the various water types and will also contribute to biorefining of microalgal biomass by extracting protein for development of alternative food protein ingredients. RISE will use polysaccharide-enriched fractions from the biorefinery to develop fibre prototypes for use in wound care and regenerative medicine. | L14: The overall objective of the SEAlgaePower project is to develop innovative microalgae-based technologies to clean wastewater from the aquaculture and seafood processing industry while simultaneously producing biomass for novel ingredients in a sustainable way. The specific aims are to: (i) select suitable microalgae species from the North and the Mediterranean Sea in a lab-scale cultivation system based on the ability to grow in different wastewater types; (ii) develop protocols for pilot-scale algae cultivation and wastewater cleaning; (iii) develop biorefinery protocols for protein, lipid and carbohydrate recovery from the microalgal biomass; (iv) develop microalgae-based product prototypes and ingredients; (v) assess environmental and socio-economic aspects associated with the project solutions for wastewater cleaning, microalgae cultivation and biomass valorisation, and (v) maximise the project impact, visibility, and legacy. In this project, UGOT will employ a two-stage cultivation in lab-scale for screening of microalgae growth in wastewater from salmon aquaculture and process waters from the seafood industry. Chalmers will analyse the biochemical composition of the various water types and will also contribute to biorefining of microalgal biomass by extracting protein for development of alternative food protein ingredients. RISE will use polysaccharide-enriched fractions from the biorefinery to develop fibre prototypes for use in wound care and regenerative medicine. | M14: Yes | N14: Plant-based | O14: Ingredient optimisation | Q14: 5734593 | R14: SEK | S14: 542741 | T14: 2025-08-01 | U14: 2025 | V14: 2028-07-31 | W14: 2028 | X14: Cornelia Spetea Wiklund, Markus Andersson Trojer, Ingrid Undeland | Y14: University of Gothenburg | Z14: University of Gothenburg | AA14: grid.8761.8 | AB14: Gothenburg | AD14: Sweden | AE14: Swedish Research Council for Environment Agricultural Sciences and Spatial Planning | AF14: cOAlition S | AG14: Sweden | AH14: 20901:Bioprocessteknik, Bioprocess Technology (SCB); 2:Teknik, Engineering and Technology (SCB); 209:Industriell bioteknik, Industrial Biotechnology (SCB) | AI14: Not available | AK14: https://www.vr.se/swecris.html#/project/2024-02716_Formas | AL14: https://app.dimensions.ai/details/grant/grant.15078549 | AM14: 31 Biological Sciences; 3106 Industrial Biotechnology | AO14: Generic health relevance | AU14: B12 Engineering
A15: 2025 Dimensions F | B15: 1529 | C15: grant.15051286 | D15: =ISNUMBER(MATCH(C15, 'Airtable copy'!N:N, 0)) -> FALSE | E15: =VLOOKUP(C15,'Airtable copy'!N:N,1,FALSE) -> #REF! | F15: =ISNUMBER(MATCH(C15, 'Grants tracker download'!O:O, 0)) -> FALSE | G15: =VLOOKUP(C15,'Grants tracker download'!O:O,1,FALSE) -> #REF! | H15: 360345 | I15: SEAlgaePower: Sustainable development of microalgae-based products using waste streams from aquaculture and seafood processing industry | J15: SEAlgaePower: Sustainable development of microalgae-based products using waste streams from aquaculture and seafood processing industry | K15: The fast-growing land-based aquaculture and seafood processing industry generate large amounts of nutrient-rich wastewater, posing a high cost for discharge and environmental impact. At the same time, there is an increasing demand for new resources intended for carbon-neutral production of food, material and energy. The ability of microalgae to perform photosynthesis and efficiently convert dissolved nutrients into valuable biomass could contribute to solving this dual problem. The overall objective of SEAlgaePower is to develop microalgae-based technologies to clean wastewater from the aquaculture and seafood processing industry while simultaneously producing biomass for novel ingredients in a sustainable way. The specific aims are to: (i) select suitable microalgae species/strains from the North and the Mediterranean Sea in a lab-scale cultivation system based on the ability to grow in different wastewater types; ((ii) develop pilot-scale algae cultivation protocols and wastewater cleaning; (iii) develop biorefinery protocols for protein, lipid and carbohydrate recovery from the microalgal biomass; (iv) develop microalgae-based prototypes and ingredients; (v) assess environmental and socio-economic aspects associated with the project solutions on wastewater cleaning, microalgae cultivation and biomass valorisation, and (v) maximise the project impact, visibility, and legacy. The SEAlgaePower consortium, coordinated by the University of Gothenburg, consists of thirteen partners from seven countries: Chalmers University of Technology, NORCE Norwegian Research Centre, University of Aveiro, University of Palermo, Sustainable Innovation Technology Services, RISE Research Institutes of Sweden, Nordicflexhouse, Danish Technological Institute, Universidade de Sao Paulo, Norwegian Institute of Bioeconomy Research, Klädesholmen Seafood, and RAGN-SELLS HAVBRUK. | L15: The fast-growing land-based aquaculture and seafood processing industry generate large amounts of nutrient-rich wastewater, posing a high cost for discharge and environmental impact. At the same time, there is an increasing demand for new resources intended for carbon-neutral production of food, material and energy. The ability of microalgae to perform photosynthesis and efficiently convert dissolved nutrients into valuable biomass could contribute to solving this dual problem. The overall objective of SEAlgaePower is to develop microalgae-based technologies to clean wastewater from the aquaculture and seafood processing industry while simultaneously producing biomass for novel ingredients in a sustainable way. The specific aims are to: (i) select suitable microalgae species/strains from the North and the Mediterranean Sea in a lab-scale cultivation system based on the ability to grow in different wastewater types; ((ii) develop pilot-scale algae cultivation protocols and wastewater cleaning; (iii) develop biorefinery protocols for protein, lipid and carbohydrate recovery from the microalgal biomass; (iv) develop microalgae-based prototypes and ingredients; (v) assess environmental and socio-economic aspects associated with the project solutions on wastewater cleaning, microalgae cultivation and biomass valorisation, and (v) maximise the project impact, visibility, and legacy. The SEAlgaePower consortium, coordinated by the University of Gothenburg, consists of thirteen partners from seven countries: Chalmers University of Technology, NORCE Norwegian Research Centre, University of Aveiro, University of Palermo, Sustainable Innovation Technology Services, RISE Research Institutes of Sweden, Nordicflexhouse, Danish Technological Institute, Universidade de Sao Paulo, Norwegian Institute of Bioeconomy Research, Klädesholmen Seafood, and RAGN-SELLS HAVBRUK. | M15: Yes | N15: Plant-based | O15: Ingredient optimisation | Q15: 2890999 | R15: NOK | S15: 262284 | T15: 2025-01-01 | U15: 2025 | V15: 2028-12-31 | W15: 2028 | X15: Hanna Böpple | Y15: NORCE RESEARCH AS | AE15: The Research Council of Norway | AF15: cOAlition S | AG15: Norway | AH15: BIOTEKNOLOGI-BIOTEKNOLOGI (Funding scheme) | AI15: Not available | AK15: https://prosjektbanken.forskningsradet.no/en/project/FORISS/360345 | AL15: https://app.dimensions.ai/details/grant/grant.15051286 | AM15: 31 Biological Sciences; 3106 Industrial Biotechnology; 41 Environmental Sciences; 4104 Environmental Management | AU15: B12 Engineering
A16: 2025 Dimensions F | B16: 1354 | C16: grant.14955094 | D16: =ISNUMBER(MATCH(C16, 'Airtable copy'!N:N, 0)) -> FALSE | E16: =VLOOKUP(C16,'Airtable copy'!N:N,1,FALSE) -> #REF! | F16: =ISNUMBER(MATCH(C16, 'Grants tracker download'!O:O, 0)) -> FALSE | G16: =VLOOKUP(C16,'Grants tracker download'!O:O,1,FALSE) -> #REF! | H16: 101213354; 272325; CleanAlgae2Value; 10.3030/101213354 | I16: Demonstrating a cost competitive, sustainable, scalable intensified micro-algae bioprocess for the production of food-grade medium value, carbon negative Ingredients exceeding Market Standards | J16: Demonstrating a cost competitive, sustainable, scalable intensified micro-algae bioprocess for the production of food-grade medium value, carbon negative Ingredients exceeding Market Standards | K16: Micro-Algae offer a solution to many of the European bioeconomy needs. Nevertheless, significant challenges still exist to their acceptance on the market, including organoleptic and functionality challenges. CleanAlgae2Value seeks to unlock such potential via a cascading approach to white-microalgae-derived medium-price ingredients, including protein isolates, oils, natural pigments and starch. The project will build and operate a replicable “upgrading-module” to drastically enhance relevant biorefineries performance via a cost-competitive, sustainable, and scalable microalgae fractionation and valorisation process for producing food-grade, medium-value, carbon-negative ingredients that exceed market standards. More specifically, the project will prove the effectiveness and efficiency of a “Micro-Algae Biorefinery Upgrade Module” (MABUM), able to unlock productions of protein isolates, protein concentrates, starch-rich fraction and oils (respectively 2, 1.3, 3.98 and 1.8 tons) to be validated into 15 prototypes, 13 for food and 2 for bio-packaging markets. The project will do so while increasing operative margins, by decreasing “value-normalised” CAPEX and OPEX, also thanks to modelling optimisation, contributing to market penetration. Importantly, CleanAlgae2Value would also benefit from synergies with a recently granted EIC Accelerator project, which focuses on upstream algae production from CO2 via SOL two-step fermentation, using solely CO2 as carbon source. The project brings together 16 organizations from 9 European countries, collaborating with end-users to produce added value ingredients. Holistic evaluations, including both empirical (surveys, workshops) and horizontal considerations (LCA, TEA, SSbD), will allow for the assessment of market acceptance and environmental, economic and societal sustainability, as well as further support and boost the project DCE activities and pathways towards EFSA positive opinion for those ingredients that still require it. | L16: Micro-Algae offer a solution to many of the European bioeconomy needs. Nevertheless, significant challenges still exist to their acceptance on the market, including organoleptic and functionality challenges. CleanAlgae2Value seeks to unlock such potential via a cascading approach to white-microalgae-derived medium-price ingredients, including protein isolates, oils, natural pigments and starch. The project will build and operate a replicable “upgrading-module” to drastically enhance relevant biorefineries performance via a cost-competitive, sustainable, and scalable microalgae fractionation and valorisation process for producing food-grade, medium-value, carbon-negative ingredients that exceed market standards. More specifically, the project will prove the effectiveness and efficiency of a “Micro-Algae Biorefinery Upgrade Module” (MABUM), able to unlock productions of protein isolates, protein concentrates, starch-rich fraction and oils (respectively 2, 1.3, 3.98 and 1.8 tons) to be validated into 15 prototypes, 13 for food and 2 for bio-packaging markets. The project will do so while increasing operative margins, by decreasing “value-normalised” CAPEX and OPEX, also thanks to modelling optimisation, contributing to market penetration. Importantly, CleanAlgae2Value would also benefit from synergies with a recently granted EIC Accelerator project, which focuses on upstream algae production from CO2 via SOL two-step fermentation, using solely CO2 as carbon source. The project brings together 16 organizations from 9 European countries, collaborating with end-users to produce added value ingredients. Holistic evaluations, including both empirical (surveys, workshops) and horizontal considerations (LCA, TEA, SSbD), will allow for the assessment of market acceptance and environmental, economic and societal sustainability, as well as further support and boost the project DCE activities and pathways towards EFSA positive opinion for those ingredients that still require it. | M16: Yes | N16: Plant-based | O16: Ingredient optimisation | Q16: 7483218 | R16: EUR | S16: 7941964 | T16: 2025-10-01 | U16: 2025 | V16: 2029-09-30 | W16: 2029 | Y16: DELTA ANONYMI VIOMICHANIKI KAI EMPORIKI ETAIREIA TROFIMON MONOPROSOPI A.E.; CENTRE FOR PROCESS INNOVATION LIMITED LBG; CENTRO NACIONAL DE TECNOLOGIA Y SEGURIDAD ALIMENTARIA; EROSKI SCOOP; BEVO, biotehnoloske resitve, d.o.o; BIO BASE EUROPE PILOT PLANT VZW; MAGFI LTD; KNOELL GERMANY GMBH; DANMARKS TEKNISKE UNIVERSITET; AUZO LAGUN S. COOP; SOLMEGIA MONOPROSOPI I.K.E.; Hooked Foods AB; EURO-FUNDING EU PROJECTS SOCIEDAD LIMITADA; NUEVAS TECNOLOGIAS PARA EL DESARROLLO DE PACKAGING Y PRODUCTOS AGROALIMENTARIOS CON COMPONENTE PLASTICA SL; CHALMERS TEKNISKA HOGSKOLA AB | Z16: Centre for Process Innovation; National Centre for Technology and Food Safety; Eroski S Coop; Bevo Biotehnoloske Resitve doo; Bio Base Europe; Technical University of Denmark; Chalmers University of Technology | AA16: grid.420713.3; grid.433452.7; grid.745750.4; grid.613057.6; grid.432888.d; grid.5170.3; grid.5371.0 | AB16: Redcar; San Adrián; Ghent; Kongens Lyngby; Gothenburg | AC16: Hovedstaden | AD16: United Kingdom; Spain; Spain; Slovenia; Belgium; Denmark; Sweden | AE16: European Commission | AF16: EC & ERC - European Union; cOAlition S | AG16: Belgium | AH16: HORIZON.2.6 - Food, Bioeconomy Natural Resources, Agriculture and Environment (Programme); HORIZON-JU-IA - HORIZON JU Innovation Actions (Funding scheme); HORIZON-JU-CBE-2024 (Call for proposal) | AI16: Not available | AK16: https://cordis.europa.eu/project/id/101213354 | AL16: https://app.dimensions.ai/details/grant/grant.14955094 | AM16: 31 Biological Sciences; 3106 Industrial Biotechnology | AU16: C13 Architecture, Built Environment and Planning | AV16: 12 Responsible Consumption and Production; 2 Zero Hunger
A17: 2025 Dimensions F | B17: 1097 | C17: grant.15162542 | D17: =ISNUMBER(MATCH(C17, 'Airtable copy'!N:N, 0)) -> FALSE | E17: =VLOOKUP(C17,'Airtable copy'!N:N,1,FALSE) -> #REF! | F17: =ISNUMBER(MATCH(C17, 'Grants tracker download'!O:O, 0)) -> FALSE | G17: =VLOOKUP(C17,'Grants tracker download'!O:O,1,FALSE) -> #REF! | H17: PCI2025-167111-2 | I17: MICROALGAL BIOMASS VALORIZATION FOR SUSTAINABLE PRODUCTION OF FUNCTIONAL FOOD AND FEED INGREDIENTS | J17: MICROALGAL BIOMASS VALORIZATION FOR SUSTAINABLE PRODUCTION OF FUNCTIONAL FOOD AND FEED INGREDIENTS | K17: EL PROYECTO BIOVAL RESPONDE AL CRECIENTE DESAFIO DE GARANTIZAR ALIMENTOS SOSTENIBLES Y SALUDABLES MEDIANTE EL DESARROLLO DE UNA BIORREFINERIA AVANZADA DE MICROALGAS, CONCEBIDA BAJO UN MODELO DE CERO RESIDUOS Y ECONOMICAMENTE VIABLE. SE TRABAJARA CON TRES ESPECIES MARINAS DE ALTO POTENCIAL BIOTECNOLOGICO (PHAEODACTYLUM TRICORNUTUM, TETRASELMIS CHUII Y SKELETONEMA MARINOI), ORIENTANDO LA PRODUCCION HACIA 2-MONOACILGLICERIDOS (2-MAGS) DE ELEVADO VALOR AÑADIDO, ESPECIALMENTE ENRIQUECIDOS EN ACIDOS GRASOS OMEGA-3 (EPA Y DHA), CON APLICACIONES FUNCIONALES EN LA INDUSTRIA ALIMENTARIA PARA LA PREVENCION DEL SINDROME METABOLICO. LA SINTESIS QUIMICA CONVENCIONAL DE MAGS PRESENTA LIMITACIONES CRITICAS (ALTAS TEMPERATURAS, CATALIZADORES Y SUBPRODUCTOS TOXICOS COMO ESTERES DE GLICIDILO). BIOVAL PROPONE UNA ESTRATEGIA DISRUPTIVA Y SOSTENIBLE BASADA EN LA EXTRACCION VERDE DE 2-MAGS NATIVOS Y, PRINCIPALMENTE, EN SU SINTESIS ENZIMATICA CONTROLADA, GARANTIZANDO PRODUCTOS MAS PUROS Y SEGUROS, CON MAYOR EFICIENCIA DE PROCESO. LA INNOVACION ABARCA TODA LA CADENA DE VALOR: CULTIVO: IMPLEMENTACION DE ESTRATEGIAS MIXOTROFICAS EMPLEANDO SUBPRODUCTOS AGRICOLAS HIDROLIZADOS COMO FUENTE DE CARBONO ORGANICO, OPTIMIZANDO PRODUCTIVIDAD DE BIOMASA Y LIPIDOS. DIGITALIZACION: USO DE INTELIGENCIA ARTIFICIAL MEDIANTE REDES NEURONALES ARTIFICIALES PARA MODELAR Y OPTIMIZAR CONDICIONES DE CULTIVO EN TIEMPO REAL. MEJORA DE CEPAS: APLICACION DE TECNOLOGIAS OMICAS (GENOMICA, TRANSCRIPTOMICA Y METABOLOMICA) PARA IDENTIFICAR Y MODULAR RUTAS METABOLICAS CLAVE EN LA BIOSINTESIS DE 2-MAGS. VALIDACION FUNCIONAL: ENSAYOS IN VITRO E IN VIVO PARA EVALUAR LA BIOACTIVIDAD DE LOS 2-MAGS (CAPACIDAD ANTIINFLAMATORIA Y MEJORA DE LA SENSIBILIDAD A LA INSULINA). EL PROCESO SE DISEÑARA PARA ALCANZAR TRL 6, VALIDANDO LA TECNOLOGIA EN UN ENTORNO INDUSTRIALMENTE RELEVANTE. LAS FRACCIONES RESIDUALES (PROTEINAS, CARBOHIDRATOS) SE CO-VALORIZARAN EN PIENSOS FUNCIONALES PARA ACUICULTURA, CERRANDO EL CICLO PRODUCTIVO Y MAXIMIZANDO EL APROVECHAMIENTO INTEGRAL DE LA BIOMASA. BIOVAL CONTRIBUIRA A LOS OBJETIVOS DEL SUSTAINABLE BLUE ECONOMY PARTNERSHIP, IMPULSANDO LA BIOECONOMIA AZUL CIRCULAR, LA REDUCCION DE LA HUELLA DE CARBONO Y LA GENERACION DE INGREDIENTES FUNCIONALES SEGUROS Y SOSTENIBLES, CON IMPACTO DIRECTO EN LA SALUD PUBLICA, LA COMPETITIVIDAD INDUSTRIAL Y LA RESILIENCIA DEL SECTOR ACUICOLA EUROPEO. | L17: The BIOVAL project responds to the growing challenge of ensuring sustainable and healthy food through the development of an advanced microalgae biorefinery, designed under a zero-waste and economically viable model. We will work with three marine species with high biotechnological potential (Phaeodactylum tricornutum, Tetraselmis chuii, and Skeletonema marinoi), focusing production on high-value-added 2-monoacylglycerides (2-MAGS), especially those enriched in omega-3 fatty acids (EPA and DHA), with functional applications in the food industry for the prevention of metabolic syndrome. The conventional chemical synthesis of MAGS presents critical limitations (high temperatures, catalysts, and toxic byproducts such as glycidyl esters). BIOVAL proposes a disruptive and sustainable strategy based on the green extraction of native 2-MAGS and, primarily, on their controlled enzymatic synthesis, guaranteeing purer and safer products with greater process efficiency. The innovation encompasses the entire value chain: CULTIVATION: Implementation of mixotrophic strategies using hydrolyzed agricultural byproducts as a source of organic carbon, optimizing biomass and lipid productivity. DIGITALIZATION: Use of artificial intelligence through artificial neural networks to model and optimize cultivation conditions in real time. Strain Enhancement: Application of omics technologies (genomics, transcription, and metabolomics) to identify and modulate key metabolic pathways in 2-magnesium biosynthesis. Functional Validation: In vitro and in vivo assays to evaluate the bioactivity of 2-magnesium (anti-inflammatory capacity and insulin sensitivity enhancement). The process will be designed to achieve a Technology Readiness Level (TRL) of 6, validating the technology in an industrially relevant setting. The residual fractions (proteins, carbohydrates) will be co-valorized in functional aquaculture feeds, closing the production cycle and maximizing the comprehensive use of biomass. BIOVAL will contribute to the Sustainable Blue Economy Partnership objectives, promoting the circular blue bioeconomy, reducing the carbon footprint, and generating safe and sustainable functional ingredients, with a direct impact on public health, industrial competitiveness, and the resilience of the European aquaculture sector. | M17: Yes | N17: Plant-based | O17: Ingredient optimisation | Q17: 212500 | R17: EUR | S17: 225527 | T17: 2025-01-01 | U17: 2025 | Y17: UNIVERSIDAD DE ALMERIA | Z17: University of Almería | AA17: grid.28020.38 | AB17: Almería | AD17: Spain | AE17: State Research Agency | AG17: Spain | AH17: International Collaboration Projects (Call) | AI17: Not available | AK17: https://www.aei.gob.es/ayudas-concedidas/buscador-ayudas-concedidas | AL17: https://app.dimensions.ai/details/grant/grant.15162542 | AM17: 31 Biological Sciences; 3106 Industrial Biotechnology; 32 Biomedical and Clinical Sciences; 3205 Medical Biochemistry and Metabolomics | AU17: B12 Engineering | AV17: 12 Responsible Consumption and Production
A18: 2025 Dimensions F | B18: 1091 | C18: grant.14973726 | D18: =ISNUMBER(MATCH(C18, 'Airtable copy'!N:N, 0)) -> FALSE | E18: =VLOOKUP(C18,'Airtable copy'!N:N,1,FALSE) -> #REF! | F18: =ISNUMBER(MATCH(C18, 'Grants tracker download'!O:O, 0)) -> FALSE | G18: =VLOOKUP(C18,'Grants tracker download'!O:O,1,FALSE) -> #REF! | H18: 101219355; 273209; SOLARSPOON; 10.3030/101219355 | I18: Solar-driven synthesis of proteins and lipids via photoelectrochemistry of living organisms | J18: Solar-driven synthesis of proteins and lipids via photoelectrochemistry of living organisms | K18: Biohybrid systems offer unique energy-efficient routes to harness solar energy for the fixation of CO2 and nitrogen into valuable, complex molecules. This project will integrate living photosynthetic bacteria and food-producing autotrophic bacteria into stand-alone photoelectrochemical devices tailored for the direct production of proteins and lipids from sunlight, air and water. Cyanobacteria will supply electrons via light-driven water oxidation, organic dyes will provide these electrons with sufficient energy to generate substrates that would directly feed either a culture or a consortia of food producing microorganisms in the same device. The result will be the demonstration of the first direct conversion of CO2 and N2 from air to protein- or lipid-rich food materials using solar energy, with the aim to produce a prototype that can reach 1% solar-conversion efficiency or surpass present food production processes via agriculture. Our bioengineering efforts will focus on three key innovations: (i) overcoming complex electron transfer pathway barriers at the cell-electrode interface, aided by the coupling of electrode engineering with advanced modelling of the interface; (ii) expanding the range of Solar-to-X products to two essential food groups (proteins and lipids), enabled by the formation of novel microbial consortia on redox polymer films that mitigate their conflicting microenvironment needs; and iii) device engineering that synergizes the different outputs and needs of the bio-anode and cathode whilst also facilitating easy food-product collection. The delivery of our envisioned Solar-to-Food devices will open the door to re-imagining sustainable food production for off-grid locations, kitchens in future households and spaceships. Current food industries, such as our partner Solar Foods, would be an immediate benefactor. Our envisioned solar-to-lipids production process could be a stepping stone to fuels production lines of the future. | L18: Biohybrid systems offer unique energy-efficient routes to harness solar energy for the fixation of CO2 and nitrogen into valuable, complex molecules. This project will integrate living photosynthetic bacteria and food-producing autotrophic bacteria into stand-alone photoelectrochemical devices tailored for the direct production of proteins and lipids from sunlight, air and water. Cyanobacteria will supply electrons via light-driven water oxidation, organic dyes will provide these electrons with sufficient energy to generate substrates that would directly feed either a culture or a consortia of food producing microorganisms in the same device. The result will be the demonstration of the first direct conversion of CO2 and N2 from air to protein- or lipid-rich food materials using solar energy, with the aim to produce a prototype that can reach 1% solar-conversion efficiency or surpass present food production processes via agriculture. Our bioengineering efforts will focus on three key innovations: (i) overcoming complex electron transfer pathway barriers at the cell-electrode interface, aided by the coupling of electrode engineering with advanced modelling of the interface; (ii) expanding the range of Solar-to-X products to two essential food groups (proteins and lipids), enabled by the formation of novel microbial consortia on redox polymer films that mitigate their conflicting microenvironment needs; and iii) device engineering that synergizes the different outputs and needs of the bio-anode and cathode whilst also facilitating easy food-product collection. The delivery of our envisioned Solar-to-Food devices will open the door to re-imagining sustainable food production for off-grid locations, kitchens in future households and spaceships. Current food industries, such as our partner Solar Foods, would be an immediate benefactor. Our envisioned solar-to-lipids production process could be a stepping stone to fuels production lines of the future. | M18: Yes | N18: Fermentation | O18: Bioprocess design | Q18: 3999732 | R18: EUR | S18: 4244915 | T18: 2025-11-01 | U18: 2025 | V18: 2029-10-31 | W18: 2029 | Y18: THE CHANCELLOR MASTERS AND SCHOLARS OF THE UNIVERSITY OF CAMBRIDGE; IMPERIAL COLLEGE OF SCIENCE TECHNOLOGY AND MEDICINE; TECHNISCHE UNIVERSITAET MUENCHEN; DANMARKS TEKNISKE UNIVERSITET; SOLAR FOODS OY | Z18: University of Cambridge; Imperial College London; Technical University of Munich; Technical University of Denmark; Solar Foods Oy | AA18: grid.5335.0; grid.7445.2; grid.6936.a; grid.5170.3; grid.679995.d | AB18: Cambridge; London; Munich; Kongens Lyngby | AC18: Westminster; Hovedstaden | AD18: United Kingdom; United Kingdom; Germany; Denmark; Finland | AE18: European Commission | AF18: EC & ERC - European Union; cOAlition S | AG18: Belgium | AH18: HORIZON.3.1 - The European Innovation Council (EIC) (Programme); HORIZON-EIC - HORIZON EIC Grants (Funding scheme); HORIZON-EIC-2024-PATHFINDERCHALLENGES-01 (Call for proposal) | AI18: Not available | AK18: https://cordis.europa.eu/project/id/101219355 | AL18: https://app.dimensions.ai/details/grant/grant.14973726 | AM18: 31 Biological Sciences; 34 Chemical Sciences; 40 Engineering; 4004 Chemical Engineering | AU18: B12 Engineering | AV18: 2 Zero Hunger; 7 Affordable and Clean Energy
A19: 2025 Dimensions F | B19: 1064 | C19: grant.14704971 | D19: =ISNUMBER(MATCH(C19, 'Airtable copy'!N:N, 0)) -> FALSE | E19: =VLOOKUP(C19,'Airtable copy'!N:N,1,FALSE) -> #REF! | F19: =ISNUMBER(MATCH(C19, 'Grants tracker download'!O:O, 0)) -> FALSE | G19: =VLOOKUP(C19,'Grants tracker download'!O:O,1,FALSE) -> #REF! | H19: 25-23-20221 | I19: Development of approaches to complex processing of microalgae biomass for the production of cosmetic and food products | J19: Development of approaches to complex processing of microalgae biomass for the production of cosmetic and food products | K19: The proposed study is devoted to the development of fundamental improved approaches to the complex processing of microalgae biomass by hydrolysis and hydrolysis-reduction to obtain a set of products that are promising for use in the cosmetic and food industries, such as protein-carbohydrate extracts with antioxidant activity and higher polyols used as sugar substitutes and in pharmaceuticals. The relevance of the research is justified by the following factors. 1. The deficit, absence of a significant amount of domestic production, and the high cost and low availability under sanctions of imported bio-raw materials for the production of cosmetic and cosmeceutical products based on microalgae biomass. 2. The significant demand for sorbitol, which is widely used in the food, cosmetics industry and in medicine, in Russia with complete import dependence. 3. Approaches using microalgae to obtain valuable products are highly relevant from an environmental point of view. It has been shown that microalgae can be cultivated using water containing organic pollutants. Thus, microalgae cultivation can be used in water purification processes with the simultaneous production of high-margin products. 4. Development of methods for synthesizing microalgae with their subsequent processing meets modern requirements for increasing the carbon neutrality of production, since microalgae actively consume carbon dioxide during their growth. The project will last for two years, and upon its completion, the following fundamental results will be obtained. 1. New promising microalgae strains have been identified, the biomass of which has a high potential for use in the cosmetics industry (antioxidant activity of aqueous hydrolysates) and the food industry (high carbohydrate content). 2. Effective approaches to hydrothermal and acid hydrolysis of microalgae biomass to obtain carbohydrates and aqueous hydrolysates, including the isolation and purification of carbohydrates, have been developed. 3. The study has been conducted of the prospects for using aqueous hydrolysates as cosmetics for external use (skin care) taking into account data on antioxidant activity. 4. Methods have been developed for preparing carbohydrate raw materials from microalgae by removing impurities that prevent deep processing into valuable substances. 5. The approach has been developed for the catalytic hydrolysis-reduction of carbohydrates from microalgae biomass to obtain higher polyols (sorbitol) used in the food industry (sweetener). The project will be carried out at the intersection of catalysis and biotechnology. An interdisciplinary approach to the work will allow obtaining results that are highly innovative. The novelty of the project can also be noted in the following: 1. In the creation of a complex technology for obtaining a group of products suitable for use in cosmetology and the food industry. 2. In the use of original highly effective solid catalysts for the formation of polyhydric alcohols. 3. In the development of an effective method for purifying microalgae biomass carbohydrates from impurities, which allows removing restrictions on the processing of such raw materials into valuable products. 4. For the first time, a method for obtaining polyhydric alcohols, such as sorbitol, from microalgae carbohydrates (glucose and starch) will be developed. 5. In a single-stage one-pot approach to the hydrolysis-reduction of the carbohydrate component of microalgae biomass. 6. For the first time, the possibility of using some collection and our own strains of microalgae of the genus Chlorella, Parachlorella, Desmodesmus, Bracteacoccus and others to create cosmetics and food products will be studied. 7. For the first time, the antioxidant activity of aqueous extracts from the biomass of the microalgae strains used in this work will be studied. | L19: The proposed study is devoted to the development of fundamental improved approaches to the complex processing of microalgae biomass by hydrolysis and hydrolysis-reduction to obtain a set of products that are promising for use in the cosmetic and food industries, such as protein-carbohydrate extracts with antioxidant activity and higher polyols used as sugar substitutes and in pharmaceuticals. The relevance of the research is justified by the following factors. 1. The deficit, absence of a significant amount of domestic production, and the high cost and low availability under sanctions of imported bio-raw materials for the production of cosmetic and cosmeceutical products based on microalgae biomass. 2. The significant demand for sorbitol, which is widely used in the food, cosmetics industry and in medicine, in Russia with complete import dependence. 3. Approaches using microalgae to obtain valuable products are highly relevant from an environmental point of view. It has been shown that microalgae can be cultivated using water containing organic pollutants. Thus, microalgae cultivation can be used in water purification processes with the simultaneous production of high-margin products. 4. Development of methods for synthesizing microalgae with their subsequent processing meets modern requirements for increasing the carbon neutrality of production, since microalgae actively consume carbon dioxide during their growth. The project will last for two years, and upon its completion, the following fundamental results will be obtained. 1. New promising microalgae strains have been identified, the biomass of which has a high potential for use in the cosmetics industry (antioxidant activity of aqueous hydrolysates) and the food industry (high carbohydrate content). 2. Effective approaches to hydrothermal and acid hydrolysis of microalgae biomass to obtain carbohydrates and aqueous hydrolysates, including the isolation and purification of carbohydrates, have been developed. 3. The study has been conducted of the prospects for using aqueous hydrolysates as cosmetics for external use (skin care) taking into account data on antioxidant activity. 4. Methods have been developed for preparing carbohydrate raw materials from microalgae by removing impurities that prevent deep processing into valuable substances. 5. The approach has been developed for the catalytic hydrolysis-reduction of carbohydrates from microalgae biomass to obtain higher polyols (sorbitol) used in the food industry (sweetener). The project will be carried out at the intersection of catalysis and biotechnology. An interdisciplinary approach to the work will allow obtaining results that are highly innovative. The novelty of the project can also be noted in the following: 1. In the creation of a complex technology for obtaining a group of products suitable for use in cosmetology and the food industry. 2. In the use of original highly effective solid catalysts for the formation of polyhydric alcohols. 3. In the development of an effective method for purifying microalgae biomass carbohydrates from impurities, which allows removing restrictions on the processing of such raw materials into valuable products. 4. For the first time, a method for obtaining polyhydric alcohols, such as sorbitol, from microalgae carbohydrates (glucose and starch) will be developed. 5. In a single-stage one-pot approach to the hydrolysis-reduction of the carbohydrate component of microalgae biomass. 6. For the first time, the possibility of using some collection and our own strains of microalgae of the genus Chlorella, Parachlorella, Desmodesmus, Bracteacoccus and others to create cosmetics and food products will be studied. 7. For the first time, the antioxidant activity of aqueous extracts from the biomass of the microalgae strains used in this work will be studied. | M19: Yes | N19: Plant-based | O19: Ingredient optimisation | P19: Microalgae; cultivation; antioxidant activity; carbohydrates; carbohydrate biomass; hydrolysis; hydrolysis-hydrogenation catalysts; sorbitol | Q19: 0 | S19: 0 | T19: 2025-01-01 | U19: 2025 | V19: 2026-12-31 | W19: 2026 | X19: Nikolay Gromov | Y19: Federal Research Center Boreskov Institute of Catalysis | Z19: Boreskov Institute of Catalysis | AA19: grid.418421.a | AB19: Novosibirsk | AD19: Russia | AE19: Russian Science Foundation | AG19: Russia | AI19: Not available | AK19: http://www.rscf.ru/en/enprjcard?rid=25-23-20221 | AL19: https://app.dimensions.ai/details/grant/grant.14704971 | AM19: 31 Biological Sciences; 3106 Industrial Biotechnology | AU19: B12 Engineering
A20: 2025 Dimensions F | B20: 1011 | C20: grant.15073719 | D20: =ISNUMBER(MATCH(C20, 'Airtable copy'!N:N, 0)) -> FALSE | E20: =VLOOKUP(C20,'Airtable copy'!N:N,1,FALSE) -> #REF! | F20: =ISNUMBER(MATCH(C20, 'Grants tracker download'!O:O, 0)) -> FALSE | G20: =VLOOKUP(C20,'Grants tracker download'!O:O,1,FALSE) -> #REF! | H20: 10.61686/YXAIY95286; FOOD.KIEM.02.004 | I20: Zilt & Zuur | J20: Zilt & Zuur | K20: The Zilt & Zuur project explores how fermentation can make toothed wrack (seaweed) more palatable and digestible. Seaweed is a sustainable protein source but is rarely consumed due to its flavour (fishy, salty) and texture. Fermentation can enhance its appeal for the hospitality and food industries. In collaboration with Michelin-starred restaurant De Kromme Watergang and Zeeuwse Zeewierhandel, HZ University of Applied Sciences is developing a fermentation protocol to create new culinary applications. This research contributes to a more sustainable food system and offers economic opportunities for Zeeland by opening new markets for fermented seaweed. | L20: The Zilt & Zuur project explores how fermentation can make toothed wrack (seaweed) more palatable and digestible. Seaweed is a sustainable protein source but is rarely consumed due to its flavour (fishy, salty) and texture. Fermentation can enhance its appeal for the hospitality and food industries. In collaboration with Michelin-starred restaurant De Kromme Watergang and Zeeuwse Zeewierhandel, HZ University of Applied Sciences is developing a fermentation protocol to create new culinary applications. This research contributes to a more sustainable food system and offers economic opportunities for Zeeland by opening new markets for fermented seaweed. | M20: Yes | N20: Plant-based | O20: End product formulation | Q20: 40000 | R20: EUR | S20: 42452 | T20: 2025-09-01 | U20: 2025 | X20: Marlies Eenennaam | Y20: HZ University of Applied Sciences | Z20: HZ University of Applied Sciences | AA20: grid.448873.4 | AB20: Flushing | AD20: Netherlands | AE20: Dutch Research Council | AF20: cOAlition S | AG20: Netherlands | AH20: KIEM GoFood KIEM GoFood 2024-2026 KIEM GoFood 2025 KIEM GoFood 2025 - Batch 1 (Funding Scheme) | AI20: Not available | AK20: https://doi.org/10.61686/YXAIY95286 | AL20: https://app.dimensions.ai/details/grant/grant.15073719 | AM20: 31 Biological Sciences; 35 Commerce, Management, Tourism and Services; 3504 Commercial Services | AU20: C17 Business and Management Studies | AV20: 2 Zero Hunger
A21: 2025 Dimensions F | B21: 987 | C21: grant.14972633 | D21: =ISNUMBER(MATCH(C21, 'Airtable copy'!N:N, 0)) -> FALSE | E21: =VLOOKUP(C21,'Airtable copy'!N:N,1,FALSE) -> #REF! | F21: =ISNUMBER(MATCH(C21, 'Grants tracker download'!O:O, 0)) -> FALSE | G21: =VLOOKUP(C21,'Grants tracker download'!O:O,1,FALSE) -> #REF! | H21: 359485 | I21: AlgFlavor, Enhancing algal biomass consumer acceptance for food markets | J21: AlgFlavor, Enhancing algal biomass consumer acceptance for food markets | K21: As society shifts away from animal-based diets driven by environmental, health and animal welfare concerns, both seaweed and microalgae (collectively referred to as algae) emerge as a promising sustainable food source. With their rich nutritional content, including protein, minerals, vitamins, fiber and omega-3 fatty acids, these low trophic marine species offer a viable solution to meet consumer demands for healthy and eco-friendly diets. Despite the potential of algae, the widespread adoption in European markets faces hurdles due to limited consumer acceptance stemming from the impact of algal biomass on taste, aroma and visual appeal in food products. AlgFlavor will tackle these concerns as it is crucial for building consumer trust and promoting the widespread use of algae in food. | L21: As society shifts away from animal-based diets driven by environmental, health and animal welfare concerns, both seaweed and microalgae (collectively referred to as algae) emerge as a promising sustainable food source. With their rich nutritional content, including protein, minerals, vitamins, fiber and omega-3 fatty acids, these low trophic marine species offer a viable solution to meet consumer demands for healthy and eco-friendly diets. Despite the potential of algae, the widespread adoption in European markets faces hurdles due to limited consumer acceptance stemming from the impact of algal biomass on taste, aroma and visual appeal in food products. AlgFlavor will tackle these concerns as it is crucial for building consumer trust and promoting the widespread use of algae in food. | M21: Yes | N21: Plant-based | O21: Consumer & market research | Q21: 2856999 | R21: NOK | S21: 259197 | T21: 2025-01-01 | U21: 2025 | V21: 2028-12-31 | W21: 2028 | X21: Runar Solstad | Y21: NOFIMA AS | Z21: Nofima | AA21: grid.22736.32 | AB21: Tromsø | AD21: Norway | AE21: The Research Council of Norway | AF21: cOAlition S | AG21: Norway | AH21: SEA-BASED-SEA-BASED (Funding scheme) | AI21: Not available | AK21: https://prosjektbanken.forskningsradet.no/en/project/FORISS/359485 | AL21: https://app.dimensions.ai/details/grant/grant.14972633 | AM21: 30 Agricultural, Veterinary and Food Sciences; 31 Biological Sciences; 3106 Industrial Biotechnology | AN21: Dietary Supplements; Nutrition | AO21: Cardiovascular | AP21: 3.3 Nutrition and chemoprevention | AU21: A06 Agriculture, Veterinary and Food Science
A22: 2025 Dimensions F | B22: 806 | C22: grant.14954840 | D22: =ISNUMBER(MATCH(C22, 'Airtable copy'!N:N, 0)) -> FALSE | E22: =VLOOKUP(C22,'Airtable copy'!N:N,1,FALSE) -> #REF! | F22: =ISNUMBER(MATCH(C22, 'Grants tracker download'!O:O, 0)) -> FALSE | G22: =VLOOKUP(C22,'Grants tracker download'!O:O,1,FALSE) -> #REF! | H22: 101180167; 272628; PRIMARY; 10.3030/101180167 | I22: New business for farmers and cooperatives in rural areas by local upcycling solutions using underutilized agricultural feedstocks | J22: New business for farmers and cooperatives in rural areas by local upcycling solutions using underutilized agricultural feedstocks | K22: PRIMARY aims to develop and pilot local solutions for the production of food, feed, bio-based materials, bioenergy, and fertilizers by valorizing agricultural biomass feedstocks, including grass, greenhouse and cotton by-products, and olive tree pruning that are currently underutilized and exist in substantial amounts in Europe. The project focuses on North-East Europe (Finland) and South-East Europe (Greece), providing business models and demonstrations in rural areas where pilot and demo plants are rare. PRIMARY works with primary producers and local actors, and pilots six process concepts: 1) separation of protein and fibre rich fractions from grass to produce food/feed and biobased materials, respectively; 2) submerged and 3) solid-state fermentation processes to upcycle the feedstocks to protein rich food and feed ingredients; 4) fibre forming technology to enable production of packaging and construction materials; 5) pelletizing process to solid biofuel for gasification to bioenergy from olive-tree pruning and cotton byproducts; 6) pyrolysis of cotton and olive byproducts to biochar for fertilizer and material applications. The solutions piloted in the project are selected based on cascading use of the feedstocks to find the highest possible value, considering the regional conditions. Sustainability of the new value chains is broadly assessed. To maximise project outcomes and impact, other partners and regions are engaged through an open innovation call to promote the ecosystem for valorizing agricultural biomass, and to show replicability of the project solutions. PRIMARY outcomes, including new processes, products and service concepts, will be communicated via various channels, including a stakeholder platform, to ensure wide exploitation of the solutions. A multi-actor approach is used in the development of processes and replicable business models, and for delivering guidance to farmers and SMEs, and advice to policymakers at national and EU level. | L22: PRIMARY aims to develop and pilot local solutions for the production of food, feed, bio-based materials, bioenergy, and fertilizers by valorizing agricultural biomass feedstocks, including grass, greenhouse and cotton by-products, and olive tree pruning that are currently underutilized and exist in substantial amounts in Europe. The project focuses on North-East Europe (Finland) and South-East Europe (Greece), providing business models and demonstrations in rural areas where pilot and demo plants are rare. PRIMARY works with primary producers and local actors, and pilots six process concepts: 1) separation of protein and fibre rich fractions from grass to produce food/feed and biobased materials, respectively; 2) submerged and 3) solid-state fermentation processes to upcycle the feedstocks to protein rich food and feed ingredients; 4) fibre forming technology to enable production of packaging and construction materials; 5) pelletizing process to solid biofuel for gasification to bioenergy from olive-tree pruning and cotton byproducts; 6) pyrolysis of cotton and olive byproducts to biochar for fertilizer and material applications. The solutions piloted in the project are selected based on cascading use of the feedstocks to find the highest possible value, considering the regional conditions. Sustainability of the new value chains is broadly assessed. To maximise project outcomes and impact, other partners and regions are engaged through an open innovation call to promote the ecosystem for valorizing agricultural biomass, and to show replicability of the project solutions. PRIMARY outcomes, including new processes, products and service concepts, will be communicated via various channels, including a stakeholder platform, to ensure wide exploitation of the solutions. A multi-actor approach is used in the development of processes and replicable business models, and for delivering guidance to farmers and SMEs, and advice to policymakers at national and EU level. | M22: Yes | N22: Fermentation | O22: Strain development / Ingredient optimisation | Q22: 4996936 | R22: EUR | S22: 5303254 | T22: 2025-05-01 | U22: 2025 | V22: 2029-04-30 | W22: 2029 | Y22: ELLINIKOS GEORGIKOS ORGANISMOS - DIMITRA; ETHNIKO KENTRO EREVNAS KAI TECHNOLOGIKIS ANAPTYXIS; FIBERWOOD OY; TEKNOLOGIAN TUTKIMUSKESKUS VTT OY; MAA- JA METSATALOUSTUOTTAJAIN KESKUSLIITTO MTK RY; AGROTIKOS SYNETAIRISMOS KARDITSAS I NEA ENOSI; LUONNONVARAKESKUS; REFRAME FOOD ASTIKI MI KERDOSKOPIKI ETAIRIA; ENERGEIAKH KOINOTHTA KARDITSAS SYNPE; MTU CIVITTA FOUNDATION; MINOA ENERGEIAKI KOINOTITA POLITON SYN.P.E; VALIO OY | Z22: VTT Technical Research Centre of Finland; Natural Resources Institute Finland; Valio Oy | AA22: grid.6324.3; grid.22642.30; grid.438888.7 | AB22: Espoo; Helsinki; Helsinki | AD22: Finland; Finland; Finland | AE22: European Commission | AF22: EC & ERC - European Union; cOAlition S | AG22: Belgium | AH22: HORIZON.2.6 - Food, Bioeconomy Natural Resources, Agriculture and Environment (Programme); HORIZON-IA - HORIZON Innovation Actions (Funding scheme); HORIZON-CL6-2024-CIRCBIO-02 (Call for proposal) | AI22: Not available | AK22: https://cordis.europa.eu/project/id/101180167 | AL22: https://app.dimensions.ai/details/grant/grant.14954840 | AM22: 31 Biological Sciences; 3106 Industrial Biotechnology; 44 Human Society; 4406 Human Geography | AU22: B12 Engineering | AV22: 2 Zero Hunger
A23: 2025 Dimensions F | B23: 738 | C23: grant.15145615 | D23: =ISNUMBER(MATCH(C23, 'Airtable copy'!N:N, 0)) -> FALSE | E23: =VLOOKUP(C23,'Airtable copy'!N:N,1,FALSE) -> #REF! | F23: =ISNUMBER(MATCH(C23, 'Grants tracker download'!O:O, 0)) -> FALSE | G23: =VLOOKUP(C23,'Grants tracker download'!O:O,1,FALSE) -> #REF! | I23: AlgFlavor - Verbeteren van de consumentenacceptatie van algen voor de voedselmarkt | J23: AlgFlavor - Improving consumer acceptance of algae for the food market | K23: AlgFlavor gaat over het gebruik van zeewier en microalgen (samen alg genoemd) als duurzamevoedselbron. Deze zijn rijk aan voedingsstoffen zoals eiwitten, mineralen en omega-3 vetzuren, enkunnen helpen aan de groeiende vraag naar gezonde, duurzame voeding. Er zijn uitdagingen omvoedsel op basis van algen beter te maken, voornamelijk vanwege hun smaak en geur.Om deze uitdagingen aan te pakken, werkt AlgFlavor aan het verbeteren van deconsumentenacceptatie van voedingsmiddelen met algen. Verschillende soorten algen hebbenverschillende smaken, variërend van bitter tot hartig. Sommige algen hebben zelfs een smaak dielijkt op zeevruchten, waardoor ze geschikt zijn voor plantaardige alternatieven voor zeevruchten.De smaak van algen kan worden beïnvloed door hoe ze worden geteeld en verwerkt. AlgFlavor zaldeze omstandigheden optimaliseren om een consistente smaak te garanderen en om algen teverwerken in verschillende voedingsproducten (oa brood, sauzen).Algen hebben veelbelovende smaak- en voedingseigenschappen, maar moeten consistenter,betaalbaarder en beter worden voor consumptie. AlgFlavor zal dit doen door sensorische evaluatiesen chemische analyses uit te voeren en diverse voedselprototypes te ontwikkelen.Het ultieme doel is om een markt te creëren voor voedingsmiddelen op basis van algen, gericht opplantaardige alternatieven voor zeevruchten, door de consumentenacceptatie te verbeteren en debehoeften van zowel producenten als consumenten te begrijpen. | L23: AlgFlavor focuses on the use of seaweed and microalgae (collectively called algae) as a sustainable food source. These are rich in nutrients such as protein, minerals, and omega-3 fatty acids and can help meet the growing demand for healthy, sustainable food. There are challenges to improving algae-based foods, primarily due to their taste and aroma. To address these challenges, AlgFlavor is working to improve consumer acceptance of algae-based foods. Different types of algae have distinct flavors, ranging from bitter to savory. Some algae even have a taste similar to seafood, making them suitable for plant-based seafood alternatives. The flavor of algae can be influenced by how it is grown and processed. AlgFlavor will optimize these conditions to ensure consistent flavor and to incorporate algae into various food products (e.g., bread, sauces). Algae has promising flavor and nutritional properties but needs to become more consistent, affordable, and better for consumption. AlgFlavor will achieve this by conducting sensory evaluations and chemical analyses and developing various food prototypes. The ultimate goal is to create a market for algae-based foods, focusing on plant-based seafood alternatives, by improving consumer acceptance and understanding the needs of both producers and consumers. | M23: Yes | N23: Plant-based | O23: Consumer & market research | P23: 75 | Q23: 0 | S23: 0 | T23: 2025-09-01 | U23: 2025 | X23: Christine Yung Hung | Y23: Ghent University | Z23: Ghent University | AA23: grid.5342.0 | AB23: Ghent | AD23: Belgium | AE23: Research Foundation - Flanders | AF23: ICRP - International Cancer Research Partnership | AG23: Belgium | AI23: Not available | AK23: https://researchportal.be/nl/project/algflavor-verbeteren-van-de-consumentenacceptatie-van-algen-voor-de-voedselmarkt | AL23: https://app.dimensions.ai/details/grant/grant.15145615 | AM23: 30 Agricultural, Veterinary and Food Sciences; 3006 Food Sciences | AN23: Complementary and Integrative Health; Dietary Supplements; Nutrition | AO23: Metabolic and endocrine | AP23: 3.3 Nutrition and chemoprevention | AR23: Public Health | AU23: A06 Agriculture, Veterinary and Food Science | AV23: 2 Zero Hunger
A24: 2025 Dimensions F | B24: 677 | C24: grant.15148228 | D24: =ISNUMBER(MATCH(C24, 'Airtable copy'!N:N, 0)) -> FALSE | E24: =VLOOKUP(C24,'Airtable copy'!N:N,1,FALSE) -> #REF! | F24: =ISNUMBER(MATCH(C24, 'Grants tracker download'!O:O, 0)) -> FALSE | G24: =VLOOKUP(C24,'Grants tracker download'!O:O,1,FALSE) -> #REF! | H24: UKRI1967 | I24: UKProNet2025 | J24: UKProNet2025 | K24: Proteins orchestrate all of life’s functions. All organisms dedicate a large proportion of their resources to evolutionarily conserved mechanisms of protein homeostasis (“proteostasis”), an umbrella term that describes the synthesis, folding, trafficking and degradation of proteins. These conserved protein quality control (PQC) processes are coordinated across biological scale (from molecules, organelles, cells, tissues, to organismal level) and are critical to enable responses to physiologic and stress-related cues. It is increasingly apparent that a deep understanding of proteostasis and how it can be leveraged is critical to tackle humanity’s major challenges: Ageing and Health. PQC declines with age, causing accumulation of toxic protein aggregates that drive normal ageing and its pathologies (e.g. neurodegeneration). Strategies to mitigate this PQC failure are urgently required. Emerging targeted protein degradation technologies provide new therapeutic horizons for disease. To fully exploit these mechanisms requires a deep understanding of PQC systems, combined with novel synthetic biology approaches that leverage proteostasis mechanisms from other species. Food security. Strategies to improve crop yields, nutritional quality, resilience to pathogens and climate change are critical for the health of the growing global population. The importance of proteostasis in plants is exemplified by the extraordinary number of genes dedicated to PQC in crop genomes compared to humans. These genes, which have evolved to deal with pathogens and environmental stresses, provide a rich opportunity to engineer plants/animals with improved resilience/yields. Barriers to progress. These key scientific areas require, and are fertile ground for, cross-disciplinary and cross-sector collaboration and innovation. The UK has excellent strengths in proteostasis research, but these are siloed into smaller communities with limited intercommunication. There is clearly a strong case for a well-integrated overarching community with a bold vision to be world leading in this crucial field of biology. To overcome these barriers, the UK Proteostasis Network (UKProNet) will address three key objectives: Objective 1. Integrate the UK Proteostasis communities to drive a holistic understanding of proteostasis across biological scales and model systems by promoting integration between research silos and sectors (academia and industry). A primary goal for UKProNet, identified via a community survey, is to enhance uptake of foundational and evolving technologies including artificial intelligence (A.I.). Objective 2. Empower the community to tackle key societal challenges by leveraging proteostasis across kingdoms of life to enhance adaptations to proteostasis challenges and organismal resilience across the lifespan. Objective 3. Strengthen the national and international profile of UK Proteostasis by enhancing our visibility on-line (through website provision, social media, newsletters, protocol and reagent database), early career researcher (ECR) support and at high-profile annual meetings. To achieve these goals, we will run community-led workshops (to disseminate key proteostasis technologies and A.I.), provide pump-priming grants, lab exchange awards and summer studentships. A dedicated, well-funded ECR committee will develop a strategy to ensure that the leaders-of-tomorrow have a central role in shaping the proteostasis landscape. Our activities will promote an inclusive environment where people from marginalised or underrepresented groups can feel empowered to lead and drive best practices in equality, diversity and inclusion. A UKProNet steering group of elected community members, plus an external advisory board (diverse in gender, career stage and lived experience) will provide ongoing monitoring and advice on strategy and evaluation. Together we will build upon the UKs expertise to develop a thriving, world-leading community of proteostasis researchers. | L24: Proteins orchestrate all of life’s functions. All organisms dedicate a large proportion of their resources to evolutionarily conserved mechanisms of protein homeostasis (“proteostasis”), an umbrella term that describes the synthesis, folding, trafficking and degradation of proteins. These conserved protein quality control (PQC) processes are coordinated across biological scale (from molecules, organelles, cells, tissues, to organismal level) and are critical to enable responses to physiologic and stress-related cues. It is increasingly apparent that a deep understanding of proteostasis and how it can be leveraged is critical to tackle humanity’s major challenges: Ageing and Health. PQC declines with age, causing accumulation of toxic protein aggregates that drive normal ageing and its pathologies (e.g. neurodegeneration). Strategies to mitigate this PQC failure are urgently required. Emerging targeted protein degradation technologies provide new therapeutic horizons for disease. To fully exploit these mechanisms requires a deep understanding of PQC systems, combined with novel synthetic biology approaches that leverage proteostasis mechanisms from other species. Food security. Strategies to improve crop yields, nutritional quality, resilience to pathogens and climate change are critical for the health of the growing global population. The importance of proteostasis in plants is exemplified by the extraordinary number of genes dedicated to PQC in crop genomes compared to humans. These genes, which have evolved to deal with pathogens and environmental stresses, provide a rich opportunity to engineer plants/animals with improved resilience/yields. Barriers to progress. These key scientific areas require, and are fertile ground for, cross-disciplinary and cross-sector collaboration and innovation. The UK has excellent strengths in proteostasis research, but these are siloed into smaller communities with limited intercommunication. There is clearly a strong case for a well-integrated overarching community with a bold vision to be world leading in this crucial field of biology. To overcome these barriers, the UK Proteostasis Network (UKProNet) will address three key objectives: Objective 1. Integrate the UK Proteostasis communities to drive a holistic understanding of proteostasis across biological scales and model systems by promoting integration between research silos and sectors (academia and industry). A primary goal for UKProNet, identified via a community survey, is to enhance uptake of foundational and evolving technologies including artificial intelligence (A.I.). Objective 2. Empower the community to tackle key societal challenges by leveraging proteostasis across kingdoms of life to enhance adaptations to proteostasis challenges and organismal resilience across the lifespan. Objective 3. Strengthen the national and international profile of UK Proteostasis by enhancing our visibility on-line (through website provision, social media, newsletters, protocol and reagent database), early career researcher (ECR) support and at high-profile annual meetings. To achieve these goals, we will run community-led workshops (to disseminate key proteostasis technologies and A.I.), provide pump-priming grants, lab exchange awards and summer studentships. A dedicated, well-funded ECR committee will develop a strategy to ensure that the leaders-of-tomorrow have a central role in shaping the proteostasis landscape. Our activities will promote an inclusive environment where people from marginalised or underrepresented groups can feel empowered to lead and drive best practices in equality, diversity and inclusion. A UKProNet steering group of elected community members, plus an external advisory board (diverse in gender, career stage and lived experience) will provide ongoing monitoring and advice on strategy and evaluation. Together we will build upon the UKs expertise to develop a thriving, world-leading community of proteostasis researchers. | M24: Yes | N24: Cross-cutting | O24: Other (Network/Coordination) | Q24: 585382 | R24: GBP | S24: 740294 | T24: 2025-03-30 | U24: 2025 | V24: 2028-03-30 | W24: 2028 | X24: Della David, Colin Adrain, Bernadette Carroll, Simon Cook, Ari Sadanandom | Y24: Babraham Institute | Z24: Babraham Institute | AA24: grid.418195.0 | AB24: Cambridge | AD24: United Kingdom | AE24: Biotechnology and Biological Sciences Research Council | AF24: ICRP - International Cancer Research Partnership; cOAlition S; UKRI - UK Research and Innovation | AG24: United Kingdom | AH24: Research and Innovation (Project Category) | AI24: Not available | AK24: https://gtr.ukri.org/projects?ref=UKRI1967 | AL24: https://app.dimensions.ai/details/grant/grant.15148228 | AM24: 31 Biological Sciences; 3101 Biochemistry and Cell Biology | AN24: Health Disparities and Racial or Ethnic Minority Health Research | AO24: Generic health relevance | AP24: 1.5 Resources and infrastructure (underpinning) | AQ24: Biomedical | AR24: Basic Science | AU24: A06 Agriculture, Veterinary and Food Science
A25: 2025 Dimensions F | B25: 660 | C25: grant.15145414 | D25: =ISNUMBER(MATCH(C25, 'Airtable copy'!N:N, 0)) -> FALSE | E25: =VLOOKUP(C25,'Airtable copy'!N:N,1,FALSE) -> #REF! | F25: =ISNUMBER(MATCH(C25, 'Grants tracker download'!O:O, 0)) -> FALSE | G25: =VLOOKUP(C25,'Grants tracker download'!O:O,1,FALSE) -> #REF! | I25: VegVit | J25: VegVit | K25: "VegVit" is een interdisciplinair project dat gericht is op de ontwikkeling van een assortiment veganistische zuivel- en vleesalternatieven met een verbeterd nutritioneel profiel (vitamine B12, maar ook proteïnekwaliteit/breder aminozuurprofiel). Het eerste concrete doel van het project is dat voedselveilige starterculturen geïdentificeerd en geselecteerd kunnen worden die onder geschikte omstandigheden hoge niveaus van vitamine B12 vormen. Het tweede concrete doel is dat vitamine B12-verrijkte ingrediënten geproduceerd kunnen worden door eerst grondstoffen zoals geëxtrudeerde plantaardige eiwitten of eiwitsuspensies te fermenteren. Deze verrijkte ingrediënten kunnen vervolgens in een tweede stap worden omgezet in hoogwaardige analogen met verhoogde B12-gehaltes en een beter proteïnekwaliteit. Het derde concrete doel is dat vitamine B12 in-situ gevormd wordt via een co-fermentatieproces, door tijdens het productieproces van salami- yoghurt- of smeerkaasanalogen geschikte starterculturen toe te voegen. Afhankelijk van de aard en samenstelling van de matrix (geselecteerde ingrediënten, homogene of heterogene matrix structuur, pH, wateractiviteit) kan de ene aanpak voordeliger zijn dan de andere. Hierbij ligt de focus op het creëren van producten die zowel in kwaliteit als voedingswaarde voldoen aan de verwachtingen van de consument. | L25: "VegVit" is an interdisciplinary project aimed at developing a range of vegan dairy and meat alternatives with an improved nutritional profile (vitamin B12, as well as protein quality/broader amino acid profile). The first concrete goal of the project is to identify and select food-safe starter cultures that produce high levels of vitamin B12 under suitable conditions. The second concrete goal is to produce vitamin B12-enriched ingredients by first fermenting raw materials such as extruded vegetable proteins or protein suspensions. These enriched ingredients can then be converted in a second step into high-quality analogues with increased B12 levels and improved protein quality. The third concrete goal is to produce vitamin B12 in situ via a co-fermentation process, by adding suitable starter cultures during the production process of salami, yogurt, or cheese spread analogues. Depending on the nature and composition of the matrix (selected ingredients, homogeneous or heterogeneous matrix structure, pH, water activity), one approach may be more advantageous than another. The focus here is on creating products that meet consumer expectations in both quality and nutritional value. | M25: Yes | N25: Plant-based | O25: Ingredient optimisation / End product formulation | P25: fermentation; vitamin B12; vegan alternatives | Q25: 0 | S25: 0 | T25: 2025-09-01 | U25: 2025 | X25: Myriam Loeffler | Y25: KU Leuven | Z25: KU Leuven | AA25: grid.5596.f | AB25: Leuven | AD25: Belgium | AE25: Flanders Innovation and Entrepreneurship | AG25: Belgium | AI25: Not available | AK25: https://researchportal.be/nl/project/vegvit | AL25: https://app.dimensions.ai/details/grant/grant.15145414 | AM25: 30 Agricultural, Veterinary and Food Sciences; 3006 Food Sciences | AN25: Dietary Supplements; Nutrition | AP25: 3.3 Nutrition and chemoprevention | AU25: A06 Agriculture, Veterinary and Food Science
A26: 2025 Dimensions F | B26: 630 | C26: grant.15145355 | D26: =ISNUMBER(MATCH(C26, 'Airtable copy'!N:N, 0)) -> FALSE | E26: =VLOOKUP(C26,'Airtable copy'!N:N,1,FALSE) -> #REF! | F26: =ISNUMBER(MATCH(C26, 'Grants tracker download'!O:O, 0)) -> FALSE | G26: =VLOOKUP(C26,'Grants tracker download'!O:O,1,FALSE) -> #REF! | I26: Een systeembiologie benadering om EPS-productie door melkzuurbacteriën te optimaliseren voor voedseltoepassingen | J26: A systems biology approach to optimize EPS production by lactic acid bacteria for food applications | K26: In-situ heteropolysaccharide (HePS)-producerende melkzuurbacteriën (LAB), zoals Lactobacillus plantarum, hebben de aandacht van de voedselindustrie getrokken, aangezien HePS structurerende, viscositeit verhogende en emulgerende eigenschappen hebben. Bepaalde stressfactoren kunnen echter, afhankelijk van de gebruikte stam, de HePS-vorming bevorderen of verminderen, wat mogelijk commerciële toepassingen beperkt. Dit project heeft als doel om beter te begrijpen waarom de biosynthese van HePS binnen dezelfde LAB-soort anders reageert op verschillende koolstofbronnen, evenals op temperatuur en zout (stress), en welke combinatie de in-situ HePS-productie het beste stimuleert (gekwantificeerd door middel van HPLC). Dit zal worden onderzocht door groeitesten (e.g. high-throughput fenotypering) te combineren met verschillende omics-technieken, wat zal leiden tot de identificatie van HePS-geassocieerde genen/eiwitten. De resultaten zullen worden gevalideerd in een (plantaardige) yoghurt(analoog), waarbij niet alleen de HePS-vorming wordt geëvalueerd, maar ook de verzuringskinetiek en de structuurvorming, die samen de textuureigenschappen beïnvloeden. | L26: In situ heteropolysaccharide (HePS)-producing lactic acid bacteria (LAB), such as Lactobacillus plantarum, have attracted the attention of the food industry, as HePS possesses structuring, viscosity-enhancing, and emulsifying properties. However, certain stress factors can either promote or reduce HePS formation, depending on the strain used, potentially limiting commercial applications. This project aims to better understand why HePS biosynthesis within the same LAB species responds differently to different carbon sources, as well as to temperature and salt (stress), and which combination best stimulates in situ HePS production (quantified by HPLC). This will be investigated by combining growth assays (e.g., high-throughput phenotyping) with various omics techniques, leading to the identification of HePS-associated genes/proteins. The results will be validated in a (plant-based) yoghurt (analogue), evaluating not only HePS formation but also acidification kinetics and structure formation, which together influence texture properties. | M26: Yes | N26: Fermentation | O26: Ingredient optimisation | P26: food application; heteropolysaccharides (heps); stimulation of in-situ heps-formation; lactobacillus plantarum; omics technologies | Q26: 0 | S26: 0 | T26: 2025-10-01 | U26: 2025 | X26: Myriam Loeffler, Sam Crauwels, Florian Weiland | Y26: KU Leuven | Z26: KU Leuven | AA26: grid.5596.f | AB26: Leuven | AD26: Belgium | AE26: Flemish Government | AG26: Belgium | AI26: Not available | AK26: https://researchportal.be/nl/project/een-systeembiologie-benadering-om-eps-productie-door-melkzuurbacterien-te-optimaliseren | AL26: https://app.dimensions.ai/details/grant/grant.15145355 | AM26: 31 Biological Sciences; 3106 Industrial Biotechnology | AU26: B12 Engineering
A27: 2025 Dimensions F | B27: 570 | C27: grant.14934327 | D27: =ISNUMBER(MATCH(C27, 'Airtable copy'!N:N, 0)) -> FALSE | E27: =VLOOKUP(C27,'Airtable copy'!N:N,1,FALSE) -> #REF! | F27: =ISNUMBER(MATCH(C27, 'Grants tracker download'!O:O, 0)) -> FALSE | G27: =VLOOKUP(C27,'Grants tracker download'!O:O,1,FALSE) -> #REF! | H27: UTF 753.03.25 | I27: UpGrain Presswasser-Aufbereitung | J27: UpGrain press water treatment | K27: Die Firma UpGrain AG hat zusammen mit der Brauerei Locher ein Verfahren entwickelt, bei dem aus dem Nebenstrom des Biertrebers verschiedene Produkte gewonnen werden. Die so gewonnenen Proteine weisen auch gegenüber pflanzlichen Proteinen eine geringere Treibhausgasbelastung auf, weil die Belastung aus der Primärproduktion entfällt. 2023 wurde die erste Anlage bei der Brauerei Locher in Betrieb genommen. Einzelne Produkte aus den zurückgewonnenen Gerstenproteine und -fasern sind bereits im Handel erhältlich. UpGrain verkauft die Anlage und Technologie für das Biertreber-Recycling, entwickelt und vertreibt aber auch die Produkte aus den zurückgewonnenen Bestandteilen. Damit der Prozess möglichst nachhaltig ist, erfolgt die Trocknung des Trebers mechanisch. Dabei fallen grosse Mengen an Presswasser an – allein bei der Brauerei Locher 35'000 l /Tag. Dessen CSB (Chemischer Sauerstoff-Bedarf) -Wert als Mass für die organische Belastung ist zu hoch für die direkte Einleitung in die Kanalisation oder um in einer Biogasanlage vergärt zu werden. Deshalb kann die Anlage für das Biertreber Upcycling zurzeit nur in Teillast betrieben werden. Die Presswasseraufbereitung ist damit ein Knackpunkt im ganzen Prozess, gleichzeitig aber ein weiterer Nebenstrom, dessen Inhaltsstoffe in einem nächsten Schritt verwertet werden könnten In diesem Projekt soll ein Verfahren zur Abtrennung der Feststoffe aus dem Presswasser entwickelt werden. In Vorversuchen hat sich die Kombination aus Sedimentation (z.B. Zentrifugation) mit einer anschliessenden Membranfiltration als erfolgversprechend gezeigt. Neben der geeigneten Kombination von Trennoperationen müssen auch die optimalen Prozessparameter gefunden werden, um einen stabilen und ökonomischen Trennprozess zu gewährleisten. Mit der Gruppe «Lebensmittelprozesstechnologie und Innovation» der Berner Fachhochschule wird ein in diesem Bereich erfahrener Partner aus der Forschung beigezogen. | L27: UpGrain AG, together with the Locher Brewery, has developed a process in which various products are extracted from the sidestream of spent grains. The proteins obtained in this way also have a lower greenhouse gas impact than plant proteins because the impact from primary production is eliminated. The first plant at the Locher Brewery went into operation in 2023. Individual products made from the recovered barley proteins and fibers are already commercially available. UpGrain sells the plant and technology for spent grain recycling, but also develops and distributes the products made from the recovered components. To ensure the process is as sustainable as possible, the spent grain is dried mechanically. This process produces large quantities of press water – 35,000 liters per day at the Locher Brewery alone. Its COD (Chemical Oxygen Demand) value, a measure of organic pollution, is too high for direct discharge into the sewer system or for fermentation in a biogas plant. For this reason, the spent grain upcycling plant can currently only operate at partial capacity. Press water treatment is therefore a crucial point in the entire process, but at the same time it represents another side stream whose constituents could be utilized in a subsequent step. This project aims to develop a process for separating the solids from the press water. Preliminary tests have shown that a combination of sedimentation (e.g., centrifugation) followed by membrane filtration is promising. In addition to finding the right combination of separation operations, optimal process parameters must also be found to ensure a stable and economical separation process. The "Food Process Technology and Innovation" group at the Bern University of Applied Sciences is a research partner with experience in this field. | M27: Yes | N27: Plant-based | O27: Ingredient optimisation | Q27: 149999 | R27: CHF | S27: 168399 | T27: 2025-02-27 | U27: 2025 | V27: 2025-09-30 | W27: 2025 | X27: Vincent Vida, Aurèle Meyer, Christoph Denkel | Y27: Berner Fachhochschule Lebensmittelprozesstechnologie | Z27: Bern University of Applied Sciences | AA27: grid.424060.4 | AB27: Burgdorf | AD27: Switzerland | AE27: Federal Office for the Environment | AG27: Switzerland | AI27: Not available | AK27: https://www.aramis.admin.ch/Grunddaten/?ProjectID=57661&Sprache=en-US | AL27: https://app.dimensions.ai/details/grant/grant.14934327 | AM27: 40 Engineering; 4004 Chemical Engineering; 4011 Environmental Engineering | AU27: B12 Engineering
A28: 2025 Dimensions F | B28: 396 | C28: grant.15162599 | D28: =ISNUMBER(MATCH(C28, 'Airtable copy'!N:N, 0)) -> FALSE | E28: =VLOOKUP(C28,'Airtable copy'!N:N,1,FALSE) -> #REF! | F28: =ISNUMBER(MATCH(C28, 'Grants tracker download'!O:O, 0)) -> FALSE | G28: =VLOOKUP(C28,'Grants tracker download'!O:O,1,FALSE) -> #REF! | H28: PCI2025-167076-2 | I28: RESOURCE RECOVERY FROM WASTEWATER BASED ON PHOTO-BIO-ELECTROCHEMICAL AND MEMBRANE PROCESSES WITH MINIMAL CHEMICAL ADDITION TO OBTAIN ADDED VALUE GOODS | J28: RESOURCE RECOVERY FROM WASTEWATER BASED ON PHOTO-BIO-ELECTROCHEMICAL AND MEMBRANE PROCESSES WITH MINIMAL CHEMICAL ADDITION TO OBTAIN ADDED VALUE GOODS | K28: EL PROYECTO REWADD TIENE COMO OBJETIVO DESARROLLAR PROCESOS PARA RECUPERAR, CONCENTRAR Y RECICLAR NUTRIENTES, ESPECIALMENTE NITROGENO Y FOSFORO, DE LAS CORRIENTES DE AGUAS RESIDUALES, A LA VEZ QUE SE ABORDA LA ELIMINACION DE CONTAMINANTES DE PEOCUPACION EMERGENTE. EL OBJETIVO GLOBAL DEL PROYECTO ES CAMBIAR LA CONCEPCION TRADICIONAL DE LAS PLANTAS DE TRATAMIENTO DE AGUAS RESIDUALES COMO INSTALACIONES DE GESTION DE RESIDUOS POR UN NUEVO PARADIGMA EN EL QUE LAS AGUAS RESIDUALES SE CONSIDEREN UNA FUENTE DE RECURSOS Y LAS PLANTAS DE TRATAMIENTO SE CONVIERTAN EN FABRICAS PARA PRODUCIR BIENES DE VALOR AÑADIDO Y GARANTIZAR LA SEGURIDAD HIDRICA PARA TODOS. EN REWADD SE EXPLORA LA PRODUCCION DE PRODUCTOS DE ALTO VALOR AÑADIDO A PARTIR DE CUATRO FUENTES DE AGUA: EL EFLUENTE QUE SALE DEL CLARIFICADOR PRIMARIO DE LAS PLANTAS DE TRATAMIENTO DE AGUAS RESIDUALES, EL EFLUENTE QUE SALE DEL CLARIFICADOR SECUNDARIO, LAS FRACCIONES LIQUIDAS RESULTANTES DE LOS BIORREACTORES ANAEROBICOS Y LAS AGUAS RESIDUALES GENERADAS EN LA INDUSTRIA ALIMENTARIA. LOS ESQUEMAS DE PROCESO INVESTIGADOS EN REWADD SE BASAN EN PROCESOS DE ELECTROMEMBRANA Y PROCESOS DE MEMBRANA POR GRADIENTE DE PRESION, Y EN SISTEMAS HIBRIDOS BIO Y FOTOELECTROQUIMICOS. ESTOS PROCESOS, COMBINADOS DE MANERA EFICIENTE, DAN LUGAR A SINERGIAS ENTRE SUS RESPECTIVAS CORRIENTES DE SALIDA, QUE PUEDEN UTILIZARSE COMO MATERIAS PRIMAS EN OTRAS UNIDADES DE PROCESO. LOS PRODUCTOS DE VALOR AÑADIDO OBTENIDOS A PARTIR DE LOS DIFERENTES ESQUEMAS DE PROCESO INCLUYEN FERTILIZANTES N-P, PRODUCTOS PROTEICOS UNICELULARES, SOLUCIONES ACIDAS Y ALCALINAS, Y AGUA LIMPIA PARA SU REUTILIZACION. A MODO DE EJEMPLO, LOS FLUJOS RICOS EN ALCALIS Y N-P GENERADOS POR LA ELECTRODIALISIS DE MEMBRANA BIPOLAR SE ALIMENTARAN A SISTEMAS DE CRISTALIZACION PARA LA PRODUCCION DE FERTILIZANTES, MIENTRAS QUE LAS SOLUCIONES ACIDAS SE PUEDEN UTILIZAR EN LA LIMPIEZA DE MEMBRANAS DE OSMOSIS INVERSA. A DIFERENCIA DE LOS METODOS MAS AVANZADOS PARA LA ELIMINACION DE NUTRIENTES, ESTAS TECNOLOGIAS PERMITEN AHORRAR EN LA ADICION DE PRODUCTOS QUIMICOS E IMPLICAN UNA REDUCCION DEL VOLUMEN DE LODOS GENERADOS EN LAS PLANTAS DE TRATAMIENTO DE AGUAS RESIDUALES. LAS TECNOLOGIAS PROPUESTAS FUNCIONAN A TEMPERATURA AMBIENTE, SON MODULARES Y FACILMENTE ESCALABLES, Y PUEDEN ALIMENTARSE FACILMENTE MEDIANTE UNA RED ELECTRIFICADA O FUENTES DE ENERGIA RENOVABLES. EL PROYECTO INCLUYE ACTIVIDADES PARA PROBAR LAS UNIDADES DE FUNCIONAMIENTO A ESCALA DE LABORATORIO, REEVALUAR Y OPTIMIZAR SU ACOPLAMIENTO EN DIFERENTES ESQUEMAS DE PROCESO, Y REALIZAR ESTUDIOS DE EVALUACION DEL CICLO DE VIDA, TECNOECONOMICOS Y DE ESCALABILIDAD PARA GARANTIZAR LA FUTURA IMPLEMENTACION DEL PROCESO A MAYOR ESCALA. ADEMAS, SE LLEVARAN A CABO PRUEBAS PILOTO CON EFLUENTES GENERADOS EN LA INDUSTRIA ALIMENTARIA Y CON AGUAS RESIDUALES URBANAS. | M28: Yes | N28: Fermentation | O28: Bioprocess design | Q28: 257500 | R28: EUR | S28: 273286 | T28: 2025-01-01 | U28: 2025 | Y28: UNIVERSITAT POLITÈCNICA DE VALÈNCIA | Z28: Universitat Politècnica de València | AA28: grid.157927.f | AB28: Valencia | AD28: Spain | AE28: State Research Agency | AG28: Spain | AH28: International Collaboration Projects (Call) | AI28: Not available | AK28: https://www.aei.gob.es/ayudas-concedidas/buscador-ayudas-concedidas | AL28: https://app.dimensions.ai/details/grant/grant.15162599 | AM28: 40 Engineering; 4004 Chemical Engineering; 4011 Environmental Engineering | AU28: B12 Engineering | AV28: 13 Climate Action; 6 Clean Water and Sanitation
A29: 2025 Dimensions PB | B29: 791 | C29: grant.14917108 | D29: =ISNUMBER(MATCH(C29, 'Airtable copy'!N:N, 0)) -> FALSE | E29: =VLOOKUP(C29,'Airtable copy'!N:N,1,FALSE) -> #REF! | F29: =ISNUMBER(MATCH(C29, 'Grants tracker download'!O:O, 0)) -> FALSE | G29: =VLOOKUP(C29,'Grants tracker download'!O:O,1,FALSE) -> #REF! | H29: 101182843 | I29: Scientific Exchange to assess QUality and Risks of FOODs obtained by novel processing and PackagingTechnologies | J29: Scientific Exchange to assess QUality and Risks of FOODs obtained by novel processing and PackagingTechnologies | K29: The goal of SEQUR FOOD is to build an international scientific network including researchers from EU and South America that will work on the development of novel food processing technologies, (i.e. UV treatment, cold plasma processing, nanoemulsification, freeze concentration and drying) and/or active bioactive packaging (i.e. bacterial cellulose, antibacterial paper, etc.) to obtain safe products for the EU market with higher shelf-life and high nutritional and functional properties. This includes optimization of the novel food processing technologies, nutritional and risk assessment of these technologies and obtained products as novel foods within EFSA’s framework, and documenting their health claims, if relevant. To achieve this objective, a consortium of 5 universities from EU (Greece, Poland, Romania, and Spain) with expertise in all the aspects of EU risk assessment, 1 plant-based products processing company based in Poland together with 1 university and 1 research institute from South America (Colombia) with extended expertise in novel food processing techniques will work on a variety of case studies spread across several novel food processing technologies and products relevant for Colombia: fruit (passionfruit, uchuva (Physalis peruviana L.), blueberries); cold brewed coffee; oat milk (including oat grains and nuts needed for its production); and high oleic palm oil as compared to olive oil. These case studies will be a proof of concept for the holistic assessment of each technology-foodstuff pair and will constitute the basis for further research, but also for food processors, the principal stakeholders of the project. The activities proposed in SEQUR FOOD are innovative in many aspects. The most important innovation is the holistic approach of new food product development in terms of the complete physico-chemical, microbiological, nutritional and functional properties, but also sensory evaluation and multicultural consumer acceptance. | L29: The goal of SEQUR FOOD is to build an international scientific network including researchers from EU and South America that will work on the development of novel food processing technologies, (i.e. UV treatment, cold plasma processing, nanoemulsification, freeze concentration and drying) and/or active bioactive packaging (i.e. bacterial cellulose, antibacterial paper, etc.) to obtain safe products for the EU market with higher shelf-life and high nutritional and functional properties. This includes optimization of the novel food processing technologies, nutritional and risk assessment of these technologies and obtained products as novel foods within EFSA’s framework, and documenting their health claims, if relevant. To achieve this objective, a consortium of 5 universities from EU (Greece, Poland, Romania, and Spain) with expertise in all the aspects of EU risk assessment, 1 plant-based products processing company based in Poland together with 1 university and 1 research institute from South America (Colombia) with extended expertise in novel food processing techniques will work on a variety of case studies spread across several novel food processing technologies and products relevant for Colombia: fruit (passionfruit, uchuva (Physalis peruviana L.), blueberries); cold brewed coffee; oat milk (including oat grains and nuts needed for its production); and high oleic palm oil as compared to olive oil. These case studies will be a proof of concept for the holistic assessment of each technology-foodstuff pair and will constitute the basis for further research, but also for food processors, the principal stakeholders of the project. The activities proposed in SEQUR FOOD are innovative in many aspects. The most important innovation is the holistic approach of new food product development in terms of the complete physico-chemical, microbiological, nutritional and functional properties, but also sensory evaluation and multicultural consumer acceptance. | M29: Yes | N29: Plant-based | O29: Food safety & quality | P29: novel foods; bioactive food packaging; shelf life; risk assessment; functional foods | Q29: 1656000 | R29: EUR | S29: 1757503 | T29: 2025-01-01 | U29: 2025 | V29: 2028-12-31 | W29: 2028 | Y29: UNIVERSITATEA DE STIINTE AGRICOLE SI MEDICINA VETERINARA CLUJ NAPOCA; PANEPISTIMIO KRITIS; SZKOLA GLOWNA GOSPODARSTWA WIEJSKIEGO; UNIVERSIDAD DE SEVILLA; UNIVERSIDAD POLITECNICA DE CARTAGENA; WITPOL SPOLKA Z OGRANICZONA ODPOWIEDZIALNOSCIA; UNIVERSIDAD DE LA SABANA; Corporación Vidarium, Centro de Investigación en Nutrición Salud y Bienestar; AGENCIA ESTATAL CONSEJO SUPERIOR DE INVESTIGACIONES CIENTIFICAS | Z29: University of Agricultural Sciences and Veterinary Medicine of Cluj-Napoca; University of Crete; Warsaw University of Life Sciences; University of Seville; Polytechnic University of Cartagena; University of La Sabana; Spanish National Research Council | AA29: grid.413013.4; grid.8127.c; grid.13276.31; grid.9224.d; grid.218430.c; grid.412166.6; grid.4711.3 | AB29: Cluj-Napoca; Rethymno; Warsaw; Seville; Cartagena; Chía; Madrid | AC29: Andalucía | AD29: Romania; Greece; Poland; Spain; Spain; Colombia; Spain | AE29: European Commission | AF29: EC & ERC - European Union; cOAlition S | AG29: Belgium | AH29: Horizon Europe (HORIZON) (Programme) | AI29: Not available | AK29: https://ec.europa.eu/info/funding-tenders/opportunities/portal/screen/opportunities/projects-details/43108390/101182843/HORIZON | AL29: https://app.dimensions.ai/details/grant/grant.14917108 | AM29: 30 Agricultural, Veterinary and Food Sciences; 3006 Food Sciences | AN29: Nutrition | AO29: Metabolic and endocrine | AP29: 3.3 Nutrition and chemoprevention | AU29: A06 Agriculture, Veterinary and Food Science | AV29: 2 Zero Hunger
A30: 2025 Dimensions gen | B30: 1303 | C30: grant.14972658 | D30: =ISNUMBER(MATCH(C30, 'Airtable copy'!N:N, 0)) -> FALSE | E30: =VLOOKUP(C30,'Airtable copy'!N:N,1,FALSE) -> #REF! | F30: =ISNUMBER(MATCH(C30, 'Grants tracker download'!O:O, 0)) -> FALSE | G30: =VLOOKUP(C30,'Grants tracker download'!O:O,1,FALSE) -> #REF! | H30: 359541 | I30: Unlocking Potential of Seaweeds and Halophytes through Biorefinery for Enhanced Resilience in Aquaculture Agri-Food and Chemical Industries | J30: Unlocking Potential of Seaweeds and Halophytes through Biorefinery for Enhanced Resilience in Aquaculture Agri-Food and Chemical Industries | K30: The ReSEAlience project is rethinking how we use marine plants like seaweed and Salicornia, a salt-tolerant plant, to create a more sustainable future. By developing a smart, eco-friendly “biorefinery,” the project turns these plants into useful products—like biofuels, animal feed, and even textiles—while helping to clean our oceans. One of the project’s key ideas is using these plants in Integrated Multi-Trophic Aquaculture (IMTA) systems. This means growing fish, shellfish, and plants together in a way that helps reduce pollution, especially excess nutrients in the water. At the heart of the process is a green extraction method called HALOREFINE, which safely pulls out valuable compounds from the plants without using harmful chemicals. Remaining fractions after extraction of main and valuable component is turned into other materials—like cellulose for textiles, sugars for energy, and proteins for feed—ensuring nothing is wasted. In an exciting twist, co-streams after plant processing is even being turned into sustainable fabrics. Special methods are used to extract fibers from both Salicornia and seaweed, offering an eco-friendly alternative to cotton and synthetic materials. With this zero-waste approach, ReSEAlience is showing how sea plants can power a cleaner, more resilient future across farming, fashion, and fuel. | L30: The ReSEAlience project is rethinking how we use marine plants like seaweed and Salicornia, a salt-tolerant plant, to create a more sustainable future. By developing a smart, eco-friendly “biorefinery,” the project turns these plants into useful products—like biofuels, animal feed, and even textiles—while helping to clean our oceans. One of the project’s key ideas is using these plants in Integrated Multi-Trophic Aquaculture (IMTA) systems. This means growing fish, shellfish, and plants together in a way that helps reduce pollution, especially excess nutrients in the water. At the heart of the process is a green extraction method called HALOREFINE, which safely pulls out valuable compounds from the plants without using harmful chemicals. Remaining fractions after extraction of main and valuable component is turned into other materials—like cellulose for textiles, sugars for energy, and proteins for feed—ensuring nothing is wasted. In an exciting twist, co-streams after plant processing is even being turned into sustainable fabrics. Special methods are used to extract fibers from both Salicornia and seaweed, offering an eco-friendly alternative to cotton and synthetic materials. With this zero-waste approach, ReSEAlience is showing how sea plants can power a cleaner, more resilient future across farming, fashion, and fuel. | M30: Yes | N30: Plant-based | O30: Ingredient optimisation | Q30: 2775999 | R30: NOK | S30: 251849 | T30: 2025-01-01 | U30: 2025 | V30: 2028-12-31 | W30: 2028 | X30: Rasa Slizyte | Y30: SINTEF OCEAN AS | Z30: SINTEF Ocean AS | AA30: grid.410353.0 | AB30: Trondheim | AD30: Norway | AE30: The Research Council of Norway | AF30: cOAlition S | AG30: Norway | AH30: SEA-BASED-SEA-BASED (Funding scheme) | AI30: Not available | AK30: https://prosjektbanken.forskningsradet.no/en/project/FORISS/359541 | AL30: https://app.dimensions.ai/details/grant/grant.14972658 | AM30: 30 Agricultural, Veterinary and Food Sciences; 31 Biological Sciences; 41 Environmental Sciences; 4104 Environmental Management | AU30: D32 Art and Design: History, Practice and Theory | AV30: 12 Responsible Consumption and Production
A31: 2025 Dimensions gen | B31: 1302 | C31: grant.15195759 | D31: =ISNUMBER(MATCH(C31, 'Airtable copy'!N:N, 0)) -> FALSE | E31: =VLOOKUP(C31,'Airtable copy'!N:N,1,FALSE) -> #REF! | F31: =ISNUMBER(MATCH(C31, 'Grants tracker download'!O:O, 0)) -> FALSE | G31: =VLOOKUP(C31,'Grants tracker download'!O:O,1,FALSE) -> #REF! | H31: NWA.1766.24.021 | I31: REAP2SOW: Resilient and Efficient Agricultural Proteins to Sustain Our World | J31: REAP2SOW: Resilient and Efficient Agricultural Proteins to Sustain Our World | K31: REAP2SOW aims to develop sustainable, climate-resilient food systems by promoting novel plant-based protein crops like quinoa, white lupin, and aardaker. These crops enhance biodiversity, improve soil health, and support the protein transition away from animal-based sources. The project integrates research on breeding, soil ecosystem functions, cultivation practices, consumer behavior, health impacts, and supply chains. Through its interlinked work packages, REAP2SOW focuses on genetic improvement, nutrient use efficiency, food safety, consumer acceptance, and historical insights. It emphasizes outreach to policymakers, farmers, and the public, fostering a resilient, sustainable food system for the Netherlands. | L31: REAP2SOW aims to develop sustainable, climate-resilient food systems by promoting novel plant-based protein crops like quinoa, white lupin, and aardaker. These crops enhance biodiversity, improve soil health, and support the protein transition away from animal-based sources. The project integrates research on breeding, soil ecosystem functions, cultivation practices, consumer behavior, health impacts, and supply chains. Through its interlinked work packages, REAP2SOW focuses on genetic improvement, nutrient use efficiency, food safety, consumer acceptance, and historical insights. It emphasizes outreach to policymakers, farmers, and the public, fostering a resilient, sustainable food system for the Netherlands. | M31: Yes | N31: Plant-based | O31: Crop development | Q31: 6776354 | R31: EUR | S31: 7191779 | T31: 2025-01-01 | U31: 2025 | X31: Wouter Kohlen, Jan Willem Erisman, Yvonne Westphal, Jessica Kiefte-de Jong, Cheng Liu, Arnout Fischer, Petra Rozema-Hoekerd, Kaisa Kajala, Peter Bourke, Harry Wichers, Viola Willemsen, Andries Temme, Casper Quist, Ellis Hoffland, Harm Zwarts, Julian Helfenstein, Martijn Zanten, José Mogollón, Patrik Henriksson, Peter Bodegom, Klaas Bouwmeester, Thekla Bismarck, Emilia Hannula, Jonne Rodenburg, Anneke Horstman, Joran Lammers, Robert Loo, Steven Driever, Funda Yildirim, Bob Douma, Sylvia Kalli | Y31: Wageningen University & Research; Universiteit Leiden; Stichting Wageningen Research; Universiteit Utrecht; Rijksuniversiteit Groningen; Jan IngenHousz Institute; Universiteit Twente | Z31: Wageningen University & Research; Leiden University; Utrecht University; University of Groningen; University of Twente | AA31: grid.4818.5; grid.5132.5; grid.5477.1; grid.4830.f; grid.6214.1 | AB31: Wageningen; Leiden; Utrecht; Groningen; Enschede | AC31: Utrecht; Groningen; Overijssel | AD31: Netherlands; Netherlands; Netherlands; Netherlands; Netherlands | AE31: Dutch Research Council | AF31: cOAlition S | AG31: Netherlands | AH31: NWA L1 - Research on Routes by Consortia 2024 - NWA-ORC 2024 (Funding Scheme) | AI31: Not available | AL31: https://app.dimensions.ai/details/grant/grant.15195759 | AM31: 30 Agricultural, Veterinary and Food Sciences; 3006 Food Sciences | AO31: Generic health relevance | AU31: A06 Agriculture, Veterinary and Food Science | AV31: 11 Sustainable Cities and Communities; 12 Responsible Consumption and Production; 2 Zero Hunger
A32: 2025 Dimensions gen | B32: 1216 | C32: grant.14912380 | D32: =ISNUMBER(MATCH(C32, 'Airtable copy'!N:N, 0)) -> FALSE | E32: =VLOOKUP(C32,'Airtable copy'!N:N,1,FALSE) -> #REF! | F32: =ISNUMBER(MATCH(C32, 'Grants tracker download'!O:O, 0)) -> FALSE | G32: =VLOOKUP(C32,'Grants tracker download'!O:O,1,FALSE) -> #REF! | H32: 10.61686/EBLWP68612; NWA.1418.24.024 | I32: Plant Power: Leveraging Consumer Insights and Food Environments for Long-Term Dietary Change | J32: Plant Power: Leveraging Consumer Insights and Food Environments for Long-Term Dietary Change | K32: A shift toward more plant-based proteins is essential for the environment, public health, and animal welfare. In the Netherlands, this transition is slow, and the consumption of animal proteins remains high (61%). This project explores how long-term behavior change toward plant-based diets can be promoted and how a more sustainable food environment can be supported. | L32: A shift toward more plant-based proteins is essential for the environment, public health, and animal welfare. In the Netherlands, this transition is slow, and the consumption of animal proteins remains high (61%). This project explores how long-term behavior change toward plant-based diets can be promoted and how a more sustainable food environment can be supported. | M32: Yes | N32: Plant-based | O32: Consumer & market research | Q32: 150000 | R32: EUR | S32: 159195 | T32: 2025-05-01 | U32: 2025 | X32: Marleen Onwezen | Y32: Stichting Wageningen Research | Z32: Wageningen University & Research | AA32: grid.4818.5 | AB32: Wageningen | AD32: Netherlands | AE32: Dutch Research Council | AF32: cOAlition S | AG32: Netherlands | AH32: NWA L3 - Vernieuwing - Innovatieve projecten in routes 2024 (Funding Scheme) | AI32: Not available | AK32: https://doi.org/10.61686/EBLWP68612 | AL32: https://app.dimensions.ai/details/grant/grant.14912380 | AM32: 31 Biological Sciences; 32 Biomedical and Clinical Sciences; 3210 Nutrition and Dietetics | AN32: Dietary Supplements; Nutrition | AU32: A06 Agriculture, Veterinary and Food Science
A33: 2025 Dimensions gen | B33: 1165 | C33: grant.15196842 | D33: =ISNUMBER(MATCH(C33, 'Airtable copy'!N:N, 0)) -> FALSE | E33: =VLOOKUP(C33,'Airtable copy'!N:N,1,FALSE) -> #REF! | F33: =ISNUMBER(MATCH(C33, 'Grants tracker download'!O:O, 0)) -> FALSE | G33: =VLOOKUP(C33,'Grants tracker download'!O:O,1,FALSE) -> #REF! | H33: EP.1721.25.007 | I33: Accelerating plant-based protein emulsion design with microfluidics and intelligent software tools for sustainable foods (MIPRODESIGN) | J33: Accelerating plant-based protein emulsion design with microfluidics and intelligent software tools for sustainable foods (MIPRODESIGN) | K33: - | L33: - | M33: Yes | N33: Plant-based | O33: Texturisation methods | Q33: 360477 | R33: EUR | S33: 382576 | T33: 2025-01-01 | U33: 2025 | X33: Karin Schroën | Y33: Wageningen University & Research | Z33: Wageningen University & Research | AA33: grid.4818.5 | AB33: Wageningen | AD33: Netherlands | AE33: Dutch Research Council | AF33: cOAlition S | AG33: Netherlands | AH33: INT - EU Partnerschappen (1) - Sustainable Future of Food Systems (FutureFoodS) Call 2024 (Funding Scheme) | AI33: Not available | AL33: https://app.dimensions.ai/details/grant/grant.15196842 | AM33: 31 Biological Sciences; 46 Information and Computing Sciences; 4612 Software Engineering | AN33: Bioengineering; Biotechnology
A34: 2025 Dimensions gen | B34: 1111 | C34: grant.14956082 | D34: =ISNUMBER(MATCH(C34, 'Airtable copy'!N:N, 0)) -> FALSE | E34: =VLOOKUP(C34,'Airtable copy'!N:N,1,FALSE) -> #REF! | F34: =ISNUMBER(MATCH(C34, 'Grants tracker download'!O:O, 0)) -> FALSE | G34: =VLOOKUP(C34,'Grants tracker download'!O:O,1,FALSE) -> #REF! | H34: 235045 | I34: Enhancing biodiversity and ecosystem services through legume production and dietary change (BiodiversityField2Fork) | J34: Enhancing biodiversity and ecosystem services through legume production and dietary change (BiodiversityField2Fork) | K34: Background and rationale: Agricultural production is essential for humans but can pose a threat to biodiversity and ecosystem services. It has led to significant decline in biodiversity due to intensification and land use change. Impacts are driven by food consumption patterns, particularly by animal-based foods. Legumes play a key role in substituting animal protein. A transition to a more plant-based diet, combined with increased legume cultivation, is therefore a promising pathway to reduce environmental impacts and improve both biodiversity and ecosystem services both in Switzerland and abroad.Overall objectives: The BiodiversityField2Fork project aims to assess the potential for increasing biodiversity and ecosystem services through the dual pathways of a dietary shift towards more plant-based foods and the simultaneous cultivation of more food legumes in Switzerland.Specific aims: The following research questions will be answered:1.How can a legume-based food system be designed to enhance ecosystem services and improve biodiversity conditions compared to the current food system, while ensuring that the population receives an adequate amount and quality of nutrition?2.How do changes in dietary patterns and cropping systems influence agricultural land use and land-use change, both domestically and abroad, and what potential does this transformation have for biodiversity conditions and the provision of ecosystem services?3.What are the synergies and trade-offs between the provision of ecosystem services, enhancement of biodiversity, other environmental impacts such as climate change and eutrophication and the nutritional needs of the population in the transition to a more legume-based food system?4.What are the promoting and hindering factors for this transition, caused by conflicting stakeholder interests, and how could barriers be overcome?5.What are the most promising pathways for a transition to a more legume-based food system that enhances biodiversity and ecosystem services, considering factors such as crop selection, production methods, and consumer acceptance?Methods: The project will follow an iterative process, starting with a transdisciplinary co-creation process, which will lay the foundation for the products, consumption scenarios and transition pathways to be analysed and discuss interim results as well as the need to change modelling assumptions. We will assess the impact of legume crops and cropping systems on biodiversity and ecosystem services using the SALCA method (Swiss Agricultural Life Cycle Assessment). The relevant legume-based food products, value chains and diets and their impact on biodiversity and ecosystem services will be evaluated. With the SWISSfoodSys model, we will simulate scenarios for the whole Swiss food system with increased legume production and consumption and their impact on domestic agricultural production, import volumes of foods and feeds. We will simulate scenarios that are optimized for their impact on biodiversity and ecosystem services. The global impact of these scenarios on biodiversity and ecosystem services will be assessed using the FABIO (food and agriculture biomass input output) model together with multi-regional input-output data.Expected results: We will provide scientific evidence of the impact of specific legume cropping and legume-based food systems on biodiversity and ecosystem services, taking a holistic view of worldwide impacts and linking them to other environmental impacts (including climate change) and economic indicators. We will calculate the impact of legume crops and cropping systems as well as legume-based food value chains and diets in Switzerland on biodiversity and ecosystem services. Simultaneously, we will investigate the quantity and origin of foods and feeds imported into Switzerland and their impact on biodiversity and ecosystem services abroad. These data will be used to calculate the impact of the whole Swiss food system on biodiversity and ecosystem services for a number of scenarios with an increased legume production and consumption. These scenarios will be optimized for their biodiversity and ecosystem service impact. The outputs we generate will be geared towards stakeholders (fact sheets, discussions at workshops, entries on agripedia.ch, policy briefs) as well as the scientific community.Impact: Our research project will provide scientific evidence for addressing urgent challenges to biodiversity and ecosystem services by targeting food production and consumption as a key levers. We analyse interactions between all relevant points in the value chain and will produce actionable results for key stakeholders, disseminating knowledge directly to practitioners and consumers. With an improved understanding of the impacts of the food system on biodiversity and the benefits of promoting ecosystem services, we expect stakeholders to become more strongly motivated to enact change along the dual pathways of changing agricultural land use in Switzerland and adapting the Swiss food system to enhance biodiversity and ecosystem services. | L34: Background and rationale: Agricultural production is essential for humans but can pose a threat to biodiversity and ecosystem services. It has led to significant decline in biodiversity due to intensification and land use change. Impacts are driven by food consumption patterns, particularly by animal-based foods. Legumes play a key role in substituting animal protein. A transition to a more plant-based diet, combined with increased legume cultivation, is therefore a promising pathway to reduce environmental impacts and improve both biodiversity and ecosystem services both in Switzerland and abroad.Overall objectives: The BiodiversityField2Fork project aims to assess the potential for increasing biodiversity and ecosystem services through the dual pathways of a dietary shift towards more plant-based foods and the simultaneous cultivation of more food legumes in Switzerland.Specific aims: The following research questions will be answered:1.How can a legume-based food system be designed to enhance ecosystem services and improve biodiversity conditions compared to the current food system, while ensuring that the population receives an adequate amount and quality of nutrition?2.How do changes in dietary patterns and cropping systems influence agricultural land use and land-use change, both domestically and abroad, and what potential does this transformation have for biodiversity conditions and the provision of ecosystem services?3.What are the synergies and trade-offs between the provision of ecosystem services, enhancement of biodiversity, other environmental impacts such as climate change and eutrophication and the nutritional needs of the population in the transition to a more legume-based food system?4.What are the promoting and hindering factors for this transition, caused by conflicting stakeholder interests, and how could barriers be overcome?5.What are the most promising pathways for a transition to a more legume-based food system that enhances biodiversity and ecosystem services, considering factors such as crop selection, production methods, and consumer acceptance?Methods: The project will follow an iterative process, starting with a transdisciplinary co-creation process, which will lay the foundation for the products, consumption scenarios and transition pathways to be analysed and discuss interim results as well as the need to change modelling assumptions. We will assess the impact of legume crops and cropping systems on biodiversity and ecosystem services using the SALCA method (Swiss Agricultural Life Cycle Assessment). The relevant legume-based food products, value chains and diets and their impact on biodiversity and ecosystem services will be evaluated. With the SWISSfoodSys model, we will simulate scenarios for the whole Swiss food system with increased legume production and consumption and their impact on domestic agricultural production, import volumes of foods and feeds. We will simulate scenarios that are optimized for their impact on biodiversity and ecosystem services. The global impact of these scenarios on biodiversity and ecosystem services will be assessed using the FABIO (food and agriculture biomass input output) model together with multi-regional input-output data.Expected results: We will provide scientific evidence of the impact of specific legume cropping and legume-based food systems on biodiversity and ecosystem services, taking a holistic view of worldwide impacts and linking them to other environmental impacts (including climate change) and economic indicators. We will calculate the impact of legume crops and cropping systems as well as legume-based food value chains and diets in Switzerland on biodiversity and ecosystem services. Simultaneously, we will investigate the quantity and origin of foods and feeds imported into Switzerland and their impact on biodiversity and ecosystem services abroad. These data will be used to calculate the impact of the whole Swiss food system on biodiversity and ecosystem services for a number of scenarios with an increased legume production and consumption. These scenarios will be optimized for their biodiversity and ecosystem service impact. The outputs we generate will be geared towards stakeholders (fact sheets, discussions at workshops, entries on agripedia.ch, policy briefs) as well as the scientific community.Impact: Our research project will provide scientific evidence for addressing urgent challenges to biodiversity and ecosystem services by targeting food production and consumption as a key levers. We analyse interactions between all relevant points in the value chain and will produce actionable results for key stakeholders, disseminating knowledge directly to practitioners and consumers. With an improved understanding of the impacts of the food system on biodiversity and the benefits of promoting ecosystem services, we expect stakeholders to become more strongly motivated to enact change along the dual pathways of changing agricultural land use in Switzerland and adapting the Swiss food system to enhance biodiversity and ecosystem services. | M34: Yes | N34: Plant-based | O34: Impact assessments | P34: ecosystem services of legumes; biodiversity of legumes; food legumes; dietary change; land use change; crop diversification; environmental impact | Q34: 749801 | R34: CHF | S34: 841774 | T34: 2025-11-01 | U34: 2025 | V34: 2028-10-31 | W34: 2028 | X34: Maria Bystricky, Utkur Djanibekov, Stephan Pfister, Sanzio Rombini, Dany Schulthess, Philippe Jeanneret, Thomas Nemecek, Albert von Ow, Christie Walker | Y34: Forschungsgruppe Ökobilanzen Agroscope, Switzerland; Agroscope, Ukraine; Chair of Ecological Systems Design Institute of Environmental Engineering ETH Zürich, Switzerland; AGRIDEA, Switzerland; Strickhof, Switzerland; Agricultural Landscapes and Biodiversity Institute for Sustainability Sciences ISS Agroscope, Switzerland; Forschungsanstalt Agroscope Environmental Analytics, Switzerland; Institute of Environmental Engineering - IfU D-BAUG ETH Zurich, Switzerland | Z34: Agroscope; ETH Zurich; AGRIDEA | AA34: grid.417771.3; grid.5801.c; grid.483057.d | AB34: Bern; Zurich; Lausanne | AD34: Switzerland; Switzerland; Switzerland | AE34: Swiss National Science Foundation | AF34: cOAlition S | AG34: Switzerland | AH34: NFP 82 - Biodiversity and Ecosystem Services (Funding Instrument); National Research Programmes (NRPs) (Funding Instrument Hierarchy); Programmes (Funding Instrument Hierarchy) | AI34: Not available | AK34: https://data.snf.ch/grants/grant/235045 | AL34: https://app.dimensions.ai/details/grant/grant.14956082 | AM34: 30 Agricultural, Veterinary and Food Sciences; 41 Environmental Sciences; 4102 Ecological Applications | AN34: Nutrition | AO34: Oral and gastrointestinal | AU34: A06 Agriculture, Veterinary and Food Science | AV34: 15 Life on Land; 2 Zero Hunger
A35: 2025 Dimensions gen | B35: 1065 | C35: grant.15195859 | D35: =ISNUMBER(MATCH(C35, 'Airtable copy'!N:N, 0)) -> FALSE | E35: =VLOOKUP(C35,'Airtable copy'!N:N,1,FALSE) -> #REF! | F35: =ISNUMBER(MATCH(C35, 'Grants tracker download'!O:O, 0)) -> FALSE | G35: =VLOOKUP(C35,'Grants tracker download'!O:O,1,FALSE) -> #REF! | H35: 10.61686/JBVZB40581; 406.XS.25.02.108 | I35: Food workers of the world unite! A qualitative investigation of labour relations in alternative food system transitions | J35: Food workers of the world unite! A qualitative investigation of labour relations in alternative food system transitions | K35: Our contemporary food system is failing us: it is widely recognised we must transition to alternative forms of food production and consumption built on principles of sustainability and justice. Missing in this debate about transition, however, is the position of agricultural and food workers, who are often the most marginalised actors in food systems. This project will investigate what happens to labour in alternative food systems through in-depth case studies of agroecological farms and plant-based protein companies in the Netherlands and Ireland. The insights generated by the project will help support positive outcomes for labour in alternative food system transitions. | L35: Our contemporary food system is failing us: it is widely recognised we must transition to alternative forms of food production and consumption built on principles of sustainability and justice. Missing in this debate about transition, however, is the position of agricultural and food workers, who are often the most marginalised actors in food systems. This project will investigate what happens to labour in alternative food systems through in-depth case studies of agroecological farms and plant-based protein companies in the Netherlands and Ireland. The insights generated by the project will help support positive outcomes for labour in alternative food system transitions. | M35: Yes | N35: Cross-cutting | O35: Impact assessments | Q35: 49554 | R35: EUR | S35: 52591 | T35: 2025-12-01 | U35: 2025 | X35: Mark Vicol | Y35: Wageningen University & Research | Z35: Wageningen University & Research | AA35: grid.4818.5 | AB35: Wageningen | AD35: Netherlands | AE35: Dutch Research Council | AF35: cOAlition S | AG35: Netherlands | AH35: SGW Open Competitie XS 2025 - ronde 2 (Funding Scheme) | AI35: Not available | AK35: https://doi.org/10.61686/JBVZB40581 | AL35: https://app.dimensions.ai/details/grant/grant.15195859 | AM35: 44 Human Society; 4406 Human Geography; 4410 Sociology | AU35: C14 Geography and Environmental Studies | AV35: 2 Zero Hunger
A36: 2025 Dimensions gen | B36: 988 | C36: grant.15164609 | D36: =ISNUMBER(MATCH(C36, 'Airtable copy'!N:N, 0)) -> FALSE | E36: =VLOOKUP(C36,'Airtable copy'!N:N,1,FALSE) -> #REF! | F36: =ISNUMBER(MATCH(C36, 'Grants tracker download'!O:O, 0)) -> FALSE | G36: =VLOOKUP(C36,'Grants tracker download'!O:O,1,FALSE) -> #REF! | H36: 2024/53/N/NZ9/03652 | I36: Badanie potencjału kompleksów białkowo-pektynowych do poprawy właściwości funkcjonalnych tuszy do druku 3D | J36: Investigating the potential of protein-pectin complexes to improve the functional properties of 3D printing inks | K36: Starzenie się społeczeństwa to problem globalny XXI wieku, który wpływa na liczne obszary życia, w tym również na sektor spożywczy. Przy tak zmieniającej się strukturze demograficznej, zapewnienie odżywczej i atrakcyjnej wizualnie żywności dla osób starszych czy hospitalizowanych stało się istotnym wyzwaniem. Technologią umożliwiającą tworzenie takiej żywności jest druk 3D, który pozwala na przygotowanie produktów o złożonej strukturze, uzyskiwan ych warstwa po warstwie, zgodnie z zaprojektowanym modelem cyfrowym. Zaletą tej technologii jest możliwość dostosowania cech żywieniowych i sen sorycznych do indywidualnych potrzeb konsumentów. Jednakże większość produktów spożywczych, w tym również owoce, mogą być drukowane dopiero po przetworzeniu i dodaniu substancji poprawiających ich płynność. Większość takich substancji nie jest pozytywnie p ostrzegana przez konsumentów (np. guma guar, karagen), wymaga specyficznych warunków żelowania, lub ich żelowanie trwa bardzo długo. Dodatek białka do owoców może poprawić teksturę produktów, a dodatkowo przyczynić się do poprawy ich wartości odżywczej. Większość białek roślinnych charakteryzuje się jednak niekorzystnymi właściwościami funkcjonalnymi w porównaniu do białek pochodzenia zwierzęcego , dlatego należy poszukiwać metod modyfikacji ich właściwości, które jednocześnie będą przyjazne dla środowiska. Tworzenie kompleksów z pektynami oraz wybrane metody fizyczne (obróbki ultradźwiękami i mikrofal ami) mogą wpływać na zmianę struktury i poprawę właściwości białek roślinnych, zwiększając tym samym możliwości ich zastosowania. Celem projektu jest kompleksowa ocena potencjału wykorzystania kompleksów białko konopne-pektyna do tworzenia past do druku 3D z wytłoków owocowych. Zostanie zbadany wpływ obróbek ultradźwiękami i mikrofalami na wybrane właściwości kompleksów. Ponadto, aby ocenić możliwość utrwalenia wydrukowanego materiału, zostanie przeprowadzone suszenie mikrofalowo-próżniowe o różnych parametrach, a także suszenie konwekcyjne i liofilizacja jako metody referencyjne. Do tworzenia kompleksów zostaną wykorzystane i zolat lub koncentrat białka konopnego oraz wybrane preparaty pektynowe z pektyny cytrusowej i/lub jabłkowej. Kompleksy zostaną poddane obróbkom ultradźwiękowej i mikrofalowej i zbadane zostaną ich właściwości fizyczne i chemiczne. Równolegle, wytłoki owocowe o pożądanej konsystencji i strukturze zostaną uzyskane przez wyciskanie soku, homogenizację i przetarcie przez sito. Kompleksy białkowo-pektynowe o najbardziej obiecujących właściwościach zostaną dodane do przetworzonych wytłoków w celu wytworzenia pasty do druku 3D. Proces druku 3D zostanie zoptymalizowany, z uwzględnieniem licznych parametrów, w tym średnicy dyszy, prędkości drukowania czy współczynnik wypełnienia, a następnie zbadane zostaną właściwości fizyczne i chemiczne drukowanych past. Wybrane warianty wydruków zostaną po ddane suszeniu mikrofalowo-próżniowemu, w którym temperatura, optymalizowane będą temperatura, ciśnienie i moc mikrofal. Hipoteza badawcza zakłada, że odpowiedni skład (rodzaj pektyny, stężenie białka i stosunek białko/pektyna), warunki środowiskowe (pH, temperatura, siła jonowa) oraz łagodna obróbka wspomagająca (ultradźwięki, mikrofale) pozwolą na uzyskanie kompleksów białko konopne-pektyna o pożądanych właściwościach funkcjonalnych i będą mogły posłużyć do p oprawy drukowalności wytłoków owocowych. Badanie będzie odpowiedzią na globalne problemy, takie jak zagospodarowanie produktów ubocznych z przemysłu spożywczego (wytłoki, pektyny - przemysł owocowo-warzywny, białko konopne – przemysł olejarski) czy rosnąca zapotrzebowanie na żywność pochodzenia roślinnego – naturalną i bogatą w składniki odżywcze. Zaproponowane badania pomogą zrozumieć interakcje między białkiem konopnym a pektyną poddawanym wybranym obróbkom fizycznym, co może przyczynić się do potencjalnego stosowania takich kompleksów jako alternatyw dla negatywnie postrzeganych stabilizatorów stosowanych w żywności roślinnej. Dodatkowo, badania dostarczą nowej wiedzy na temat drukowalności wytłoków owocowych oraz możliwości wykorzystania kompleksów białkowo -pektynowych w celu poprawy drukowalności past spożywczych. Wyniki badań mogą być interesujące również w związku z poszukiwaniem rozwiązań w zakresie utrwalania produktów drukowanych 3D , co w przyszłości mogłoby przyczynić się do zwiększenia ich dostępności na rynku. Rezultaty projektu mogą b yć przydatne w przyszłości do projektowania żywności o określonych cechach sensorycznych, np. specyficznej teksturze i strukturze, a także żywieniowych, np. o zwiększonej zawartości składników biologicznie czynnych. | L36: The aging population is a global problem of the 21st century, affecting numerous areas of life, including the food sector. With such a changing demographic structure, providing nutritious and visually appealing food for the elderly and hospitalized has become a significant challenge. The technology enabling the creation of such food is 3D printing, which allows for the preparation of products with complex structures, obtained layer by layer, according to a designed digital model. The advantage of this technology is the ability to customize nutritional and sensory characteristics to individual consumer needs. However, most food products, including fruit, can be printed only after processing and the addition of substances that improve their flowability. Most of these substances are not positively perceived by consumers (e.g., guar gum, carrageenan), require specific gelation conditions, or their gelation takes a very long time. Adding protein to fruit can improve the texture of products and additionally contribute to their nutritional value. However, most plant proteins have unfavorable functional properties compared to animal proteins, so it is necessary to seek methods for modifying their properties that are also environmentally friendly. The formation of complexes with pectins and selected physical methods (ultrasound and microwave treatment) can alter the structure and improve the properties of plant proteins, thus increasing their application potential. The aim of the project is to comprehensively assess the potential of using hemp protein-pectin complexes to create pastes for 3D printing from fruit pomace. The effect of ultrasonic and microwave treatments on selected properties of the complexes will be examined. Furthermore, to assess the possibility of fixing the printed material, microwave-vacuum drying with various parameters will be conducted, as well as convective drying and freeze-drying as reference methods. Hemp protein isolate or concentrate, as well as selected pectin preparations from citrus and/or apple pectin, will be used to create the complexes. The complexes will be subjected to ultrasonic and microwave treatments, and their physical and chemical properties will be examined. In parallel, fruit pomace with the desired consistency and structure will be obtained by squeezing the juice, homogenizing it, and sieving it. Protein-pectin complexes with the most promising properties will be added to the processed pomace to produce a paste for 3D printing. The 3D printing process will be optimized, taking into account numerous parameters, including nozzle diameter, printing speed, and fill factor. The physical and chemical properties of the printed pastes will then be examined. Selected print variants will then be subjected to microwave-vacuum drying, with optimized temperature, pressure, and microwave power. The research hypothesis assumes that the appropriate composition (pectin type, protein concentration, and protein/pectin ratio), environmental conditions (pH, temperature, ionic strength), and mild auxiliary processing (ultrasound, microwaves) will allow for the production of hemp protein-pectin complexes with the desired functional properties and can be used to improve the printability of fruit pomace. The research will be a response to global problems, such as the management of by-products from the food industry (pomace, pectin - fruit and vegetable industry, hemp protein - oil industry) or the growing demand for plant-based food - natural and rich in nutrients.The proposed research will help understand the interactions between hemp protein and pectin subjected to selected physical treatments, which may contribute to the potential use of such complexes as alternatives to the negatively perceived stabilizers used in plant-based foods. Additionally, the research will provide new knowledge on the printability of fruit pomace and the possibility of using protein-pectin complexes to improve the printability of food pastes. The research results may also be of interest in connection with the search for solutions for the stabilization of 3D printed products, which could contribute to their increased availability on the market in the future. The project results may be useful in the future for designing foods with specific sensory characteristics, such as specific texture and structure, as well as nutritional characteristics, such as those with increased content of biologically active ingredients. | M36: Yes | N36: Plant-based | O36: Texturisation methods | P36: Hemp protein; pectin; convection drying; freeze-drying; texture.; microwaves; structure; rheological properties; 3D printing; fruit pomace; microwave-vacuum drying; ultrasounds | Q36: 210000 | R36: PLN | S36: 52868 | T36: 2025-02-05 | U36: 2025 | V36: 2028-02-04 | W36: 2028 | X36: Magdalena Urszula Trusińska | Y36: Szkoła Główna Gospodarstwa Wiejskiego w Warszawie | Z36: Warsaw University of Life Sciences | AA36: grid.13276.31 | AB36: Warsaw | AD36: Poland | AE36: National Science Center | AF36: cOAlition S | AG36: Poland | AH36: PRELUDIUM 23 (Competition) | AI36: Not available | AK36: https://projekty.ncn.gov.pl/index.php?projekt_id=614524 | AL36: https://app.dimensions.ai/details/grant/grant.15164609 | AM36: 30 Agricultural, Veterinary and Food Sciences; 3006 Food Sciences | AU36: B12 Engineering | AV36: 2 Zero Hunger
A37: 2025 Dimensions gen | B37: 643 | C37: grant.15053559 | D37: =ISNUMBER(MATCH(C37, 'Airtable copy'!N:N, 0)) -> FALSE | E37: =VLOOKUP(C37,'Airtable copy'!N:N,1,FALSE) -> #REF! | F37: =ISNUMBER(MATCH(C37, 'Grants tracker download'!O:O, 0)) -> FALSE | G37: =VLOOKUP(C37,'Grants tracker download'!O:O,1,FALSE) -> #REF! | H37: 10154415 | I37: Designing a manufacturing facility of the future for cell cultivated products | J37: Designing a manufacturing facility of the future for cell cultivated products | K37: The UN's goal of eliminating hunger will be missed by 660m people (WHO) with food production needing to increase by 50% by 2050 and projected protein provision being insufficient for healthy diets. Traditional food production cannot meet this demand, with livestock agriculture already consuming 70% of available arable land and 27% of global freshwater. It is a major contributor to climate change, contributing 15% of all global anthropogenic greenhouse gas emissions, alongside agriculture-related pollution and eutrophication and human health risks including zoonotic disease and antibiotic resistance. Cell cultivated food products from plant and animal cells are accepted as a game-changing sustainable solution to these challenges, with the potential to produce products indistinguishable from conventional agricultural products through cultivation of cells using bioprocessing techniques. However, this nascent industry urgently needs solutions to enable production-at-scale to realise the enormous potential to feed more people with fewer resources, decarbonising meat production and reducing land and water usage. Key technological barriers to entry and scale for new cell cultivated products include the prohibitively long, expensive, high risk product development cycles and the huge cost of setting up and optimising equipment, manufacturing facilities and processes. Manufacturing foods of the future require facilities of the future to support their production. These facilities need to be designed with a customer, people and planet centric design in order to fulfil the expectation of reducing environmental impact from food production. | L37: The UN's goal of eliminating hunger will be missed by 660m people (WHO) with food production needing to increase by 50% by 2050 and projected protein provision being insufficient for healthy diets. Traditional food production cannot meet this demand, with livestock agriculture already consuming 70% of available arable land and 27% of global freshwater. It is a major contributor to climate change, contributing 15% of all global anthropogenic greenhouse gas emissions, alongside agriculture-related pollution and eutrophication and human health risks including zoonotic disease and antibiotic resistance. Cell cultivated food products from plant and animal cells are accepted as a game-changing sustainable solution to these challenges, with the potential to produce products indistinguishable from conventional agricultural products through cultivation of cells using bioprocessing techniques. However, this nascent industry urgently needs solutions to enable production-at-scale to realise the enormous potential to feed more people with fewer resources, decarbonising meat production and reducing land and water usage. Key technological barriers to entry and scale for new cell cultivated products include the prohibitively long, expensive, high risk product development cycles and the huge cost of setting up and optimising equipment, manufacturing facilities and processes. Manufacturing foods of the future require facilities of the future to support their production. These facilities need to be designed with a customer, people and planet centric design in order to fulfil the expectation of reducing environmental impact from food production. | M37: Yes | N37: Cross-cutting | O37: Other | Q37: 74716 | R37: GBP | S37: 94487 | T37: 2025-05-31 | U37: 2025 | V37: 2025-10-31 | W37: 2025 | X37: Jamie Thompson | Y37: EXTRACELLULAR LTD; CAWSAM BIOPROCESS CONSULTING LTD | AE37: Innovate UK | AF37: cOAlition S; UKRI - UK Research and Innovation | AG37: United Kingdom | AH37: Business Connect (Project Category) | AI37: Not available | AK37: https://gtr.ukri.org/projects?ref=10154415 | AL37: https://app.dimensions.ai/details/grant/grant.15053559 | AM37: 30 Agricultural, Veterinary and Food Sciences; 40 Engineering; 4014 Manufacturing Engineering | AU37: A06 Agriculture, Veterinary and Food Science | AV37: 13 Climate Action; 2 Zero Hunger
A38: 2025 Dimensions gen | B38: 587 | C38: grant.15145313 | D38: =ISNUMBER(MATCH(C38, 'Airtable copy'!N:N, 0)) -> FALSE | E38: =VLOOKUP(C38,'Airtable copy'!N:N,1,FALSE) -> #REF! | F38: =ISNUMBER(MATCH(C38, 'Grants tracker download'!O:O, 0)) -> FALSE | G38: =VLOOKUP(C38,'Grants tracker download'!O:O,1,FALSE) -> #REF! | I38: Opbouwen van een kennisbasis voor ‘ultrasound’-geïnduceerde wijzigingen in de structuur en functionaliteit van peulvruchtproteïnen | J38: Building a knowledge base for ultrasound-induced changes in the structure and functionality of legume proteins | K38: ‘Ultrasound’ behandelingen kunnen de structurele organisatie van peulvruchtproteïnen en bijgevolg hun functionaliteit in voeding veranderen. Dit project beoogt een fundamentele kennisbasis op te bouwen over hoge-intensiteit ‘ultrasound’ behandelingen voor structurele en functionele modificatie van peulvruchtproteïnen. Een veelvoud aan ‘ultrasound’ behandelingen met verschillende intensiteiten zal onderzocht worden, met als doel specifieke structurele wijzigingen in natieve soja-, erwt-, en veldboonproteïnen te veroorzaken, zoals sub-unit dissociatie of aggregatie. Een specifieke focus is het karakteriseren en begrijpen van deze structurele veranderingen op meerdere lengteschalen. De opgebouwde analytische toolbox zal dan gebruikt worden om de invloed van pH en ionische sterkte tijdens ‘ultrasound’ behandeling op de geïnduceerde structurele wijzigingen te begrijpen. Tot slot zullen de emulgerende eigenschappen van structureel verschillende stalen bestudeerd worden. Mechanistische inzichten zullen verkregen worden uit olie-water interfase tensiometrie en geavanceerde microscopie. Het project zal resulteren in (i) het begrijpen van ‘ultrasound’-geïnduceerde structurele wijzigingen in natieve plantaardige globulines over verschillende lengteschalen, en (ii) betekenisvolle relaties tussen de structuur van peulvruchtproteïnen en hun emulgerende eigenschappen. Hierdoor draagt het project bij aan de eiwittransitie door de toepasbaarheid van peulvruchtproteïnen in voeding te verhogen. | L38: Ultrasound treatments can alter the structural organization of legume proteins and, consequently, their functionality in food. This project aims to build a fundamental knowledge base on high-intensity ultrasound treatments for structural and functional modification of legume proteins. A variety of ultrasound treatments with different intensities will be investigated, aiming to induce specific structural changes in native soy, pea, and faba bean proteins, such as subunit dissociation or aggregation. A specific focus is on characterizing and understanding these structural changes at multiple length scales. The developed analytical toolbox will then be used to understand the influence of pH and ionic strength during ultrasound treatment on the induced structural changes. Finally, the emulsifying properties of structurally different samples will be studied. Mechanistic insights will be obtained from oil-water interphase tensiometry and advanced microscopy. The project will result in (i) understanding ultrasound-induced structural changes in native plant globulins across different length scales, and (ii) meaningful relationships between the structure of legume proteins and their emulsifying properties. In doing so, the project contributes to the protein transition by increasing the applicability of legume proteins in food. | M38: Yes | N38: Plant-based | O38: Ingredient optimisation | P38: legume proteins; food emulsions; ultrasound | Q38: 0 | S38: 0 | T38: 2025-10-01 | U38: 2025 | X38: Arno Wouters, Ben Van den Wouwer | Y38: KU Leuven | Z38: KU Leuven | AA38: grid.5596.f | AB38: Leuven | AD38: Belgium | AE38: Research Foundation - Flanders | AF38: ICRP - International Cancer Research Partnership | AG38: Belgium | AI38: Not available | AK38: https://researchportal.be/nl/project/opbouwen-van-een-kennisbasis-voor-ultrasound-geinduceerde-wijzigingen-de-structuur-en | AL38: https://app.dimensions.ai/details/grant/grant.15145313 | AM38: 30 Agricultural, Veterinary and Food Sciences; 3006 Food Sciences; 31 Biological Sciences | AN38: Biomedical Imaging | AO38: Generic health relevance | AU38: B12 Engineering
