Workbook

Sheet Airtable copy
A1: Title | B1: Abstract | C1: Original title | D1: Database | E1: Total amount | F1: Gov contribution | G1: Currency | H1: Total amount (USD) | I1: Gov contribution (USD) | J1: Total amount (EUR) | K1: Gov & NP contribution (EUR) | L1: Funding decision | M1: copy to external database | N1: URL for announcement | O1: Identification code | R1: Notes (external) | S1: Notes (internal) | T1: Project lead (PI) | U1: PI department | V1: PI organisation | W1: PI organisation type | X1: PI organisation country | Y1: PI organisation region | Z1: PI organisation state | AA1: PI organisation zip code | AB1: PI organisation congressional district | AC1: Collaborator names | AD1: Collaborator institutions | AE1: Multiple organisation recipients | AF1: Date request submitted | AG1: Year request submitted | AH1: Date award announced | AI1: Project start date | AJ1: Duration of award (months) | AK1: Project status | AL1: Annual expenditures | AM1: Funder name | AN1: Sub-funder | AO1: Funding call | AP1: Success rate | AQ1: Funder type | AR1: Funder Country | AS1: Funder region | AT1: Production platform | AU1: Sub-production pillar | AV1: microalgae | AW1: Award purpose | AX1: End product type | AY1: sub-end product | AZ1: Research category | BA1: GFI grantee | BB1: APP site | BC1: Minority serving institution | BD1: Date added | BE1: Last modified | BF1: GFI LOS | BG1: Link to LOS | BH1: GFI partner | BI1: Tier | BJ1: Year project started | BK1: End date | BL1: duration (years) | BM1: Years active | BN1: 2020 | BO1: 2021 | BP1: 2022 | BQ1: 2023 | BR1: 2024 | BS1: 2025 | BT1: 2026 | BU1: 2027 | BV1: 2028 | BW1: 2029 | BX1: 2030 | BY1: 2031 | BZ1: 2032 | CA1: 2033 | CB1: 2034 | CC1: 2035
A2: Denmark announces 1 billion kroner for plant-based foods in historic climate agreement | D2: airtable | E2: 1250000000 | F2: 1250000000 | G2: DKK | H2: 177000000 | I2: 177000000 | J2: =E2*0.13 -> 162500000 | K2: =F2*0.13 -> 162500000 | L2: Committed | M2: checked | N2: https://gfieurope.org/blog/denmark-plant-based-investment-in-climate-agreement/ | R2: Original award amount is DKK 1,250,000,000. | S2: In 2021 State of Global Policy Report. 12.04.23: I think this article is an update on this funding: https://www.forbes.com/sites/danieladelorenzo/2023/09/10/denmarks-195-millions-plant-based-fund-receives-overwhelming-number-of-applicants/?sh=3d41434eb034 | T2: TBD | U2: n/a | V2: Multiple | W2: TBD | X2: Denmark | Y2: Europe | Z2: n/a | AE2: Yes | AI2: 44475 | AJ2: 9 | AK2: In progress | AL2: 19666667 | AM2: Danish Government | AQ2: Government | AR2: Denmark | AS2: Europe | AT2: Plant-based | AW2: Research and development, Equipment and infrastructure | AX2: Agnostic | BD2: 45029 | BE2: 45264 | BI2: Tier 4 (No GFI involvement) | BJ2: 2021 | BK2: 47644
A3: Plant2Food | B3: The new collaborative platform Plant2Food will accelerate the development of plant-based foods. Researchers and companies will collaborate in exploring complex challenges within plant and food science and sharing new knowledge across sectors – without taking out patents based on the results. The Novo Nordisk Foundation is supporting the platform with up to DKK 200 million (€27 million) over the next 5 years. It is necessary to convert a big part of our food production to plant-based foods if we want to make the most appropriate use of our agricultural land as well as being able to feed a growing world population. The key to accelerating this transition is developing a greater selection of tasty, nutritious and sustainable plant-based food products that are also affordable to consumers. A new collaboration platform, Plant2Food, will be a hub for researchers and companies who want to collaborate to solve some of the complex issues of developing plant-based foods – without taking out patents based on the results. | D3: airtable | E3: 200000000 | F3: 200000000 | G3: DKK | H3: 28473000 | I3: 0 | J3: =E3*0.13 -> 26000000 | K3: =F3*0.13 -> 26000000 | L3: Awarded | M3: checked | N3: https://novonordiskfonden.dk/en/news/new-open-collaborative-platform-will-accelerate-the-development-of-plant-based-foods/ | R3: Original award amount is DKK 200,000,000. | T3: Marie Louise Conradsen | U3: Natural Sciences | V3: Aarhus University | W3: University | X3: Denmark | Y3: Europe | Z3: n/a | AD3: University of Copenhagen, Technical University of Denmark, Wageningen University and Research, Food and Bio Cluster Denmark | AE3: Yes | AI3: 44875 | AJ3: 5 | AK3: In progress | AL3: 5694600 | AM3: Novo Nordisk Foundation | AQ3: Non-profit | AR3: Denmark | AS3: Europe | AT3: Plant-based | AW3: Research and development | AX3: =IFERROR(INDEX('full database 2024'!AR:AR, MATCH(A3, 'full database 2024'!B:B, 0)), "") | AZ3: cross-cutting | BD3: 44984 | BE3: 45035 | BI3: Tier 4 (No GFI involvement) | BJ3: 2022 | BK3: 2027 | BL3: =BK3-BJ3+1 -> 6 | BM3: =TEXTJOIN(", ", TRUE, SEQUENCE(1, BL3, BJ3)) -> 2022, 2023, 2024, 2025, 2026, 2027 | BN3: =IF(ISNUMBER(SEARCH(BN$1, $BM3)), ($K3/$BL3), "") | BO3: =IF(ISNUMBER(SEARCH(BO$1, $BM3)), ($K3/$BL3), "") | BP3: =IF(ISNUMBER(SEARCH(BP$1, $BM3)), ($K3/$BL3), "") -> 4333333.3 | BQ3: =IF(ISNUMBER(SEARCH(BQ$1, $BM3)), ($K3/$BL3), "") -> 4333333.3 | BR3: =IF(ISNUMBER(SEARCH(BR$1, $BM3)), ($K3/$BL3), "") -> 4333333.3 | BS3: =IF(ISNUMBER(SEARCH(BS$1, $BM3)), ($K3/$BL3), "") -> 4333333.3 | BT3: =IF(ISNUMBER(SEARCH(BT$1, $BM3)), ($K3/$BL3), "") -> 4333333.3 | BU3: =IF(ISNUMBER(SEARCH(BU$1, $BM3)), ($K3/$BL3), "") -> 4333333.3 | ... CC3: =IF(ISNUMBER(SEARCH(CC$1, $BM3)), ($K3/$BL3), "")
A4: CO2 as a sustainable raw material in our future food production | B4: In a new consortium, companies and university researchers will create a sustainable source of proteins for human food derived from CO2. The aim is to help fight the rising global problems with food insecurity and greenhouse-gas emissions from agriculture. Two leading foundations are supporting the initiative with up to DKK 200 million (€27 million). | D4: airtable | E4: 100000000 | F4: 100000000 | G4: DKK | H4: 27000000 | I4: 0 | J4: =E4*0.13 -> 13000000 | K4: =F4*0.13 -> 13000000 | L4: Awarded | M4: checked | N4: https://novonordiskfonden.dk/en/news/co2-as-a-sustainable-raw-material-in-our-future-food-production/ | R4: Original award amount is DKK 200,000,000. Halved to reflect removal of US portion | T4: Claus Crone Fuglsang | U4: n/a | V4: Novozymes A/S | W4: For profit | X4: Denmark | Y4: Europe | Z4: n/a | AD4: Topsoe A/S, Washington University St. Louis, Novo Nordisk Foundation CO2 Research Center (CORC) at Aarhus University | AE4: Yes | AI4: 45078 | AJ4: 2 | AK4: In progress | AL4: 13500000 | AM4: Novo Nordisk Foundation | AQ4: Non-profit | AR4: Denmark | AS4: Europe, North America | AT4: Fermentation | AU4: PF | AW4: Research and development | AX4: =IFERROR(INDEX('full database 2024'!AR:AR, MATCH(A4, 'full database 2024'!B:B, 0)), "") | AZ4: Feedstocks | BD4: 45377 | BE4: 45779 | BI4: Tier 4 (No GFI involvement) | BJ4: 2023 | BK4: 2025 | BL4: =BK4-BJ4+1 -> 3 | BM4: =TEXTJOIN(", ", TRUE, SEQUENCE(1, BL4, BJ4)) -> 2023, 2024, 2025 | BN4: =IF(ISNUMBER(SEARCH(BN$1, $BM4)), ($K4/$BL4), "") | BO4: =IF(ISNUMBER(SEARCH(BO$1, $BM4)), ($K4/$BL4), "") | BP4: =IF(ISNUMBER(SEARCH(BP$1, $BM4)), ($K4/$BL4), "") | BQ4: =IF(ISNUMBER(SEARCH(BQ$1, $BM4)), ($K4/$BL4), "") -> 4333333.3 | BR4: =IF(ISNUMBER(SEARCH(BR$1, $BM4)), ($K4/$BL4), "") -> 4333333.3 | BS4: =IF(ISNUMBER(SEARCH(BS$1, $BM4)), ($K4/$BL4), "") -> 4333333.3 | BT4: =IF(ISNUMBER(SEARCH(BT$1, $BM4)), ($K4/$BL4), "") | BU4: =IF(ISNUMBER(SEARCH(BU$1, $BM4)), ($K4/$BL4), "") | ... CC4: =IF(ISNUMBER(SEARCH(CC$1, $BM4)), ($K4/$BL4), "")
A5: Precision Technology: Biotechnology, smart sensors, and advanced data analysis | B5: The project has three sub-goals: Developing modern biotechnology to produce food Develop spectroscopic methods for food characterization, for the management and optimization of products and processes Develop data analytical methods that convert complex data into relevant, reliable and useful information Three enabling technologies It is necessary to produce more sustainably, reduce food waste and make full use of our raw materials. To achieve this, there is a need for precision technology that enables the food industry to produce the products and qualities needed, while minimizing food waste. This research program will contribute to this by developing three enabling technologies: New biotechnological processes that both provide better utilization of residual raw materials and can be used for the future production of important food components such as protein and fatty acids. We will develop new processes based on combinations of enzymatic protein hydrolysis, precision fermentation and meat cultivation. Smart sensors for rapid measurement of food quality that enable measurement and control of production processes to minimize waste and optimize yield and final quality. We will develop spectroscopic methods for in-line quality control and chemical characterization, and study how these can be applied in systems that facilitate product differentiation, consumer satisfaction and personalized nutrition. Data analytics tools that transform large and complex data into relevant, reliable and usable information. Such tools are essential to unlock the potential of technologies 1 and 2, as well as other scientific disciplines and a modern digitalized food industry. We will specifically work on challenges related to prediction and interpretation of data by combining methods from statistics, chemometrics and machine learning. | D5: airtable | E5: 64200000 | F5: 64200000 | G5: NOK | J5: =E5*0.087 -> 5585400 | K5: =F5*0.087 -> 5585400 | L5: Awarded | M5: checked | N5: https://nofima.no/prosjekt/precision-food-production/ | R5: Original award amount is estimated to be NOK 75,000,000. This was determined from the overall pool of funding available for this call (NOK 300,000,000) and the fact that four programs were awarded funding (300 million / 4 = 75 million). https://www.forskningsradet.no/en/call-for-proposals/2020/nye-strategiske-programmer-for-nofima-2021-2024/. Updated amount - link from funder here: https://prosjektbanken.forskningsradet.no/en/project/FORISS/314111?Kilde=FORISS&distribution=Ar&chart=bar&calcType=funding&Sprak=no&sortBy=score&sortOrder=desc&resultCount=30&offset=30&source=FORISS&projectId=270048&Fritekst=fermentation&Ar=2025&Ar=2024&Ar=2023&Ar=2022&Ar=2021&Ar=2020 | T5: Jens Petter Wold | U5: n/a | V5: Nofima | W5: For profit | X5: Norway | Y5: Europe | Z5: n/a | AC5: Ingrid Måge; Nils Kristian Afseth; Sissel Rønning; Lars Axelsson; Elin Katinka; Riiser Dankel | AD5: Nofima | AE5: No | AI5: 44197 | AJ5: 4 | AK5: In progress | AL5: 1767689 | AM5: Foundation for Research Levy on Agricultural Products (FFL) | AP5: https://www.forskningsradet.no/en/call-for-proposals/2020/nye-strategiske-programmer-for-nofima-2021-2024/ | AQ5: Government | AR5: Norway | AS5: Europe | AT5: Cross-cutting | AU5: CellAg | AW5: Research and development | AX5: =IFERROR(INDEX('full database 2024'!AR:AR, MATCH(A5, 'full database 2024'!B:B, 0)), "") | AZ5: Bioprocess design | BD5: 44985 | BE5: 45036 | BI5: Tier 4 (No GFI involvement) | BJ5: 2021 | BK5: 2025 | BL5: =BK5-BJ5+1 -> 5 | BM5: =TEXTJOIN(", ", TRUE, SEQUENCE(1, BL5, BJ5)) -> 2021, 2022, 2023, 2024, 2025 | BN5: =IF(ISNUMBER(SEARCH(BN$1, $BM5)), ($K5/$BL5), "") | BO5: =IF(ISNUMBER(SEARCH(BO$1, $BM5)), ($K5/$BL5), "") -> 1117080 | BP5: =IF(ISNUMBER(SEARCH(BP$1, $BM5)), ($K5/$BL5), "") -> 1117080 | BQ5: =IF(ISNUMBER(SEARCH(BQ$1, $BM5)), ($K5/$BL5), "") -> 1117080 | BR5: =IF(ISNUMBER(SEARCH(BR$1, $BM5)), ($K5/$BL5), "") -> 1117080 | BS5: =IF(ISNUMBER(SEARCH(BS$1, $BM5)), ($K5/$BL5), "") -> 1117080 | BT5: =IF(ISNUMBER(SEARCH(BT$1, $BM5)), ($K5/$BL5), "") | BU5: =IF(ISNUMBER(SEARCH(BU$1, $BM5)), ($K5/$BL5), "") | ... CC5: =IF(ISNUMBER(SEARCH(CC$1, $BM5)), ($K5/$BL5), "")
A6: SEEDFOOD: Functional and palatable plant seed storage proteins for sustainable foods | B6: The Foundation has awarded one of the 2021 grants to Marianne Nissen Lund, Professor from the Department of Food Science, University of Copenhagen. Marianne Nissen Lund has received a grant of DKK 56 million for the project SEEDFOOD: Functional and Palatable Plant Seed Storage Proteins for Sustainable Foods. The project aims to discover more efficient ways of utilizing protein from rapeseed, which is currently being used for animal feed. Rapeseed is a very widespread crop in northern Europe, but rapeseed protein is mostly used as animal feed rather than as food for humans. The reasons for this include taste and undesirable components and also that rapeseed protein in its natural form is not good at forming the types of structures that are desirable in food. The SEEDFOOD project aims to transform rapeseed protein into a food ingredient and to investigate how it can be processed to be more palatable, including taste and texture. “Rapeseed is promising because it contains many essential amino acids – the ones that people cannot make themselves – and the content is also higher than in other plant sources. Today, however, rapeseed oil is the only rapeseed food product marketed for humans. Using rapeseed in human food requires the removal of the bitterness and creating a palatable texture from this protein source. For example, yogurt should be soft and creamy and not gritty and sticky. In this research, we will create knowledge about how to use rapeseed protein in food and develop techniques to do this. We will not actually develop specific rapeseed-based products, but we aim to create a protein ingredient the food industry can use in plant-based foods for people,” says Marianne Nissen Lund. | D6: airtable | E6: 55900000 | F6: 55900000 | G6: DKK | H6: 8172831 | I6: 0 | J6: =E6*0.13 -> 7267000 | K6: =F6*0.13 -> 7267000 | L6: Awarded | M6: checked | N6: https://novonordiskfonden.dk/en/news/major-grants-awarded-for-research-on-plant-proteins-as-meat-alternatives/ | R6: Original award amount is DKK 55,900,000. | T6: Marianne Nissen Lund | U6: Food Science | V6: University of Copenhagen | W6: University | X6: Denmark | Y6: Europe | Z6: n/a | AE6: No | AI6: 44354 | AJ6: 6 | AK6: In progress | AL6: 1362139 | AM6: Novo Nordisk Foundation | AQ6: Non-profit | AR6: Denmark | AS6: Europe | AT6: Plant-based | AW6: Research and development | AX6: =IFERROR(INDEX('full database 2024'!AR:AR, MATCH(A6, 'full database 2024'!B:B, 0)), "") | AZ6: Ingredient optimisation | BD6: 45020 | BE6: 45035 | BI6: Tier 4 (No GFI involvement) | BJ6: 2021 | BK6: 2027 | BL6: =BK6-BJ6+1 -> 7 | BM6: =TEXTJOIN(", ", TRUE, SEQUENCE(1, BL6, BJ6)) -> 2021, 2022, 2023, 2024, 2025, 2026, 2027 | BN6: =IF(ISNUMBER(SEARCH(BN$1, $BM6)), ($K6/$BL6), "") | BO6: =IF(ISNUMBER(SEARCH(BO$1, $BM6)), ($K6/$BL6), "") -> 1038142.9 | BP6: =IF(ISNUMBER(SEARCH(BP$1, $BM6)), ($K6/$BL6), "") -> 1038142.9 | BQ6: =IF(ISNUMBER(SEARCH(BQ$1, $BM6)), ($K6/$BL6), "") -> 1038142.9 | BR6: =IF(ISNUMBER(SEARCH(BR$1, $BM6)), ($K6/$BL6), "") -> 1038142.9 | BS6: =IF(ISNUMBER(SEARCH(BS$1, $BM6)), ($K6/$BL6), "") -> 1038142.9 | BT6: =IF(ISNUMBER(SEARCH(BT$1, $BM6)), ($K6/$BL6), "") -> 1038142.9 | BU6: =IF(ISNUMBER(SEARCH(BU$1, $BM6)), ($K6/$BL6), "") -> 1038142.9 | ... CC6: =IF(ISNUMBER(SEARCH(CC$1, $BM6)), ($K6/$BL6), "")
A7: National Alternative Proteins Innovation and Knowledge Centre (NAPIC) | B7: To secure a continued supply of safe, tasty, affordable and functional/healthy proteins while supporting Net Zero goals and future-proofing UK food security, a phased-transition towards low-emission alternative proteins (APs) with a reduced reliance on animal agriculture is imperative. However, population-level access to and acceptance of APs is hindered by a highly complex marketplace challenged by taste, cost, health and safety concerns for consumers, and the fear of diminished livelihoods by farmers. Furthermore, complex regulatory pathways and limited access to affordable and accessible scale-up infrastructure impose challenges for industry and SMEs in particular. Synergistic bridging of the UK's trailblazing science and innovation strengths in AP with manufacturing power is key to realising the UK's ambitious growth potential in AP of £6.8B annually and could create 25,000 jobs across multiple sectors. The National Alternative Protein Innovation Centre (NAPIC), a cohesive pan-UK centre, will revolutionise the UK's agri-food sector by harnessing our world-leading science base through a co-created AP strategy across the Discovery?Innovation?Commercialisation pipeline to support the transition to a sustainable, high growth, blended protein bioeconomy using a consumer-driven approach, thereby changing the economics for farmers and other stakeholders throughout the supply chain. Built on four interdisciplinary knowledge pillars, PRODUCE, PROCESS, PERFORM and PEOPLE covering the entire value chain of AP, we will enable an efficacious and safe translation of new transformative technologies unlocking the benefits of APs. Partnering with global industry, regulators, investors, academic partners and policymakers, and engaging in an open dialogue with UK citizens, NAPIC will produce a clear roadmap for the development of a National Protein Strategy for the UK. NAPIC will enable us to PRODUCE tasty, nutritious, safe, and affordable AP foods and feedstocks necessary to safeguard present and future generations, while reducing concerns about ultra-processed foods and assisting a just-transition for producers. Our PROCESS Pillar will catalyse bioprocessing at scale, mainstreaming cultivated meat and precision fermentation, and diversify AP sources across the terrestrial and aquatic kingdoms of life, delivering economies of scale. Delivering a just-transition to an AP-rich future, we will ensure AP PERFORM, both pre-consumption, and post-consumption, safeguarding public health. Finally, NAPIC is all about PEOPLE, guiding a consumers' dietary transition, and identifying new business opportunities for farmers, future-proofing the UK's protein supply against reliance on imports. Working with UK industry, the third sector and academia, NAPIC will create a National Knowledge base for AP addressing the unmet scientific, commercial, technical and regulatory needs of the sector, develop new tools and standards for product quality and safety and simplify knowledge transfer by catalysing collaboration. NAPIC will ease access to existing innovation facilities and hubs, accelerating industrial adoption underpinned by informed regulatory pathways. We will develop the future leaders of this rapidly evolving sector with bespoke technical, entrepreneurial, regulatory and policy training, and promote knowledge exchange through our unrivalled international network of partners across multiple continents including Protein Industries Canada and the UK-Irish Co-Centre, SUREFOOD. NAPIC will provide a robust and sustainable platform of open innovation and responsible data exchange that mitigates risks associated with this emerging sector and addresses concerns of consumers and producers. Our vision is to make "alternative proteins mainstream for a sustainable planet" and our ambition is to deliver a world-leading innovation and knowledge centre to put the UK at the forefront of the fights for population health equity and against climate change. | D7: airtable | E7: 38000000 | F7: 16001352 | G7: GBP | H7: 48859450 | I7: 18697500 | J7: =E7*1.19 -> 45220000 | K7: =F7*1.19 -> 19041609 | L7: Awarded | M7: checked | N7: https://www.ukri.org/news/national-alternative-protein-innovation-centre-launches/ | O7: grant.14485806 | R7: Original fund amount is GBP 15,000,000. | S7: Per GFI Europe August Report: BBSRC and Innovate UK announced a £15 million investment over 5 years to support the development of an Alternative Proteins Innovation and Knowledge Centre (IKC). The Alternative Proteins IKC will support collaborative research partnerships between businesses and academic researchers and create a nucleating point for the growth of the alternative protein industry in the UK. This announcement follows on from the work that GFI Europe (particularly Seren, Stella and Linus) has done over the past two years engaging with BBSRC and Innovate UK on funding priorities in this space, which led to alternative proteins going into their strategic plans as a priority area for co-investment, and which had already led to the £16m call on Novel Foods they launched earlier in the year. | T7: Anwesha Sarkar | U7: n/a | V7: University Of Leeds | W7: University | X7: UK | Y7: Europe | Z7: n/a | AI7: 45515 | AJ7: 5 | AK7: In progress | AL7: 9771890 | AM7: UK Research and Innovation (UKRI) | AN7: Biotechnology and Biological Sciences Research Council (BBSRC) | AP7: https://www.ukri.org/opportunity/alternative-proteins-innovation-and-knowledge-centre/ | AQ7: Government | AR7: United Kingdom | AS7: Europe | AT7: Cross-cutting | AW7: Research and development, Education and training, Research infrastructure, Networking | AX7: Agnostic | AZ7: cross-cutting | BD7: 45177 | BE7: 45779 | BH7: checked | BI7: Tier 2 (Significant GFI involvement) | BJ7: 2024 | BK7: 2029 | BL7: =BK7-BJ7+1 -> 6 | BM7: =TEXTJOIN(", ", TRUE, SEQUENCE(1, BL7, BJ7)) -> 2024, 2025, 2026, 2027, 2028, 2029 | BN7: =IF(ISNUMBER(SEARCH(BN$1, $BM7)), ($K7/$BL7), "") | BO7: =IF(ISNUMBER(SEARCH(BO$1, $BM7)), ($K7/$BL7), "") | BP7: =IF(ISNUMBER(SEARCH(BP$1, $BM7)), ($K7/$BL7), "") | BQ7: =IF(ISNUMBER(SEARCH(BQ$1, $BM7)), ($K7/$BL7), "") | BR7: =IF(ISNUMBER(SEARCH(BR$1, $BM7)), ($K7/$BL7), "") -> 3173601.5 | BS7: =IF(ISNUMBER(SEARCH(BS$1, $BM7)), ($K7/$BL7), "") -> 3173601.5 | BT7: =IF(ISNUMBER(SEARCH(BT$1, $BM7)), ($K7/$BL7), "") -> 3173601.5 | BU7: =IF(ISNUMBER(SEARCH(BU$1, $BM7)), ($K7/$BL7), "") -> 3173601.5 | ... CC7: =IF(ISNUMBER(SEARCH(CC$1, $BM7)), ($K7/$BL7), "")
A8: Germany Earmarks €38M Investment for Alt-Protein Transition in 2024 Federal Budget | D8: airtable | E8: 38000000 | F8: 38000000 | G8: EUR | H8: 41115050 | I8: 41115050 | J8: 38000000 | K8: 38000000 | L8: Committed | M8: checked | N8: https://www.greenqueen.com.hk/germany-federal-budget-bundestag-2024-38-million-investment-alt-protein-plant-based/?utm_source=foodtechweekly.beehiiv.com&utm_medium=newsletter&utm_campaign=foodtech-weekly-174-by-daniel-s-ruben | R8: Original amount committed is EUR 38,000,000. | S8: From Ivo's email on Nov. 17, 2023: "We have been closely supporting this path and, together with these MPs, we have been working on the topic in an "Alternative Proteins Roundtable" since September 2022 and have actively helped to shape and initiate the measures adopted this week. In particular, the topic of a competence centre and an alternative protein strategy was introduced to this group primarily by us as GFI, but of course we were also calling for all the other measures agreed." | T8: TBD | U8: n/a | V8: TBD | W8: TBD | X8: Germany | Y8: Europe | Z8: n/a | AE8: Yes | AI8: 45292 | AJ8: 1 | AK8: Not started | AL8: 41115050 | AM8: Federal Ministry of Food and Agriculture (BMEL) | AQ8: Government | AR8: Germany | AS8: Europe | AT8: Cross-cutting | AU8: Agnostic | AW8: Research and development, Education and training, Equipment and infrastructure | AX8: Agnostic | BD8: 45264 | BE8: 45264 | BI8: Tier 2 (Significant GFI involvement) | BJ8: 2024 | BK8: 45658
A9: Solar Foods receives a €34 million grant to ramp-up Factory 01 and start preparations for Factory 02 | D9: airtable | E9: 34000000 | F9: 34000000 | G9: EUR | H9: 37298680 | I9: 37298680 | J9: 34000000 | K9: 34000000 | L9: Awarded | M9: checked | N9: https://solarfoods.com/solar-foods-receives-a-34-million-grant-to-ramp-up-factory-01-and-start-preparations-for-factory-02/ | R9: Original award amount is EUR 34,000,000. | T9: Pasi Vainikka | U9: n/a | V9: Solar Foods | W9: For profit | X9: Finland | Y9: Europe | Z9: n/a | AE9: No | AI9: 44917 | AJ9: 3 | AK9: In progress | AL9: 12432893 | AM9: Business Finland | AQ9: Government | AR9: Finland | AS9: Europe | AT9: Fermentation | AU9: PF | AW9: Equipment and infrastructure | AX9: =IFERROR(INDEX('full database 2024'!AR:AR, MATCH(A9, 'full database 2024'!B:B, 0)), "") | AZ9: Bioprocess design, Feedstocks, End product formulation, Food safety & quality | BD9: 45034 | BE9: 45035 | BI9: Tier 4 (No GFI involvement) | BJ9: 2022 | BK9: 2025 | BL9: =BK9-BJ9+1 -> 4 | BM9: =TEXTJOIN(", ", TRUE, SEQUENCE(1, BL9, BJ9)) -> 2022, 2023, 2024, 2025 | BN9: =IF(ISNUMBER(SEARCH(BN$1, $BM9)), ($K9/$BL9), "") | BO9: =IF(ISNUMBER(SEARCH(BO$1, $BM9)), ($K9/$BL9), "") | BP9: =IF(ISNUMBER(SEARCH(BP$1, $BM9)), ($K9/$BL9), "") -> 8500000 | BQ9: =IF(ISNUMBER(SEARCH(BQ$1, $BM9)), ($K9/$BL9), "") -> 8500000 | BR9: =IF(ISNUMBER(SEARCH(BR$1, $BM9)), ($K9/$BL9), "") -> 8500000 | BS9: =IF(ISNUMBER(SEARCH(BS$1, $BM9)), ($K9/$BL9), "") -> 8500000 | BT9: =IF(ISNUMBER(SEARCH(BT$1, $BM9)), ($K9/$BL9), "") | BU9: =IF(ISNUMBER(SEARCH(BU$1, $BM9)), ($K9/$BL9), "") | ... CC9: =IF(ISNUMBER(SEARCH(CC$1, $BM9)), ($K9/$BL9), "")
A10: Green technology for plant-based food (GreenPlantFood) | B10: To maintain national food self-sufficiency and employment, and competitiveness of the Norwegian agricultural sector and food industry there is need for more knowledge on the selection of suitable plant material combined with green technology processing. The main objective in this project is to facilitate green technology towards plant-based food in Norway with a significant proportion of Nordic Raw Materials into attractive and healthy products with low environmental footprint. Furthermore, a project looking at extended utilisation of protein sources, needs to focus on their complete utilization, including side streams. Pulses (peas and faba beans), together with cereals (oat and barley), are realistic candidates for extended food uses as is, or as protein sources. It is also a goal to find replacement for soya, which is imported and have a negative environmental footprint. Pulses are high-quality protein sources but contain a range of different compounds (polysaccharides, fat, polyphenols, anti-nutrients etc) that needs attention through green processing solutions. Farmers and advisors will benefit from understanding which varieties to grow, the best suited regions and quality parameters sought by the Norwegian food industry for plant-based products. | D10: airtable | E10: 27600000 | F10: 27600000 | G10: NOK | H10: 2604048 | I10: 2604048 | J10: =E10*0.087 -> 2401200 | K10: =F10*0.087 -> 2401200 | L10: Awarded | M10: checked | N10: https://nofima.com/projects/green-technology-for-plant-based-food/ | O10: grant.9641296 | R10: Original award amount is NOK 27,600,000 according to the Research Council of Norway website: https://prosjektbanken.forskningsradet.no/en/project/FORISS/319049?Kilde=FORISS&distribution=Ar&chart=bar&calcType=funding&Sprak=no&sortBy=score&sortOrder=desc&resultCount=30&offset=0&Fritekst=GreenPlantFood | T10: Svein Halvor Knutsen | U10: n/a | V10: Nofima | W10: For profit | X10: Norway | Y10: Europe | Z10: n/a | AC10: Sveinung Grimsby; Stefan Sahlstrøm | AD10: Nofima, Lantmännen Cerealia, AM Nutrition, Norgesmøllene, Hoff SA, Mills AS, Flowfood AS, Norwegian University of Life Sciences (NMBU), Norwegian Institute of Bioeconomy Research (NIBIO), NORSUS Norwegian Institute for Sustainability Research, Technical University of Denmark, Potsdam Institute for Climate Impact Research, "Instituto de Biologia Experimental e Tecnológica, Lisboa (iBET)", University of food technologies Plovdiv | AE10: Yes | AI10: 44287 | AJ10: 4 | AK10: In progress | AL10: 651012 | AM10: Research Council of Norway | AQ10: Government | AR10: Norway | AS10: Europe | AT10: Plant-based | AW10: Research and development | AX10: =IFERROR(INDEX('full database 2024'!AR:AR, MATCH(A10, 'full database 2024'!B:B, 0)), "") | AZ10: Ingredient optimisation | BD10: 45037 | BE10: 45037 | BI10: Tier 4 (No GFI involvement) | BJ10: 2021 | BK10: 2025 | BL10: =BK10-BJ10+1 -> 5 | BM10: =TEXTJOIN(", ", TRUE, SEQUENCE(1, BL10, BJ10)) -> 2021, 2022, 2023, 2024, 2025 | BN10: =IF(ISNUMBER(SEARCH(BN$1, $BM10)), ($K10/$BL10), "") | BO10: =IF(ISNUMBER(SEARCH(BO$1, $BM10)), ($K10/$BL10), "") -> 480240 | BP10: =IF(ISNUMBER(SEARCH(BP$1, $BM10)), ($K10/$BL10), "") -> 480240 | BQ10: =IF(ISNUMBER(SEARCH(BQ$1, $BM10)), ($K10/$BL10), "") -> 480240 | BR10: =IF(ISNUMBER(SEARCH(BR$1, $BM10)), ($K10/$BL10), "") -> 480240 | BS10: =IF(ISNUMBER(SEARCH(BS$1, $BM10)), ($K10/$BL10), "") -> 480240 | BT10: =IF(ISNUMBER(SEARCH(BT$1, $BM10)), ($K10/$BL10), "") | BU10: =IF(ISNUMBER(SEARCH(BU$1, $BM10)), ($K10/$BL10), "") | ... CC10: =IF(ISNUMBER(SEARCH(CC$1, $BM10)), ($K10/$BL10), "")
A11: SYLPLANT | B11: Arbiom, an agricultural-biotech company developing solutions to deliver next generation protein ingredients, announced today the kick-off of SYLPLANT project. This European collaborative project gathers 17 partners covering the entire food and feed value chains from feedstock manufacturers to retailers. It is co-funded by the Circular Bio-based Europe Joint Undertaking (CBE JU), a public-private partnership between the European Commission and the Bio-based Industries Consortium. SYLPLANT is built on the success of Sylfeed, a 4-year project funded by the Bio-Based Industries Joint Undertaking (predecessor of CBE JU) where Arbiom successfully scaled-up its technology and validated the performance of SylPro®, its flagship ingredient. “This factory paves the way to Arbiom’s industrial deployment. It will bring 10.000 tons/year of alternative, highly nutritional and sustainable protein to the market to answer the future food needs.” said Marc CHEVREL, CEO of Arbiom. | D11: airtable | E11: 23000000 | F11: 14000000 | G11: EUR | H11: 25829000 | I11: 15722000 | J11: 23000000 | K11: 14000000 | L11: Awarded | M11: checked | N11: https://acrobat.adobe.com/link/review?uri=urn%3Aaaid%3Ascds%3AUS%3Ad4e64a40-4679-3c42-a80f-ca1d80a890fd | R11: Original award amount is EUR 23,000,000 with EUR 14,000,000 from EU government. | T11: Amélie Drouault | U11: n/a | V11: Arbiom | W11: For profit | X11: France | Y11: Europe | Z11: n/a | AD11: FIBENOL, CENTRE DE RECHERCHE ET D’INNOVATION DE L’INSTITUT LYFE (EX INSTITUT PAUL BOCUSE) , SATT SAYENS, Bel, AGROMOUSQUETAIRES, Biozoon GmbH, CENTIV GMBH, NORMANDISE PET FOOD, BIOMAR AS, EUROFINS FOOD TESTING FRANCE, IFEU - INSTITUTE FOR ENERGY AND ENVIRONMENTAL RESEARCH HEIDELBERG, BIOECONOMY FOR CHANGE, PNO CONSULTANTS | AE11: Yes | AI11: 45078 | AJ11: 3 | AK11: In progress | AL11: 8609667 | AM11: European Commission | AN11: Circular Bio-based Europe Joint Undertaking (CBE JU) | AQ11: Joint public/private partnership | AR11: EU | AS11: Europe | AT11: Fermentation | AU11: BF | AW11: Equipment and infrastructure, Research and development | AX11: =IFERROR(INDEX('full database 2024'!AR:AR, MATCH(A11, 'full database 2024'!B:B, 0)), "") | AZ11: End product formulation | BD11: 45120 | BE11: 45123 | BI11: Tier 4 (No GFI involvement) | BJ11: 2023 | BK11: 2026 | BL11: =BK11-BJ11+1 -> 4 | BM11: =TEXTJOIN(", ", TRUE, SEQUENCE(1, BL11, BJ11)) -> 2023, 2024, 2025, 2026 | BN11: =IF(ISNUMBER(SEARCH(BN$1, $BM11)), ($K11/$BL11), "") | BO11: =IF(ISNUMBER(SEARCH(BO$1, $BM11)), ($K11/$BL11), "") | BP11: =IF(ISNUMBER(SEARCH(BP$1, $BM11)), ($K11/$BL11), "") | BQ11: =IF(ISNUMBER(SEARCH(BQ$1, $BM11)), ($K11/$BL11), "") -> 3500000 | BR11: =IF(ISNUMBER(SEARCH(BR$1, $BM11)), ($K11/$BL11), "") -> 3500000 | BS11: =IF(ISNUMBER(SEARCH(BS$1, $BM11)), ($K11/$BL11), "") -> 3500000 | BT11: =IF(ISNUMBER(SEARCH(BT$1, $BM11)), ($K11/$BL11), "") -> 3500000 | BU11: =IF(ISNUMBER(SEARCH(BU$1, $BM11)), ($K11/$BL11), "") | ... CC11: =IF(ISNUMBER(SEARCH(CC$1, $BM11)), ($K11/$BL11), "")
A12: University of Bath Cellular Agriculture Manufacturing Hub (CARMA) | B12: Imagine being able to manufacture food anywhere in the world, or even in space, so everyone, everywhere, has enough nutritious food to eat! This dream can be achieved through Cellular Agriculture (Cell Ag). Cell Ag enables the production of food products that would normally come from an animal, such as meat and milk from cows, or from monocultures of crops such as oil palm trees, without having to keep increasing animal or plant numbers to feed our growing global population. Cell Ag, uses biological cell-level processes to create food via the 'building blocks of life' - the proteins, fats and carbohydrates. By delivering these building blocks, Cell Ag will transform food production by complementing traditional food production, so not only can we feed the world, but we can manufacture the food so that sustainability and social responsibility is embedded from the outset. Why would we wish to use Cell Ag rather than animals? Let's take the example of the building block, protein, from traditional meat. Life Cycle Assessments have shown that when comparing traditional meat manufacturing against the expected benefits of using Cell Ag, there is a predicted reduction in greenhouse gas emissions, and land use, of up to 95%. The analysis also estimates that we could achieve up to 50% reduction in the use of water, compared to cattle farming. And we could reduce need for intensive farming so improving animal welfare too. So, with these benefits and the urgent need to achieve Net Zero Manufacturing and protect the planets resources. Why do we not have Cell Ag manufacturing in our homes or across all our food manufacturing sectors? There are several reasons - and our research will remove these blockers to Cell Ag manufacturing. Current status of Cell Ag Manufacturing research and outputs in the UK: In the UK (and across the World), there are pockets of excellent research being done, but little that focuses on delivering useable and scalable manufacturing machinery, processes, and systems in a coherent manner. The research tends to be in silos and focussed on aspects of the Manufacturing Value Chain. There are fundamental areas of research that need to be delivered to enable us to realise the Cell Ag potential, as well as transforming current research outputs to be useable. Through this Hub we will bring together the pockets of excellence in the UK, and deliver a coherent and targeted research programme that will ensure the UK Cell Ag research ecosystem is world-leading and has manufacturing impact. Rather than target a particular sector/type of food/product - the Hub will deliver manufacturing research which will enable production of food building blocks at local, regional and international levels. Our vision is to be the world leader in delivering materials, manufacturing processes and skills to escalate the world's adoption of sustainable Cell Ag food production. We will achieve this through becoming the net exporter of the building blocks of life. | D12: airtable | E12: 21214469 | F12: 12302109 | G12: GBP | H12: 26130285 | I12: 15655848 | J12: =E12*1.19 -> 25245218 | K12: =F12*1.19 -> 14639510 | L12: Awarded | M12: checked | N12: https://gtr.ukri.org/projects?ref=EP%2FX038114%2F1 | O12: grant.13519746 | R12: Original award amount is GBP 21,214,469 with GBP 12,302,109 coming from government. | S12: GFI Europe helped with the proposal and will sit on the advisory board. | T12: Marianne Ellis | U12: Chemical Engineering | V12: University of Bath | W12: University | X12: UK | Y12: Europe | Z12: n/a | AD12: Royal Agricultural University, University College London (UCL), University of Aberystwyth, University of Birmingham, 3D Bio-Tissues Ltd, Campden BRI, Cellular Agriculture Ltd, Clean Food Group, Hoxton Farms, MilliporeSigma, Multus Biotechnology Limited, Naturbeads Ltd, Qkine Ltd, Quest Meat, Roslin Technologies Limited, Veolia Water Technologies, Ivy Farm Technologies Limited | AE12: Yes | AI12: 45108 | AJ12: 7 | AK12: Not started | AL12: 3732898 | AM12: UK Research and Innovation (UKRI) | AN12: Engineering and Physical Sciences Research Council (EPSRC) | AO12: research hub | AQ12: Joint public/private partnership | AR12: United Kingdom | AS12: Europe | AT12: Cross-cutting | AU12: CellAg | AW12: Research and development, Education and training | AX12: =IFERROR(INDEX('full database 2024'!AR:AR, MATCH(A12, 'full database 2024'!B:B, 0)), "") | AZ12: cross-cutting | BA12: checked | BD12: 45014 | BE12: 45779 | BF12: checked | BH12: checked | BI12: Tier 2 (Significant GFI involvement) | BJ12: 2023 | BK12: 2030 | BL12: =BK12-BJ12+1 -> 8 | BM12: =TEXTJOIN(", ", TRUE, SEQUENCE(1, BL12, BJ12)) -> 2023, 2024, 2025, 2026, 2027, 2028, 2029, 2030 | BN12: =IF(ISNUMBER(SEARCH(BN$1, $BM12)), ($K12/$BL12), "") | BO12: =IF(ISNUMBER(SEARCH(BO$1, $BM12)), ($K12/$BL12), "") | BP12: =IF(ISNUMBER(SEARCH(BP$1, $BM12)), ($K12/$BL12), "") | BQ12: =IF(ISNUMBER(SEARCH(BQ$1, $BM12)), ($K12/$BL12), "") -> 1829938.7 | BR12: =IF(ISNUMBER(SEARCH(BR$1, $BM12)), ($K12/$BL12), "") -> 1829938.7 | BS12: =IF(ISNUMBER(SEARCH(BS$1, $BM12)), ($K12/$BL12), "") -> 1829938.7 | BT12: =IF(ISNUMBER(SEARCH(BT$1, $BM12)), ($K12/$BL12), "") -> 1829938.7 | BU12: =IF(ISNUMBER(SEARCH(BU$1, $BM12)), ($K12/$BL12), "") -> 1829938.7 | ... CC12: =IF(ISNUMBER(SEARCH(CC$1, $BM12)), ($K12/$BL12), "")
A13: ARRIVAL (ARRIVAL of Cellular Agriculture-Enabling biotechnology for Future Food Production) | B13: Global food production must increase more than 60% towards 2050, and as a result, there has been increasing pressure on the livestock sector to meet the growing demand for high-value animal protein. Although plant-based alternatives have a lot of potentials, these cannot truly mimic animal proteins, recreate the nutritional value, nor the mouthfeel, taste, or functionality. Also, from a circular bioeconomy perspective, increased recycling of waste streams from food production will be necessary. We will employ ground-breaking new, enabling, and fundamentally different technologies to produce food proteins by Cellular Agriculture (CellAg). There are two kinds of CellAg production systems, precision fermentation, and cultured meat, and in ARRIVAL we will use both to produce milk, egg, and meat proteins, homologous to proteins normally produced through conventional agriculture, using Norwegian raw materials and by-products as input. CellAg is a revolution in food production that can lead to major changes in agricultural production and ownership, land use, policymaking, food habits, and ethical questions. In ARRIVAL we aim to enable wider implementation of alternative animal protein sources in food production chains, as well as preparing society, consumers, and the food industry for the potential impacts of this radical shift in production methods. In addition to investigating the technological changes CellAg represents, we will through a transdisciplinary approach explore the foundations that must be laid before Norwegian consumers and society will and can adapt to this technology. Through ARRIVAL we will develop enabling biotechnology and knowledge, which will improve and modernize the existing land-based food industry. The novel biotechnological methodology to be developed will in long term potentially be the foundation of a new kind of Norwegian food industry that will produce tomorrow's food in a smart, sustainable, and innovative way. | D13: airtable | E13: 20000000 | F13: 20000000 | G13: NOK | H13: 1993440 | I13: 1993440 | J13: =E13*0.087 -> 1740000 | K13: =F13*0.087 -> 1740000 | L13: Awarded | M13: checked | N13: https://nofima.com/press-release/norwegian-focus-on-new-food-technology/ | O13: grant.13201908 | R13: Original award amount is NOK 20,000,000. | T13: Sissel Beate Rønning | U13: n/a | V13: Nofima | W13: For profit | X13: Norway | Y13: Europe | Z13: n/a | AD13: Sintef Industry, OsloMet, Ruralis, The Norwegian Board of Technology, Nortura AS, Norilia AS, TINE AS | AE13: Yes | AI13: 44927 | AJ13: 4 | AK13: In progress | AL13: 498360 | AM13: Research Council of Norway | AQ13: Government | AR13: Norway | AS13: Europe | AT13: Cross-cutting | AU13: CellAg | AW13: Research and development | AX13: =IFERROR(INDEX('full database 2024'!AR:AR, MATCH(A13, 'full database 2024'!B:B, 0)), "") | AZ13: Cell culture media, Host strain development , Bioprocess design | BD13: 44959 | BE13: 45779 | BI13: Tier 4 (No GFI involvement) | BJ13: 2023 | BK13: 2027 | BL13: =BK13-BJ13+1 -> 5 | BM13: =TEXTJOIN(", ", TRUE, SEQUENCE(1, BL13, BJ13)) -> 2023, 2024, 2025, 2026, 2027 | BN13: =IF(ISNUMBER(SEARCH(BN$1, $BM13)), ($K13/$BL13), "") | BO13: =IF(ISNUMBER(SEARCH(BO$1, $BM13)), ($K13/$BL13), "") | BP13: =IF(ISNUMBER(SEARCH(BP$1, $BM13)), ($K13/$BL13), "") | BQ13: =IF(ISNUMBER(SEARCH(BQ$1, $BM13)), ($K13/$BL13), "") -> 348000 | BR13: =IF(ISNUMBER(SEARCH(BR$1, $BM13)), ($K13/$BL13), "") -> 348000 | BS13: =IF(ISNUMBER(SEARCH(BS$1, $BM13)), ($K13/$BL13), "") -> 348000 | BT13: =IF(ISNUMBER(SEARCH(BT$1, $BM13)), ($K13/$BL13), "") -> 348000 | BU13: =IF(ISNUMBER(SEARCH(BU$1, $BM13)), ($K13/$BL13), "") -> 348000 | ... CC13: =IF(ISNUMBER(SEARCH(CC$1, $BM13)), ($K13/$BL13), "")
A14: Sustainable use of marine and industrial waters to unlock the potential of seaweeds as a future food source | B14: Seaweed farming offers a unique possibility to feed the growing global population without putting further pressure on access to land and fresh water.Also, there is no need for fertilizers but rather a net uptake of nutrients, thereby mitigating eutrophication. Seaweed farming offers a unique possibility to feed the growing global population without putting further pressure on access to land and fresh water. Also, there is no need for fertilizers but rather a net uptake of nutrients, thereby mitigating eutrophication. SUSWEED aims at releasing the potential of Swedish seaweed as a future sustainable food source according to models which have positive effects on both marine and industrial waters. This will be achieved via development of novel cultivation techniques for Ulva fenestrata and Palmaria palmata based both in the ocean and as part of a system to purify nutrient-rich food industry process waters. Harvested seaweed will be stabilized and pre-processed into tasty, nutritious, and safe intermediate raw materials to incorporate in new fish-based and vegan food products. These are developed to reach broad acceptance for seaweed as a new sustainable food commodity. SUSWEED puts great emphasis on solving non-technical challenges of the new industrial symbiosis between seaweed farmers and generators of process waters and other resources which can make the seaweed industry more sustainable. Safety is carefully addressed by monitoring levels of heavy metals and their accessibility for uptake. The project is built on a strong multidisciplinary partnership with industries and academia which has pioneered the development of state-of-the-art research and applications concerning seaweed in Sweden during the last 10 years. | D14: airtable | E14: 19991495 | F14: 19991495 | G14: SEK | H14: 1879201 | I14: 1879201 | J14: =E14*0.091 -> 1819226 | K14: =F14*0.091 -> 1819226 | L14: Awarded | M14: checked | N14: https://research.chalmers.se/en/project/11357 | V14: University of Gothenburg | X14: Sweden | Y14: Europe | AI14: 44938 | AJ14: 61 | AK14: Ended | AL14: 30807 | AM14: Swedish Research Council for Environment Agricultural Sciences and Spatial Planning (FORMAS) | AQ14: Government | AR14: Sweden | AS14: Europe | AT14: Plant-based | AW14: Research and development | AX14: =IFERROR(INDEX('full database 2024'!AR:AR, MATCH(A14, 'full database 2024'!B:B, 0)), "") | AZ14: End product formulation, Crop development, Ingredient optimisation | BD14: 45596 | BE14: 45596 | BJ14: 2023 | BK14: 2031 | BL14: =BK14-BJ14+1 -> 9 | BM14: =TEXTJOIN(", ", TRUE, SEQUENCE(1, BL14, BJ14)) -> 2023, 2024, 2025, 2026, 2027, 2028, 2029, 2030, 2031 | BN14: =IF(ISNUMBER(SEARCH(BN$1, $BM14)), ($K14/$BL14), "") | BO14: =IF(ISNUMBER(SEARCH(BO$1, $BM14)), ($K14/$BL14), "") | BP14: =IF(ISNUMBER(SEARCH(BP$1, $BM14)), ($K14/$BL14), "") | BQ14: =IF(ISNUMBER(SEARCH(BQ$1, $BM14)), ($K14/$BL14), "") -> 202136.23 | BR14: =IF(ISNUMBER(SEARCH(BR$1, $BM14)), ($K14/$BL14), "") -> 202136.23 | BS14: =IF(ISNUMBER(SEARCH(BS$1, $BM14)), ($K14/$BL14), "") -> 202136.23 | BT14: =IF(ISNUMBER(SEARCH(BT$1, $BM14)), ($K14/$BL14), "") -> 202136.23 | BU14: =IF(ISNUMBER(SEARCH(BU$1, $BM14)), ($K14/$BL14), "") -> 202136.23 | ... CC14: =IF(ISNUMBER(SEARCH(CC$1, $BM14)), ($K14/$BL14), "")
A15: GRAPHENE MEMBRANES - FUTURE ENABLER FOR BETTER PLANT-BASED FOODS AND BEVERAGES | B15: The aim of this project is to explore the application of graphene oxide (GO) membranes for more healthy, sustainable, and responsible plant-based food and beverages production. Graphene has unique applications in chemistry and biology due to possibility of attaching various chemical functional group. This allows construction of active membranes to form a perfect separation of organic molecule. A plant-based lifestyle can lower the impact of climate change, but exclusive plant-based diets could also have negative effect on humans. This project resolves these challenges by applying a novel membrane technology to plant-based foods and beverages separation. Obtained knowledge and scientific results could have multiple applications and far reaching impact. The project will target selective removal of sugars, alcohol, and acids to obtain a more balanced plant-based diet, by investigating and applying novel membrane technology. Currently, the only way of reducing sugars is conversion into alcohol or acids and subsequent removal, resulting in reduced nutritional value due to micronutrient oxidation and degradation of bio-active proteins. Reduction of sugars will provide healthier variants, improve glycemic index and balance protein/carbohydrate/fiber ratios, which are problematic in many plant foods due to low protein/fiber content. Similarly, direct acid removal from juices or fermented foods will reduce risk of dental damage. Finally, any food and beverages produced by yeast fermentation could benefit from selective alcohol removal. The challenges will be to develop and eventually improve membrane selectivity for the proposed targets, optimize flux potential, reduce fouling and increase chemical resistance during cleaning. Since the membrane composition is a key element in achieving the proposed results, a cross functional collaboration is necessary. GO membrane tasks will be addressed by the Graphene Engineering and Innovation Centre at UoM (UK) and DTU (DK) using state-of-the-art facilities equipped with different microscopies, electronic/optical measuring, Nanoscale Thermal Analysis, and chemical modification capabilities. Process understanding, validation and evaluation will take place at Carlsberg Research Laboratory (CRL) utilizing extensive analytical, fermentation, and beverage capabilities. As part of SYLPLANT, the consortium will work on the sequent objectives for the next three years: • Constructing & operating Arbiom’s first plant in France to reach 10,000 ton per year of ingredient production. • Validating the use of SylPro® in feed applications including aquafeed and petfood and insights. gathering consumer Figure 1: Arbiom’s first plant design • Developing the next generation of foods such as cheese analogs, meat-analogs, and specialized nutrition products with Arbiom’s ingredient. | D15: airtable | E15: 19980675 | F15: 19980675 | G15: DKK | H15: 2912812 | I15: 0 | J15: =E15*0.13 -> 2597487.8 | K15: =F15*0.13 -> 2597487.8 | L15: Awarded | M15: checked | N15: https://www.carlsbergfondet.dk/en/Forskningsaktiviteter/Bevillingsstatistik/Bevillingsoversigt/CF21_0677_Birgitte-Skadhauge | O15: need to check | R15: Original award amount is DKK 19,980,675. | T15: Birgitte Skadhauge | U15: n/a | V15: Carlsberg Research Laboratory | W15: For profit | X15: Denmark | Y15: Europe | Z15: n/a | AD15: University of Manchester, Technical University of Denmark | AE15: Yes | AI15: 44348 | AJ15: 3 | AK15: Completed | AL15: 970937 | AM15: Carlsberg Foundation | AO15: TRL 1-3 | AQ15: Non-profit | AR15: Denmark | AS15: Europe | AT15: Plant-based | AW15: Research and development | AX15: =IFERROR(INDEX('full database 2024'!AR:AR, MATCH(A15, 'full database 2024'!B:B, 0)), "") | AZ15: Ingredient optimisation | BD15: 45421 | BE15: 45448 | BI15: Tier 4 (No GFI involvement) | BJ15: 2021 | BK15: 2024 | BL15: =BK15-BJ15+1 -> 4 | BM15: =TEXTJOIN(", ", TRUE, SEQUENCE(1, BL15, BJ15)) -> 2021, 2022, 2023, 2024 | BN15: =IF(ISNUMBER(SEARCH(BN$1, $BM15)), ($K15/$BL15), "") | BO15: =IF(ISNUMBER(SEARCH(BO$1, $BM15)), ($K15/$BL15), "") -> 649371.94 | BP15: =IF(ISNUMBER(SEARCH(BP$1, $BM15)), ($K15/$BL15), "") -> 649371.94 | BQ15: =IF(ISNUMBER(SEARCH(BQ$1, $BM15)), ($K15/$BL15), "") -> 649371.94 | BR15: =IF(ISNUMBER(SEARCH(BR$1, $BM15)), ($K15/$BL15), "") -> 649371.94 | BS15: =IF(ISNUMBER(SEARCH(BS$1, $BM15)), ($K15/$BL15), "") | BT15: =IF(ISNUMBER(SEARCH(BT$1, $BM15)), ($K15/$BL15), "") | BU15: =IF(ISNUMBER(SEARCH(BU$1, $BM15)), ($K15/$BL15), "") | ... CC15: =IF(ISNUMBER(SEARCH(CC$1, $BM15)), ($K15/$BL15), "")
A16: Cellular food for sustainable production and innovative food concepts (CellFood) | B16: - With CellFood, we can, over the next five years, support the development of projects ranging from technological solutions to consumer acceptance. This will generate more knowledge on both the development of cellular foods and how we – over time – will be able to sell the products to the consumers. One thing is to make the products, another thing is to encourage people that the products are something they should consider being a part of their future, sustainable diet. | D16: airtable | E16: 15000000 | F16: 15000000 | G16: DKK | H16: 2135505 | I16: 0 | J16: =E16*0.13 -> 1950000 | K16: =F16*0.13 -> 1950000 | L16: Awarded | M16: checked | N16: https://dca.au.dk/en/current-news/news/show/artikel/institut-for-foedevarer-saetter-skub-i-udviklingen-af-cellulaere-foedevarer | O16: n/a | R16: Original award amount is DKK 15,000,000. | S16: GFI U.S. and GFI Europe provided letters of support. | T16: Jette Feveile Young | U16: Food Science | V16: Aarhus University | W16: University | X16: Denmark | Y16: Europe | Z16: n/a | AC16: Liisa Lähteenmäki; Stig Purup; Esben Skipper Sørensen; Clarissa Schwab; Steen Brock; Stella Spanou; Jesper Emborg; Mogens Sandø Lund | AD16: Aarhus University | AE16: No | AF16: 44321 | AG16: 2021 | AI16: 44774 | AJ16: 4 | AK16: In progress | AL16: 533876 | AM16: Aarhus University Research Foundation (AUFF) | AQ16: Non-profit | AR16: Denmark | AS16: Europe | AT16: Cross-cutting | AU16: CellAg | AW16: Research and development, Education and training | AX16: =IFERROR(INDEX('full database 2024'!AR:AR, MATCH(A16, 'full database 2024'!B:B, 0)), "") | AZ16: Cell line development | BD16: 44980 | BE16: 45566 | BF16: checked | BG16: https://docs.google.com/document/d/1tLlVtTn3KFv7qG4X8ZMC2gpJaQ1j-sRhGUMvrdp5kOM/edit?usp=share_link | BI16: Tier 3 (Minimal GFI involvement, e.g. LoS) | BJ16: 2022 | BK16: 2026 | BL16: =BK16-BJ16+1 -> 5 | BM16: =TEXTJOIN(", ", TRUE, SEQUENCE(1, BL16, BJ16)) -> 2022, 2023, 2024, 2025, 2026 | BN16: =IF(ISNUMBER(SEARCH(BN$1, $BM16)), ($K16/$BL16), "") | BO16: =IF(ISNUMBER(SEARCH(BO$1, $BM16)), ($K16/$BL16), "") | BP16: =IF(ISNUMBER(SEARCH(BP$1, $BM16)), ($K16/$BL16), "") -> 390000 | BQ16: =IF(ISNUMBER(SEARCH(BQ$1, $BM16)), ($K16/$BL16), "") -> 390000 | BR16: =IF(ISNUMBER(SEARCH(BR$1, $BM16)), ($K16/$BL16), "") -> 390000 | BS16: =IF(ISNUMBER(SEARCH(BS$1, $BM16)), ($K16/$BL16), "") -> 390000 | BT16: =IF(ISNUMBER(SEARCH(BT$1, $BM16)), ($K16/$BL16), "") -> 390000 | BU16: =IF(ISNUMBER(SEARCH(BU$1, $BM16)), ($K16/$BL16), "") | ... CC16: =IF(ISNUMBER(SEARCH(CC$1, $BM16)), ($K16/$BL16), "")
A17: Microbial Food Hub | B17: We propose the creation of an Engineering Biology Hub for Microbial Foods. The aim of the Hub is to harness the joint potential of two important scientific fields - engineering biology and microbial foods - in order to transform our existing food production system into one that is better for the environment, more resilient to climatic or political shocks, and that gives consumers healthier and tastier products. Background: Current food systems are unsustainable. Traditional farming and agriculture contribute significantly to climate change, and this is exacerbated by the alarming levels of food waste. Damage to the planet is mirrored by impacts on human health: a significant portion of the global population suffers malnutrition, while diseases linked to ultra-processed and high-calorie diets continue to rise. The way we produce and consume food has to change, and to change quickly if we are to have any chance of meeting targets for clean growth. Microbial foods - produced by microorganisms like yeast and fungi - offer a way to make this urgently needed transformation. Microbial foods are produced using different types of fermentation, with this process employed to produce large quantities of protein and other nutrients (biomass fermentation), to modulate and process plant and animal-derived products (traditional fermentation) or to produce new food ingredients (precision fermentation). Microbes grow rapidly, don't need large amounts of land or water to grow, and can use food by-products ('food waste') as feedstocks. In addition, microbial foods are less affected by adverse weather and can be produced locally - reducing transport costs, carbon footprint, and our dependence on food imports. Engineering biology applies engineering principles to biology, enabling scientists to build and manufacture novel biological systems and products. Tools from engineering biology have recently been applied to optimise microbial food production, and microbes can now be manipulated to be more productive, tastier and more nutritious. Applying engineering biology to microbial foods has the potential to radically change the way food is produced, and this creates an important and timely opportunity to address some of the most critical health and sustainability challenges of our time. The Hub: The first of its kind in the world, the new Hub will build on the UK's world-leading expertise and facilities in engineering biology and microbial foods. It will bring together academics, industrial partners, food organisations and consumers in a wide-ranging and ambitious programme of work that creates a clear route from scientific research to new food products on the shelf. At the heart of the Hub's activity will be eleven research projects, each addressing a separate challenge that needs to be overcome if large-scale production of diverse microbial food products is to be achieved. Project will use cutting-edge engineering biology methods, and will benefit from the Hub's additional focus on education, regulation and commercialisation, to ensure research outputs are translated into meaningful benefits. Overall, our objectives are : - To advance research into how engineering biology can be used to produce microbial foods - To develop new capabilities for developing microbial foods using engineering biology - To open new routes for this research to benefit human health and environmental sustainability Meeting these objectives will establish the Hub as an internationally-recognised reference for research, innovation and translation in the application of engineering biology to microbial foods - demonstrating UK leadership in this field, attracting the best global talent, and delivering more sustainable, productive, resilient and healthy food systems. Technical Summary We propose an Engineering Biology Hub for Microbial Foods, integrating world-leading research and innovation, education, translation and commercialisation. The overarching vision is to harness the joint potentials of engineering biology and the microbial food revolution to create and deliver a more sustainable, productive, resilient and healthy food system. The Hub's research programme encompasses projects focused on 'Applications' (biomass fermentation, traditional fermentation, precision fermentation), and 'Capabilities' (scale-up, artificial intelligence, strain engineering, food technology and nutrition) at the interface of engineering biology and microbial foods. Projects will be underpinned by a range of cutting-edge tools and approaches from engineering biology, including automation, microbial community design, bioprocessing, modelling, systems biology and strain engineering. To ensure research outputs are translated into meaningful change, projects are complemented by a range of different 'Paths' (e.g. commercialisation, education, regulation, communication, etc). The Hub's objectives across these areas are: 'Applications': To advance engineering biology research to produce microbial foods. 'Capabilities': To develop new capabilities for the development of microbial foods using engineering biology (for the members of the Hub and beyond). 'Paths': To support present and future research into engineering biology for microbial foods, and translation of this research into positive, real-world impacts. Meeting these three objectives will establish UK leadership in the field, with the Hub an internationally-recognised reference for this application of engineering biology. | D17: airtable | E17: 14000000 | F17: 12634909 | G17: GBP | H17: 17427480 | I17: 14937840 | J17: =E17*1.19 -> 16660000 | K17: =F17*1.19 -> 15035542 | L17: Awarded | M17: checked | N17: https://www.foodingredientsfirst.com/news/uk-government-injects-%C2%A312m-into-microbial-food-hub-for-alt-protein-innovation.html | O17: grant.14049711 | T17: Rodrigo Ledesma-Amaro | V17: Imperial College London | W17: University | X17: UK | Y17: Europe | AC17: Professors Paul Freemont (Department of Infectious Disease), Karen Polizzi (Department of Chemical Engineering), Gary Frost (Department of Metabolism, Digestion and Reproduction), Tom Ellis (Department of Bioengineering) and Geoff Baldwin (Department of Life Sciences). | AE17: No | AH17: 45331 | AI17: 45383 | AJ17: 5 | AK17: In progress | AL17: 3485496 | AM17: UK Research and Innovation (UKRI) | AN17: Biotechnology and Biological Sciences Research Council (BBSRC) | AQ17: Government | AR17: United Kingdom | AS17: Europe | AT17: Fermentation | AU17: PF | AW17: Research and development | AX17: =IFERROR(INDEX('full database 2024'!AR:AR, MATCH(A17, 'full database 2024'!B:B, 0)), "") | AZ17: cross-cutting | BD17: 45406 | BE17: 45779 | BF17: checked | BG17: https://docs.google.com/document/d/197_vHTSaVQSB77rGsyhQRGBpcoXMK26A/edit | BH17: checked | BJ17: 2024 | BK17: 2029 | BL17: =BK17-BJ17+1 -> 6 | BM17: =TEXTJOIN(", ", TRUE, SEQUENCE(1, BL17, BJ17)) -> 2024, 2025, 2026, 2027, 2028, 2029 | BN17: =IF(ISNUMBER(SEARCH(BN$1, $BM17)), ($K17/$BL17), "") | BO17: =IF(ISNUMBER(SEARCH(BO$1, $BM17)), ($K17/$BL17), "") | BP17: =IF(ISNUMBER(SEARCH(BP$1, $BM17)), ($K17/$BL17), "") | BQ17: =IF(ISNUMBER(SEARCH(BQ$1, $BM17)), ($K17/$BL17), "") | BR17: =IF(ISNUMBER(SEARCH(BR$1, $BM17)), ($K17/$BL17), "") -> 2505923.6 | BS17: =IF(ISNUMBER(SEARCH(BS$1, $BM17)), ($K17/$BL17), "") -> 2505923.6 | BT17: =IF(ISNUMBER(SEARCH(BT$1, $BM17)), ($K17/$BL17), "") -> 2505923.6 | BU17: =IF(ISNUMBER(SEARCH(BU$1, $BM17)), ($K17/$BL17), "") -> 2505923.6 | ... CC17: =IF(ISNUMBER(SEARCH(CC$1, $BM17)), ($K17/$BL17), "")
A18: Like-A-Pro: From niche to mainstream - alternative proteins for everybody and everywhere | B18: The interest of Europeans in alternative proteins is becoming clear and this trend is the perfect ground for the dietary shift towards sustainable and healthy nutrition and food systems, in line with the ambitions of the EU Green Deal, Farm to Fork strategy and EU’s climate goals. Yet, this interest is not reflected in the European dietary patterns, as alternative proteins are mainly consumed by early adopters, while the majority is less receptive towards alternatives or have limited possibilities to integrate them in the diets. This gap between interest and consumption is due to obstacles in the food environments such as product limited offering, suboptimal product taste, isolated product placement in shops or menus etc. Without overcoming these obstacles, alternative proteins will remain a niche. LIKE-A-PRO aims at mainstreaming alternative proteins, making them accessible, available, and acceptable to everybody (from children to elderly, vulnerable groups) and everywhere (across Europe, in urban, peri-urban, and rural areas). To achieve this, key representatives along the entire alternative protein value chain (growers, producers, cooks, retailers, consumers, researchers) will work together in a trans-disciplinary consortium. To improve European food environments towards fostering alternative protein consumption, practical solutions will be co-designed with citizens. This social innovation will take place in 11 living labs and in 4 real life food environments. For a diversified alternative protein offering, 16 new alternative protein products will be developed with 7 sustainable, healthy, and novel sources. To secure result deployment, the project will actively involve middle food system actors (+35,000 companies) – via co-creation and capacity building. For a maximised impact, innovative communication campaigns will be launched in 6 countries, reaching 8 M citizens in 4 years. | D18: airtable | E18: 13909093 | F18: 11999660 | G18: EUR | H18: 14715959 | I18: 12695760 | J18: 13909093 | K18: 11999660 | L18: Awarded | M18: checked | N18: https://cordis.europa.eu/project/id/101083961 | O18: grant.13029417 | R18: Original award amount is €13,909,092.76 with the EU government contribution being €11,999,659.64. | T18: Robin Simsa | U18: n/a | V18: ASOCIACION PARA LA INVESTIGACION DESARROLLO E INNOVACION DEL SECTOR AGROALIMENTARIO (ADISA) | W18: For profit | X18: Spain | Y18: Europe | Z18: n/a | AD18: Asociacion para la investigacion desarrollo e innovacion del sector agroalimentario , Proti Farm R&D BV, Ynsect, Moreforsking AS, Rimfrost AS, Calidris Bio, Asociacion professional de productores de sustratos y hongos de la rioja Navarra y arragon, Kinoko-Tech , Celabor SCRL, Biozoon GmbH, Revo Foods GmbH, Flowfood AS, Carnes de teruel SA, Naturuel SL, Collaborating centre on sustainable consumption and production gGmbH, SWPS Uniwersytet Humanistycznospoleczny, The American College of Greece Research Center, ITC – inovacijsko tehnoloski grozd murska sobota, Zeytince ekolojik yasami desteklemedernegi, Demos Research Institute OY, Foodlab Proef, Basque culinary center fundazioa, Stichting Food Valley, FBCD AS, Spread European Safety GEIE, Federazione Italiana dell Industiaalimentare Associazione, Federacao das Industrias Portuguesas Agroalimentares, Federacion Espanola de Industrias de la Alimentacion y Bebidas, Syndesmos Ellinikon Viomichanion Trofimon Somateio, Tuerkiye Suet et Gida Sanayicileri ve Uereticileri Birligi Dernegi, Gospodarska Zbornica Slovenije, Lebensmittelversuchsanstalt, Potravinarska Komora Ceske Republiky, Association Nationale des Industries Alimentaires, Eurizon SL, Green Food Lab B.V., Fundacion Gaiker, Alimentos Sanygran S.L., Safe Food Advocacy Europe, 21 Markets BV | AE18: Yes | AI18: 44866 | AJ18: 4 | AK18: In progress | AL18: 3678990 | AM18: European Commission | AN18: Cluster 6: Food, Bioeconomy Natural Resources, Agriculture and Environment | AQ18: Joint public/private partnership | AR18: EU | AS18: Europe | AT18: Plant-based | AU18: TF | AW18: Research and development, Education and training, Research infrastructure | AX18: =IFERROR(INDEX('full database 2024'!AR:AR, MATCH(A18, 'full database 2024'!B:B, 0)), "") | AZ18: Consumer and market research, Env/impact assessments, Health/nutrition | BD18: 44984 | BE18: 45779 | BI18: Tier 4 (No GFI involvement) | BJ18: 2022 | BK18: 2026 | BL18: =BK18-BJ18+1 -> 5 | BM18: =TEXTJOIN(", ", TRUE, SEQUENCE(1, BL18, BJ18)) -> 2022, 2023, 2024, 2025, 2026 | BN18: =IF(ISNUMBER(SEARCH(BN$1, $BM18)), ($K18/$BL18), "") | BO18: =IF(ISNUMBER(SEARCH(BO$1, $BM18)), ($K18/$BL18), "") | BP18: =IF(ISNUMBER(SEARCH(BP$1, $BM18)), ($K18/$BL18), "") -> 2399932 | BQ18: =IF(ISNUMBER(SEARCH(BQ$1, $BM18)), ($K18/$BL18), "") -> 2399932 | BR18: =IF(ISNUMBER(SEARCH(BR$1, $BM18)), ($K18/$BL18), "") -> 2399932 | BS18: =IF(ISNUMBER(SEARCH(BS$1, $BM18)), ($K18/$BL18), "") -> 2399932 | BT18: =IF(ISNUMBER(SEARCH(BT$1, $BM18)), ($K18/$BL18), "") -> 2399932 | BU18: =IF(ISNUMBER(SEARCH(BU$1, $BM18)), ($K18/$BL18), "") | ... CC18: =IF(ISNUMBER(SEARCH(CC$1, $BM18)), ($K18/$BL18), "")
A19: HealthFerm: Innovative pulse and cereal-based food fermentations for human health and sustainable diets | B19: Food fermentation is a natural process in which food components are converted by microbial growth of desired yeast and bacteria and enzymes. It is an ancient technique purported to promote the growth of beneficial bacteria in the gut. Food and health experts on the EU-funded HealthFerm project will advance fermentation technology and enable the transition from traditional to sustainable grain-based fermented foods. These will be rich in protein and designed to offer maximum health benefits to EU consumers. For optimal results, they will unravel the relationship between fermentation, the gut microbiome, grain-based foods and health. Moreover, they will identify and employ suitable microorganisms in the development of novel grain-based food sources and assess their impact on gut health. | D19: airtable | E19: 11 303 944.75 | F19: 11 303 944.75 | G19: EUR | J19: 11303945 | K19: 11303945 | L19: Awarded | M19: checked | N19: https://cordis.europa.eu/project/id/101060247/reporting | O19: grant.12941144 | R19: Original award amount is EUR 13,100,000 with EUR 11.3MM from European Union’s Horizon Europe Framework Programme for Research and Innovation. EUR 1.8MM from the Swiss government listed separately | T19: Christophe Courtin | U19: Food and Microbial Technology | V19: Katholieke Universiteit Leuven (KU Leuven) | W19: University | X19: Belgium | Y19: Europe | Z19: n/a | AD19: Puratos Nv, Vib Vzw, Vrije Universiteit Brussel, Chr. Hansen A/S, Kobenhavns Universitet, Healthgrain Forum Ry, Helsingin Yliopisto, Ita-Suomen Yliopisto, VTT Technical Research Centre of Finland Ltd, Turun Yliopisto, Valio Oy, Centre de Recherche de l’Institut Paul Bocuse, EURICE - European Research and Project Office GmbH, Libera Universita Di Bolzano, Institutul De Biologie Bucuresti, Sveriges Lantbruksuniversitet, Chalmers Tekniska Hogskola Ab, Umea Universitet, Eidgenössische Technische Hochschule Zürich, Planted Foods AG, Bridge2Food (Foodcompanions BV) | AE19: Yes | AI19: 44805 | AJ19: 4 | AK19: In progress | AL19: 3470337 | AM19: European Commission | AN19: Cluster 6: Food, Bioeconomy Natural Resources, Agriculture and Environment | AQ19: Government | AR19: EU | AS19: Europe | AT19: Plant-based | AU19: TF | AW19: Research and development | AX19: =IFERROR(INDEX('full database 2024'!AR:AR, MATCH(A19, 'full database 2024'!B:B, 0)), "") | AZ19: Ingredient optimisation, Health/nutrition, Consumer and market research | BD19: 44985 | BE19: 45035 | BI19: Tier 2 (Significant GFI involvement) | BJ19: 2022 | BK19: 2026 | BL19: =BK19-BJ19+1 -> 5 | BM19: =TEXTJOIN(", ", TRUE, SEQUENCE(1, BL19, BJ19)) -> 2022, 2023, 2024, 2025, 2026 | BN19: =IF(ISNUMBER(SEARCH(BN$1, $BM19)), ($K19/$BL19), "") | BO19: =IF(ISNUMBER(SEARCH(BO$1, $BM19)), ($K19/$BL19), "") | BP19: =IF(ISNUMBER(SEARCH(BP$1, $BM19)), ($K19/$BL19), "") -> 2260789 | BQ19: =IF(ISNUMBER(SEARCH(BQ$1, $BM19)), ($K19/$BL19), "") -> 2260789 | BR19: =IF(ISNUMBER(SEARCH(BR$1, $BM19)), ($K19/$BL19), "") -> 2260789 | BS19: =IF(ISNUMBER(SEARCH(BS$1, $BM19)), ($K19/$BL19), "") -> 2260789 | BT19: =IF(ISNUMBER(SEARCH(BT$1, $BM19)), ($K19/$BL19), "") -> 2260789 | BU19: =IF(ISNUMBER(SEARCH(BU$1, $BM19)), ($K19/$BL19), "") | ... CC19: =IF(ISNUMBER(SEARCH(CC$1, $BM19)), ($K19/$BL19), "")
A20: Grant to Enifer for commercial-scale mycoprotein facility | B20: Finnish biotech startup Enifer announces that it has received a grant worth over €12 million from the European Union’s NextGenerationEU programme, to construct its first commercial-scale mycoprotein facility in the Uusimaa region (the exact location has not been revealed). | D20: airtable | E20: 12000000 | F20: 12000000 | G20: EUR | H20: 13145700 | I20: 13145700 | J20: 12000000 | K20: 12000000 | L20: Awarded | M20: checked | N20: https://vegconomist.com/investments-finance/enifer-e12m-eu-grant-mycoprotein-facility-finland/?utm_medium=email&utm_source=rasa_io&utm_campaign=newsletter | R20: Original award amount is EUR 12,000,000 from the European Union’s NextGenerationEU programme, approved by Business Finland. | T20: Simo Ellilä | U20: n/a | V20: Enifer | W20: For profit | X20: Finland | Y20: Europe | Z20: n/a | AE20: No | AI20: 45301 | AJ20: 2 | AK20: In progress | AL20: 6572850 | AM20: European Commission | AN20: NextGenerationEU | AQ20: Government | AR20: EU | AS20: Europe | AT20: Fermentation | AU20: BF | AW20: Equipment and infrastructure | AX20: =IFERROR(INDEX('full database 2024'!AR:AR, MATCH(A20, 'full database 2024'!B:B, 0)), "") | AZ20: Bioprocess design | BD20: 45303 | BE20: 45303 | BI20: Tier 4 (No GFI involvement) | BJ20: 2024 | BK20: 2026 | BL20: =BK20-BJ20+1 -> 3 | BM20: =TEXTJOIN(", ", TRUE, SEQUENCE(1, BL20, BJ20)) -> 2024, 2025, 2026 | BN20: =IF(ISNUMBER(SEARCH(BN$1, $BM20)), ($K20/$BL20), "") | BO20: =IF(ISNUMBER(SEARCH(BO$1, $BM20)), ($K20/$BL20), "") | BP20: =IF(ISNUMBER(SEARCH(BP$1, $BM20)), ($K20/$BL20), "") | BQ20: =IF(ISNUMBER(SEARCH(BQ$1, $BM20)), ($K20/$BL20), "") | BR20: =IF(ISNUMBER(SEARCH(BR$1, $BM20)), ($K20/$BL20), "") -> 4000000 | BS20: =IF(ISNUMBER(SEARCH(BS$1, $BM20)), ($K20/$BL20), "") -> 4000000 | BT20: =IF(ISNUMBER(SEARCH(BT$1, $BM20)), ($K20/$BL20), "") -> 4000000 | BU20: =IF(ISNUMBER(SEARCH(BU$1, $BM20)), ($K20/$BL20), "") | ... CC20: =IF(ISNUMBER(SEARCH(CC$1, $BM20)), ($K20/$BL20), "")
A21: SYNAGRI: Developing synergies between the bioeconomy and regional food systems for a sustainable future | B21: The aim of SYNAGRI is to understand the capacity for integration between an emerging bioeconomy and regional food systems, and develop strategies to promote an integrated, sustainable food system. The project will contribute to theoretical developments in systems thinking, understand how food systems can be transformed through integration and its implications for social, environmental, and economic sustainability. Scenario evaluation will identify desirable trajectories and policy options to achieve them. The main outcome will be to advance a systems perspective on Norwegian food systems and assist Norway in identifying prospects for value creation through food system-bioeconomy integration. | D21: airtable | E21: 11955980 | F21: 11955980 | G21: NOK | H21: 1213201 | I21: 1213201 | J21: =E21*0.087 -> 1040170.3 | K21: =F21*0.087 -> 1040170.3 | L21: Awarded | M21: checked | N21: https://prosjektbanken.forskningsradet.no/en/project/FORISS/325403 | T21: Richard Helliwell | V21: STIFTELSEN RURALIS INSTITUTT FOR RURAL- OG REGIONALFORSKNING | X21: Norway | Y21: Europe | AI21: 44197 | AL21: 1213201 | AM21: Research Council of Norway | AQ21: Government | AR21: Norway | AS21: Europe | AT21: Cross-cutting | AU21: All | AW21: Research and development | AX21: =IFERROR(INDEX('full database 2024'!AR:AR, MATCH(A21, 'full database 2024'!B:B, 0)), "") | AZ21: Env/impact assessments | BD21: 45596 | BE21: 45596 | BJ21: 2021 | BK21: 2021 | BL21: =BK21-BJ21+1 -> 1 | BM21: =TEXTJOIN(", ", TRUE, SEQUENCE(1, BL21, BJ21)) -> 2021 | BN21: =IF(ISNUMBER(SEARCH(BN$1, $BM21)), ($K21/$BL21), "") | BO21: =IF(ISNUMBER(SEARCH(BO$1, $BM21)), ($K21/$BL21), "") -> 1040170.3 | BP21: =IF(ISNUMBER(SEARCH(BP$1, $BM21)), ($K21/$BL21), "") | BQ21: =IF(ISNUMBER(SEARCH(BQ$1, $BM21)), ($K21/$BL21), "") | BR21: =IF(ISNUMBER(SEARCH(BR$1, $BM21)), ($K21/$BL21), "") | BS21: =IF(ISNUMBER(SEARCH(BS$1, $BM21)), ($K21/$BL21), "") | BT21: =IF(ISNUMBER(SEARCH(BT$1, $BM21)), ($K21/$BL21), "") | BU21: =IF(ISNUMBER(SEARCH(BU$1, $BM21)), ($K21/$BL21), "") | ... CC21: =IF(ISNUMBER(SEARCH(CC$1, $BM21)), ($K21/$BL21), "")
A22: AlinOVeg: Innovating in plant-based food | B22: AlinOVeg's objective is to develop innovative solutions and products (pea and fava bean varieties, protein ingredients, plant-based alternatives to cheese and plant-based desserts) and to create a strong and sustainable French sector. To achieve this, AlinOVeg relies upon a development driven by consumers’ expectations. AlinOVeg will offer products with optimal functional, nutritional, and organoleptic qualities. In addition, the project will rely on the development of more sustainable processes thanks to a large varietal selection, new valorization processes and more resilient local sectors. AlinOVeg will also address farmers directly to better meet their needs and enable them to optimize the value of pea and fava bean crops. This 5-year project will be marked by key research and development milestones to remove technological barriers along the value chain. Supported by France 2030 as part of the call for projects operated by Bpifrance "Food Needs of Tomorrow" of the "Sustainable and Healthy Food" acceleration strategy, AlinOVeg aims to be launched on the world market in the coming years. | D22: airtable | E22: 11400000 | F22: 8300000 | G22: EUR | H22: 12110619 | I22: 8817380 | J22: 11400000 | K22: 8300000 | L22: Awarded | M22: checked | N22: https://www.futureofproteinproduction.com/post/pea-and-fava-bean-focus-of-new-multi-million-dollar-french-project | R22: Original award amount is EUR 11,400,000 with EUR 8,300,000 coming from the French government. Pea and fava beans are the primary plant inputs that will be investigated as part of this research. | T22: Pierre Courduroux | U22: n/a | V22: Roquette | W22: For profit | X22: France | Y22: Europe | Z22: n/a | AD22: Agri Obtentions, Eurial, Greencell, INRAE, Université Lumière Lyon 2 | AE22: Yes | AI22: 44985 | AJ22: 5 | AK22: In progress | AL22: 2422124 | AM22: BpiFrance | AQ22: Joint public/private partnership | AR22: France | AS22: Europe | AT22: Plant-based | AW22: Research and development | AX22: =IFERROR(INDEX('full database 2024'!AR:AR, MATCH(A22, 'full database 2024'!B:B, 0)), "") | AY22: Cheese | AZ22: End product formulation | BD22: 44985 | BE22: 45035 | BI22: Tier 4 (No GFI involvement) | BJ22: 2023 | BK22: 2028 | BL22: =BK22-BJ22+1 -> 6 | BM22: =TEXTJOIN(", ", TRUE, SEQUENCE(1, BL22, BJ22)) -> 2023, 2024, 2025, 2026, 2027, 2028 | BN22: =IF(ISNUMBER(SEARCH(BN$1, $BM22)), ($K22/$BL22), "") | BO22: =IF(ISNUMBER(SEARCH(BO$1, $BM22)), ($K22/$BL22), "") | BP22: =IF(ISNUMBER(SEARCH(BP$1, $BM22)), ($K22/$BL22), "") | BQ22: =IF(ISNUMBER(SEARCH(BQ$1, $BM22)), ($K22/$BL22), "") -> 1383333.3 | BR22: =IF(ISNUMBER(SEARCH(BR$1, $BM22)), ($K22/$BL22), "") -> 1383333.3 | BS22: =IF(ISNUMBER(SEARCH(BS$1, $BM22)), ($K22/$BL22), "") -> 1383333.3 | BT22: =IF(ISNUMBER(SEARCH(BT$1, $BM22)), ($K22/$BL22), "") -> 1383333.3 | BU22: =IF(ISNUMBER(SEARCH(BU$1, $BM22)), ($K22/$BL22), "") -> 1383333.3 | ... CC22: =IF(ISNUMBER(SEARCH(CC$1, $BM22)), ($K22/$BL22), "")
A23: SOYSTAINABLE (ANR-22-PLEG-003): towards a source of local and sustainable soy protein in human food resilient to climate change | B23: Over the next six years, the SOYSTAINABLE scientific project, officially launched on Thursday, February 9, will help promote local soybean crops for human consumption that are sustainable and resilient to climate change. The project, funded by the ANR (National Agency for Research in the Environment) as part of France 2030, will be coordinated by Jean-Malo Couzigou, CNRS research fellow at the Plant Sciences Research Laboratory. It will be supported by the University of Toulouse III – Paul Sabatier, the coordinating institution. | D23: airtable | E23: 11209955 | F23: 2999797 | G23: EUR | H23: 12238602 | I23: 3275064 | J23: 11209955 | K23: 2999797 | L23: Awarded | M23: checked | N23: https://www.univ-tlse3.fr/un-projet-de-grande-envergure-pour-developper-la-culture-du-soja-germe-en-france | R23: Original award amount is EUR 11,209,955.38 with EUR 2,999,797.00 provided by the ANR and EUR 8,210,158.38 contributed by project partners. | T23: Jean-Malo Couzigou | U23: n/a | V23: French National Center for Scientific Research (CNRS) | W23: Government research agency | X23: France | Y23: Europe | Z23: n/a | AD23: University of Toulouse III – Paul Sabatier, "National Research Institute for Agriculture, Food and the Environment (INRAE)", National Center for Scientific Research (CNRS), University of Caen Normandy, Paris-Saclay University, PURPAN School of Engineering (Toulouse INP-Purpan), UniLaSalle polytechnic institute, Lidea, RAGT 2N, De Sangosse, Terres Inovia, Opera Gardens | AE23: Yes | AI23: 44927 | AJ23: 6 | AK23: In progress | AL23: 2039767 | AM23: French National Research Agency (ANR) | AP23: https://anr.fr/fr/detail/call/developper-les-proteines-vegetales-et-diversifier-les-sources-de-proteines-volet-1-proteines-d/ | AQ23: Joint public/private partnership | AR23: France | AS23: Europe | AT23: Plant-based | AW23: Research and development | AX23: =IFERROR(INDEX('full database 2024'!AR:AR, MATCH(A23, 'full database 2024'!B:B, 0)), "") | AZ23: Crop development | BD23: 45057 | BE23: 45057 | BI23: Tier 4 (No GFI involvement) | BJ23: 2023 | BK23: 2029 | BL23: =BK23-BJ23+1 -> 7 | BM23: =TEXTJOIN(", ", TRUE, SEQUENCE(1, BL23, BJ23)) -> 2023, 2024, 2025, 2026, 2027, 2028, 2029 | BN23: =IF(ISNUMBER(SEARCH(BN$1, $BM23)), ($K23/$BL23), "") | BO23: =IF(ISNUMBER(SEARCH(BO$1, $BM23)), ($K23/$BL23), "") | BP23: =IF(ISNUMBER(SEARCH(BP$1, $BM23)), ($K23/$BL23), "") | BQ23: =IF(ISNUMBER(SEARCH(BQ$1, $BM23)), ($K23/$BL23), "") -> 428542.43 | BR23: =IF(ISNUMBER(SEARCH(BR$1, $BM23)), ($K23/$BL23), "") -> 428542.43 | BS23: =IF(ISNUMBER(SEARCH(BS$1, $BM23)), ($K23/$BL23), "") -> 428542.43 | BT23: =IF(ISNUMBER(SEARCH(BT$1, $BM23)), ($K23/$BL23), "") -> 428542.43 | BU23: =IF(ISNUMBER(SEARCH(BU$1, $BM23)), ($K23/$BL23), "") -> 428542.43 | ... CC23: =IF(ISNUMBER(SEARCH(CC$1, $BM23)), ($K23/$BL23), "")
A24: Harnessing the microbial potential of fermented foods for healthy and sustainable food systems (DOMINO) | B24: Food and beverage fermentation dates back 7 000 years. Despite this long history, we know very little about the benefits of such a diet. The EU-funded DOMINO project will study the health impacts of a diet based on fermented food (milk kefir) on a healthy population and a cohort suffering from metabolic syndrome to better focus on health biomarkers and inform dietary recommendations. We are also missing strategies to ensure food production sustainability. The project will thus carry out six plant-based fermented food case studies within the framework of citizen science. These food prototypes will help to develop an open-access database and new computational tools for profiling food microbiomes’ metabolic interaction during food fermentation and their overlap with the healthy gut microbiome. | D24: airtable | E24: 10815148 | F24: 10815148 | G24: EUR | H24: 11871463 | I24: 11871463 | J24: 10815148 | K24: 10815148 | L24: Awarded | M24: checked | N24: https://cordis.europa.eu/project/id/101060218 | R24: Original award amount is EUR 10,815,148. The award is not focused solely toward the development of fermentation-derived meat, eggs, or dairy but on fermented foods more broadly. | T24: Stéphane Chaillou | U24: Food Microbial Ecology | V24: INSTITUT NATIONAL DE RECHERCHE POUR L'AGRICULTURE, L'ALIMENTATION ET L'ENVIRONNEMENT (INRAE) | W24: Government research agency | X24: France | Y24: Europe | Z24: n/a | AD24: INSTITUT NATIONAL DES SCIENCES ET INDUSTRIES DU VIVANT ET DE L'ENVIRONNEMENT - AGROPARISTECH, CENTRE DE RECHERCHE EN NUTRITION HUMAINE D'AUVERGNE, TEAGASC - AGRICULTURE AND FOOD DEVELOPMENT AUTHORITY, UNIVERSITA DEGLI STUDI DI TORINO, UNIVERSITA DEGLI STUDI DI TRENTO, UNIVERSITA DEGLI STUDI DI NAPOLI FEDERICO II, AGENCIA ESTATAL CONSEJO SUPERIOR DE INVESTIGACIONES CIENTIFICAS, Technical University of Munich, STICHTING VU, AIT AUSTRIAN INSTITUTE OF TECHNOLOGY GMBH, EUROPEAN FOOD INFORMATION COUNCIL, INSTITUT DE RECHERCHE POUR LE DEVELOPPEMENT, INRAE TRANSFERT SAS, AKTSIASELTS TOIDU- JA FERMENTATSIOONITEHNOLOOGIA ARENDUSKESKUS, Green Spot Technologies, HERBEL CREST LIMITED, F.LLI MERANO SOCIETA PER AZIONI, LES NOUVEAUX AFFINEURS, MOOREPARK TECHNOLOGY LTD, IMPERIAL COLLEGE OF SCIENCE TECHNOLOGY AND MEDICINE | AE24: Yes | AI24: 44986 | AJ24: 5 | AK24: In progress | AL24: 2374293 | AM24: European Commission | AN24: Cluster 6: Food, Bioeconomy Natural Resources, Agriculture and Environment | AQ24: Government | AR24: EU | AS24: Europe | AT24: Plant-based | AU24: TF | AW24: Research and development | AX24: =IFERROR(INDEX('full database 2024'!AR:AR, MATCH(A24, 'full database 2024'!B:B, 0)), "") | AZ24: Health/nutrition, End product formulation, Consumer and market research | BD24: 45037 | BE24: 45037 | BI24: Tier 4 (No GFI involvement) | BJ24: 2023 | BK24: 2028 | BL24: =BK24-BJ24+1 -> 6 | BM24: =TEXTJOIN(", ", TRUE, SEQUENCE(1, BL24, BJ24)) -> 2023, 2024, 2025, 2026, 2027, 2028 | BN24: =IF(ISNUMBER(SEARCH(BN$1, $BM24)), ($K24/$BL24), "") | BO24: =IF(ISNUMBER(SEARCH(BO$1, $BM24)), ($K24/$BL24), "") | BP24: =IF(ISNUMBER(SEARCH(BP$1, $BM24)), ($K24/$BL24), "") | BQ24: =IF(ISNUMBER(SEARCH(BQ$1, $BM24)), ($K24/$BL24), "") -> 1802524.7 | BR24: =IF(ISNUMBER(SEARCH(BR$1, $BM24)), ($K24/$BL24), "") -> 1802524.7 | BS24: =IF(ISNUMBER(SEARCH(BS$1, $BM24)), ($K24/$BL24), "") -> 1802524.7 | BT24: =IF(ISNUMBER(SEARCH(BT$1, $BM24)), ($K24/$BL24), "") -> 1802524.7 | BU24: =IF(ISNUMBER(SEARCH(BU$1, $BM24)), ($K24/$BL24), "") -> 1802524.7 | ... CC24: =IF(ISNUMBER(SEARCH(CC$1, $BM24)), ($K24/$BL24), "")
A25: Umiami acquires Unilever factory to establish 'Made-in-France plant-based meat' | B25: The purchase of the new facility has been made possible by a $30 million funding round in April, which was claimed to be the largest ever of its kind in the European plant-based sector. At the time, Umiami said it had already acquired major clients in Northern Europe, North America, and South East Asia. Speaking about the facility, the company’s CEO and co-founder Tristan Maurel said the location in France’s Alsace region had been a strategic choice. “All the local authorities welcomed us with extraordinary professionalism and enthusiasm, emphasising the union of all political sides to promote local economic and industrial dynamism,” he said. “The industrial know-how of the region and the strategic positioning at the heart of Europe convinced us that Alsace was conducive to our development. We are delighted to be able to contribute to local job creation and national food sovereignty by establishing ourselves in Duppigheim.” | D25: airtable | E25: 10400000 | F25: 10400000 | G25: EUR | H25: 11425804 | I25: 11425804 | J25: 10400000 | K25: 10400000 | L25: Awarded | M25: checked | N25: https://www.futureofproteinproduction.com/post/umiami-acquires-unilever-factory-to-establish-made-in-france-plant-based-meat?utm_campaign=Future%20of%20Protein%20Production%20Newsletter&utm_medium=email&_hsmi=237582309&_hsenc=p2ANqtz--ls134Q_DcfIXtZ0iaQCrzIsZibCzyZhRWcCiqD4NJp-FN4s_jil3nqi4CL4N5n9dw3QiuNcS1eqBk_6rgTgYOGwiS6Q&utm_content=237580038&utm_source=hs_email | R25: Original award amount is EUR 10,400,000 with EUR 7,400,000 coming from the French government and EUR 3,000,000 coming from the Grand-Est regional government. | T25: Tristan Maurel | U25: n/a | V25: Umiami | W25: For profit | X25: France | Y25: Europe | Z25: n/a | AE25: No | AI25: 44903 | AJ25: 2 | AK25: In progress | AL25: 5712902 | AM25: BpiFrance, Grand-Est Region | AP25: https://www.bpifrance.fr/nos-appels-a-projets-concours/appel-a-projets-france-2030-premiere-usine | AQ25: Government | AR25: France | AS25: Europe | AT25: Plant-based | AW25: Equipment and infrastructure | AX25: =IFERROR(INDEX('full database 2024'!AR:AR, MATCH(A25, 'full database 2024'!B:B, 0)), "") | BD25: 45036 | BE25: 45265 | BI25: Tier 4 (No GFI involvement) | BJ25: 2022 | BK25: 2024 | BL25: =BK25-BJ25+1 -> 3 | BM25: =TEXTJOIN(", ", TRUE, SEQUENCE(1, BL25, BJ25)) -> 2022, 2023, 2024 | BN25: =IF(ISNUMBER(SEARCH(BN$1, $BM25)), ($K25/$BL25), "") | BO25: =IF(ISNUMBER(SEARCH(BO$1, $BM25)), ($K25/$BL25), "") | BP25: =IF(ISNUMBER(SEARCH(BP$1, $BM25)), ($K25/$BL25), "") -> 3466666.7 | BQ25: =IF(ISNUMBER(SEARCH(BQ$1, $BM25)), ($K25/$BL25), "") -> 3466666.7 | BR25: =IF(ISNUMBER(SEARCH(BR$1, $BM25)), ($K25/$BL25), "") -> 3466666.7 | BS25: =IF(ISNUMBER(SEARCH(BS$1, $BM25)), ($K25/$BL25), "") | BT25: =IF(ISNUMBER(SEARCH(BT$1, $BM25)), ($K25/$BL25), "") | BU25: =IF(ISNUMBER(SEARCH(BU$1, $BM25)), ($K25/$BL25), "") | ... CC25: =IF(ISNUMBER(SEARCH(CC$1, $BM25)), ($K25/$BL25), "")
A26: Gap resolutIon in sAfety, NuTritional, alLergenicity and Environmental assessments to promote Alternative Protein utilization and the dietary Shift (GIANT LEAPS) | D26: airtable | E26: 10347863 | F26: 10272862 | G26: EUR | H26: 11338774 | I26: 11256591 | J26: 10347863 | K26: 10272862 | L26: Awarded | M26: checked | N26: https://cordis.europa.eu/project/id/101059632 | R26: Original award amount is EUR 10,347,863 with EUR 10,272,862 coming from government. | T26: Paul Vos | U26: Food, Health, and Consumer Research | V26: Wageningen University and Research | W26: University | X26: Netherlands | Y26: Europe | Z26: n/a | AD26: INSTITUT DE RECERCA I TECNOLOGIA AGROALIMENTARIES, MATIS OHF, UNIVERSITY COLLEGE CORK, VTT Technical Research Centre of Finland Ltd, UNIVERSITA DEGLI STUDI DI NAPOLI FEDERICO II, LUONNONVARAKESKUS, Wageningen University and Research, German Institute for Food Technology eV (DIL), TEAGASC - AGRICULTURE AND FOOD DEVELOPMENT AUTHORITY, "INSTITUT NATIONAL DE RECHERCHE POUR L'AGRICULTURE, L'ALIMENTATION ET L'ENVIRONNEMENT", INSTITUT NATIONAL DES SCIENCES ET INDUSTRIES DU VIVANT ET DE L'ENVIRONNEMENT - AGROPARISTECH, MEDICAL UNIVERSITY SOFIA, FUNDACION AZTI - AZTI FUNDAZIOA, "IRIS TECHNOLOGY SOLUTIONS, SOCIEDAD LIMITADA", STICHTING EFFOST, Bridge2Food (Foodcompanions BV), VIVA MARIS GMBH, Solar Foods, ASSOCIACAO OCEANO VERDE LABORATORIO COLABORATIVO PARA O DESENVOLVIMENTO DE TECNOLOGIAS E PRODUTOS VERDES DO OCEANO, EUROPA MEDIA SZOLGALTATO NON PROFITKOZHASZNU KFT, VERHAGEN FRANCISCUS, Mosa Meat, NAPIFERYN BIOTECH SP ZOO, CAPACITY DEVELOPMENT IN NUTRITION RESEARCH-CAPNUTRA, FC CV, DEUTSCHER ALLERGIE- UND ASTHMABUND E.V., ROQUETTE FRERES SA, RUKOV JAKOB LEWIN, NUTRICIA RESEARCH BV, EIDGENOESSISCHE TECHNISCHE HOCHSCHULE ZUERICH, AGT Food and Ingredients, University of Manchester, UNILEVER U.K. CENTRAL RESOURCES LIMITED | AE26: Yes | AI26: 44805 | AJ26: 4 | AK26: In progress | AL26: 2834694 | AM26: European Commission | AN26: Cluster 6: Food, Bioeconomy Natural Resources, Agriculture and Environment | AQ26: Government | AR26: EU | AS26: Europe | AT26: Cross-cutting | AU26: All | AW26: Research and development | AX26: =IFERROR(INDEX('full database 2024'!AR:AR, MATCH(A26, 'full database 2024'!B:B, 0)), "") | AZ26: Health/nutrition, Food safety & quality, Ingredient optimisation, Env/impact assessments | BD26: 45035 | BE26: 45035 | BI26: Tier 4 (No GFI involvement) | BJ26: 2022 | BK26: 2026 | BL26: =BK26-BJ26+1 -> 5 | BM26: =TEXTJOIN(", ", TRUE, SEQUENCE(1, BL26, BJ26)) -> 2022, 2023, 2024, 2025, 2026 | BN26: =IF(ISNUMBER(SEARCH(BN$1, $BM26)), ($K26/$BL26), "") | BO26: =IF(ISNUMBER(SEARCH(BO$1, $BM26)), ($K26/$BL26), "") | BP26: =IF(ISNUMBER(SEARCH(BP$1, $BM26)), ($K26/$BL26), "") -> 2054572.4 | BQ26: =IF(ISNUMBER(SEARCH(BQ$1, $BM26)), ($K26/$BL26), "") -> 2054572.4 | BR26: =IF(ISNUMBER(SEARCH(BR$1, $BM26)), ($K26/$BL26), "") -> 2054572.4 | BS26: =IF(ISNUMBER(SEARCH(BS$1, $BM26)), ($K26/$BL26), "") -> 2054572.4 | BT26: =IF(ISNUMBER(SEARCH(BT$1, $BM26)), ($K26/$BL26), "") -> 2054572.4 | BU26: =IF(ISNUMBER(SEARCH(BU$1, $BM26)), ($K26/$BL26), "") | ... CC26: =IF(ISNUMBER(SEARCH(CC$1, $BM26)), ($K26/$BL26), "")
A27: Solar Foods accelerates production of climate-friendly protein with investment from The Finnish Climate Fund | B27: Solar Foods has received €10 million in funding from The Finnish Climate Fund. It is the first investment by the funding organisation. The subordinated loan now granted will go towards starting commercial-scale production of the innovative Solein® protein, which radically reduces the impact of food production on the climate. The funding from The Finnish Climate Fund brings the financing total for Solar Foods to €35 million. Solar Foods has turned sci-fi into reality—it is now possible to produce nutritionally complete protein using carbon dioxide in the air and electricity as its primary raw materials. The innovation, rooted in the combined sresearch efforts of VTT Technical Research Centre of Finland and LUT University in Finland, is now in the commercialisation stage with industrial-scale production of the Solein protein about to get underway. The loan from The Finnish Climate Fund will be used to build the demonstrator facility. The facility will include the Solein Experience Hub and a future-food bar to provide citizens with an entirely new level of transparency in food production. This production facility, presently being designed, is scheduled to begin operations in early 2023. | D27: airtable | E27: 10000000 | F27: 10000000 | G27: EUR | H27: 10969100 | I27: 10969100 | J27: 10000000 | K27: 10000000 | L27: Awarded | M27: checked | N27: https://solarfoods.com/solar-foods-accelerates-production-of-climate-friendly-protein-with-investment-from-the-finnish-climate-fund/#:~:text=The%20funding%20from%20The%20Finnish,as%20its%20primary%20raw%20materials. | R27: Original award amount is EUR 10,000,000. This is a government loan. | T27: Pasi Vainikka | U27: n/a | V27: Solar Foods | W27: For profit | X27: Finland | Y27: Europe | Z27: n/a | AE27: No | AI27: 44416 | AJ27: 2 | AK27: In progress | AL27: 5484550 | AM27: Finnish Climate Fund | AQ27: Government | AR27: Finland | AS27: Europe | AT27: Fermentation | AU27: PF | AW27: Equipment and infrastructure | AX27: =IFERROR(INDEX('full database 2024'!AR:AR, MATCH(A27, 'full database 2024'!B:B, 0)), "") | BD27: 45034 | BE27: 45035 | BI27: Tier 4 (No GFI involvement) | BJ27: 2021 | BK27: 2023 | BL27: =BK27-BJ27+1 -> 3 | BM27: =TEXTJOIN(", ", TRUE, SEQUENCE(1, BL27, BJ27)) -> 2021, 2022, 2023 | BN27: =IF(ISNUMBER(SEARCH(BN$1, $BM27)), ($K27/$BL27), "") | BO27: =IF(ISNUMBER(SEARCH(BO$1, $BM27)), ($K27/$BL27), "") -> 3333333.3 | BP27: =IF(ISNUMBER(SEARCH(BP$1, $BM27)), ($K27/$BL27), "") -> 3333333.3 | BQ27: =IF(ISNUMBER(SEARCH(BQ$1, $BM27)), ($K27/$BL27), "") -> 3333333.3 | BR27: =IF(ISNUMBER(SEARCH(BR$1, $BM27)), ($K27/$BL27), "") | BS27: =IF(ISNUMBER(SEARCH(BS$1, $BM27)), ($K27/$BL27), "") | BT27: =IF(ISNUMBER(SEARCH(BT$1, $BM27)), ($K27/$BL27), "") | BU27: =IF(ISNUMBER(SEARCH(BU$1, $BM27)), ($K27/$BL27), "") | ... CC27: =IF(ISNUMBER(SEARCH(CC$1, $BM27)), ($K27/$BL27), "")
A28: Umiami secures funding for US expansion | D28: airtable | E28: 10000000 | F28: 10000000 | G28: EUR | H28: 10786050 | I28: 10786050 | J28: 10000000 | K28: 10000000 | L28: Awarded | M28: checked | N28: https://tech.eu/2023/10/03/plant-based-meat-alternatives-firm-umiami-eur325m-us-expansion/ | R28: Total fundraising amount was EUR 32,500,000 but here we are only including the government-backed amount, which we estimate at EUR 10,000,000. | T28: Tristan Maurel | U28: n/a | V28: Umiami | W28: For profit | X28: France | Y28: Europe | Z28: n/a | AE28: No | AI28: 45202 | AJ28: 5 | AK28: In progress | AL28: 2157210 | AM28: BpiFrance | AQ28: Joint public/private partnership | AR28: France | AS28: Europe | AT28: Plant-based | AW28: Equipment and infrastructure | AX28: =IFERROR(INDEX('full database 2024'!AR:AR, MATCH(A28, 'full database 2024'!B:B, 0)), "") | BD28: 45265 | BE28: 45265 | BI28: Tier 4 (No GFI involvement) | BJ28: 2023 | BK28: 2028 | BL28: =BK28-BJ28+1 -> 6 | BM28: =TEXTJOIN(", ", TRUE, SEQUENCE(1, BL28, BJ28)) -> 2023, 2024, 2025, 2026, 2027, 2028 | BN28: =IF(ISNUMBER(SEARCH(BN$1, $BM28)), ($K28/$BL28), "") | BO28: =IF(ISNUMBER(SEARCH(BO$1, $BM28)), ($K28/$BL28), "") | BP28: =IF(ISNUMBER(SEARCH(BP$1, $BM28)), ($K28/$BL28), "") | BQ28: =IF(ISNUMBER(SEARCH(BQ$1, $BM28)), ($K28/$BL28), "") -> 1666666.7 | BR28: =IF(ISNUMBER(SEARCH(BR$1, $BM28)), ($K28/$BL28), "") -> 1666666.7 | BS28: =IF(ISNUMBER(SEARCH(BS$1, $BM28)), ($K28/$BL28), "") -> 1666666.7 | BT28: =IF(ISNUMBER(SEARCH(BT$1, $BM28)), ($K28/$BL28), "") -> 1666666.7 | BU28: =IF(ISNUMBER(SEARCH(BU$1, $BM28)), ($K28/$BL28), "") -> 1666666.7 | ... CC28: =IF(ISNUMBER(SEARCH(CC$1, $BM28)), ($K28/$BL28), "")
A29: new VALue landscapes for plant PROtein Pathways (VALPRO Path) | B29: The current European plant-protein landscape is flawed. Heightened societal awareness of the environmental impact of consuming animal-based protein is driving the public’s awareness of alternative, sustainable sources of dietary protein. Yet, production systems are focussed heavily on the production of feedstock for direct transfer into animal sectors in an attempt to counter the EU’s over-dependency on imported feed. In essence, there is an absence of premium supply chains - farmers miss out on added-value opportunities that exist within the crops they already grow across Europe. There is a need to increase resilience in farming systems to mitigate against increasingly volatile climate patterns and to support farming systems to meet Farm-to-Fork strategic objectives. Built on the principles of co-creation, innovation and demonstration, VALPRO Path will design, validate and deliver sustainable and competitive plant protein crop systems and value chains. Focussed on underpinning economic value for all actors in the supply chain, it will exploit beyond state-of-the-art innovations, demonstrating and evaluating potential across 5 multi-stakeholder ‘living lab’ innovation production systems (IPSs). With strong industry involvement, the project will deliver a stronger ecosystem for plant protein production, supported with robust evidence of the social, economic, environmental, climate and health benefits. VALPRO Path will deliver new, sustainable business models, showing how focussed research can come into practice. Sustainable diversification of rotations with grain legumes will support the transition to more environmentally sustainable farming. European agriculture is at a juncture in regards to the sustainable provision of dietary protein. It can embrace opportunities presented through existing innovations that are integrated into real-life scenarios to support stakeholders realise the new market opportunities that exist for indigenous, fully traceable plant protein. | D29: airtable | E29: 9647489 | F29: 8662360 | G29: EUR | H29: 10531777 | I29: 9456351 | J29: 9647489 | K29: 8662360 | L29: Awarded | M29: checked | N29: https://cordis.europa.eu/project/id/101059824 | O29: grant.12960983 | R29: Original award amount is EUR 9,647,489 with EUR 8,662,360 coming from government. | T29: Ewen Mullins | U29: Crop Science | V29: Teagasc | W29: Government research agency | X29: Ireland | Y29: Europe | Z29: n/a | AD29: Aarhus University, UNIVERSITA DEGLI STUDI DI TORINO, ETHNICON METSOVION POLYTECHNION, FOODSCALE HUB GREECE ASSOCIATION FOR ENTREPREUNERSHIP AND INNOVATION ASTIKI MI KERDOSKOPIKI ETAIREIA, LEIBNIZ-ZENTRUM FUER AGRARLANDSCHAFTSFORSCHUNG (ZALF) e.V., AGENCIA ESTATAL CONSEJO SUPERIOR DE INVESTIGACIONES CIENTIFICAS, CONFEDERAZIONE GENERALE DELL AGRICOLTURA ITALIANA, AGRICOLUS S.R.L, Wageningen University and Research, BEOTANICS LIMITED, PORTFOLIO CONCENTRATE SOLUTIONS UNLIMITED COMPANY, DIGNITY IDIOTIKI KEFALAIOUXIKI ETAIREIA, MOOREPARK TECHNOLOGY LTD, MOLINO PEILA SOCIETA PER AZIONI SIGLABILE MOLINO PEILA SPA, GLOBAL NETWORKS GEMEINNUTZIGE UNTERNEHMERGESELLSCHAFT HAFTUNGSBESCHRANT, FARMB PSIFIAKI GEORGIA ANONIMI ETAIRIA, PROLUPIN GMBH, FATTORIA SOLIDALE DEL CIRCEO COOPERATIVA SOCIALE DI PRODUZIONE E LAVORO, TEALDI ROBERTO, KERRY GROUP SERVICES INTERNATIONAL LIMITED, KPAD LTD | AE29: Yes | AI29: 44805 | AJ29: 4 | AK29: In progress | AL29: 2632944 | AM29: European Commission | AN29: Cluster 6: Food, Bioeconomy Natural Resources, Agriculture and Environment | AQ29: Joint public/private partnership | AR29: EU | AS29: Europe | AT29: Plant-based | AW29: Research and development | AX29: =IFERROR(INDEX('full database 2024'!AR:AR, MATCH(A29, 'full database 2024'!B:B, 0)), "") | AZ29: Ingredient optimisation, Crop development, Env/impact assessments | BD29: 45057 | BE29: 45779 | BI29: Tier 4 (No GFI involvement) | BJ29: 2022 | BK29: 2026 | BL29: =BK29-BJ29+1 -> 5 | BM29: =TEXTJOIN(", ", TRUE, SEQUENCE(1, BL29, BJ29)) -> 2022, 2023, 2024, 2025, 2026 | BN29: =IF(ISNUMBER(SEARCH(BN$1, $BM29)), ($K29/$BL29), "") | BO29: =IF(ISNUMBER(SEARCH(BO$1, $BM29)), ($K29/$BL29), "") | BP29: =IF(ISNUMBER(SEARCH(BP$1, $BM29)), ($K29/$BL29), "") -> 1732472 | BQ29: =IF(ISNUMBER(SEARCH(BQ$1, $BM29)), ($K29/$BL29), "") -> 1732472 | BR29: =IF(ISNUMBER(SEARCH(BR$1, $BM29)), ($K29/$BL29), "") -> 1732472 | BS29: =IF(ISNUMBER(SEARCH(BS$1, $BM29)), ($K29/$BL29), "") -> 1732472 | BT29: =IF(ISNUMBER(SEARCH(BT$1, $BM29)), ($K29/$BL29), "") -> 1732472 | BU29: =IF(ISNUMBER(SEARCH(BU$1, $BM29)), ($K29/$BL29), "") | ... CC29: =IF(ISNUMBER(SEARCH(CC$1, $BM29)), ($K29/$BL29), "")
A30: SMART PROTEIN | B30: It is undeniable that protein is an indispensable part of the human diet, but the way we produce and consume it today presents many challenges, in terms of both global consumption patterns and their social, environmental and economic impacts. Providing a growing global population with healthy diets from sustainable food systems is therefore an immediate challenge. SMART PROTEIN aims to industrially validate and demonstrate innovative, cost-effective and resource-efficient, EU-produced, nutritious plant (fava bean, lentil, chickpea, quinoa) and microbial biomass proteins from edible fungi by up-cycling side streams from pasta (pasta residues), bread (bread crust) and beer (spent yeast and malting rootlets) industries. The alternative SMART protein will be used for the production of ingredients and products for direct human consumption, through developing future-proofed protein supply chains with a positive impact on bio-economy, environment, biodiversity, human nutrition, food and nutrition security and consumer trust and acceptance. These priorities will be addressed through global partnerships forged with consortium members from Europe, North America, Israel, Thailand and New Zealand to develop and demonstrate a climate-smart, sustainable protein-food system for a healthy Europe. We will harness plant and microbial protein knowledge to significantly enhance the sustainability and resilience of a new European protein supply chain, improve professional skills and competencies, and support the creation of new jobs in the food sector and bioeconomy. | D30: airtable | E30: 9607844 | F30: 8179215 | G30: EUR | H30: 10308928 | I30: 8776052 | J30: 9607844 | K30: 8179215 | L30: Awarded | M30: checked | N30: https://cordis.europa.eu/project/id/862957 | O30: grant.8709639 | R30: Original award amount is EUR 9,607,844 with EUR 8,179,215 from the EU government. | T30: Emanuele Zannini | U30: n/a | V30: University College Cork | W30: University | X30: Ireland | Y30: Europe | Z30: n/a | AD30: TEAGASC - AGRICULTURE AND FOOD DEVELOPMENT AUTHORITY, GLANBIA IRELAND DESIGNATED ACTIVITY COMPANY, BEOTANICS LIMITED, UCC ACADEMY DESIGNATED ACTIVITY COMPANY, SOGUIMA COMERCIO INDUSTRIA ALIMENTAR SA, INSTITUTO NAVARRO DE TECNOLOGIAS E INFRAESTRUCTURAS AGROALIMENTARIAS SA, CONTROL DE PORCIONES SA, UNIVERSITEIT GENT, ANHEUSER-BUSCH INBEV, DELPHY BV, NUTRICIA RESEARCH BV, Kobenhavns Universitet, Chr. Hansen A/S, SICCADANIA A/S, NOVOZYMES A/S, FRAUNHOFER GESELLSCHAFT ZUR FORDERUNG DER ANGEWANDTEN FORSCHUNG EV, PROVEG, EURA AG, DOHLER GMBH, MULLER'S MUHLER GMBH, GEBRUDER WOERLE GESELLSCHAFT M B H, UNIVERSITA DEGLI STUDI DI UDINE, Libera Universita Di Bolzano, MOGU SRL, BARILLA G. E R. FRATELLI SPA, ARCA SOCIETA' A RESPONSABILITA' LIMITATA SOCIETA' BENEFIT, QUINOA MARCHE SRL SEMPLIFICATA, EQUI-NOM LTD, HAUTE ECOLE SPECIALISEE DE SUISSE OCCIDENTALE, THAI UNION GROUP PUBLIC COMPANY LIMITED, AGRESEARCH LIMITED, "THE GOOD FOOD INSTITUTE, INC." | AE30: Yes | AI30: 43831 | AJ30: 4 | AK30: In progress | AL30: 2577232 | AM30: European Commission | AN30: SOCIETAL CHALLENGES - Food security, sustainable agriculture and forestry, marine, maritime and inland water research, and the bioeconomy | AQ30: Joint public/private partnership | AR30: EU | AS30: Europe | AT30: Plant-based | AU30: TF | AW30: Research and development | AX30: =IFERROR(INDEX('full database 2024'!AR:AR, MATCH(A30, 'full database 2024'!B:B, 0)), "") | AZ30: cross-cutting | BD30: 44999 | BE30: 45779 | BH30: checked | BI30: Tier 2 (Significant GFI involvement) | BJ30: 2020 | BK30: 2024 | BL30: =BK30-BJ30+1 -> 5 | BM30: =TEXTJOIN(", ", TRUE, SEQUENCE(1, BL30, BJ30)) -> 2020, 2021, 2022, 2023, 2024 | BN30: =IF(ISNUMBER(SEARCH(BN$1, $BM30)), ($K30/$BL30), "") -> 1635843 | BO30: =IF(ISNUMBER(SEARCH(BO$1, $BM30)), ($K30/$BL30), "") -> 1635843 | BP30: =IF(ISNUMBER(SEARCH(BP$1, $BM30)), ($K30/$BL30), "") -> 1635843 | BQ30: =IF(ISNUMBER(SEARCH(BQ$1, $BM30)), ($K30/$BL30), "") -> 1635843 | BR30: =IF(ISNUMBER(SEARCH(BR$1, $BM30)), ($K30/$BL30), "") -> 1635843 | BS30: =IF(ISNUMBER(SEARCH(BS$1, $BM30)), ($K30/$BL30), "") | BT30: =IF(ISNUMBER(SEARCH(BT$1, $BM30)), ($K30/$BL30), "") | BU30: =IF(ISNUMBER(SEARCH(BU$1, $BM30)), ($K30/$BL30), "") | ... CC30: =IF(ISNUMBER(SEARCH(CC$1, $BM30)), ($K30/$BL30), "")
A31: Polish Government Backs LabFarm With Grant for Cultivated Chicken | B31: The grant will enable LabFarm to optimize bioprocesses, scale up production, work on proprietary growth media, develop products, and expand its team. | D31: airtable | E31: 9000000 | F31: 9000000 | G31: PLN | H31: 2324250 | I31: 2324250 | J31: =E31*0.23 -> 2070000 | K31: =F31*0.23 -> 2070000 | L31: Awarded | M31: checked | N31: https://vegconomist.com/politics-law/polish-government-labfarm-e2m-grant-cultivated-chicken/ | O31: need to check | R31: Original award amount is PLN 9,000,000. | T31: Stanisław Łoboziak | U31: n/a | V31: LabFarm | W31: For profit | X31: Poland | Y31: Europe | Z31: n/a | AE31: No | AI31: 45499 | AJ31: 2 | AK31: In progress | AL31: 1162125 | AM31: National Centre for Research and Development (NCBR) | AO31: TRL 4-6 | AQ31: Government | AR31: Poland | AS31: Europe | AT31: Cultivated | AW31: Research and development | AX31: Meat | AY31: Chicken | AZ31: Cell culture media, Bioprocess design | BD31: 45520 | BE31: 45520 | BI31: Tier 4 (No GFI involvement) | BJ31: 2024 | BK31: 2026 | BL31: =BK31-BJ31+1 -> 3 | BM31: =TEXTJOIN(", ", TRUE, SEQUENCE(1, BL31, BJ31)) -> 2024, 2025, 2026 | BN31: =IF(ISNUMBER(SEARCH(BN$1, $BM31)), ($K31/$BL31), "") | BO31: =IF(ISNUMBER(SEARCH(BO$1, $BM31)), ($K31/$BL31), "") | BP31: =IF(ISNUMBER(SEARCH(BP$1, $BM31)), ($K31/$BL31), "") | BQ31: =IF(ISNUMBER(SEARCH(BQ$1, $BM31)), ($K31/$BL31), "") | BR31: =IF(ISNUMBER(SEARCH(BR$1, $BM31)), ($K31/$BL31), "") -> 690000 | BS31: =IF(ISNUMBER(SEARCH(BS$1, $BM31)), ($K31/$BL31), "") -> 690000 | BT31: =IF(ISNUMBER(SEARCH(BT$1, $BM31)), ($K31/$BL31), "") -> 690000 | BU31: =IF(ISNUMBER(SEARCH(BU$1, $BM31)), ($K31/$BL31), "") | ... CC31: =IF(ISNUMBER(SEARCH(CC$1, $BM31)), ($K31/$BL31), "")
A32: Intelligent Collections of Food Legumes Genetic Resources for European Agrofood Systems (INCREASE) | D32: airtable | E32: 8826825 | F32: 7000000 | G32: EUR | H32: 10062581 | I32: 7979999 | J32: 8826825 | K32: 7000000 | L32: Awarded | M32: checked | N32: https://cordis.europa.eu/project/id/862862 | O32: grant.9065977 | S32: not focused on APs, but extremely relevant | V32: Agricultural Institute of Slovenia | W32: Consortium | X32: Italy | Y32: Europe | AD32: Banca de Resurse Genetice Vegetale Mihai Cristea Suceava, Centre National de la Recherche Scientifique CNRS, Communita del Mais Spinato di Gandino, Consiglio per la Ricera in Agricoltura e l'Analisi dell'Economia Agraria DCS-Fürth, European Research and Project Office GmbH, Federal Research Center the N.I. Vavilov All-Russian Institute of Plant Genetic Resources, Food and Agriculture Organization of the United Nations FAO, Institut National de Recherche pour l'Agriculture l'Alimentation et l'Environnement, Instituto Nacional de Investigation y Tecnologia Agraria y Alimentaria OA MP, Instytut Genetyki Roslin Poiskiej Akademii Nauk, Instytut Hodowli I Aklimayzacji Roslin - Panstwowy Instytut Badawczy, International Centre for Agricultural Research in the Dry Areas, International Crops Research Institute for the Semi-Arid Tropics Isea SRL, Leibniz-Institut für Pflanzengenetik und Kulturpflanzenforschung, Max-Planck-Gesellschaft zur Förderung der Wissenschaften e.V., North Dakota State University Servicio Regional de Investigation y Desarrollo Agroalimentario del Principado de Asturias, Statiunea de Cercetare Dezvoltare Pentru Legumicultura Bacau Terres Inovia, Universidad Nacional de la Plata - Instituto de Biotecnología y Biología Molecular, Universidade Catolica Portuguesa, Università degli Studi della Basilicata, Università Politecnica delle Marche, University of Saskatchewan, University of California Davis | AE32: Yes | AI32: 43952 | AL32: 10062581 | AM32: European Commission | AN32: SOCIETAL CHALLENGES - Food security, sustainable agriculture and forestry, marine, maritime and inland water research, and the bioeconomy | AQ32: Government | AR32: EU | AS32: Europe | AT32: Plant-based | AW32: Research and development | AX32: =IFERROR(INDEX('full database 2024'!AR:AR, MATCH(A32, 'full database 2024'!B:B, 0)), "") | AZ32: Crop development | BD32: 45377 | BE32: 45779 | BI32: Tier 4 (No GFI involvement) | BJ32: 2020 | BK32: 2026 | BL32: =BK32-BJ32+1 -> 7 | BM32: =TEXTJOIN(", ", TRUE, SEQUENCE(1, BL32, BJ32)) -> 2020, 2021, 2022, 2023, 2024, 2025, 2026 | BN32: =IF(ISNUMBER(SEARCH(BN$1, $BM32)), ($K32/$BL32), "") -> 1000000 | BO32: =IF(ISNUMBER(SEARCH(BO$1, $BM32)), ($K32/$BL32), "") -> 1000000 | BP32: =IF(ISNUMBER(SEARCH(BP$1, $BM32)), ($K32/$BL32), "") -> 1000000 | BQ32: =IF(ISNUMBER(SEARCH(BQ$1, $BM32)), ($K32/$BL32), "") -> 1000000 | BR32: =IF(ISNUMBER(SEARCH(BR$1, $BM32)), ($K32/$BL32), "") -> 1000000 | BS32: =IF(ISNUMBER(SEARCH(BS$1, $BM32)), ($K32/$BL32), "") -> 1000000 | BT32: =IF(ISNUMBER(SEARCH(BT$1, $BM32)), ($K32/$BL32), "") -> 1000000 | BU32: =IF(ISNUMBER(SEARCH(BU$1, $BM32)), ($K32/$BL32), "") | ... CC32: =IF(ISNUMBER(SEARCH(CC$1, $BM32)), ($K32/$BL32), "")
A33: Solar Foods: Commercializing Solein | D33: airtable | E33: 8600000 | F33: 4300000 | G33: EUR | H33: 9136081 | I33: 4568040 | J33: 8600000 | K33: 4300000 | L33: Awarded | M33: checked | N33: https://solarfoods.com/business-finland-greenlights-solar-foods-e8-6m-project/ | R33: Original award amount is EUR 8,600,000 with EUR 4,300,000 coming from Business Finland. | S33: I included this because my understanding is that this was non-dilutive financing from Business Finland. | T33: Pasi Vainikka | U33: n/a | V33: Solar Foods | W33: For profit | X33: Finland | Y33: Europe | Z33: n/a | AE33: No | AI33: 44166 | AJ33: 3 | AK33: In progress | AL33: 3045360 | AM33: Business Finland | AQ33: Government | AR33: Finland | AS33: Europe | AT33: Fermentation | AU33: PF | AW33: Equipment and infrastructure | AX33: =IFERROR(INDEX('full database 2024'!AR:AR, MATCH(A33, 'full database 2024'!B:B, 0)), "") | BD33: 44985 | BE33: 45035 | BI33: Tier 4 (No GFI involvement) | BJ33: 2020 | BK33: 2023 | BL33: =BK33-BJ33+1 -> 4 | BM33: =TEXTJOIN(", ", TRUE, SEQUENCE(1, BL33, BJ33)) -> 2020, 2021, 2022, 2023 | BN33: =IF(ISNUMBER(SEARCH(BN$1, $BM33)), ($K33/$BL33), "") -> 1075000 | BO33: =IF(ISNUMBER(SEARCH(BO$1, $BM33)), ($K33/$BL33), "") -> 1075000 | BP33: =IF(ISNUMBER(SEARCH(BP$1, $BM33)), ($K33/$BL33), "") -> 1075000 | BQ33: =IF(ISNUMBER(SEARCH(BQ$1, $BM33)), ($K33/$BL33), "") -> 1075000 | BR33: =IF(ISNUMBER(SEARCH(BR$1, $BM33)), ($K33/$BL33), "") | BS33: =IF(ISNUMBER(SEARCH(BS$1, $BM33)), ($K33/$BL33), "") | BT33: =IF(ISNUMBER(SEARCH(BT$1, $BM33)), ($K33/$BL33), "") | BU33: =IF(ISNUMBER(SEARCH(BU$1, $BM33)), ($K33/$BL33), "") | ... CC33: =IF(ISNUMBER(SEARCH(CC$1, $BM33)), ($K33/$BL33), "")
A34: Blue fields for a green future -seaweed as a source of sustainable foods | D34: airtable | E34: 7999955 | F34: 7999955 | G34: SEK | H34: 751996 | I34: 751996 | J34: =E34*0.091 -> 727995.91 | K34: =F34*0.091 -> 727995.91 | L34: Awarded | M34: checked | V34: Chalmers University of Technology | X34: Sweden | Y34: Europe | AI34: 44208 | AJ34: 49 | AK34: Ended | AL34: 15347 | AM34: Swedish Research Council for Environment Agricultural Sciences and Spatial Planning (FORMAS) | AQ34: Government | AR34: Sweden | AS34: Europe | AT34: Plant-based | AW34: Research and development | AX34: =IFERROR(INDEX('full database 2024'!AR:AR, MATCH(A34, 'full database 2024'!B:B, 0)), "") | AZ34: Crop development, Ingredient optimisation | BD34: 45596 | BE34: 45596 | BJ34: 2021 | BK34: 2025 | BL34: =BK34-BJ34+1 -> 5 | BM34: =TEXTJOIN(", ", TRUE, SEQUENCE(1, BL34, BJ34)) -> 2021, 2022, 2023, 2024, 2025 | BN34: =IF(ISNUMBER(SEARCH(BN$1, $BM34)), ($K34/$BL34), "") | BO34: =IF(ISNUMBER(SEARCH(BO$1, $BM34)), ($K34/$BL34), "") -> 145599.18 | BP34: =IF(ISNUMBER(SEARCH(BP$1, $BM34)), ($K34/$BL34), "") -> 145599.18 | BQ34: =IF(ISNUMBER(SEARCH(BQ$1, $BM34)), ($K34/$BL34), "") -> 145599.18 | BR34: =IF(ISNUMBER(SEARCH(BR$1, $BM34)), ($K34/$BL34), "") -> 145599.18 | BS34: =IF(ISNUMBER(SEARCH(BS$1, $BM34)), ($K34/$BL34), "") -> 145599.18 | BT34: =IF(ISNUMBER(SEARCH(BT$1, $BM34)), ($K34/$BL34), "") | BU34: =IF(ISNUMBER(SEARCH(BU$1, $BM34)), ($K34/$BL34), "") | ... CC34: =IF(ISNUMBER(SEARCH(CC$1, $BM34)), ($K34/$BL34), "")
A35: Tying blue and green resources via 3D food printing for diverse and sustainable future foods | D35: airtable | E35: 7999174 | F35: 7999174 | G35: SEK | H35: 751922 | I35: 751922 | J35: =E35*0.091 -> 727924.83 | K35: =F35*0.091 -> 727924.83 | L35: Awarded | M35: checked | V35: Chalmers University of Technology | X35: Sweden | Y35: Europe | AI35: 44208 | AJ35: 49 | AK35: Ended | AL35: 15345 | AM35: Swedish Research Council for Environment Agricultural Sciences and Spatial Planning (FORMAS) | AQ35: Government | AR35: Sweden | AS35: Europe | AT35: Plant-based | AW35: Research and development | AX35: =IFERROR(INDEX('full database 2024'!AR:AR, MATCH(A35, 'full database 2024'!B:B, 0)), "") | AZ35: Texturisation methods | BD35: 45596 | BE35: 45596 | BJ35: 2021 | BK35: 2025 | BL35: =BK35-BJ35+1 -> 5 | BM35: =TEXTJOIN(", ", TRUE, SEQUENCE(1, BL35, BJ35)) -> 2021, 2022, 2023, 2024, 2025 | BN35: =IF(ISNUMBER(SEARCH(BN$1, $BM35)), ($K35/$BL35), "") | BO35: =IF(ISNUMBER(SEARCH(BO$1, $BM35)), ($K35/$BL35), "") -> 145584.97 | BP35: =IF(ISNUMBER(SEARCH(BP$1, $BM35)), ($K35/$BL35), "") -> 145584.97 | BQ35: =IF(ISNUMBER(SEARCH(BQ$1, $BM35)), ($K35/$BL35), "") -> 145584.97 | BR35: =IF(ISNUMBER(SEARCH(BR$1, $BM35)), ($K35/$BL35), "") -> 145584.97 | BS35: =IF(ISNUMBER(SEARCH(BS$1, $BM35)), ($K35/$BL35), "") -> 145584.97 | BT35: =IF(ISNUMBER(SEARCH(BT$1, $BM35)), ($K35/$BL35), "") | BU35: =IF(ISNUMBER(SEARCH(BU$1, $BM35)), ($K35/$BL35), "") | ... CC35: =IF(ISNUMBER(SEARCH(CC$1, $BM35)), ($K35/$BL35), "")
A36: ‘ReSus’: Retail for change - Sustainable food production through collaborative commitments | D36: airtable | E36: 7999052 | F36: 7999052 | G36: SEK | H36: 751911 | I36: 751911 | J36: =E36*0.091 -> 727913.73 | K36: =F36*0.091 -> 727913.73 | L36: Awarded | M36: checked | V36: The Royal Swedish Academy of Sciences | X36: Sweden | Y36: Europe | AI36: 44208 | AJ36: 49 | AK36: Ended | AL36: 15345 | AM36: Swedish Research Council for Environment Agricultural Sciences and Spatial Planning (FORMAS) | AQ36: Government | AR36: Sweden | AS36: Europe | AT36: Plant-based | AW36: Research and development | AX36: =IFERROR(INDEX('full database 2024'!AR:AR, MATCH(A36, 'full database 2024'!B:B, 0)), "") | AZ36: Consumer and market research | BD36: 45596 | BE36: 45596 | BJ36: 2021 | BK36: 2025 | BL36: =BK36-BJ36+1 -> 5 | BM36: =TEXTJOIN(", ", TRUE, SEQUENCE(1, BL36, BJ36)) -> 2021, 2022, 2023, 2024, 2025 | BN36: =IF(ISNUMBER(SEARCH(BN$1, $BM36)), ($K36/$BL36), "") | BO36: =IF(ISNUMBER(SEARCH(BO$1, $BM36)), ($K36/$BL36), "") -> 145582.75 | BP36: =IF(ISNUMBER(SEARCH(BP$1, $BM36)), ($K36/$BL36), "") -> 145582.75 | BQ36: =IF(ISNUMBER(SEARCH(BQ$1, $BM36)), ($K36/$BL36), "") -> 145582.75 | BR36: =IF(ISNUMBER(SEARCH(BR$1, $BM36)), ($K36/$BL36), "") -> 145582.75 | BS36: =IF(ISNUMBER(SEARCH(BS$1, $BM36)), ($K36/$BL36), "") -> 145582.75 | BT36: =IF(ISNUMBER(SEARCH(BT$1, $BM36)), ($K36/$BL36), "") | BU36: =IF(ISNUMBER(SEARCH(BU$1, $BM36)), ($K36/$BL36), "") | ... CC36: =IF(ISNUMBER(SEARCH(CC$1, $BM36)), ($K36/$BL36), "")
A37: AgriLoop: Pushing the frontier of circular agriculture by converting residues into novel economic, social and environmental opportunities | D37: airtable | E37: 7825297 | F37: 7825297 | G37: EUR | H37: 8450954 | I37: 8450954 | J37: 7825297 | K37: 7825297 | L37: Awarded | M37: checked | N37: https://cordis.europa.eu/project/id/101081776 | X37: France | Y37: Europe | AD37: ; ; Veneto; ; ; ; ; Languedoc-Roussillon; ; ; ; ; ; ; Lisboa; York; Syddanmark; Emilia-Romagna; ; ; Lazio; | AE37: France; China; Italy; Belgium; Belgium; Switzerland; China; France; China; China; China; Spain; China; Spain; Portugal; United Kingdom; Denmark; Italy; China; China; Italy; Netherlands | AI37: 44896 | AL37: 8450954 | AM37: European Commission | AN37: Cluster 6: Food, Bioeconomy Natural Resources, Agriculture and Environment | AQ37: Government | AR37: EU | AS37: Europe | AT37: Cross-cutting | AU37: All | AW37: Research and development | AX37: =IFERROR(INDEX('full database 2024'!AR:AR, MATCH(A37, 'full database 2024'!B:B, 0)), "") | AZ37: Ingredient optimisation, Feedstocks | BD37: 45596 | BE37: 45596 | BJ37: 2022 | BK37: 2026 | BL37: =BK37-BJ37+1 -> 5 | BM37: =TEXTJOIN(", ", TRUE, SEQUENCE(1, BL37, BJ37)) -> 2022, 2023, 2024, 2025, 2026 | BN37: =IF(ISNUMBER(SEARCH(BN$1, $BM37)), ($K37/$BL37), "") | BO37: =IF(ISNUMBER(SEARCH(BO$1, $BM37)), ($K37/$BL37), "") | BP37: =IF(ISNUMBER(SEARCH(BP$1, $BM37)), ($K37/$BL37), "") -> 1565059.4 | BQ37: =IF(ISNUMBER(SEARCH(BQ$1, $BM37)), ($K37/$BL37), "") -> 1565059.4 | BR37: =IF(ISNUMBER(SEARCH(BR$1, $BM37)), ($K37/$BL37), "") -> 1565059.4 | BS37: =IF(ISNUMBER(SEARCH(BS$1, $BM37)), ($K37/$BL37), "") -> 1565059.4 | BT37: =IF(ISNUMBER(SEARCH(BT$1, $BM37)), ($K37/$BL37), "") -> 1565059.4 | BU37: =IF(ISNUMBER(SEARCH(BU$1, $BM37)), ($K37/$BL37), "") | ... CC37: =IF(ISNUMBER(SEARCH(CC$1, $BM37)), ($K37/$BL37), "")
A38: Cultured meat and cultured seafood – state of play and future prospects in the EU | D38: airtable | E38: 7000000 | F38: 7000000 | G38: EUR | H38: 7667380 | I38: 7667380 | J38: 7000000 | K38: 7000000 | L38: Committed | M38: checked | N38: https://gfieurope.org/blog/horizon-europe-announces-e25-million-for-sustainable-proteins/ | R38: Original award commitment is EUR 7,000,000. | T38: TBD | U38: n/a | V38: TBD | W38: TBD | X38: TBD | Y38: Europe | Z38: n/a | AE38: Yes | AF38: 45028 | AG38: 2023 | AK38: Not started | AL38: 7667380 | AM38: European Commission | AP38: https://ec.europa.eu/info/funding-tenders/opportunities/portal/screen/opportunities/topic-details/horizon-cl6-2023-farm2fork-01-13;callCode=null;freeTextSearchKeyword=HORIZON-CL6-2023-FARM2FORK-01-13;matchWholeText=true;typeCodes=0,1,2,8;statusCodes=31094501,31094502,31094503;programmePeriod=null;programCcm2Id=43108390;programDivisionCode=null;focusAreaCode=null;destinationGroup=null;missionGroup=null;geographicalZonesCode=null;programmeDivisionProspect=null;startDateLte=null;startDateGte=null;crossCuttingPriorityCode=null;cpvCode=null;performanceOfDelivery=null;sortQuery=sortStatus;orderBy=asc;onlyTenders=false;topicListKey=topicSearchTablePageState | AQ38: Government | AR38: EU | AS38: Europe | AT38: Cultivated | AU38: Meat, Seafood | AW38: Research and development | AX38: Meat, Seafood | BD38: 45035 | BE38: 45035 | BI38: Tier 4 (No GFI involvement) | BJ38: 2023
A39: Center for Innovation in Alternative Proteins (CiPA) | D39: airtable | E39: 7000000 | F39: 7000000 | G39: EUR | H39: 7429065 | I39: 7429065 | J39: 7000000 | K39: 7000000 | L39: Awarded | M39: checked | N39: https://gfieurope.org/blog/catalonia-invest-e7-million-in-cipa-hub-to-lead-alternative-protein-science-in-southern-europe/ | R39: Original award amount is EUR 7,000,000 from the Department of Climate Action, Food and Rural Agenda of the Generalitat of Catalonia and the Institute of Agri-Food Research and Technology (IRTA). | T39: Joan Tibau | U39: n/a | V39: Institute of Agrifood Research and Technology (IRTA) Monells | W39: Government research agency | X39: Spain | Y39: Europe | Z39: n/a | AE39: Yes | AI39: 45208 | AJ39: 4 | AK39: In progress | AL39: 1857266 | AM39: Department of Climate Action, Food and Rural Agenda of the Generalitat of Catalonia, Institute of Agri-Food Research and Technology (IRTA) | AQ39: Government | AR39: Spain | AS39: Europe | AT39: Cross-cutting | AU39: All | AW39: Equipment and infrastructure, Research and development | AX39: =IFERROR(INDEX('full database 2024'!AR:AR, MATCH(A39, 'full database 2024'!B:B, 0)), "") | AZ39: cross-cutting | BD39: 45210 | BE39: 45210 | BI39: Tier 4 (No GFI involvement) | BJ39: 2023 | BK39: 2027 | BL39: =BK39-BJ39+1 -> 5 | BM39: =TEXTJOIN(", ", TRUE, SEQUENCE(1, BL39, BJ39)) -> 2023, 2024, 2025, 2026, 2027 | BN39: =IF(ISNUMBER(SEARCH(BN$1, $BM39)), ($K39/$BL39), "") | BO39: =IF(ISNUMBER(SEARCH(BO$1, $BM39)), ($K39/$BL39), "") | BP39: =IF(ISNUMBER(SEARCH(BP$1, $BM39)), ($K39/$BL39), "") | BQ39: =IF(ISNUMBER(SEARCH(BQ$1, $BM39)), ($K39/$BL39), "") -> 1400000 | BR39: =IF(ISNUMBER(SEARCH(BR$1, $BM39)), ($K39/$BL39), "") -> 1400000 | BS39: =IF(ISNUMBER(SEARCH(BS$1, $BM39)), ($K39/$BL39), "") -> 1400000 | BT39: =IF(ISNUMBER(SEARCH(BT$1, $BM39)), ($K39/$BL39), "") -> 1400000 | BU39: =IF(ISNUMBER(SEARCH(BU$1, $BM39)), ($K39/$BL39), "") -> 1400000 | ... CC39: =IF(ISNUMBER(SEARCH(CC$1, $BM39)), ($K39/$BL39), "")
A40: Synbio Powerlabs scale up facility | B40: With the support of a €2.99 million grant from the Finnish government, Synbio Powerlabs is transforming a large food-grade facility, located near Helsinki, into a multi-purpose site for food innovation. The new facility, due to go live in early 2025, has been designed to help scale the production capabilities of start-ups operating in innovative industries such as precision fermentation, biomass fermentation and cell-based meat. Additional info: https://www.thecellbase.com/posts/ivy-farm-and-synbio-powerlabs-partner-to-produce-cultivated-meat-at-world-s-largest-facility | D40: airtable | E40: 6600000 | F40: 2990000 | G40: EUR | H40: 7170603 | I40: 3248500 | J40: 6600000 | K40: 2990000 | L40: Awarded | M40: checked | N40: https://advancedbiofuelsusa.info/synbio-powerlabs-secures-e-6-6-million-funding-to-build-a-revolutionary-biotechnology-plant-for-precision-fermentation | O40: n/a | R40: Original award amount is EUR 6,600,000. | T40: Nina Pulkkis | U40: n/a | V40: Synbio Powerlabs | W40: For profit | X40: Finland | Y40: Europe | Z40: n/a | AE40: No | AF40: 45428 | AH40: 45427 | AI40: 45427 | AJ40: 2 | AK40: In progress | AL40: 3585302 | AM40: Business Finland | AO40: pilot facility | AQ40: Government | AR40: Finland | AS40: Europe | AT40: Cross-cutting | AU40: CellAg | AW40: Equipment and infrastructure | AX40: =IFERROR(INDEX('full database 2024'!AR:AR, MATCH(A40, 'full database 2024'!B:B, 0)), "") | BD40: 45428 | BE40: 45434 | BI40: Tier 4 (No GFI involvement) | BJ40: 2024 | BK40: 2026 | BL40: =BK40-BJ40+1 -> 3 | BM40: =TEXTJOIN(", ", TRUE, SEQUENCE(1, BL40, BJ40)) -> 2024, 2025, 2026 | BN40: =IF(ISNUMBER(SEARCH(BN$1, $BM40)), ($K40/$BL40), "") | BO40: =IF(ISNUMBER(SEARCH(BO$1, $BM40)), ($K40/$BL40), "") | BP40: =IF(ISNUMBER(SEARCH(BP$1, $BM40)), ($K40/$BL40), "") | BQ40: =IF(ISNUMBER(SEARCH(BQ$1, $BM40)), ($K40/$BL40), "") | BR40: =IF(ISNUMBER(SEARCH(BR$1, $BM40)), ($K40/$BL40), "") -> 996666.67 | BS40: =IF(ISNUMBER(SEARCH(BS$1, $BM40)), ($K40/$BL40), "") -> 996666.67 | BT40: =IF(ISNUMBER(SEARCH(BT$1, $BM40)), ($K40/$BL40), "") -> 996666.67 | BU40: =IF(ISNUMBER(SEARCH(BU$1, $BM40)), ($K40/$BL40), "") | ... CC40: =IF(ISNUMBER(SEARCH(CC$1, $BM40)), ($K40/$BL40), "")
A41: Tasty pea and bean food products: An integrated approach of plant breeding, raw material processing and food product development | D41: airtable | E41: 6000000 | F41: 6000000 | G41: SEK | H41: 564000 | I41: 564000 | J41: =E41*0.091 -> 546000 | K41: =F41*0.091 -> 546000 | L41: Awarded | M41: checked | V41: Swedish University of Agricultural Sciences | X41: Sweden | Y41: Europe | AI41: 44573 | AJ41: 38 | AK41: Ended | AL41: 14842 | AM41: Swedish Research Council for Environment Agricultural Sciences and Spatial Planning (FORMAS) | AQ41: Government | AR41: Sweden | AS41: Europe | AT41: Plant-based | AW41: Research and development | AX41: =IFERROR(INDEX('full database 2024'!AR:AR, MATCH(A41, 'full database 2024'!B:B, 0)), "") | AZ41: cross-cutting | BD41: 45596 | BE41: 45596 | BJ41: 2022 | BK41: 2025 | BL41: =BK41-BJ41+1 -> 4 | BM41: =TEXTJOIN(", ", TRUE, SEQUENCE(1, BL41, BJ41)) -> 2022, 2023, 2024, 2025 | BN41: =IF(ISNUMBER(SEARCH(BN$1, $BM41)), ($K41/$BL41), "") | BO41: =IF(ISNUMBER(SEARCH(BO$1, $BM41)), ($K41/$BL41), "") | BP41: =IF(ISNUMBER(SEARCH(BP$1, $BM41)), ($K41/$BL41), "") -> 136500 | BQ41: =IF(ISNUMBER(SEARCH(BQ$1, $BM41)), ($K41/$BL41), "") -> 136500 | BR41: =IF(ISNUMBER(SEARCH(BR$1, $BM41)), ($K41/$BL41), "") -> 136500 | BS41: =IF(ISNUMBER(SEARCH(BS$1, $BM41)), ($K41/$BL41), "") -> 136500 | BT41: =IF(ISNUMBER(SEARCH(BT$1, $BM41)), ($K41/$BL41), "") | BU41: =IF(ISNUMBER(SEARCH(BU$1, $BM41)), ($K41/$BL41), "") | ... CC41: =IF(ISNUMBER(SEARCH(CC$1, $BM41)), ($K41/$BL41), "")
A42: Tackling barriers to increased acceptance of meat analogues through taste enhancement using healthy fats | B42: Substituting meat with more environmentally friendly proteins such as meat analogues has become more accepted by consumers. However, resistance grounded in taste preferences persists. Fats are a key carrier of flavor and represent an opportunity for sensorial improvement in these products. Meat analogues often contain fats rich in healthy unsaturated fatty acids, which are typically liquid at room temperature (RT), affecting their mechanical and structural properties. The impact of this on the sensory experience is under-researched. The potential for using oleogels, which are more solid at RT and thus closer in mechanical terms to the fats found in meat, here is also relatively unknown. This project aims to assess the role of healthy vegetable fats and oleogels in enhancing the taste of meat analogues. Prototypes varying in fat type, content, and processing will be developed, evaluated sensorially (profiling and liking) and behaviorally (performance in meal preparation), and benchmarked against existing commercial products. The prototypes will also be comprehensively characterized instrumentally in order to describe the sensory data in physiochemical terms, increasing knowledge on the origin of the sensory experiences and expediting future product development. | D42: airtable | E42: 6000000 | F42: 6000000 | G42: SEK | H42: 564000 | I42: 564000 | J42: =E42*0.091 -> 546000 | K42: =F42*0.091 -> 546000 | L42: Awarded | M42: checked | N42: https://www.vr.se/swecris.html#/project/2022-01928_Formas | O42: grant.13285563 | T42: Annika Krona | V42: RISE Research Institutes of Sweden | X42: Sweden | Y42: Europe | AI42: 44896 | AJ42: 36 | AK42: Progress | AL42: 15667 | AM42: Swedish Research Council for Environment Agricultural Sciences and Spatial Planning (FORMAS) | AQ42: Government | AR42: Sweden | AS42: Europe | AT42: Plant-based | AW42: Research and development | AX42: =IFERROR(INDEX('full database 2024'!AR:AR, MATCH(A42, 'full database 2024'!B:B, 0)), "") | AZ42: End product formulation | BD42: 45596 | BE42: 45779 | BJ42: 2022 | BK42: 2025 | BL42: =BK42-BJ42+1 -> 4 | BM42: =TEXTJOIN(", ", TRUE, SEQUENCE(1, BL42, BJ42)) -> 2022, 2023, 2024, 2025 | BN42: =IF(ISNUMBER(SEARCH(BN$1, $BM42)), ($K42/$BL42), "") | BO42: =IF(ISNUMBER(SEARCH(BO$1, $BM42)), ($K42/$BL42), "") | BP42: =IF(ISNUMBER(SEARCH(BP$1, $BM42)), ($K42/$BL42), "") -> 136500 | BQ42: =IF(ISNUMBER(SEARCH(BQ$1, $BM42)), ($K42/$BL42), "") -> 136500 | BR42: =IF(ISNUMBER(SEARCH(BR$1, $BM42)), ($K42/$BL42), "") -> 136500 | BS42: =IF(ISNUMBER(SEARCH(BS$1, $BM42)), ($K42/$BL42), "") -> 136500 | BT42: =IF(ISNUMBER(SEARCH(BT$1, $BM42)), ($K42/$BL42), "") | BU42: =IF(ISNUMBER(SEARCH(BU$1, $BM42)), ($K42/$BL42), "") | ... CC42: =IF(ISNUMBER(SEARCH(CC$1, $BM42)), ($K42/$BL42), "")
A43: A strong pulse - resilient Swedish grain legume supply from field and factory to fork | B43: Resilient supply of domestic grain legumes for human food will increase Sweden’s disaster preparedness and feed the population in an uncertain future. Grain legume cultivation and processing will increase food system resilience by added nutrients, less need for fertilizer, low environmental impact, and exploiting growing conditions in Sweden. This project aims to create a more sustainable, resilient food system by expanding Swedish capacity for growing plant-based proteins; optimizing production chains by increasing primary production of grain legumes; and developing novel foods from a plant-based intermediary (hydrogel). In work package (WP1), we will simulate expanded Swedish grain legume production and assess economic and environmental impacts. In WP2, we will optimize potential Swedish grain legumes as model substrates and develop pre-treatments to reduce anti-nutritional factors and off-flavors, moderate particle size and improve gel stabilization in plant-based proteins. WP3 will investigate interactions between protein gel matrix and flavor additives to improve texture, sensory properties and flavor release in the food matrix. In WP4, we will assess the resilience of primary and secondary domestic grain legume production and evaluate effects on resilience of exposure to severe disturbances. Policy support will be developed in WP5, in close collaboration with researchers in food science, agricultural economics and policy, and environmental science and technology. | D43: airtable | E43: 5999351 | F43: 5999351 | G43: SEK | H43: 563939 | I43: 563939 | J43: =E43*0.091 -> 545940.94 | K43: =F43*0.091 -> 545940.94 | L43: Awarded | M43: checked | N43: https://www.vr.se/swecris.html#/project/2022-02407_Formas | O43: grant.13285726 | V43: Swedish University of Agricultural Sciences | X43: Sweden | Y43: Europe | AI43: 44573 | AJ43: 38 | AK43: Ended | AL43: 14840 | AM43: Swedish Research Council for Environment Agricultural Sciences and Spatial Planning (FORMAS) | AQ43: Government | AR43: Sweden | AS43: Europe | AT43: Plant-based | AW43: Research and development | AX43: =IFERROR(INDEX('full database 2024'!AR:AR, MATCH(A43, 'full database 2024'!B:B, 0)), "") | AZ43: Crop development, Ingredient optimisation | BD43: 45596 | BE43: 45779 | BJ43: 2022 | BK43: 2025 | BL43: =BK43-BJ43+1 -> 4 | BM43: =TEXTJOIN(", ", TRUE, SEQUENCE(1, BL43, BJ43)) -> 2022, 2023, 2024, 2025 | BN43: =IF(ISNUMBER(SEARCH(BN$1, $BM43)), ($K43/$BL43), "") | BO43: =IF(ISNUMBER(SEARCH(BO$1, $BM43)), ($K43/$BL43), "") | BP43: =IF(ISNUMBER(SEARCH(BP$1, $BM43)), ($K43/$BL43), "") -> 136485.24 | BQ43: =IF(ISNUMBER(SEARCH(BQ$1, $BM43)), ($K43/$BL43), "") -> 136485.24 | BR43: =IF(ISNUMBER(SEARCH(BR$1, $BM43)), ($K43/$BL43), "") -> 136485.24 | BS43: =IF(ISNUMBER(SEARCH(BS$1, $BM43)), ($K43/$BL43), "") -> 136485.24 | BT43: =IF(ISNUMBER(SEARCH(BT$1, $BM43)), ($K43/$BL43), "") | BU43: =IF(ISNUMBER(SEARCH(BU$1, $BM43)), ($K43/$BL43), "") | ... CC43: =IF(ISNUMBER(SEARCH(CC$1, $BM43)), ($K43/$BL43), "")
A44: SensAlg - A sensory foundation for increased consumption of Swedish macroalgae | D44: airtable | E44: 5998593 | F44: 5998593 | G44: SEK | H44: 563868 | I44: 563868 | J44: =E44*0.091 -> 545871.96 | K44: =F44*0.091 -> 545871.96 | L44: Awarded | M44: checked | V44: Uppsala University | X44: Sweden | Y44: Europe | AI44: 44573 | AJ44: 38 | AK44: Ended | AL44: 14839 | AM44: Swedish Research Council for Environment Agricultural Sciences and Spatial Planning (FORMAS) | AQ44: Government | AR44: Sweden | AS44: Europe | AT44: Plant-based | AW44: Research and development | AX44: =IFERROR(INDEX('full database 2024'!AR:AR, MATCH(A44, 'full database 2024'!B:B, 0)), "") | AZ44: Ingredient optimisation | BD44: 45596 | BE44: 45596 | BJ44: 2022 | BK44: 2025 | BL44: =BK44-BJ44+1 -> 4 | BM44: =TEXTJOIN(", ", TRUE, SEQUENCE(1, BL44, BJ44)) -> 2022, 2023, 2024, 2025 | BN44: =IF(ISNUMBER(SEARCH(BN$1, $BM44)), ($K44/$BL44), "") | BO44: =IF(ISNUMBER(SEARCH(BO$1, $BM44)), ($K44/$BL44), "") | BP44: =IF(ISNUMBER(SEARCH(BP$1, $BM44)), ($K44/$BL44), "") -> 136467.99 | BQ44: =IF(ISNUMBER(SEARCH(BQ$1, $BM44)), ($K44/$BL44), "") -> 136467.99 | BR44: =IF(ISNUMBER(SEARCH(BR$1, $BM44)), ($K44/$BL44), "") -> 136467.99 | BS44: =IF(ISNUMBER(SEARCH(BS$1, $BM44)), ($K44/$BL44), "") -> 136467.99 | BT44: =IF(ISNUMBER(SEARCH(BT$1, $BM44)), ($K44/$BL44), "") | BU44: =IF(ISNUMBER(SEARCH(BU$1, $BM44)), ($K44/$BL44), "") | ... CC44: =IF(ISNUMBER(SEARCH(CC$1, $BM44)), ($K44/$BL44), "")
A45: IMPROVED VALORIZATION OF MARINE SOURCES AND PROCESSING WASTE FOR RESOURCE EFFICIENT BLUE FOOD/FEED AND ENVIRONMENTALLY SUSTAINABLE MATERIALS DEVELOPMENT | D45: airtable | E45: 5613000 | F45: 5613000 | G45: SEK | H45: 527622 | I45: 527622 | J45: =E45*0.091 -> 510783 | K45: =F45*0.091 -> 510783 | L45: Awarded | M45: checked | V45: KTH, Royal Institute of Technology | X45: Sweden | Y45: Europe | AI45: 45293 | AJ45: 37 | AK45: Progress | AL45: 14260 | AM45: Swedish Research Council for Environment Agricultural Sciences and Spatial Planning (FORMAS) | AQ45: Government | AR45: Sweden | AS45: Europe | AT45: Plant-based | AW45: Research and development | AX45: Agnostic | AZ45: Ingredient optimisation, Feedstocks | BD45: 45596 | BE45: 45596 | BJ45: 2024 | BK45: 2027 | BL45: =BK45-BJ45+1 -> 4 | BM45: =TEXTJOIN(", ", TRUE, SEQUENCE(1, BL45, BJ45)) -> 2024, 2025, 2026, 2027 | BN45: =IF(ISNUMBER(SEARCH(BN$1, $BM45)), ($K45/$BL45), "") | BO45: =IF(ISNUMBER(SEARCH(BO$1, $BM45)), ($K45/$BL45), "") | BP45: =IF(ISNUMBER(SEARCH(BP$1, $BM45)), ($K45/$BL45), "") | BQ45: =IF(ISNUMBER(SEARCH(BQ$1, $BM45)), ($K45/$BL45), "") | BR45: =IF(ISNUMBER(SEARCH(BR$1, $BM45)), ($K45/$BL45), "") -> 127695.75 | BS45: =IF(ISNUMBER(SEARCH(BS$1, $BM45)), ($K45/$BL45), "") -> 127695.75 | BT45: =IF(ISNUMBER(SEARCH(BT$1, $BM45)), ($K45/$BL45), "") -> 127695.75 | BU45: =IF(ISNUMBER(SEARCH(BU$1, $BM45)), ($K45/$BL45), "") -> 127695.75 | ... CC45: =IF(ISNUMBER(SEARCH(CC$1, $BM45)), ($K45/$BL45), "")
A46: HYDROCOW: generating milk from carbon dioxide and electricity | D46: airtable | E46: 5500000 | F46: 5500000 | G46: EUR | H46: 5983477 | I46: 5983477 | J46: 5500000 | K46: 5500000 | L46: Awarded | M46: checked | N46: https://tech.eu/2023/09/11/hydrocow-generating-milk-from-carbon-dioxide-and-electricity/ | R46: Original award amount is EUR 5,500,000. | T46: Pasi Vainikka | U46: n/a | V46: Solar Foods | W46: For profit | X46: Finland | Y46: Europe | Z46: n/a | AD46: University of Groningen, RWTH Aachen University, FGen AG | AE46: Yes | AI46: 45180 | AJ46: 4 | AK46: In progress | AL46: 1495869 | AM46: European Commission | AN46: European Innovation Council (EIC) | AQ46: Government | AR46: EU | AS46: Europe | AT46: Fermentation | AU46: PF | AW46: Research and development | AX46: =IFERROR(INDEX('full database 2024'!AR:AR, MATCH(A46, 'full database 2024'!B:B, 0)), "") | AY46: Milk | AZ46: Feedstocks, Bioprocess design | BD46: 45245 | BE46: 45247 | BI46: Tier 4 (No GFI involvement) | BJ46: 2023 | BK46: 2027 | BL46: =BK46-BJ46+1 -> 5 | BM46: =TEXTJOIN(", ", TRUE, SEQUENCE(1, BL46, BJ46)) -> 2023, 2024, 2025, 2026, 2027 | BN46: =IF(ISNUMBER(SEARCH(BN$1, $BM46)), ($K46/$BL46), "") | BO46: =IF(ISNUMBER(SEARCH(BO$1, $BM46)), ($K46/$BL46), "") | BP46: =IF(ISNUMBER(SEARCH(BP$1, $BM46)), ($K46/$BL46), "") | BQ46: =IF(ISNUMBER(SEARCH(BQ$1, $BM46)), ($K46/$BL46), "") -> 1100000 | BR46: =IF(ISNUMBER(SEARCH(BR$1, $BM46)), ($K46/$BL46), "") -> 1100000 | BS46: =IF(ISNUMBER(SEARCH(BS$1, $BM46)), ($K46/$BL46), "") -> 1100000 | BT46: =IF(ISNUMBER(SEARCH(BT$1, $BM46)), ($K46/$BL46), "") -> 1100000 | BU46: =IF(ISNUMBER(SEARCH(BU$1, $BM46)), ($K46/$BL46), "") -> 1100000 | ... CC46: =IF(ISNUMBER(SEARCH(CC$1, $BM46)), ($K46/$BL46), "")
A47: FERMI: FErmentations optimized by Rational Models to Improve plant-based substrates | B47: The food supply chain is responsible for 26% of the global greenhouse gas emissions. Switching to more plant-based diets is expected to have a considerable impact for the reduction of greenhouse gases but plant-proteins often do not have the desired sensory, techno-functional, or nutritional properties. Fermentation can improve these properties, but our understanding of the underlying biochemical reactions is limited. In this project we will combine high tech analytical methods with artificial intelligence to predict and validate the unknown microbial functions. This will allow to rationally design optimal fermentations to make more tasty, healthy, and sustainable plant-based foods. | D47: airtable | E47: 5300000 | F47: 2650000 | G47: EUR | H47: 5752222 | I47: 2876111 | J47: 5300000 | K47: 2650000 | L47: Awarded | M47: checked | N47: https://www.nwo.nl/en/researchprogrammes/perspectief/perspectief-grants/fermi-fermentations-optimized-by-rational-models-to-improve-plant-based-substrates | O47: grant.14369095 | R47: Original award amount is EUR 5,300,000. Exact government contribution is unknown but is estimated based on RFA statement that the government contribution will be at least 50% of the total project cost. | S47: GFI grantee Eddy Smid is involved in this project. The Mediterranean Food Lab is a GFI grantee alum. | T47: Herwig Bachmann | U47: Systems Biology | V47: VU Amsterdam | W47: University | X47: Netherlands | Y47: Europe | Z47: n/a | AD47: Delft University of Technology, VU University, Wageningen University and Research, Arla, Brannatura, Chr. Hansen A/S, Ferrero, FrieslandCampina, INTERNATIONAL FLAVORS & FRAGRANCES IFF, Mediterranean Food Lab, NIZO Food Research, Roquette Canada, Upfield | AE47: Yes | AI47: 45323 | AJ47: 6 | AK47: In progress | AL47: 958704 | AM47: Dutch Research Council (NWO) | AQ47: Joint public/private partnership | AR47: Netherlands | AS47: Europe | AT47: Plant-based | AU47: TF | AW47: Research and development | AX47: =IFERROR(INDEX('full database 2024'!AR:AR, MATCH(A47, 'full database 2024'!B:B, 0)), "") | AZ47: Ingredient optimisation | BA47: checked | BD47: 45341 | BE47: 45644 | BI47: Tier 4 (No GFI involvement) | BJ47: 2024 | BK47: 2030 | BL47: =BK47-BJ47+1 -> 7 | BM47: =TEXTJOIN(", ", TRUE, SEQUENCE(1, BL47, BJ47)) -> 2024, 2025, 2026, 2027, 2028, 2029, 2030 | BN47: =IF(ISNUMBER(SEARCH(BN$1, $BM47)), ($K47/$BL47), "") | BO47: =IF(ISNUMBER(SEARCH(BO$1, $BM47)), ($K47/$BL47), "") | BP47: =IF(ISNUMBER(SEARCH(BP$1, $BM47)), ($K47/$BL47), "") | BQ47: =IF(ISNUMBER(SEARCH(BQ$1, $BM47)), ($K47/$BL47), "") | BR47: =IF(ISNUMBER(SEARCH(BR$1, $BM47)), ($K47/$BL47), "") -> 378571.43 | BS47: =IF(ISNUMBER(SEARCH(BS$1, $BM47)), ($K47/$BL47), "") -> 378571.43 | BT47: =IF(ISNUMBER(SEARCH(BT$1, $BM47)), ($K47/$BL47), "") -> 378571.43 | BU47: =IF(ISNUMBER(SEARCH(BU$1, $BM47)), ($K47/$BL47), "") -> 378571.43 | ... CC47: =IF(ISNUMBER(SEARCH(CC$1, $BM47)), ($K47/$BL47), "")
A48: CULTUREDMEAT | D48: airtable | E48: 5200000 | F48: 5200000 | G48: EUR | H48: 6310000 | I48: 6310000 | J48: 5200000 | K48: 5200000 | L48: Awarded | M48: checked | N48: https://www.bio-hk.com/news/industry-news/spains-biotech-foods-to-lead-us6-3m-government-backed-cultured-meat-project/ | R48: Original award amount is EUR 5,200,000. | T48: Iñigo Charola | U48: n/a | V48: Biotech Foods SL | W48: For profit | X48: Spain | Y48: Europe | Z48: n/a | AD48: BDI Biotech, Neoalgae, Argal, Autonomous University of Madrid, Oviedo University, Barcelona Science Park, University of Seville, University of Granada | AE48: Yes | AI48: 44217 | AJ48: 3 | AK48: In progress | AL48: 2103333 | AM48: Center for Industrial Technological Development (CDTI) | AQ48: Government | AR48: Spain | AS48: Europe | AT48: Cultivated | AW48: Research and development | AX48: =IFERROR(INDEX('full database 2024'!AR:AR, MATCH(A48, 'full database 2024'!B:B, 0)), "") | AZ48: Cell line development, Cell culture media | BD48: 44985 | BE48: 45035 | BI48: Tier 3 (Minimal GFI involvement, e.g. LoS) | BJ48: 2021 | BK48: 2024 | BL48: =BK48-BJ48+1 -> 4 | BM48: =TEXTJOIN(", ", TRUE, SEQUENCE(1, BL48, BJ48)) -> 2021, 2022, 2023, 2024 | BN48: =IF(ISNUMBER(SEARCH(BN$1, $BM48)), ($K48/$BL48), "") | BO48: =IF(ISNUMBER(SEARCH(BO$1, $BM48)), ($K48/$BL48), "") -> 1300000 | BP48: =IF(ISNUMBER(SEARCH(BP$1, $BM48)), ($K48/$BL48), "") -> 1300000 | BQ48: =IF(ISNUMBER(SEARCH(BQ$1, $BM48)), ($K48/$BL48), "") -> 1300000 | BR48: =IF(ISNUMBER(SEARCH(BR$1, $BM48)), ($K48/$BL48), "") -> 1300000 | BS48: =IF(ISNUMBER(SEARCH(BS$1, $BM48)), ($K48/$BL48), "") | BT48: =IF(ISNUMBER(SEARCH(BT$1, $BM48)), ($K48/$BL48), "") | BU48: =IF(ISNUMBER(SEARCH(BU$1, $BM48)), ($K48/$BL48), "") | ... CC48: =IF(ISNUMBER(SEARCH(CC$1, $BM48)), ($K48/$BL48), "")
A49: New sustainable proteins for food, feed and non-food bio-based applications (InnoProtein) | B49: InnoProtein addresses this challenge by tapping into unexploited sustainable protein sources to accelerate Europe’s moves towards protein self-sufficiency. The project aims to obtain single-cell proteins from sources including microalgae, bacteria and fungi and proteins from insects. They will be used in food, animal feed and non-food bio-based products such as stimulants and plastics within a circular and zero-waste perspective. | D49: airtable | E49: 5043848 | F49: 4592392 | G49: EUR | H49: 5447355 | I49: 4959783 | J49: 5043848 | K49: 4592392 | L49: Awarded | M49: checked | N49: https://www.cbe.europa.eu/projects/innoprotein | V49: FUNDACION TECNALIA RESEARCH & INNOVATION | X49: Spain | Y49: Europe | AD49: AIMPLAS - ASOCIACION DE INVESTIGACION DE MATERIALES PLASTICOS Y CONEXAS, BIOTREND-INOVACAO E ENGENHARIA EM BIOTECNOLOGIA SA, A4F ALGAFUEL SA, NATURSTOFF-TECHNIK GMBH, COMGRAF SAS, SUEROS Y DERIVADOS SL, PROMIC SA, VYZKUMNY USTAV VETERINARNIHO LEKARSTVI, TECHNOLOGICAL UNIVERSITY DUBLIN, BIOZOON GMBH, ENKOA SYSTEMS SL, ZERO EMISSIONS ENGINEERING BV, EUROPEAN FOOD INFORMATION COUNCIL, SCL ITALIA SPA | AI49: 45078 | AK49: Completed | AL49: 5447355 | AM49: European Commission | AN49: Circular Bio-based Europe Joint Undertaking (CBE JU) | AQ49: Government | AR49: EU | AS49: Europe | AT49: Cross-cutting | AW49: Research and development | AX49: Agnostic | AZ49: Bioprocess design, Ingredient optimisation | BD49: 45596 | BE49: 45596 | BJ49: 2022 | BK49: 2022 | BL49: =BK49-BJ49+1 -> 1 | BM49: =TEXTJOIN(", ", TRUE, SEQUENCE(1, BL49, BJ49)) -> 2022 | BN49: =IF(ISNUMBER(SEARCH(BN$1, $BM49)), ($K49/$BL49), "") | BO49: =IF(ISNUMBER(SEARCH(BO$1, $BM49)), ($K49/$BL49), "") | BP49: =IF(ISNUMBER(SEARCH(BP$1, $BM49)), ($K49/$BL49), "") -> 4592392 | BQ49: =IF(ISNUMBER(SEARCH(BQ$1, $BM49)), ($K49/$BL49), "") | BR49: =IF(ISNUMBER(SEARCH(BR$1, $BM49)), ($K49/$BL49), "") | BS49: =IF(ISNUMBER(SEARCH(BS$1, $BM49)), ($K49/$BL49), "") | BT49: =IF(ISNUMBER(SEARCH(BT$1, $BM49)), ($K49/$BL49), "") | BU49: =IF(ISNUMBER(SEARCH(BU$1, $BM49)), ($K49/$BL49), "") | ... CC49: =IF(ISNUMBER(SEARCH(CC$1, $BM49)), ($K49/$BL49), "")
A50: Leveraging Scaffolding-, Emulsion-, and Extrusion Technologies to Enable the Production of Healthy and Sustainable Composite Meat Alternatives | B50: This first generation of meat alternatives do not yet fulfill broad consumer demands on eating quality traits including structure, juiciness, and tenderness, and often contains high proportions of unhealthy saturated fatty acids. Thus, the aim of this project is to develop critical scientific understanding that could pave the way for production of the next generation of meat alternatives by leveraging scaffolding, emulsion, and extrusion technologies. In WP 1, we will investigate the possibility of integrating plant-based scaffolds and animal cells to produce structured cultivated meats. In WPs 2-3, we will combine emulsion and extrusion technologies to provide plant protein-based meat alternatives with the tenderness and juiciness they are lacking, which is currently an outstanding challenge the industry is facing. In addition, we will explore the possibilities of using cultivated meats to further provide them with muscle meat-like texture. In WP 4, we will use locally attractive Swedish ingredients to produce hybrid meat alternatives based on the newfound knowledge from WPs 1-3. WP 5 will be focused on dissemination of acquired knowledge, identification of potential collaborators, and preparation for taking the knowledge derived to higher TRL-levels together with industrial collaborators. The project is expected to uncover the potential of producing the next generation of healthy and sustainable meat alternatives applied to different raw materials from Sweden and beyond. | D50: airtable | E50: 4970184 | F50: 4970184 | G50: SEK | H50: 467197 | I50: 467197 | J50: =E50*0.091 -> 452286.74 | K50: =F50*0.091 -> 452286.74 | L50: Awarded | M50: checked | N50: https://www.vr.se/swecris.html#/project/2022-02804_Formas | O50: grant.13528598 | T50: Mursalin Sajib | V50: Chalmers tekniska högskola | X50: Sweden | Y50: Europe | AI50: 45139 | AJ50: 36 | AK50: Progress | AL50: 12978 | AM50: Swedish Research Council for Environment Agricultural Sciences and Spatial Planning (FORMAS) | AQ50: Government | AR50: Sweden | AS50: Europe | AT50: Cross-cutting | AU50: CM for PB | AW50: Research and development | AX50: =IFERROR(INDEX('full database 2024'!AR:AR, MATCH(A50, 'full database 2024'!B:B, 0)), "") | AZ50: Texturisation methods | BD50: 45596 | BE50: 45779 | BJ50: 2023 | BK50: 2025 | BL50: =BK50-BJ50+1 -> 3 | BM50: =TEXTJOIN(", ", TRUE, SEQUENCE(1, BL50, BJ50)) -> 2023, 2024, 2025 | BN50: =IF(ISNUMBER(SEARCH(BN$1, $BM50)), ($K50/$BL50), "") | BO50: =IF(ISNUMBER(SEARCH(BO$1, $BM50)), ($K50/$BL50), "") | BP50: =IF(ISNUMBER(SEARCH(BP$1, $BM50)), ($K50/$BL50), "") | BQ50: =IF(ISNUMBER(SEARCH(BQ$1, $BM50)), ($K50/$BL50), "") -> 150762.25 | BR50: =IF(ISNUMBER(SEARCH(BR$1, $BM50)), ($K50/$BL50), "") -> 150762.25 | BS50: =IF(ISNUMBER(SEARCH(BS$1, $BM50)), ($K50/$BL50), "") -> 150762.25 | BT50: =IF(ISNUMBER(SEARCH(BT$1, $BM50)), ($K50/$BL50), "") | BU50: =IF(ISNUMBER(SEARCH(BU$1, $BM50)), ($K50/$BL50), "") | ... CC50: =IF(ISNUMBER(SEARCH(CC$1, $BM50)), ($K50/$BL50), "")
A51: Fermented seaweed as a new high-value ingredient for the food and nutraceuticals markets | B51: Purpose and goal: The growing occurrence of dietary and lifestyle-related diseases combined with climate change has urged the need to rethink what we eat. People want healthier, more sustainable and plant-based foods that offer health benefits paired with reduced emissions. Seaweed can perfectly fill this gap, but still has unsolved quality and supply chain issues. Through fermentation processing we will unlock seaweed health and flavour potential and solve the production bottlenecks needed to conquer the market. Expected results and effects: SEAPRO goals and results are two-fold: Scientific: 1) Establish timing for the deployment and harvest of two species, Saccharina latissima (S.L.) and Alaria esculenta 2) Formulation of the optimal fermentation conditions that ensures improved: - taste, flavour and increased microbiological stability (shelf-life up to >2 months). Technological: 1) A fully developed and scalable fermented seaweed production process, which allows storing seaweed over longer periods (2 months) 2) Develop and validate the complete value chain with industrial-scale capability (WP6). Approach and implementation: SEAPRO’s unique fermentation concept will allow us to meet upcoming demand using adapted cultivation. We will offer seaweed raw material with demonstrated functional benefits adapted to the needs of the food and nutraceutical markets. The features are: - a highly efficient method for stabilising wet biomass - a markedly reduced production cost - refining of sensorial (texture, taste and appearance) and health properties, - improvement of food safety and shelf life of non-dried products, through a completely traceable and certified production pathway | D51: airtable | E51: 4920671 | F51: 4920671 | G51: SEK | H51: 462543 | I51: 462543 | J51: =E51*0.091 -> 447781.06 | K51: =F51*0.091 -> 447781.06 | L51: Awarded | M51: checked | N51: https://www.vr.se/swecris.html#/project/2021-03368_Vinnova | O51: grant.9881554 | R51: Pulled from database | T51: Olof Böök | V51: Aventure AB | X51: Sweden | Y51: Europe | AI51: 44205 | AJ51: 37 | AK51: Ended | AL51: 12501 | AM51: Vinnova | AQ51: Government | AR51: Sweden | AS51: Europe | AT51: Plant-based | AU51: TF | AW51: Research and development | AX51: =IFERROR(INDEX('full database 2024'!AR:AR, MATCH(A51, 'full database 2024'!B:B, 0)), "") | AZ51: Ingredient optimisation | BD51: 45596 | BE51: 45596 | BJ51: 2021 | BK51: 2024 | BL51: =BK51-BJ51+1 -> 4 | BM51: =TEXTJOIN(", ", TRUE, SEQUENCE(1, BL51, BJ51)) -> 2021, 2022, 2023, 2024 | BN51: =IF(ISNUMBER(SEARCH(BN$1, $BM51)), ($K51/$BL51), "") | BO51: =IF(ISNUMBER(SEARCH(BO$1, $BM51)), ($K51/$BL51), "") -> 111945.27 | BP51: =IF(ISNUMBER(SEARCH(BP$1, $BM51)), ($K51/$BL51), "") -> 111945.27 | BQ51: =IF(ISNUMBER(SEARCH(BQ$1, $BM51)), ($K51/$BL51), "") -> 111945.27 | BR51: =IF(ISNUMBER(SEARCH(BR$1, $BM51)), ($K51/$BL51), "") -> 111945.27 | BS51: =IF(ISNUMBER(SEARCH(BS$1, $BM51)), ($K51/$BL51), "") | BT51: =IF(ISNUMBER(SEARCH(BT$1, $BM51)), ($K51/$BL51), "") | BU51: =IF(ISNUMBER(SEARCH(BU$1, $BM51)), ($K51/$BL51), "") | ... CC51: =IF(ISNUMBER(SEARCH(CC$1, $BM51)), ($K51/$BL51), "")
A52: Onego Bio egg white technology | D52: airtable | E52: 4500000 | F52: 4500000 | G52: EUR | H52: 4768402 | I52: 4768402 | J52: 4500000 | K52: 4500000 | L52: Awarded | M52: checked | N52: https://www.labiotech.eu/trends-news/onego-bio-funding-sustainable-egg-white/ | R52: Original award amount is EUR 4,500,000. Onego Bio is a biotech spin-off from VTT Technical Research Centre of Finland. | T52: Maija Itkonen | U52: n/a | V52: Onego Bio | W52: For profit | X52: Finland | Y52: Europe | Z52: n/a | AE52: No | AI52: 44812 | AJ52: 2 | AK52: In progress | AL52: 2384201 | AM52: Business Finland | AQ52: Government | AR52: Finland | AS52: Europe | AT52: Fermentation | AU52: PF | AW52: Research and development | AX52: =IFERROR(INDEX('full database 2024'!AR:AR, MATCH(A52, 'full database 2024'!B:B, 0)), "") | AZ52: Bioprocess design | BD52: 44985 | BE52: 45035 | BI52: Tier 4 (No GFI involvement) | BJ52: 2022 | BK52: 2024 | BL52: =BK52-BJ52+1 -> 3 | BM52: =TEXTJOIN(", ", TRUE, SEQUENCE(1, BL52, BJ52)) -> 2022, 2023, 2024 | BN52: =IF(ISNUMBER(SEARCH(BN$1, $BM52)), ($K52/$BL52), "") | BO52: =IF(ISNUMBER(SEARCH(BO$1, $BM52)), ($K52/$BL52), "") | BP52: =IF(ISNUMBER(SEARCH(BP$1, $BM52)), ($K52/$BL52), "") -> 1500000 | BQ52: =IF(ISNUMBER(SEARCH(BQ$1, $BM52)), ($K52/$BL52), "") -> 1500000 | BR52: =IF(ISNUMBER(SEARCH(BR$1, $BM52)), ($K52/$BL52), "") -> 1500000 | BS52: =IF(ISNUMBER(SEARCH(BS$1, $BM52)), ($K52/$BL52), "") | BT52: =IF(ISNUMBER(SEARCH(BT$1, $BM52)), ($K52/$BL52), "") | BU52: =IF(ISNUMBER(SEARCH(BU$1, $BM52)), ($K52/$BL52), "") | ... CC52: =IF(ISNUMBER(SEARCH(CC$1, $BM52)), ($K52/$BL52), "")
A53: E!381, FAVORIT, The Green Dairy Sweden Holding AB | B53: Purpose and goal: The project will develop plant-based dairy products based on fermented fava bean with a minimum of additives, as a resilient and sustainable alternative to soy. The goal is a market introduction of healthy and sustainable yogurt-like products from Nordic crops and natural bioprocesses. Partners: The Green Dairy, TFTAK (Estonia), Lund University. Expected results and effects: Competitors use questionable additives to create plant-based yogurt products instead of natural bioprocesses. A prestudy by the project partners has shown that fermented fava bean has great market potential for yogurt-like products. The project will scale this complex bioprocess from lab scale to mass production and market introduction. Approach and implementation: Raw materials and bacterial cultures are analyzed and selected. The production process is developed from lab scale to full scale, in dialogue with producers. Natural additives (berries, herbs, etc.) are evaluated. A human intervention study by Lund University will provide information about effects on gut microbiome, blood analytes and wellbeing compared to traditional products. A market strategy is developed. | D53: airtable | E53: 4356398 | F53: 4356398 | G53: SEK | H53: 409501 | I53: 409501 | J53: =E53*0.091 -> 396432.22 | K53: =F53*0.091 -> 396432.22 | L53: Awarded | M53: checked | N53: https://www.vr.se/swecris.html#/project/2022-00807_Vinnova | O53: grant.12896203 | V53: The Green Dairy Sweden Holding AB | X53: Sweden | Y53: Europe | AI53: 44565 | AJ53: 37 | AK53: Ended | AL53: 11068 | AM53: Vinnova | AQ53: Government | AR53: Sweden | AS53: Europe | AT53: Plant-based | AW53: Research and development | AX53: =IFERROR(INDEX('full database 2024'!AR:AR, MATCH(A53, 'full database 2024'!B:B, 0)), "") | AY53: Yoghurt | AZ53: Host strain development , End product formulation | BD53: 45596 | BE53: 45779 | BJ53: 2022 | BK53: 2026 | BL53: =BK53-BJ53+1 -> 5 | BM53: =TEXTJOIN(", ", TRUE, SEQUENCE(1, BL53, BJ53)) -> 2022, 2023, 2024, 2025, 2026 | BN53: =IF(ISNUMBER(SEARCH(BN$1, $BM53)), ($K53/$BL53), "") | BO53: =IF(ISNUMBER(SEARCH(BO$1, $BM53)), ($K53/$BL53), "") | BP53: =IF(ISNUMBER(SEARCH(BP$1, $BM53)), ($K53/$BL53), "") -> 79286.444 | BQ53: =IF(ISNUMBER(SEARCH(BQ$1, $BM53)), ($K53/$BL53), "") -> 79286.444 | BR53: =IF(ISNUMBER(SEARCH(BR$1, $BM53)), ($K53/$BL53), "") -> 79286.444 | BS53: =IF(ISNUMBER(SEARCH(BS$1, $BM53)), ($K53/$BL53), "") -> 79286.444 | BT53: =IF(ISNUMBER(SEARCH(BT$1, $BM53)), ($K53/$BL53), "") -> 79286.444 | BU53: =IF(ISNUMBER(SEARCH(BU$1, $BM53)), ($K53/$BL53), "") | ... CC53: =IF(ISNUMBER(SEARCH(CC$1, $BM53)), ($K53/$BL53), "")
A54: Marie Skłodowska-Curie Action Edible Soft Matter | B54: Food and environmental transitions are worldwide major challenges as illustrated by the Farm to Fork Strategy, at the heart of the EU Green Deal, and by the United Nations Development Goals. Sustainable and healthy food requires an urgent shift from a diet rich in animal-based ingredients towards a diet enriched in plant-based ingredients. This is the challenge behind the Edible Soft Matter (ESM) project. Soft matter science has been tremendously successful in tackling complex problems involving multicomponent materials with a wide range of length and time scales and is now recognised as providing unique perspectives to understand the complexity of foods and to design new foods. ESM objective is to train and develop the employability of a new generation of eighteen young researchers, regulators, consultants and project leaders by providing them with a unique expertise in the design, production and quality assessment of innovative plant-based food products. The ESM Doctoral Candidates (DCs) will benefit from an international, interdisciplinary, and cross-sectoral training through research in basic and applied soft matter and food sciences. Through their Individual Research Projects and the network-wide training activities, characterised by a strong involvement of the non-academic partners, they will develop the hard and soft skills needed to face the current challenges related to food and environmental transitions. The consortium includes eleven Beneficiaries (including three from the non-academic sector) from seven countries and eleven Associated Partners (including four from the non-academic sector), with worldwide recognised and complementary expertise in food and soft matter sciences. All DCs will be exposed to both academic and non-academic working environments. ESM objectives are timely and the ESM unique training programme holds a great promise for the advancement of the DCs careers as well as for scientifically, technologically and socially relevant outputs. | D54: airtable | E54: 4041810 | F54: 4041810 | G54: EUR | H54: 4041810 | I54: 4041810 | J54: 4041810 | K54: 4041810 | L54: Awarded | M54: checked | N54: https://cordis.europa.eu/project/id/101168870 | O54: grant.14099440 | V54: French National Center for Scientific Research (CNRS) | W54: Government research agency | X54: France | Y54: Europe | AD54: AGENCIA ESTATAL CONSEJO SUPERIOR DE INVESTIGACIONES CIENTIFICAS, Lund University, Katholieke Universiteit Leuven (KU Leuven), Wageningen University, Cargill, Technion - Israel Institute of Technology, COMMUNAUTE D' UNIVERSITES ET ETABLISSEMENTS UNIVERSITE BOURGOGNE, Bel, Unilever | AE54: Yes | AF54: 45538 | AG54: 2024 | AH54: 45489 | AI54: 45717 | AJ54: 4 | AK54: Not started | AL54: 1010453 | AM54: European Commission | AN54: Marie Skłodowska-Curie Actions (MSCA) | AQ54: Government | AR54: EU | AS54: Europe | AT54: Plant-based | AW54: Education and training | AX54: Agnostic | AZ54: Texturisation methods | BD54: 45538 | BE54: 45736 | BI54: Tier 4 (No GFI involvement) | BJ54: 2025 | BK54: 2029 | BL54: =BK54-BJ54+1 -> 5 | BM54: =TEXTJOIN(", ", TRUE, SEQUENCE(1, BL54, BJ54)) -> 2025, 2026, 2027, 2028, 2029 | BN54: =IF(ISNUMBER(SEARCH(BN$1, $BM54)), ($K54/$BL54), "") | BO54: =IF(ISNUMBER(SEARCH(BO$1, $BM54)), ($K54/$BL54), "") | BP54: =IF(ISNUMBER(SEARCH(BP$1, $BM54)), ($K54/$BL54), "") | BQ54: =IF(ISNUMBER(SEARCH(BQ$1, $BM54)), ($K54/$BL54), "") | BR54: =IF(ISNUMBER(SEARCH(BR$1, $BM54)), ($K54/$BL54), "") | BS54: =IF(ISNUMBER(SEARCH(BS$1, $BM54)), ($K54/$BL54), "") -> 808362 | BT54: =IF(ISNUMBER(SEARCH(BT$1, $BM54)), ($K54/$BL54), "") -> 808362 | BU54: =IF(ISNUMBER(SEARCH(BU$1, $BM54)), ($K54/$BL54), "") -> 808362 | ... CC54: =IF(ISNUMBER(SEARCH(CC$1, $BM54)), ($K54/$BL54), "")
A55: New marketable, nutritious, and sustainable mycelium-based food from food industry residues | D55: airtable | E55: 4000000 | F55: 4000000 | G55: SEK | H55: 376000 | I55: 376000 | J55: =E55*0.091 -> 364000 | K55: =F55*0.091 -> 364000 | L55: Awarded | M55: checked | V55: Borås University College | X55: Sweden | Y55: Europe | AI55: 44938 | AJ55: 25 | AK55: Ended | AL55: 15040 | AM55: Swedish Research Council for Environment Agricultural Sciences and Spatial Planning (FORMAS) | AQ55: Government | AR55: Sweden | AS55: Europe | AT55: Fermentation | AU55: BF | AW55: Research and development | AX55: =IFERROR(INDEX('full database 2024'!AR:AR, MATCH(A55, 'full database 2024'!B:B, 0)), "") | AZ55: Feedstocks | BD55: 45596 | BE55: 45596 | BJ55: 2023 | BK55: 2025 | BL55: =BK55-BJ55+1 -> 3 | BM55: =TEXTJOIN(", ", TRUE, SEQUENCE(1, BL55, BJ55)) -> 2023, 2024, 2025 | BN55: =IF(ISNUMBER(SEARCH(BN$1, $BM55)), ($K55/$BL55), "") | BO55: =IF(ISNUMBER(SEARCH(BO$1, $BM55)), ($K55/$BL55), "") | BP55: =IF(ISNUMBER(SEARCH(BP$1, $BM55)), ($K55/$BL55), "") | BQ55: =IF(ISNUMBER(SEARCH(BQ$1, $BM55)), ($K55/$BL55), "") -> 121333.33 | BR55: =IF(ISNUMBER(SEARCH(BR$1, $BM55)), ($K55/$BL55), "") -> 121333.33 | BS55: =IF(ISNUMBER(SEARCH(BS$1, $BM55)), ($K55/$BL55), "") -> 121333.33 | BT55: =IF(ISNUMBER(SEARCH(BT$1, $BM55)), ($K55/$BL55), "") | BU55: =IF(ISNUMBER(SEARCH(BU$1, $BM55)), ($K55/$BL55), "") | ... CC55: =IF(ISNUMBER(SEARCH(CC$1, $BM55)), ($K55/$BL55), "")
A56: Plant-based protein isolates with low sodium content for production of healthy and sustainable foods | B56: The increasing demand for a healthy and sustainable diet can be met by eating more plant-based proteins. However, products with plant-based proteins often have high sodium levels, and contain anti-nutrients which may inhibit absorption of minerals. Sodium is added as salt (sodium chloride) to make the products palatable, but also originates from extraction of protein isolates.Excessive sodium intake impairs public health and entails significant healthcare costs for society. Thus, there is a need to reduce the sodium content in food, but a reduction must be done without negative effects on taste, texture, microbial safety, shelf-life and sustainability.The goal of the work is to contribute to healthier plant-based foods that fulfil the Swedish criteria for “The Keyhole” and comply with EU low-sodium claim level by developing methods to produce protein isolates from peas with a low content of sodium and anti-nutrients.Protein isolates are used for extruding texturised vegetable proteins, which in turn are the starting ingredient for many tasty and healthy plant-based meals. Multisensory solutions are used in the meal development to reduce the need for adding salt. The meals are evaluated in consumer studies performed in schools.Chemical, physical and sensory analyses are carried out for evaluating several different properties of the proteins to ensure their functionality and palatability. The sustainability of the processes and systems level is also evaluated. | D56: airtable | E56: 4000000 | F56: 4000000 | G56: SEK | H56: 376000 | I56: 376000 | J56: =E56*0.091 -> 364000 | K56: =F56*0.091 -> 364000 | L56: Awarded | M56: checked | N56: https://www.vr.se/swecris.html#/project/2023-02010_Formas | O56: grant.13759755 | T56: Tim Nielsen | V56: RISE Research Institutes of Sweden | X56: Sweden | Y56: Europe | AI56: 45261 | AJ56: 24 | AK56: Progress | AL56: 15667 | AM56: Swedish Research Council for Environment Agricultural Sciences and Spatial Planning (FORMAS) | AQ56: Government | AR56: Sweden | AS56: Europe | AT56: Plant-based | AW56: Research and development | AX56: =IFERROR(INDEX('full database 2024'!AR:AR, MATCH(A56, 'full database 2024'!B:B, 0)), "") | AZ56: Ingredient optimisation | BD56: 45596 | BE56: 45779 | BJ56: 2023 | BK56: 2025 | BL56: =BK56-BJ56+1 -> 3 | BM56: =TEXTJOIN(", ", TRUE, SEQUENCE(1, BL56, BJ56)) -> 2023, 2024, 2025 | BN56: =IF(ISNUMBER(SEARCH(BN$1, $BM56)), ($K56/$BL56), "") | BO56: =IF(ISNUMBER(SEARCH(BO$1, $BM56)), ($K56/$BL56), "") | BP56: =IF(ISNUMBER(SEARCH(BP$1, $BM56)), ($K56/$BL56), "") | BQ56: =IF(ISNUMBER(SEARCH(BQ$1, $BM56)), ($K56/$BL56), "") -> 121333.33 | BR56: =IF(ISNUMBER(SEARCH(BR$1, $BM56)), ($K56/$BL56), "") -> 121333.33 | BS56: =IF(ISNUMBER(SEARCH(BS$1, $BM56)), ($K56/$BL56), "") -> 121333.33 | BT56: =IF(ISNUMBER(SEARCH(BT$1, $BM56)), ($K56/$BL56), "") | BU56: =IF(ISNUMBER(SEARCH(BU$1, $BM56)), ($K56/$BL56), "") | ... CC56: =IF(ISNUMBER(SEARCH(CC$1, $BM56)), ($K56/$BL56), "")
A57: Paving the way for microbial caseins - deciphering the importance of post-translational modifications - DECIPHER | D57: airtable | E57: 3999972 | F57: 3999972 | G57: DKK | H57: 576688 | I57: 0 | J57: =E57*0.13 -> 519996.36 | K57: =F57*0.13 -> 519996.36 | L57: Awarded | M57: checked | O57: grant.13909917 | T57: Lotte Bach Larsen | V57: University of Aarhus | X57: Denmark | Y57: Europe | AI57: 44652 | AL57: 576688 | AM57: Novo Nordisk Foundation | AQ57: Non-profit | AR57: Denmark | AS57: Europe | AT57: Fermentation | AU57: PF | AW57: Research and development | AX57: =IFERROR(INDEX('full database 2024'!AR:AR, MATCH(A57, 'full database 2024'!B:B, 0)), "") | AY57: Milk | AZ57: Target molecule selection | BD57: 45596 | BE57: 45596 | BJ57: 2022 | BK57: 2022 | BL57: =BK57-BJ57+1 -> 1 | BM57: =TEXTJOIN(", ", TRUE, SEQUENCE(1, BL57, BJ57)) -> 2022 | BN57: =IF(ISNUMBER(SEARCH(BN$1, $BM57)), ($K57/$BL57), "") | BO57: =IF(ISNUMBER(SEARCH(BO$1, $BM57)), ($K57/$BL57), "") | BP57: =IF(ISNUMBER(SEARCH(BP$1, $BM57)), ($K57/$BL57), "") -> 519996.36 | BQ57: =IF(ISNUMBER(SEARCH(BQ$1, $BM57)), ($K57/$BL57), "") | BR57: =IF(ISNUMBER(SEARCH(BR$1, $BM57)), ($K57/$BL57), "") | BS57: =IF(ISNUMBER(SEARCH(BS$1, $BM57)), ($K57/$BL57), "") | BT57: =IF(ISNUMBER(SEARCH(BT$1, $BM57)), ($K57/$BL57), "") | BU57: =IF(ISNUMBER(SEARCH(BU$1, $BM57)), ($K57/$BL57), "") | ... CC57: =IF(ISNUMBER(SEARCH(CC$1, $BM57)), ($K57/$BL57), "")
A58: ADAPTide: decrypting sustainable and responsive nutrition by mapping the effects of plant-based foods on metabolic profiling | D58: airtable | E58: 3998443 | F58: 3998443 | G58: SEK | H58: 375854 | I58: 375854 | J58: =E58*0.091 -> 363858.31 | K58: =F58*0.091 -> 363858.31 | L58: Awarded | M58: checked | T58: Samira Prado | V58: Örebro universitet | X58: Sweden | Y58: Europe | AI58: 45292 | AJ58: 36 | AK58: Progress | AL58: 10440 | AM58: Swedish Research Council for Environment Agricultural Sciences and Spatial Planning (FORMAS) | AQ58: Government | AR58: Sweden | AS58: Europe | AT58: Plant-based | AW58: Research and development | AX58: =IFERROR(INDEX('full database 2024'!AR:AR, MATCH(A58, 'full database 2024'!B:B, 0)), "") | AZ58: Health/nutrition | BD58: 45596 | BE58: 45596 | BJ58: 2024 | BK58: 2027 | BL58: =BK58-BJ58+1 -> 4 | BM58: =TEXTJOIN(", ", TRUE, SEQUENCE(1, BL58, BJ58)) -> 2024, 2025, 2026, 2027 | BN58: =IF(ISNUMBER(SEARCH(BN$1, $BM58)), ($K58/$BL58), "") | BO58: =IF(ISNUMBER(SEARCH(BO$1, $BM58)), ($K58/$BL58), "") | BP58: =IF(ISNUMBER(SEARCH(BP$1, $BM58)), ($K58/$BL58), "") | BQ58: =IF(ISNUMBER(SEARCH(BQ$1, $BM58)), ($K58/$BL58), "") | BR58: =IF(ISNUMBER(SEARCH(BR$1, $BM58)), ($K58/$BL58), "") -> 90964.578 | BS58: =IF(ISNUMBER(SEARCH(BS$1, $BM58)), ($K58/$BL58), "") -> 90964.578 | BT58: =IF(ISNUMBER(SEARCH(BT$1, $BM58)), ($K58/$BL58), "") -> 90964.578 | BU58: =IF(ISNUMBER(SEARCH(BU$1, $BM58)), ($K58/$BL58), "") -> 90964.578 | ... CC58: =IF(ISNUMBER(SEARCH(CC$1, $BM58)), ($K58/$BL58), "")
A59: Barley Biofarmed Growth Factors to Make Cell Cultured Meat an Affordable Reality | B59: ORF Genetics is a female-lead plant biotechnology company biofarming protein in barley for use in medical research, stem cell technology and skincare. Since 2001, we have produced over 50 proteins, specializing in human growth factors (GFs) which regulate the growth and development of cells. Our main focus has been on GFs for skincare use and now with our team of over 80 qualified scientists, researchers, marketers and more, we are aiming at a larger market, the cell-cultured meat (CCM) industry. The CCMeat project removes the biggest hurdle CCM producers are facing to bring their alternative meat products to market. With innovations in our technology we will produce affordable, endotoxin-free growth factors designed specifically for CCM: the MESOkine™ line (patent to be filed in June 2020). This will be done by scaling cultivation from our 2000m2 state-of-the-art geothermally powered greenhouse in Iceland to in-field cultivation sites. We will also introduce a protein processing technology (patent to be filed in July 2020) that will substantially decrease production costs and lead to greater GF yields. By 2030, our MESOkine™ line will drop GF prices from 3000€/kg of cultured meat to approximately 0.7€/kg meat at scales necessary to produce over 7 million tonnes of meat. We are already providing samples to CCM customers and expect to reach a 40% market share within 5 years with our strong first mover advantage. MESOkine™ sales are expected to rise exponentially and reach profitability of €19 million by 2026. As the demand for meat continues to grow, this innovation will have a profound impact on our planet, enabling CCM to avert many of the negative consequences of conventional meat production. This includes reducing greenhouse gases by more than 250 million tonnes of CO2-eq emissions, deforestation by producing 7-52 times as much meat with one hectare of land, and antibiotic resistance by sparing over 1000 tonnes of livestock antibiotic use. | D59: airtable | E59: 3809356 | F59: 2500000 | G59: EUR | H59: 4177301 | I59: 2741475 | J59: 3809356 | K59: 2500000 | L59: Awarded | M59: checked | N59: https://cordis.europa.eu/project/id/101010029 | O59: grant.9488404 | R59: Original award amount is EUR 3,809,356 with EUR 2,500,000 coming from the EU government. | T59: Björn Örvar | U59: n/a | V59: ORF Genetics | W59: For profit | X59: Iceland | Y59: Europe | Z59: n/a | AE59: No | AI59: 44105 | AJ59: 2 | AK59: Completed | AL59: 2088651 | AM59: European Commission | AN59: SOCIETAL CHALLENGES - Food security, sustainable agriculture and forestry, marine, maritime and inland water research, and the bioeconomy | AQ59: Government | AR59: EU | AS59: Europe | AT59: Cultivated | AW59: Research and development | AX59: =IFERROR(INDEX('full database 2024'!AR:AR, MATCH(A59, 'full database 2024'!B:B, 0)), "") | AZ59: Cell culture media | BD59: 44999 | BE59: 45779 | BI59: Tier 4 (No GFI involvement) | BJ59: 2020 | BK59: 2022 | BL59: =BK59-BJ59+1 -> 3 | BM59: =TEXTJOIN(", ", TRUE, SEQUENCE(1, BL59, BJ59)) -> 2020, 2021, 2022 | BN59: =IF(ISNUMBER(SEARCH(BN$1, $BM59)), ($K59/$BL59), "") -> 833333.33 | BO59: =IF(ISNUMBER(SEARCH(BO$1, $BM59)), ($K59/$BL59), "") -> 833333.33 | BP59: =IF(ISNUMBER(SEARCH(BP$1, $BM59)), ($K59/$BL59), "") -> 833333.33 | BQ59: =IF(ISNUMBER(SEARCH(BQ$1, $BM59)), ($K59/$BL59), "") | BR59: =IF(ISNUMBER(SEARCH(BR$1, $BM59)), ($K59/$BL59), "") | BS59: =IF(ISNUMBER(SEARCH(BS$1, $BM59)), ($K59/$BL59), "") | BT59: =IF(ISNUMBER(SEARCH(BT$1, $BM59)), ($K59/$BL59), "") | BU59: =IF(ISNUMBER(SEARCH(BU$1, $BM59)), ($K59/$BL59), "") | ... CC59: =IF(ISNUMBER(SEARCH(CC$1, $BM59)), ($K59/$BL59), "")
A60: FAIRification of multiOmics data to link databases and create knowledge graphs for fermented foods | B60: A transition towards sustainable food systems is urgently needed to face challenges such as climate change or scarcity of resources. Food impact accounts for 26% of global greenhouse gas emissions. Animal-based food products in the European diet is the most important factor determining the footprint of food consumption. Plant-based dairy and meat alternatives have grown in popularity in recent years for various reasons, including sustainability and health benefits as well as lifestyle trends and dietary restrictions. However, plant-based food products can be nutritionally unbalanced, and their flavour profiles may limit their acceptance by consumers. Microorganisms have been used in making food products for millennia. Besides their primary role in food preservation, by virtue of their fermentative metabolism, they contribute to improving food safety and organoleptic properties and can provide additional health-promoting effects. However, the diversity of microbial communities driving plant-based fermentations, as well as their key genetic and phenotypic traits and potential synergies among community members, remain poorly characterized. Many data exist but they are spread into different literatures (scientific and grey) or in best case in different databases, but not always reusable because difficult to find, access and because databases are not systematically interoperable. The FAIROmics innovative interdisciplinary research programme will gather universities and private companies to enable the FAIRification of omics data and databases interoperability, and develop knowledge graphs for data-driven decision making to rationally design microbial communities for imparting desirable characteristics to plant-based fermented foods in the context of open science and its regulations. The FAIROmics training programme aims at developing Doctoral candidates’ skills at the interface between artificial intelligence, life sciences, humanities and social sciences. | D60: airtable | E60: 3747305 | F60: 3747305 | G60: EUR | H60: 4047089 | I60: 4047089 | J60: 3747305 | K60: 3747305 | L60: Awarded | M60: checked | N60: https://cordis.europa.eu/project/id/101120449 | V60: INSTITUT NATIONAL DE RECHERCHE POUR L'AGRICULTURE, L'ALIMENTATION ET L'ENVIRONNEMENT | X60: France | Y60: Europe | AD60: NIZO FOOD RESEARCH BV, ETHNIKO KAI KAPODISTRIAKO PANEPISTIMIO ATHINON, CHR. HANSEN AS, STICHTING VU, AGENCIA ESTATAL CONSEJO SUPERIOR DE INVESTIGACIONES CIENTIFICAS, KATHOLIEKE UNIVERSITEIT LEUVEN, ALMA MATER STUDIORUM - UNIVERSITA DI BOLOGNA, UNIVERSITE PAUL SABATIER TOULOUSE III, UNIVERSITAET PADERBORN, UNIVERSITE LIBRE DE BRUXELLES | AI60: 45352 | AK60: Completed | AL60: 4047089 | AM60: European Commission | AN60: Marie Skłodowska-Curie Actions (MSCA) | AQ60: Government | AR60: EU | AS60: Europe | AT60: Plant-based | AU60: TF | AW60: Research and development | AX60: =IFERROR(INDEX('full database 2024'!AR:AR, MATCH(A60, 'full database 2024'!B:B, 0)), "") | AZ60: Host strain development | BD60: 45596 | BE60: 45779 | BJ60: 2024 | BK60: 2028 | BL60: =BK60-BJ60+1 -> 5 | BM60: =TEXTJOIN(", ", TRUE, SEQUENCE(1, BL60, BJ60)) -> 2024, 2025, 2026, 2027, 2028 | BN60: =IF(ISNUMBER(SEARCH(BN$1, $BM60)), ($K60/$BL60), "") | BO60: =IF(ISNUMBER(SEARCH(BO$1, $BM60)), ($K60/$BL60), "") | BP60: =IF(ISNUMBER(SEARCH(BP$1, $BM60)), ($K60/$BL60), "") | BQ60: =IF(ISNUMBER(SEARCH(BQ$1, $BM60)), ($K60/$BL60), "") | BR60: =IF(ISNUMBER(SEARCH(BR$1, $BM60)), ($K60/$BL60), "") -> 749461 | BS60: =IF(ISNUMBER(SEARCH(BS$1, $BM60)), ($K60/$BL60), "") -> 749461 | BT60: =IF(ISNUMBER(SEARCH(BT$1, $BM60)), ($K60/$BL60), "") -> 749461 | BU60: =IF(ISNUMBER(SEARCH(BU$1, $BM60)), ($K60/$BL60), "") -> 749461 | ... CC60: =IF(ISNUMBER(SEARCH(CC$1, $BM60)), ($K60/$BL60), "")
A61: Foieture | D61: airtable | E61: 3600000 | F61: 3600000 | G61: EUR | H61: 3862692 | I61: 3862692 | J61: 3600000 | K61: 3600000 | L61: Awarded | M61: checked | N61: https://www.flandersfood.com/en/Lore%20Knaepen | R61: Original award amount is EUR 3,600,000. Award amount determined from this web page: https://en.wikipedia.org/wiki/MeaTech. | T61: Dirk von Heinrichshorst | U61: n/a | V61: Peace of Meat | W61: For profit | X61: Belgium | Y61: Europe | Z61: n/a | AD61: Solina Belgium, Nauta's Meats, Katholieke Universiteit Leuven (KU Leuven), Bio Base Europe Pilot Plant, Flanders Food | AE61: Yes | AI61: 43831 | AJ61: 3 | AK61: Completed | AL61: 1287564 | AM61: Flanders Innovation & Entrepreneurship (VLAIO) | AQ61: Government | AR61: Belgium | AS61: Europe | AT61: Cultivated | AW61: Research and development | AX61: =IFERROR(INDEX('full database 2024'!AR:AR, MATCH(A61, 'full database 2024'!B:B, 0)), "") | AZ61: Cell line development | BD61: 44999 | BE61: 45035 | BI61: Tier 4 (No GFI involvement) | BJ61: 2020 | BK61: 2023 | BL61: =BK61-BJ61+1 -> 4 | BM61: =TEXTJOIN(", ", TRUE, SEQUENCE(1, BL61, BJ61)) -> 2020, 2021, 2022, 2023 | BN61: =IF(ISNUMBER(SEARCH(BN$1, $BM61)), ($K61/$BL61), "") -> 900000 | BO61: =IF(ISNUMBER(SEARCH(BO$1, $BM61)), ($K61/$BL61), "") -> 900000 | BP61: =IF(ISNUMBER(SEARCH(BP$1, $BM61)), ($K61/$BL61), "") -> 900000 | BQ61: =IF(ISNUMBER(SEARCH(BQ$1, $BM61)), ($K61/$BL61), "") -> 900000 | BR61: =IF(ISNUMBER(SEARCH(BR$1, $BM61)), ($K61/$BL61), "") | BS61: =IF(ISNUMBER(SEARCH(BS$1, $BM61)), ($K61/$BL61), "") | BT61: =IF(ISNUMBER(SEARCH(BT$1, $BM61)), ($K61/$BL61), "") | BU61: =IF(ISNUMBER(SEARCH(BU$1, $BM61)), ($K61/$BL61), "") | ... CC61: =IF(ISNUMBER(SEARCH(CC$1, $BM61)), ($K61/$BL61), "")
A62: ECOnti - Accelerated, low ecological footprint, manufacturing platform for continuous production of biotechnological products | B62: Initial situation: Microbial processes are essential for producing various products, e.g., biopharmaceuticals, vaccines, chemicals, or food ingredients. Continuous manufacturing is considered a game-changer with a high potential for increasing bioprocess efficiency and enabling low-footprint manufacturing. However, with the current state of the art, continuous, microbial-based bioprocessing is not possible due to the high mutation rate of bacteria. Furthermore, due to the technical complexity, not a single fully autonomous biotechnological manufacturing process for the production of biopharmaceuticals has been submitted to the EMA/FDA so far. Another problem is the high energy and water consumption of large-scale biotechnological plants. Hence, as of today, worldwide, not a single fully automated, continuous bioprocess is established applying microbial cells for the production of different materials. Goals and innovation: With the ECOnti project, we aim to enable a faster, cheaper, and more efficient production of biotechnologically derived products. The problem of genetic instability is addressed in a patented technology from enGenes Biotech (WO2021123402A1) and is the basic building block for establishing a stable, continuous production process for recombinant proteins. In the project, two continuous fermentation reactors will be connected with a primary recovery unit, and continuous chromatography will be established (enGenes, Biotech and Tosoh). The individual unit operations will be connected and automated using the Qubicon® software solution (Qubicon AG). Using data-driven as well as mechanistic models, so-called hybrid models (Novasign), as well as fluid-dynamical models (SimVantage) “digital twins” will be developed and will serve as the basis for real-time monitoring and model-based predictive control. Such models will increase efficiency through time savings in the development as well as the production of biotechnologically produced materials. The targeted proof-of-concept is to be established at 1L to 10 L scale using the model Protein A, a high-value product used for the purification of monoclonal antibodies. In the medium and long term, however, the consortium envisions scales of >100-1000L. Applying computational fluid dynamics models in feedback with the hybrid models will ensure an appropriate scale-up of the process. Furthermore, based on a techno-economic evaluation of the process, appropriate cost models for the developed unit operations will be established to quantify and visualize the added value in terms of manufacturing costs, efficiency, and environmental footprint (BOKU). Results: By developing ECOnti, microbial manufacturing processes based on E. coli can be developed and implemented more economically and ecologically. We assume a downscaling factor of 10 concerning the manufacturing plant size. This downscaling significantly reduces energy and resource consumption and enables the production of products that currently cannot be manufactured cost-efficiently using biotechnology. Therefore, the full integration of this technology enables the production of molecules with very high price pressure, such as treatments for chronic disease or precision fermentation products (casein, meat). Through the cooperation of four Austrian companies, an Austrian research institution (BOKU), and Tosoh Bioscience, a leading supplier in the field of chromatography, an immanent problem is brought to a solution. The consortium represents companies all along the bioprocess (enGenes, Tosoh), modeling (Novasign, SimVantage), and automation (Qubicon) value chain. With the help of Novasign, Qubicon, and SimVantage, physical technology will be transformed into a digital environment. The digitalization of this production process is necessary due to the complexity of a continuous process. By integrating the different solutions of the individual companies, the added value is increased, and the companies mutually participate in the success of the developed technology solution. | D62: airtable | E62: 3600000 | F62: 2700000 | G62: EUR | H62: 0 | I62: 0 | J62: 3600000 | K62: 2700000 | L62: Awarded | N62: https://www.pharmaceutical-networking.com/engenes-secure-significant-funding-for-econti-e-coli-continuous-manufacturing-project/#:~:text=The%20project%20%E2%80%9CECOnti%20%E2%80%93%20Accelerated%2C,to%2010%20L%20batch%20size. | O62: grant.13727933 | V62: University of Natural Resources and Life Sciences | X62: Austria | Y62: Europe | AI62: 44929 | AL62: 0 | AM62: Austrian Research Promotion Agency (FFG) | AQ62: Government | AR62: Austria | AS62: Europe | AT62: Fermentation | AU62: PF | AW62: Research and development | AX62: =IFERROR(INDEX('full database 2024'!AR:AR, MATCH(A62, 'full database 2024'!B:B, 0)), "") | AZ62: Host strain development | BD62: 45671 | BE62: 45779 | BJ62: 2023 | BK62: 2025 | BL62: =BK62-BJ62+1 -> 3 | BM62: =TEXTJOIN(", ", TRUE, SEQUENCE(1, BL62, BJ62)) -> 2023, 2024, 2025 | BN62: =IF(ISNUMBER(SEARCH(BN$1, $BM62)), ($K62/$BL62), "") | BO62: =IF(ISNUMBER(SEARCH(BO$1, $BM62)), ($K62/$BL62), "") | BP62: =IF(ISNUMBER(SEARCH(BP$1, $BM62)), ($K62/$BL62), "") | BQ62: =IF(ISNUMBER(SEARCH(BQ$1, $BM62)), ($K62/$BL62), "") -> 900000 | BR62: =IF(ISNUMBER(SEARCH(BR$1, $BM62)), ($K62/$BL62), "") -> 900000 | BS62: =IF(ISNUMBER(SEARCH(BS$1, $BM62)), ($K62/$BL62), "") -> 900000 | BT62: =IF(ISNUMBER(SEARCH(BT$1, $BM62)), ($K62/$BL62), "") | BU62: =IF(ISNUMBER(SEARCH(BU$1, $BM62)), ($K62/$BL62), "") | ... CC62: =IF(ISNUMBER(SEARCH(CC$1, $BM62)), ($K62/$BL62), "")
A63: Valorisation of food production side-streams as multifunctional ingredients by an innovative fermentation process. | D63: airtable | E63: 3535625 | F63: 2474938 | G63: EUR | H63: 3818475 | I63: 2672933 | J63: 3535625 | K63: 2474938 | L63: Awarded | M63: checked | N63: https://cordis.europa.eu/project/id/190144130 | V63: Green Spot Technologies | X63: France | Y63: Europe | AI63: 44743 | AK63: Completed | AL63: 3818475 | AM63: European Commission | AN63: European Innovation Council (EIC) | AQ63: Government | AR63: EU | AS63: Europe | AT63: Plant-based | AU63: TF | AW63: Research and development | AX63: =IFERROR(INDEX('full database 2024'!AR:AR, MATCH(A63, 'full database 2024'!B:B, 0)), "") | AZ63: Ingredient optimisation | BD63: 45596 | BE63: 45596 | BJ63: 2022 | BK63: 2024 | BL63: =BK63-BJ63+1 -> 3 | BM63: =TEXTJOIN(", ", TRUE, SEQUENCE(1, BL63, BJ63)) -> 2022, 2023, 2024 | BN63: =IF(ISNUMBER(SEARCH(BN$1, $BM63)), ($K63/$BL63), "") | BO63: =IF(ISNUMBER(SEARCH(BO$1, $BM63)), ($K63/$BL63), "") | BP63: =IF(ISNUMBER(SEARCH(BP$1, $BM63)), ($K63/$BL63), "") -> 824979.33 | BQ63: =IF(ISNUMBER(SEARCH(BQ$1, $BM63)), ($K63/$BL63), "") -> 824979.33 | BR63: =IF(ISNUMBER(SEARCH(BR$1, $BM63)), ($K63/$BL63), "") -> 824979.33 | BS63: =IF(ISNUMBER(SEARCH(BS$1, $BM63)), ($K63/$BL63), "") | BT63: =IF(ISNUMBER(SEARCH(BT$1, $BM63)), ($K63/$BL63), "") | BU63: =IF(ISNUMBER(SEARCH(BU$1, $BM63)), ($K63/$BL63), "") | ... CC63: =IF(ISNUMBER(SEARCH(CC$1, $BM63)), ($K63/$BL63), "")
A64: The Protein Revolution | D64: airtable | E64: 3495647 | F64: 3495647 | G64: SEK | H64: 328591 | I64: 328591 | J64: =E64*0.091 -> 318103.88 | K64: =F64*0.091 -> 318103.88 | L64: Awarded | M64: checked | V64: Alba Ecological Information Institute | X64: Sweden | Y64: Europe | AI64: 45210 | AJ64: 18 | AK64: Ended | AL64: 18255 | AM64: Vinnova | AQ64: Government | AR64: Sweden | AS64: Europe | AT64: Cross-cutting | AU64: All | AW64: Research and development | AX64: =IFERROR(INDEX('full database 2024'!AR:AR, MATCH(A64, 'full database 2024'!B:B, 0)), "") | AZ64: cross-cutting | BD64: 45596 | BE64: 45596 | BJ64: 2023 | BK64: 2025 | BL64: =BK64-BJ64+1 -> 3 | BM64: =TEXTJOIN(", ", TRUE, SEQUENCE(1, BL64, BJ64)) -> 2023, 2024, 2025 | BN64: =IF(ISNUMBER(SEARCH(BN$1, $BM64)), ($K64/$BL64), "") | BO64: =IF(ISNUMBER(SEARCH(BO$1, $BM64)), ($K64/$BL64), "") | BP64: =IF(ISNUMBER(SEARCH(BP$1, $BM64)), ($K64/$BL64), "") | BQ64: =IF(ISNUMBER(SEARCH(BQ$1, $BM64)), ($K64/$BL64), "") -> 106034.63 | BR64: =IF(ISNUMBER(SEARCH(BR$1, $BM64)), ($K64/$BL64), "") -> 106034.63 | BS64: =IF(ISNUMBER(SEARCH(BS$1, $BM64)), ($K64/$BL64), "") -> 106034.63 | BT64: =IF(ISNUMBER(SEARCH(BT$1, $BM64)), ($K64/$BL64), "") | BU64: =IF(ISNUMBER(SEARCH(BU$1, $BM64)), ($K64/$BL64), "") | ... CC64: =IF(ISNUMBER(SEARCH(CC$1, $BM64)), ($K64/$BL64), "")
A65: Using biotechnology to create the next generation of sustainable foods from the roots of mushrooms | D65: airtable | E65: 3467500 | F65: 2426375 | G65: EUR | H65: 3744900 | I65: 2620485 | J65: 3467500 | K65: 2426375 | L65: Awarded | M65: checked | N65: https://cordis.europa.eu/project/id/190118690 | V65: MUSHLABS GMBH | X65: Germany | Y65: Europe | AI65: 44866 | AK65: Completed | AL65: 3744900 | AM65: European Commission | AN65: European Innovation Council (EIC) | AQ65: Government | AR65: EU | AS65: Europe | AT65: Fermentation | AU65: BF | AW65: Research and development | AX65: =IFERROR(INDEX('full database 2024'!AR:AR, MATCH(A65, 'full database 2024'!B:B, 0)), "") | AZ65: Host strain development | BD65: 45596 | BE65: 45596 | BJ65: 2022 | BK65: 2024 | BL65: =BK65-BJ65+1 -> 3 | BM65: =TEXTJOIN(", ", TRUE, SEQUENCE(1, BL65, BJ65)) -> 2022, 2023, 2024 | BN65: =IF(ISNUMBER(SEARCH(BN$1, $BM65)), ($K65/$BL65), "") | BO65: =IF(ISNUMBER(SEARCH(BO$1, $BM65)), ($K65/$BL65), "") | BP65: =IF(ISNUMBER(SEARCH(BP$1, $BM65)), ($K65/$BL65), "") -> 808791.67 | BQ65: =IF(ISNUMBER(SEARCH(BQ$1, $BM65)), ($K65/$BL65), "") -> 808791.67 | BR65: =IF(ISNUMBER(SEARCH(BR$1, $BM65)), ($K65/$BL65), "") -> 808791.67 | BS65: =IF(ISNUMBER(SEARCH(BS$1, $BM65)), ($K65/$BL65), "") | BT65: =IF(ISNUMBER(SEARCH(BT$1, $BM65)), ($K65/$BL65), "") | BU65: =IF(ISNUMBER(SEARCH(BU$1, $BM65)), ($K65/$BL65), "") | ... CC65: =IF(ISNUMBER(SEARCH(CC$1, $BM65)), ($K65/$BL65), "")
A66: Unlocking the Protein Production Potential of Non-Conventional Yeasts with Artificial Intelligence | D66: airtable | E66: 3440000 | F66: 3440000 | G66: SEK | H66: 323360 | I66: 323360 | J66: =E66*0.091 -> 313040 | K66: =F66*0.091 -> 313040 | L66: Awarded | M66: checked | V66: Chalmers University of Technology | X66: Sweden | Y66: Europe | AI66: 45292 | AJ66: 49 | AK66: Progress | AL66: 6599 | AM66: Swedish Research Council | AQ66: Government | AR66: Sweden | AS66: Europe | AT66: Fermentation | AU66: PF | AW66: Research and development | AX66: =IFERROR(INDEX('full database 2024'!AR:AR, MATCH(A66, 'full database 2024'!B:B, 0)), "") | AZ66: Host strain development | BD66: 45596 | BE66: 45596 | BJ66: 2024 | BK66: 2028 | BL66: =BK66-BJ66+1 -> 5 | BM66: =TEXTJOIN(", ", TRUE, SEQUENCE(1, BL66, BJ66)) -> 2024, 2025, 2026, 2027, 2028 | BN66: =IF(ISNUMBER(SEARCH(BN$1, $BM66)), ($K66/$BL66), "") | BO66: =IF(ISNUMBER(SEARCH(BO$1, $BM66)), ($K66/$BL66), "") | BP66: =IF(ISNUMBER(SEARCH(BP$1, $BM66)), ($K66/$BL66), "") | BQ66: =IF(ISNUMBER(SEARCH(BQ$1, $BM66)), ($K66/$BL66), "") | BR66: =IF(ISNUMBER(SEARCH(BR$1, $BM66)), ($K66/$BL66), "") -> 62608 | BS66: =IF(ISNUMBER(SEARCH(BS$1, $BM66)), ($K66/$BL66), "") -> 62608 | BT66: =IF(ISNUMBER(SEARCH(BT$1, $BM66)), ($K66/$BL66), "") -> 62608 | BU66: =IF(ISNUMBER(SEARCH(BU$1, $BM66)), ($K66/$BL66), "") -> 62608 | ... CC66: =IF(ISNUMBER(SEARCH(CC$1, $BM66)), ($K66/$BL66), "")
A67: E!2514 M3DS | D67: airtable | E67: 3417451 | F67: 3417451 | G67: SEK | H67: 321240 | I67: 321240 | J67: =E67*0.091 -> 310988.04 | K67: =F67*0.091 -> 310988.04 | L67: Awarded | M67: checked | V67: Mycorena AB | X67: Sweden | Y67: Europe | AI67: 44927 | AJ67: 12 | AK67: Ended | AL67: 26770 | AM67: Vinnova | AQ67: Government | AR67: Sweden | AS67: Europe | AT67: Fermentation | AU67: BF | AW67: Research and development | AX67: =IFERROR(INDEX('full database 2024'!AR:AR, MATCH(A67, 'full database 2024'!B:B, 0)), "") | AZ67: Host strain development | BD67: 45596 | BE67: 45596 | BJ67: 2023 | BK67: 2024 | BL67: =BK67-BJ67+1 -> 2 | BM67: =TEXTJOIN(", ", TRUE, SEQUENCE(1, BL67, BJ67)) -> 2023, 2024 | BN67: =IF(ISNUMBER(SEARCH(BN$1, $BM67)), ($K67/$BL67), "") | BO67: =IF(ISNUMBER(SEARCH(BO$1, $BM67)), ($K67/$BL67), "") | BP67: =IF(ISNUMBER(SEARCH(BP$1, $BM67)), ($K67/$BL67), "") | BQ67: =IF(ISNUMBER(SEARCH(BQ$1, $BM67)), ($K67/$BL67), "") -> 155494.02 | BR67: =IF(ISNUMBER(SEARCH(BR$1, $BM67)), ($K67/$BL67), "") -> 155494.02 | BS67: =IF(ISNUMBER(SEARCH(BS$1, $BM67)), ($K67/$BL67), "") | BT67: =IF(ISNUMBER(SEARCH(BT$1, $BM67)), ($K67/$BL67), "") | BU67: =IF(ISNUMBER(SEARCH(BU$1, $BM67)), ($K67/$BL67), "") | ... CC67: =IF(ISNUMBER(SEARCH(CC$1, $BM67)), ($K67/$BL67), "")
A68: Disrupting the food ingredient and protein markets: a breakthrough technology for large-scale microalgae cultivation. | D68: airtable | E68: 3355534 | F68: 2348873 | G68: EUR | H68: 3623976 | I68: 2536783 | J68: 3355534 | K68: 2348873 | L68: Awarded | M68: checked | N68: https://cordis.europa.eu/project/id/190186816/ | V68: ARBOREABIOFOODS LDA | X68: Portugal | Y68: Europe | AI68: 44562 | AK68: Completed | AL68: 3623976 | AM68: European Commission | AN68: European Innovation Council (EIC) | AQ68: Government | AR68: EU | AS68: Europe | AT68: Fermentation | AU68: BF | AW68: Research and development | AX68: =IFERROR(INDEX('full database 2024'!AR:AR, MATCH(A68, 'full database 2024'!B:B, 0)), "") | AZ68: Bioprocess design | BD68: 45596 | BE68: 45596 | BJ68: 2022 | BK68: 2023 | BL68: =BK68-BJ68+1 -> 2 | BM68: =TEXTJOIN(", ", TRUE, SEQUENCE(1, BL68, BJ68)) -> 2022, 2023 | BN68: =IF(ISNUMBER(SEARCH(BN$1, $BM68)), ($K68/$BL68), "") | BO68: =IF(ISNUMBER(SEARCH(BO$1, $BM68)), ($K68/$BL68), "") | BP68: =IF(ISNUMBER(SEARCH(BP$1, $BM68)), ($K68/$BL68), "") -> 1174436.5 | BQ68: =IF(ISNUMBER(SEARCH(BQ$1, $BM68)), ($K68/$BL68), "") -> 1174436.5 | BR68: =IF(ISNUMBER(SEARCH(BR$1, $BM68)), ($K68/$BL68), "") | BS68: =IF(ISNUMBER(SEARCH(BS$1, $BM68)), ($K68/$BL68), "") | BT68: =IF(ISNUMBER(SEARCH(BT$1, $BM68)), ($K68/$BL68), "") | BU68: =IF(ISNUMBER(SEARCH(BU$1, $BM68)), ($K68/$BL68), "") | ... CC68: =IF(ISNUMBER(SEARCH(CC$1, $BM68)), ($K68/$BL68), "")
A69: Functional processing of cultivated seaweeds for novel food products | D69: airtable | E69: 3333332 | F69: 3333332 | G69: SEK | H69: 313333 | I69: 313333 | J69: =E69*0.091 -> 303333.21 | K69: =F69*0.091 -> 303333.21 | L69: Awarded | M69: checked | V69: Lund University | X69: Sweden | Y69: Europe | AI69: 45293 | AJ69: 37 | AK69: Progress | AL69: 8468 | AM69: Swedish Research Council for Environment Agricultural Sciences and Spatial Planning (FORMAS) | AQ69: Government | AR69: Sweden | AS69: Europe | AT69: Plant-based | AW69: Research and development | AX69: =IFERROR(INDEX('full database 2024'!AR:AR, MATCH(A69, 'full database 2024'!B:B, 0)), "") | AZ69: Ingredient optimisation | BD69: 45596 | BE69: 45596 | BJ69: 2024 | BK69: 2027 | BL69: =BK69-BJ69+1 -> 4 | BM69: =TEXTJOIN(", ", TRUE, SEQUENCE(1, BL69, BJ69)) -> 2024, 2025, 2026, 2027 | BN69: =IF(ISNUMBER(SEARCH(BN$1, $BM69)), ($K69/$BL69), "") | BO69: =IF(ISNUMBER(SEARCH(BO$1, $BM69)), ($K69/$BL69), "") | BP69: =IF(ISNUMBER(SEARCH(BP$1, $BM69)), ($K69/$BL69), "") | BQ69: =IF(ISNUMBER(SEARCH(BQ$1, $BM69)), ($K69/$BL69), "") | BR69: =IF(ISNUMBER(SEARCH(BR$1, $BM69)), ($K69/$BL69), "") -> 75833.303 | BS69: =IF(ISNUMBER(SEARCH(BS$1, $BM69)), ($K69/$BL69), "") -> 75833.303 | BT69: =IF(ISNUMBER(SEARCH(BT$1, $BM69)), ($K69/$BL69), "") -> 75833.303 | BU69: =IF(ISNUMBER(SEARCH(BU$1, $BM69)), ($K69/$BL69), "") -> 75833.303 | ... CC69: =IF(ISNUMBER(SEARCH(CC$1, $BM69)), ($K69/$BL69), "")
A70: Feed for Meat | B70: In the Feed for Meat project, three companies, with close involvement from knowledge institutions, intend to collaborate intensively and focus on developing a sustainable, cost-efficient breeding ground for the various phases of cultured meat production. For many, cultured meat could be a good alternative. Cultured meat is meat that is biologically produced in the same way as traditional meat. However, the process takes place outside the animal under controlled conditions. A major advantage of cultured meat compared to traditional meat is its lower environmental impact. Compared to plant-based alternatives, cultured meat meets nutritional needs much better, for example in the areas of protein quality, vitamins and trace elements. | D70: airtable | E70: 3211053 | F70: 1988942 | G70: EUR | H70: 3411214 | I70: 2112922 | J70: 3211053 | K70: 1988942 | L70: Awarded | M70: checked | N70: https://www.stimulus.nl/opzuid/avada_portfolio/feed-for-meat/ | R70: Original award amount is EUR 3,211,053 with EUR 1,222,111 from private sector. | T70: Fulco van Lede | U70: n/a | V70: Nutreco Netherlands BV | W70: For profit | X70: Netherlands | Y70: Europe | Z70: n/a | AD70: Mosa Meat, Selko, Maastricht University, Brightlands Campus Greenport Venlo | AE70: Yes | AI70: 44317 | AJ70: 3 | AK70: In progress | AL70: 1137071 | AM70: European Commission | AN70: European Regional Development Fund (ERDF) | AQ70: Joint public/private partnership | AR70: EU | AS70: Europe | AT70: Cultivated | AW70: Research and development | AX70: =IFERROR(INDEX('full database 2024'!AR:AR, MATCH(A70, 'full database 2024'!B:B, 0)), "") | AZ70: cross-cutting | BD70: 44985 | BE70: 45035 | BI70: Tier 4 (No GFI involvement) | BJ70: 2021 | BK70: 2024 | BL70: =BK70-BJ70+1 -> 4 | BM70: =TEXTJOIN(", ", TRUE, SEQUENCE(1, BL70, BJ70)) -> 2021, 2022, 2023, 2024 | BN70: =IF(ISNUMBER(SEARCH(BN$1, $BM70)), ($K70/$BL70), "") | BO70: =IF(ISNUMBER(SEARCH(BO$1, $BM70)), ($K70/$BL70), "") -> 497235.5 | BP70: =IF(ISNUMBER(SEARCH(BP$1, $BM70)), ($K70/$BL70), "") -> 497235.5 | BQ70: =IF(ISNUMBER(SEARCH(BQ$1, $BM70)), ($K70/$BL70), "") -> 497235.5 | BR70: =IF(ISNUMBER(SEARCH(BR$1, $BM70)), ($K70/$BL70), "") -> 497235.5 | BS70: =IF(ISNUMBER(SEARCH(BS$1, $BM70)), ($K70/$BL70), "") | BT70: =IF(ISNUMBER(SEARCH(BT$1, $BM70)), ($K70/$BL70), "") | BU70: =IF(ISNUMBER(SEARCH(BU$1, $BM70)), ($K70/$BL70), "") | ... CC70: =IF(ISNUMBER(SEARCH(CC$1, $BM70)), ($K70/$BL70), "")
A71: Climate-ready faba beans for the Nordic and Baltic Region | D71: airtable | E71: 3162717 | F71: 3162717 | G71: SEK | H71: 297295 | I71: 297295 | J71: =E71*0.091 -> 287807.25 | K71: =F71*0.091 -> 287807.25 | L71: Awarded | M71: checked | V71: Swedish University of Agricultural Sciences | X71: Sweden | Y71: Europe | AI71: 44573 | AJ71: 49 | AK71: Ended | AL71: 6067 | AM71: Swedish Research Council for Environment Agricultural Sciences and Spatial Planning (FORMAS) | AQ71: Government | AR71: Sweden | AS71: Europe | AT71: Plant-based | AW71: Research and development | AX71: =IFERROR(INDEX('full database 2024'!AR:AR, MATCH(A71, 'full database 2024'!B:B, 0)), "") | AZ71: Crop development | BD71: 45596 | BE71: 45596 | BJ71: 2023 | BK71: 2027 | BL71: =BK71-BJ71+1 -> 5 | BM71: =TEXTJOIN(", ", TRUE, SEQUENCE(1, BL71, BJ71)) -> 2023, 2024, 2025, 2026, 2027 | BN71: =IF(ISNUMBER(SEARCH(BN$1, $BM71)), ($K71/$BL71), "") | BO71: =IF(ISNUMBER(SEARCH(BO$1, $BM71)), ($K71/$BL71), "") | BP71: =IF(ISNUMBER(SEARCH(BP$1, $BM71)), ($K71/$BL71), "") | BQ71: =IF(ISNUMBER(SEARCH(BQ$1, $BM71)), ($K71/$BL71), "") -> 57561.449 | BR71: =IF(ISNUMBER(SEARCH(BR$1, $BM71)), ($K71/$BL71), "") -> 57561.449 | BS71: =IF(ISNUMBER(SEARCH(BS$1, $BM71)), ($K71/$BL71), "") -> 57561.449 | BT71: =IF(ISNUMBER(SEARCH(BT$1, $BM71)), ($K71/$BL71), "") -> 57561.449 | BU71: =IF(ISNUMBER(SEARCH(BU$1, $BM71)), ($K71/$BL71), "") -> 57561.449 | ... CC71: =IF(ISNUMBER(SEARCH(CC$1, $BM71)), ($K71/$BL71), "")
A72: Food Provision through Sustainable Farming Systems and Value Chains | D72: airtable | E72: 3153558 | F72: 3153558 | G72: EUR | H72: 3405842 | I72: 3405842 | J72: 3153558 | K72: 3153558 | L72: Awarded | M72: checked | N72: https://cordis.europa.eu/project/id/101060538 | V72: UNIVERSITAT POLITECNICA DE VALENCIA | X72: Spain | Y72: Europe | AD72: COOPERATIVAS AGRO-ALIMENTARIAS DE ESPANA U DE COOP SOCIEDAD COOPERATIVA, LEIBNIZ-ZENTRUM FUER AGRARLANDSCHAFTSFORSCHUNG (ZALF) e.V., COPENHAGEN BUSINESS SCHOOL, KOBENHAVNS UNIVERSITET, UNIWERSYTET WARSZAWSKI, AKI AGRARKOZGAZDASAGI INTEZET NONPROFIT KFT, UNIVERSITA DEGLI STUDI DI TRENTO, FORSCHUNGSINSTITUT FUR BIOLOGISCHEN LANDBAU DEUTSCHLAND EV, HIGHCLERE CONSULTING SRL, GLOBAL NATURE FUND STIFTUNG | AI72: 44805 | AK72: Completed | AL72: 3405842 | AM72: European Commission | AN72: Cluster 6: Food, Bioeconomy Natural Resources, Agriculture and Environment | AQ72: Government | AR72: EU | AS72: Europe | AT72: Plant-based | AW72: Research and development | AX72: =IFERROR(INDEX('full database 2024'!AR:AR, MATCH(A72, 'full database 2024'!B:B, 0)), "") | AZ72: Crop development, Env/impact assessments | BD72: 45596 | BE72: 45596 | BJ72: 2022 | BK72: 2026 | BL72: =BK72-BJ72+1 -> 5 | BM72: =TEXTJOIN(", ", TRUE, SEQUENCE(1, BL72, BJ72)) -> 2022, 2023, 2024, 2025, 2026 | BN72: =IF(ISNUMBER(SEARCH(BN$1, $BM72)), ($K72/$BL72), "") | BO72: =IF(ISNUMBER(SEARCH(BO$1, $BM72)), ($K72/$BL72), "") | BP72: =IF(ISNUMBER(SEARCH(BP$1, $BM72)), ($K72/$BL72), "") -> 630711.6 | BQ72: =IF(ISNUMBER(SEARCH(BQ$1, $BM72)), ($K72/$BL72), "") -> 630711.6 | BR72: =IF(ISNUMBER(SEARCH(BR$1, $BM72)), ($K72/$BL72), "") -> 630711.6 | BS72: =IF(ISNUMBER(SEARCH(BS$1, $BM72)), ($K72/$BL72), "") -> 630711.6 | BT72: =IF(ISNUMBER(SEARCH(BT$1, $BM72)), ($K72/$BL72), "") -> 630711.6 | BU72: =IF(ISNUMBER(SEARCH(BU$1, $BM72)), ($K72/$BL72), "") | ... CC72: =IF(ISNUMBER(SEARCH(CC$1, $BM72)), ($K72/$BL72), "")
A73: U-Protein (Unlocking Protein Resource Opportunities To Evolve Ireland’s Nutrition) | B73: Research on U-Protein spans the entire production process, from the identification and characterisation of proteins from crops and the marine, to the processing of these proteins, clinical studies and finally incorporation into a consumer product. In support of the circular bioeconomy, the residual biomass from these protein sources will be assessed for bioactive components or valorised to novel or renewable products through microbial biotransformation. | D73: airtable | E73: 3000000 | F73: 3000000 | G73: EUR | H73: 3267330 | I73: 3267330 | J73: 3000000 | K73: 3000000 | L73: Awarded | M73: checked | N73: https://www.teagasc.ie/food/research-and-innovation/research-areas/food-chemistry--technology/research-projects/u-protein/ | R73: Original award amount is EUR 3,000,000. | T73: Mark Fenelon | U73: n/a | V73: Teagasc | W73: Government research agency | X73: Ireland | Y73: Europe | Z73: n/a | AD73: UNIVERSITY COLLEGE CORK, National University of Ireland (NUI) Maynooth, National University of Ireland (NUI) Galway, University of Limerick, Queens University Belfast | AE73: Yes | AI73: 44136 | AJ73: 3 | AK73: In progress | AL73: 1089110 | AM73: Department of Agriculture, Food, and the Marine | AQ73: Government | AR73: Ireland | AS73: Europe | AT73: Plant-based | AW73: Research and development | AX73: =IFERROR(INDEX('full database 2024'!AR:AR, MATCH(A73, 'full database 2024'!B:B, 0)), "") | AZ73: cross-cutting | BD73: 45020 | BE73: 45035 | BI73: Tier 4 (No GFI involvement) | BJ73: 2020 | BK73: 2023 | BL73: =BK73-BJ73+1 -> 4 | BM73: =TEXTJOIN(", ", TRUE, SEQUENCE(1, BL73, BJ73)) -> 2020, 2021, 2022, 2023 | BN73: =IF(ISNUMBER(SEARCH(BN$1, $BM73)), ($K73/$BL73), "") -> 750000 | BO73: =IF(ISNUMBER(SEARCH(BO$1, $BM73)), ($K73/$BL73), "") -> 750000 | BP73: =IF(ISNUMBER(SEARCH(BP$1, $BM73)), ($K73/$BL73), "") -> 750000 | BQ73: =IF(ISNUMBER(SEARCH(BQ$1, $BM73)), ($K73/$BL73), "") -> 750000 | BR73: =IF(ISNUMBER(SEARCH(BR$1, $BM73)), ($K73/$BL73), "") | BS73: =IF(ISNUMBER(SEARCH(BS$1, $BM73)), ($K73/$BL73), "") | BT73: =IF(ISNUMBER(SEARCH(BT$1, $BM73)), ($K73/$BL73), "") | BU73: =IF(ISNUMBER(SEARCH(BU$1, $BM73)), ($K73/$BL73), "") | ... CC73: =IF(ISNUMBER(SEARCH(CC$1, $BM73)), ($K73/$BL73), "")
A74: Towards a holistic and sustainable Swedish value chain for pea biorefinery (100%Pea) | D74: airtable | E74: 3000000 | F74: 3000000 | G74: SEK | H74: 290898 | I74: 290898 | J74: =E74*0.091 -> 273000 | K74: =F74*0.091 -> 273000 | L74: Awarded | M74: checked | N74: https://www.vinnova.se/en/p/towards-a-holistic-and-sustainable-swedish-value-chain-for-pea-biorefinery-100pea/ | R74: Original award amount is SEK 3,000,000. | T74: Mehdi Abdollahi | U74: Life Sciences, Food, and Nutrition Science | V74: Chalmers University of Technology | W74: University | X74: Sweden | Y74: Europe | Z74: n/a | AD74: Swedish University of Agricultural Sciences, Lantmännen | AE74: Yes | AI74: 44501 | AJ74: 2 | AK74: In progress | AL74: 145449 | AM74: Vinnova | AQ74: Government | AR74: Sweden | AS74: Europe | AT74: Plant-based | AW74: Research and development | AX74: =IFERROR(INDEX('full database 2024'!AR:AR, MATCH(A74, 'full database 2024'!B:B, 0)), "") | AZ74: Ingredient optimisation | BD74: 45037 | BE74: 45037 | BI74: Tier 4 (No GFI involvement) | BJ74: 2021 | BK74: 2023 | BL74: =BK74-BJ74+1 -> 3 | BM74: =TEXTJOIN(", ", TRUE, SEQUENCE(1, BL74, BJ74)) -> 2021, 2022, 2023 | BN74: =IF(ISNUMBER(SEARCH(BN$1, $BM74)), ($K74/$BL74), "") | BO74: =IF(ISNUMBER(SEARCH(BO$1, $BM74)), ($K74/$BL74), "") -> 91000 | BP74: =IF(ISNUMBER(SEARCH(BP$1, $BM74)), ($K74/$BL74), "") -> 91000 | BQ74: =IF(ISNUMBER(SEARCH(BQ$1, $BM74)), ($K74/$BL74), "") -> 91000 | BR74: =IF(ISNUMBER(SEARCH(BR$1, $BM74)), ($K74/$BL74), "") | BS74: =IF(ISNUMBER(SEARCH(BS$1, $BM74)), ($K74/$BL74), "") | BT74: =IF(ISNUMBER(SEARCH(BT$1, $BM74)), ($K74/$BL74), "") | BU74: =IF(ISNUMBER(SEARCH(BU$1, $BM74)), ($K74/$BL74), "") | ... CC74: =IF(ISNUMBER(SEARCH(CC$1, $BM74)), ($K74/$BL74), "")
A75: Standing Ovation Receives €3M from French Government and Bpifrance to Scale Non-Animal Caseins for Novel Dairy Products | D75: airtable | E75: 3000000 | F75: 3000000 | G75: EUR | H75: 3285135 | I75: 3285135 | J75: 3000000 | K75: 3000000 | L75: Awarded | M75: checked | N75: https://vegconomist.com/politics-law/standing-ovation-e3m-french-government-bpifrance-non-animal-caseins-novel-dairy-products/ | R75: Original award amount is EUR 2,000,000 from the French government, plus a EUR 1,000,000 loan from Bpifrance. | T75: Romain Chayot | U75: n/a | V75: Standing Ovation | W75: For profit | X75: France | Y75: Europe | Z75: n/a | AE75: No | AI75: 45300 | AJ75: 2 | AK75: In progress | AL75: 1642568 | AM75: French government, BpiFrance | AQ75: Government | AR75: France | AS75: Europe | AT75: Fermentation | AU75: PF | AW75: Equipment and infrastructure | AX75: =IFERROR(INDEX('full database 2024'!AR:AR, MATCH(A75, 'full database 2024'!B:B, 0)), "") | AY75: Milk | BD75: 45303 | BE75: 45303 | BI75: Tier 4 (No GFI involvement) | BJ75: 2024 | BK75: 2026 | BL75: =BK75-BJ75+1 -> 3 | BM75: =TEXTJOIN(", ", TRUE, SEQUENCE(1, BL75, BJ75)) -> 2024, 2025, 2026 | BN75: =IF(ISNUMBER(SEARCH(BN$1, $BM75)), ($K75/$BL75), "") | BO75: =IF(ISNUMBER(SEARCH(BO$1, $BM75)), ($K75/$BL75), "") | BP75: =IF(ISNUMBER(SEARCH(BP$1, $BM75)), ($K75/$BL75), "") | BQ75: =IF(ISNUMBER(SEARCH(BQ$1, $BM75)), ($K75/$BL75), "") | BR75: =IF(ISNUMBER(SEARCH(BR$1, $BM75)), ($K75/$BL75), "") -> 1000000 | BS75: =IF(ISNUMBER(SEARCH(BS$1, $BM75)), ($K75/$BL75), "") -> 1000000 | BT75: =IF(ISNUMBER(SEARCH(BT$1, $BM75)), ($K75/$BL75), "") -> 1000000 | BU75: =IF(ISNUMBER(SEARCH(BU$1, $BM75)), ($K75/$BL75), "") | ... CC75: =IF(ISNUMBER(SEARCH(CC$1, $BM75)), ($K75/$BL75), "")
